Workbook
Name L_VALID: 'Acciones_2027'!$X$2:$X$5
Name PN_AREAS: 'Catalogos_PDN'!$Q$5:$Q$51
Name PN_ESTVF: 'Catalogos_PDN'!$AF$5:$AF$8
Name PN_FUENTE: 'Catalogos_PDN'!$AC$5:$AC$12
Name PN_GASTO: 'Catalogos_PDN'!$AD$5:$AD$6
Name PN_MESES: 'Catalogos_PDN'!$Z$5:$Z$16
Name PN_METAS: 'Catalogos_PDN'!$I$5:$I$49
Name PN_MOD: 'Catalogos_PDN'!$AB$5:$AB$11
Name PN_PRIOR: 'Catalogos_PDN'!$AH$5:$AH$7
Name PN_REG2026: 'Necesidades_2026'!$A$5:$A$428
Name PN_SINO: 'Catalogos_PDN'!$AE$5:$AE$6
Name PN_TIPO: 'Catalogos_PDN'!$AG$5:$AG$15
Name PN_UNIDAD: 'Catalogos_PDN'!$AA$5:$AA$7
Name PN_FECHA: 'Catalogos_PDN'!$AN$8
Name PN_SMMLV: 'Catalogos_PDN'!$AN$7
Name PN_TOPE_MENOR: 'Catalogos_PDN'!$AN$5
Name PN_TOPE_MINIMA: 'Catalogos_PDN'!$AN$6

Sheet Instructivo_PlanAcción
A1: Plantilla Plan de Acción 2027, instructivo unificado
A2: Escuela Tecnológica Instituto Técnico Central, Oficina Asesora de Planeación. Libro único de consulta y formulación del Plan de Acción y del Plan de Necesidades 2027. Las celdas amarillas son las únicas que se diligencian; el resto del libro está protegido.
A4: 1. Para qué sirve este libro
A5: Este libro reúne en un solo archivo todo lo que una dependencia o un área funcional necesita para formular su aporte a la vigencia 2027. Aquí encuentra la propuesta del Plan de Acción que preparó la Oficina Asesora de Planeación, las acciones y actividades sugeridas para cada meta del Plan de Desarrollo Institucional (PDI) 2025 a 2032, el espacio para formular sus propias acciones, la hoja de importación que luego se carga en el SUIE y el formato del Plan de Necesidades.
A6: El libro se descarga desde el aplicativo de la Jornada de Planeación. Una vez diligenciado, el área carga su formulación en el SUIE, porque ese cargue es el insumo con el que cada área trabajará durante la jornada del 18, 19 y 20 de noviembre de 2026. Sin ese insumo el área no podrá avanzar en los talleres.
A8: 2. La ruta en cinco pasos
A9: Paso | B9: Qué hace el área | D9: Dónde
A10: 1 | B10: Ubica su área y revisa las metas que le corresponden, lo que se espera de ella en 2027 y sus compromisos pendientes de 2026. | D10: Buscador_Formulación PAA 2027
A11: 2 | B11: Lee cada meta en el Plan de Acción propuesto: qué cambia frente a 2026, las acciones sugeridas, las actividades que las componen y cómo se genera el impacto. | D11: Plan_Acción_2027 y Acciones_2027
A12: 3 | B12: Formula sus acciones, una por fila, en las columnas amarillas de la meta que le fue asignada. | D12: Formulación_Ejes_2027
A13: 4 | B13: Copia cada acción formulada en la hoja de importación, que es la que se carga en el SUIE. | D13: Importación_FormulaciónPAA2027
A14: 5 | B14: Registra los bienes, obras y servicios que cada acción requiere contratar. | D14: PlandeNecesidades
A16: Ir al Buscador para empezar
A18: 3. Cómo está organizado el Plan de Acción
A19: El PDI 2025 a 2032 se organiza en seis ejes estratégicos, veinticuatro líneas de acción y cuarenta y cinco metas estratégicas con horizonte 2032. Cada meta tiene un código de cuatro niveles que se lee de izquierda a derecha: eje, línea, objetivo estratégico y meta. Así, la meta 1.1.1.1 es la primera meta del primer objetivo de la línea 1.1 (Ampliación de cobertura) del eje 1 (Formación y pedagogía de calidad).
A20: El Plan de Acción es la forma como la Escuela convierte el PDI en trabajo de un año. Para cada meta se fija una meta institucional 2027, se definen las acciones que la harán posible y se nombran las áreas responsables. En 2027 la estructura conserva los seis ejes del PDI y se organiza así:
A21: Eje estratégico | B21: Metas | C21: Acciones propuestas | D21: Actividades propuestas
A22: 1. Formación y pedagogía de calidad | B22: 8 | C22: 13 | D22: 32
A23: 2. Investigación y producción técnico científica | B23: 7 | C23: 8 | D23: 18
A24: 3. Extensión y proyección institucional | B24: 8 | C24: 9 | D24: 25
A25: 4. Transformación institucional | B25: 12 | C25: 16 | D25: 38
A26: 5. Ampliación y modernización de la infraestructura | B26: 6 | C26: 8 | D26: 21
A27: 6. Cuidado por el bienestar y la vida | B27: 4 | C27: 8 | D27: 24
A28: Total | B28: 45 | C28: 62 | D28: 158
A31: 4. Qué cambió de 2026 a 2027
A32: La propuesta 2027 revisó una por una las metas del aplicativo 2026 contra el texto del PDI, la Matriz Plurianual de Inversiones y los informes de gestión. El resultado de esa revisión se resume en la columna «Ajuste 2027» de la hoja Plan_Acción_2027, con la explicación en la columna «Qué cambia frente a 2026».
A33: Tipo de ajuste | B33: Metas | D33: Qué significa
A34: Se mantiene | B34: 19 | D34: El enunciado y el sentido de la meta no cambian; puede ajustarse su indicador o su meta anual.
A35: Se corrige | B35: 15 | D35: Se corrige un error del aplicativo 2026: un código mal formado, un enunciado distinto al del PDI o una meta duplicada.
A36: Se reincorpora | B36: 6 | D36: La meta existe en el PDI pero no estaba en el aplicativo 2026 o no tuvo productos; vuelve al plan.
A37: Se reformula | B37: 3 | D37: La meta se cumplió como hito y en 2027 pasa a mantener o consolidar lo logrado.
A38: Se reorienta | B38: 2 | D38: La meta se cumple por un camino distinto al previsto, sin cambiar el texto del PDI hasta su revisión.
A40: Además de esos ajustes, la versión 2027 introduce tres cambios de fondo. Primero, las 158 tareas que antes se presentaban como acciones se agruparon en 62 acciones, cada una con varias actividades que la componen, porque una acción es un resultado que se logra con un conjunto de actividades y no una tarea suelta. Segundo, cada meta explica de forma explícita cómo se genera su impacto, siguiendo la Guía Metodológica para la Evaluación de Impacto Institucional. Tercero, se reincorporaron líneas que en 2026 no tuvieron productos, como la 5.3 de sedes de terceros y la 6.1 de condiciones para el bienestar, esta última con los componentes de cultura ambiental y gestión energética que decidió el Comité Institucional de Gestión y Desempeño.
A42: 5. Acción, actividad y producto: la diferencia que más importa
A43: La confusión más frecuente en la formulación es presentar una tarea como si fuera una acción. La regla es sencilla: la acción dice qué resultado va a lograr el área; las actividades dicen cómo lo va a lograr; los productos son la evidencia que queda de cada actividad.
A44: Concepto | B44: Qué es | C44: Cómo se redacta | D44: Ejemplo
A45: Acción | B45: Un resultado de mediano alcance que aporta directamente a la meta del PDI y que se logra con varias actividades a lo largo del año. | C45: Verbo en infinitivo, objeto y propósito. Debe poder responder a la pregunta: ¿qué cambia en la Escuela cuando esto se cumple? | D45: Mejorar los resultados de las pruebas Saber PRO y TyT a partir del análisis por programa y competencia, con estrategias de preparación cuyo efecto se evalúa.
A46: Actividad | B46: Cada uno de los pasos que, sumados, producen la acción. Por sí sola no transforma nada. | C46: Verbo en infinitivo y objeto concreto, con un producto verificable. | D46: Aplicar simulacros de las pruebas Saber PRO en los programas tecnológicos.
A47: Producto | B47: El bien o servicio que queda como evidencia de la actividad. | C47: Sustantivo verificable. | D47: Plan de preparación y simulacros aplicados.
A48: Tarea operativa | B48: Algo que el área hace de manera rutinaria. No se formula como acción. | C48: No se formula. | D48: Enviar correos, asistir a reuniones, elaborar un acta.
A50: Antes de escribir una acción, hágase cuatro preguntas. ¿Aporta de manera directa a una meta del PDI? ¿Necesita varias actividades para lograrse? ¿Deja productos que otra persona puede verificar? ¿Se puede decir qué cambia cuando termina? Si alguna respuesta es no, probablemente está frente a una actividad o una tarea.
A52: 6. Cómo se genera el impacto, explicado paso a paso
A53: La Guía Metodológica para la Evaluación de Impacto Institucional de la ETITC (versión 2 de 2026) explica que el impacto no es lo que la Escuela hace ni lo que entrega, sino la transformación que esas entregas producen en las personas, en la Institución o en el territorio. Para entenderlo, la guía usa la cadena de valor, que funciona como una escalera de cinco peldaños: cada peldaño se apoya en el anterior.
A54: Peldaño de la cadena de valor | B54: Pregunta que responde | D54: Ejemplo con la meta de bienestar 6.2.1.1
A55: 1. Insumos o capacidades | B55: ¿Con qué contamos? | D55: Profesionales de bienestar, presupuesto, sistema de alertas académicas.
A56: 2. Procesos o actividades | B56: ¿Qué hacemos? | D56: Identificar las causas de cancelación y acompañar a los estudiantes en riesgo.
A57: 3. Productos | B57: ¿Qué entregamos? | D57: Programa de permanencia adoptado y estudiantes atendidos.
A58: 4. Resultados | B58: ¿Qué cambia pronto, en el corto y mediano plazo? | D58: Menos estudiantes cancelan su semestre.
A59: 5. Impactos | B59: ¿Qué se transforma de manera sostenible y se le puede atribuir a la Escuela? | D59: La deserción baja y más estudiantes terminan su carrera, lo que mejora sus condiciones de vida.
A61: Dicho de manera sencilla: si la Escuela hace bien sus actividades, entrega productos; si esos productos sirven, producen resultados; y si esos resultados se sostienen en el tiempo y se pueden atribuir a la Escuela, hay impacto. Los tres primeros peldaños se controlan con el seguimiento del Plan de Acción; los dos últimos se demuestran con la evaluación de impacto.
A62: Para saber si hubo impacto, la guía pide tres cosas: una línea base, que es la situación antes de la intervención; una medición posterior con el mismo indicador; y un análisis que permita atribuir razonablemente el cambio a la acción institucional y no a factores externos como el mercado laboral o la economía. Si no se puede explicar cómo se estimó el cambio atribuible, no hay evaluación de impacto sino seguimiento.
A63: La Escuela clasifica sus impactos en diez categorías, cada una de tipo interno, externo o ambos, y los agrupa en cuatro dimensiones: académica, egresados, sector productivo y valor público.
A64: Categoría de impacto de la Guía | B64: Tipo de impacto
A65: Contribución al desarrollo social y comunitario, económico, sostenibilidad ambiental, sector educativo, sector productivo e industrial, desarrollo tecnológico, nacional e internacional | B65: Externo
A66: Cambios curriculares y en los programas académicos | B66: Interno
A67: Aporte al mejoramiento de los programas académicos, la construcción de comunidad académica, los resultados académicos y las prácticas docentes | B67: Interno
A68: Transformaciones de vidas (condiciones de vida y movilidad social) de las personas con las que se interactúa | B68: Interno y externo
A69: Transformaciones del territorio (condiciones del desarrollo, especialmente de cobertura y pertinencia en la oferta educativa) | B69: Externo
A70: Cambios en la cultura institucional, incluida la cultura de la calidad | B70: Interno
A71: Impacto a actores (estudiantes, docentes, administrativos, egresados) y organizaciones (sector externo y sociedad en general) en valores | B71: Externo
A72: Impacto en las labores sustantivas: docencia y formación, investigación e innovación, extensión y proyección social | B72: Interno
A73: Cambios en la formación integral y los aprendizajes del estudiantado | B73: Interno
A74: Contribución a la solución de problemas del contexto y la creación de nuevo conocimiento | B74: Externo
A76: En la hoja Plan_Acción_2027, cada meta trae este razonamiento ya resuelto. La columna «Cómo se genera el impacto» recorre la cadena para esa meta: lo que hacemos, lo que entregamos, lo que cambia pronto y la transformación que buscamos. La columna «Cómo sabremos que hubo impacto» dice qué señal concreta lo demostraría y con qué indicador de la guía se mide.
A77: Contenido de valor agregado elaborado por Fabián Ospina, profesional de Plan de Acción de la Oficina Asesora de Planeación, a partir de la Guía Metodológica para la Evaluación de Impacto Institucional y de lo tratado en el comité institucional con la doctora María Claudia Aponte González, a quien se remite para su revisión.
A79: 7. Las hojas del libro
A80: Hoja | B80: Para qué sirve | D80: Quién la diligencia
A81: Instructivo_PlanAcción | B81: Esta hoja. Explica la ruta, los conceptos y el seguimiento. | D81: Nadie: es de consulta.
A82: Instructivo_PlanNecesidades | B82: Explica cómo formular el Plan de Necesidades y cómo buscar el código UNSPSC. | D82: Nadie: es de consulta.
A83: Plan_Acción_2027 | B83: La propuesta meta por meta: estructura del PDI, ajuste 2027, metas, acciones, actividades, impacto y ruta de seguimiento. | D83: Nadie: es de consulta.
A84: Acciones_2027 | B84: El detalle de las 158 actividades propuestas, con la acción a la que pertenecen, el área y el producto esperado. Las columnas amarillas permiten que el área valide cada actividad. | D84: El área, en las columnas amarillas.
A85: Formulación_Ejes_2027 | B85: Las metas asignadas a cada área en los seis ejes. Aquí el área formula sus acciones con producto, fechas, responsable e indicadores. | D85: El área, en las columnas amarillas de sus filas.
A86: Buscador_Formulación PAA 2027 | B86: Al elegir el área muestra sus metas, su aporte esperado, sus compromisos 2026 y permite formular acciones adicionales. | D86: El área, en la celda C4 y en las filas de acciones adicionales.
A87: Importación_FormulaciónPAA2027 | B87: El formato que se carga en el SUIE. Una fila por acción. | D87: El área.
A88: PlandeNecesidades | B88: Los bienes, obras y servicios que cada acción requiere contratar, con su código UNSPSC. | D88: El área, en las columnas amarillas.
A90: Ver el Plan de Acción propuesto
A91: Ver las actividades por acción
A92: Ir a la formulación por ejes
A93: Ir a la hoja de importación al SUIE
A94: Ir al Plan de Necesidades
A96: 8. Cómo diligenciar la formulación por ejes
A97: En la hoja Formulación_Ejes_2027 cada bloque de color corresponde a un eje y cada fila a una meta asignada a un área. Busque las filas de su área (columna J) y diligencie las columnas amarillas en este orden: nombre de la acción, descripción de la acción y actividades que la componen, producto esperado, fechas de inicio y fin dentro de 2027, correo institucional del responsable, indicador de seguimiento, meta 2027 de la acción, unidad de medida, dimensión e indicador de impacto, si retoma un compromiso de 2026 y la evidencia verificable. La columna «Alerta de consistencia» revisa la fila y debe decir OK.
A98: Si el área necesita formular más de una acción para la misma meta, use las filas de acciones adicionales del Buscador. Escriba el nombre de la acción como un resultado y relacione las actividades en la descripción, tal como aparece en la hoja Plan_Acción_2027.
A100: 9. La hoja de importación al SUIE
A101: Esta es la hoja más importante del proceso, porque es la que el SUIE recibe. Cada fila es una acción. No se cambian los encabezados ni el nombre de las columnas. Antes del cargue, borre la fila de ejemplo.
A102: Columna | B102: Qué se escribe | D102: Ejemplo
A103: Código de meta | B103: El código exacto de la meta del PDI, con sus cuatro niveles. Si la acción no pertenece a una meta, se deja vacío y el SUIE la crea como acción independiente. | D103: 6.2.1.1
A104: Nombre de la acción | B104: La acción formulada como resultado, igual a como quedó en la hoja de formulación. Es obligatorio. | D104: Proteger la permanencia estudiantil con un programa basado en las causas de cancelación
A105: Descripción | B105: Qué se hará y cuáles actividades componen la acción. | D105: Incluye el análisis de causas de cancelación, la adopción del programa y el seguimiento a los estudiantes atendidos.
A106: Origen | B106: PDI si la acción tiene meta. Mejora u Otra si no la tiene. Es obligatorio. | D106: PDI
A107: Área | B107: El área responsable, elegida de la lista. | D107: Despacho de bienestar
A108: Responsable | B108: El correo institucional del responsable, elegido de la lista. | D108: planeacion@itc.edu.co
A109: Vigencia | B109: El año de la acción. Es obligatorio. | D109: 2027
A110: Código de la acción | B110: Opcional. Sirve para volver a cargar el archivo sin duplicar. Se recomienda usar el código de la acción propuesta. | D110: AC27.61
A112: Para cargar: guarde una copia del libro, deje en ella solo la hoja de importación con el nombre que exige el SUIE (IMPORTACIÓN) y súbala por la opción de importación de acciones del SUIE. Esta importación crea únicamente acciones; los productos y el Plan de Necesidades se gestionan en sus propias pantallas.
A113: El SUIE debe tener habilitada la vigencia 2027 y el catálogo de metas 2027 antes del cargue. Las listas de la hoja de importación son las que entrega el SUIE.
A115: 10. Reglas de calidad y convenciones
A116: Las fechas van dentro de 2027 y la de fin no puede ser anterior a la de inicio. El responsable se identifica con su correo institucional terminado en @itc.edu.co, sin tildes ni espacios. Cada acción tiene al menos un producto verificable y un indicador de seguimiento con su meta. Gris significa información de la Oficina Asesora de Planeación o calculada; amarillo, celdas para diligenciar; verde claro, ajustes de la propuesta 2027. La expresión «Sugerida por la OAP» señala una meta 2027 que ningún documento fijaba y que la Oficina propone con su lógica de cálculo.
A118: 11. Cómo se hará el seguimiento
A119: Cada trimestre el área reporta en el SUIE el avance de sus actividades y productos con su evidencia. La Oficina Asesora de Planeación verifica que los productos sean pertinentes, consolida el avance de cada acción y de cada meta en el informe trimestral del Plan de Acción y lo presenta al Comité Institucional de Gestión y Desempeño. Al cierre de la vigencia se compara el indicador de cada meta con su línea base. Para las metas con estudio de impacto se aplica la ruta de la guía: pregunta de evaluación, línea base, medición posterior y análisis de atribución.
...

Sheet Instructivo_PlanNecesidades
A1: Instructivo de formulación del Plan de Necesidades 2027
A2: Escuela Tecnológica Instituto Técnico Central, Oficina Asesora de Planeación. Complemento del Plan de Acción 2027: aquí el área dice qué necesita contratar para cumplir las acciones que formuló.
A3: Ir a la hoja PlandeNecesidades para formular
A5: 1. Propósito
A6: Con este formato cada dependencia y área funcional registra los bienes, obras y servicios que necesita contratar en 2027 para ejecutar las acciones de su Plan de Acción. En el Plan de Acción el área dice qué va a hacer; en el Plan de Necesidades dice qué necesita adquirir para hacerlo. Cada necesidad se vincula a una acción del Plan de Acción 2027 y, por medio de ella, a una meta del PDI, de modo que ningún recurso se programe sin una meta que lo justifique. La Oficina Asesora de Planeación consolida las necesidades y las entrega como insumo del Plan Anual de Adquisiciones que la Escuela publica en SECOP II.
A7: Para no confundir siglas, en este libro PAA significa Plan de Acción Anual. El Plan Anual de Adquisiciones se escribe siempre completo.
A9: 2. Marco normativo
A10: Ley 80 de 1993 y Ley 1150 de 2007, que regulan la contratación pública y sus modalidades de selección. Ley 1474 de 2011, artículo 74, que obliga a publicar a más tardar el 31 de enero de cada año el plan de acción, el presupuesto y el plan general de compras. Decreto 1082 de 2015, artículos 2.2.1.1.1.4.1 a 2.2.1.1.1.4.4, que establece que el Plan Anual de Adquisiciones lista los bienes, obras y servicios identificados con el Clasificador de Bienes y Servicios de las Naciones Unidas (UNSPSC), con su valor estimado, fuente de recursos, modalidad de selección y fecha aproximada de inicio, y que se publica en la página web y en SECOP. Decreto 111 de 1996, según el cual ninguna necesidad se contrata sin certificado de disponibilidad presupuestal.
A12: 3. Lo que dice Colombia Compra Eficiente
A13: Colombia Compra Eficiente es la agencia nacional que define las reglas y herramientas de la compra pública. Su guía para elaborar el Plan Anual de Adquisiciones y su guía de codificación de bienes y servicios coinciden en cuatro mensajes para las entidades. Primero, el Plan Anual de Adquisiciones es un instrumento de planeación que permite a la entidad identificar, registrar, programar y divulgar sus necesidades, y a los proveedores conocer con anticipación lo que la entidad va a comprar. Segundo, cada necesidad debe identificarse con el código del Clasificador de Bienes y Servicios, porque ese código es el mismo que usan el SECOP, los estudios previos, los pliegos y el Registro Único de Proponentes. Tercero, el plan no obliga a la entidad a adquirir lo que registra, pero sí debe actualizarse por lo menos una vez al año y cada vez que cambien las necesidades. Cuarto, la entidad debe codificar con el mayor nivel de detalle posible, de preferencia en el nivel de producto.
A14: La versión del clasificador que Colombia Compra Eficiente tiene implementada es la UNSPSC UNv260801, traducida al español. Cuando un bien o servicio no tiene código en el clasificador, Colombia Compra Eficiente puede definir códigos adicionales a solicitud de la entidad y los publica de manera periódica. Antes de cada vigencia conviene verificar en el sitio oficial cuál es la versión vigente.
A16: 4. Qué es el código UNSPSC
A17: El UNSPSC (Código Estándar de Productos y Servicios de las Naciones Unidas) es un catálogo que asigna a cada bien o servicio un número de ocho dígitos. El número se lee por pares: los dos primeros indican el segmento, los dos siguientes la familia, los dos siguientes la clase y los dos últimos el producto. Mientras más dígitos distintos de cero tenga el código, más preciso es.
A18: Nivel | B18: Dígitos que lo identifican | C18: Ejemplo | D18: ¿Sirve para el Plan de Necesidades?
A19: Segmento | B19: Los dos primeros | C19: 80000000, servicios de gestión, servicios profesionales de empresa y servicios administrativos | D19: No: es demasiado general.
A20: Familia | B20: Los cuatro primeros | C20: 80110000, servicios de recursos humanos | D20: No: sigue siendo general.
A21: Clase | B21: Los seis primeros; termina en 00 | C21: 80111600, servicios de personal temporal | D21: Sí, cuando no existe un producto exacto.
A22: Producto | B22: Los ocho dígitos | C22: 80111601, asistencia de oficina o administrativa temporal | D22: Sí, y es el nivel preferido.
A25: 5. Paso a paso para encontrar el código en el clasificador de Colombia Compra Eficiente
A26: Abrir el clasificador de bienes y servicios de Colombia Compra Eficiente
A27: Paso | B27: Qué hacer
A28: 1 | B28: Abra el clasificador en el enlace anterior: https://operaciones.colombiacompra.gov.co/clasificador-de-bienes-y-servicios
A29: 2 | B29: Escriba en pocas palabras qué necesita, sin artículos ni adjetivos. Por ejemplo: computador portátil, servicios de aseo, mantenimiento de ascensores. Piense en el bien o servicio, no en la acción del Plan de Acción.
A30: 3 | B30: Use el buscador por palabra clave. Si conoce un código parecido, por ejemplo uno que la Escuela usó en 2026, búsquelo por código.
A31: 4 | B31: Si prefiere navegar, baje por los niveles en orden: grupo, segmento, familia, clase y producto. Cada nivel abre las opciones del siguiente.
A32: 5 | B32: Elija el resultado cuya denominación describa mejor el objeto. Al seleccionarlo, el clasificador muestra su segmento, familia, clase y producto con el código y el nombre.
A33: 6 | B33: Prefiera el nivel de producto (ocho dígitos sin ceros al final). Si el objeto agrupa varios productos de la misma clase, use la clase (termina en 00).
A34: 7 | B34: Copie el código y péguelo en la columna M de la hoja PlandeNecesidades como número, sin espacios ni puntos. Si el objeto requiere otros códigos, regístrelos en la columna N separados por punto y coma.
A35: 8 | B35: Revise que la alerta de consistencia de la fila no indique «Código UNSPSC inválido» ni «UNSPSC a nivel de segmento o familia».
A37: En la parte final de la página del clasificador se descargan la guía de codificación y la traducción al español del clasificador completo, útiles cuando se necesita buscar sin conexión.
A38: Error frecuente de 2026 | B38: Cómo evitarlo
A39: Código vacío o escrito como texto | B39: Registre siempre ocho dígitos, como número.
A40: Varios códigos en una misma celda | B40: Un código principal en la columna M y los demás en la columna N.
A41: Código a nivel de segmento o familia | B41: Baje al menos hasta la clase.
A42: Código copiado de otra necesidad sin verificar | B42: Confirme que la denominación del código describa su objeto.
A45: 6. Cómo se relaciona una necesidad con el Plan de Acción
A46: Toda necesidad sirve a una acción. Primero se formula la acción y después se registra lo que ella requiere contratar. La lista de la columna H muestra solo las acciones de la meta elegida en la columna E. Si la necesidad sirve a una acción que el área formuló por su cuenta, elija PROPIA y escriba en la columna I el nombre de la acción tal como quedó en la formulación.
A47: Acción del Plan de Acción | B47: Necesidad bien relacionada | D47: Por qué está bien
A48: AC27.19 Convertir los desarrollos de la Escuela en propiedad intelectual protegida | B48: Prestar servicios profesionales de asesoría en propiedad industrial para la redacción y radicación de dos solicitudes de patente ante la SIC | D48: Sin esa asesoría no se obtiene el producto de la acción: las solicitudes radicadas.
A49: AC27.51 Renovar el parque de computadores de apoyo académico | B49: Adquirir 240 computadores de escritorio para las salas de sistemas | D49: El bien es el producto mismo de la actividad de reposición.
A50: AC27.59 Reducir el consumo de energía y agua con medidas de bajo costo | B50: Adquirir e instalar sensores de ocupación e iluminación LED en los bloques F, G y H | D50: La compra permite la medida de ahorro que la acción promete.
A53: 7. Cómo diligenciar la hoja PlandeNecesidades
A54: Paso | B54: Qué hacer
A55: 1 | B55: Tenga a mano su formulación del Plan de Acción: cada necesidad debe servir a una acción que ya formuló.
A56: 2 | B56: En una fila libre seleccione su área (columna B). La dependencia y el proceso aparecen solos.
A57: 3 | B57: Seleccione la meta del PDI (columna E). El eje y la línea aparecen solos.
A58: 4 | B58: Seleccione la acción del Plan de Acción 2027 (columna H) o PROPIA, y en ese caso escriba su nombre en la columna I.
A59: 5 | B59: Describa la necesidad: tipo (J), justificación (K) y objeto contractual (L). Un objeto por fila.
A60: 6 | B60: Registre el código UNSPSC (M y, si aplica, N) siguiendo el paso a paso del numeral 5.
A61: 7 | B61: Diligencie los datos para el Plan Anual de Adquisiciones (O a AA): meses estimados, duración, modalidad, fuente, tipo de gasto, valores y vigencias futuras.
A62: 8 | B62: Registre el responsable (AB a AE) y la continuidad de 2026 y la prioridad (AF a AI).
A63: 9 | B63: Verifique que la columna AJ, «Alerta de consistencia», diga OK en todas sus filas.
A66: 8. Diccionario de campos
A67: Columna | B67: Campo | C67: Qué registrar | D67: Obligatorio
A68: A | B68: N.° de necesidad | C68: Automático. Identifica la necesidad en toda la cadena. | D68: Automático
A69: B | B69: Área funcional que formula | C69: Una de las 47 áreas de la lista. | D69: Sí
A70: C y D | B70: Dependencia y proceso | C70: Automáticos. | D70: Automático
A71: E | B71: Meta estratégica del PDI | C71: La meta a la que aporta la acción que requiere la necesidad. | D71: Sí
A72: F y G | B72: Eje y línea | C72: Automáticos a partir de la meta. | D72: Automático
A73: H | B73: Acción del Plan de Acción 2027 | C73: La acción de la lista, filtrada por la meta, o PROPIA. | D73: Sí
A74: I | B74: Nombre de la acción propia | C74: Solo si eligió PROPIA. | D74: Condicional
A75: J | B75: Tipo de necesidad | C75: Servicios profesionales, apoyo a la gestión, bienes, suministro, mantenimiento, obra, consultoría, interventoría, licencias, arrendamiento u otro. | D75: Sí
A76: K | B76: Justificación | C76: Qué problema resuelve y qué producto de la acción no podría lograrse sin ella. Es la base de los estudios previos. | D76: Sí
A77: L | B77: Objeto contractual | C77: Qué se va a adquirir o contratar y para qué. | D77: Sí
A78: M | B78: Código UNSPSC principal | C78: Ocho dígitos, como número, en nivel de clase o de producto. | D78: Sí
... A91: AJ | B91: Alerta de consistencia | C91: Automática. Debe decir OK. | D91: Automático
A94: 9. Reglas de calidad
A95: Una necesidad por fila y un objeto por necesidad. Toda necesidad sirve a una acción del Plan de Acción 2027. El código UNSPSC se registra como número de ocho dígitos. Los valores se registran en pesos colombianos, sin puntos, signos ni texto. Si el contrato se paga en más de una vigencia, se marcan las vigencias futuras y su estado. El responsable se identifica con correo institucional sin tildes ni espacios. No se registra como necesidad lo que el área ejecuta con su propio personal de planta.
A96: Lo que aprendimos de 2026: hubo 207 valores escritos como texto, 43 códigos UNSPSC vacíos o múltiples en una celda, 23 formas distintas de escribir la modalidad, 41 necesidades marcadas como mínima cuantía por encima del tope y 42 registros sin correo del responsable. Este formato previene cada uno de esos errores con listas desplegables y con la alerta de consistencia.
A98: 10. Del Plan de Necesidades al Plan Anual de Adquisiciones
A99: Etapa | B99: Qué ocurre | D99: Responsable
A100: 1 | B100: El área formula sus acciones 2027. | D100: Área funcional
A101: 2 | B101: El área registra cada bien, obra o servicio que requieren esas acciones. | D101: Área funcional
A102: 3 | B102: Se revisa la consistencia: alineación con la meta y la acción, alertas y comparación con 2026. | D102: Oficina Asesora de Planeación
A103: 4 | B103: Se confirman la fuente, el rubro y la viabilidad de las vigencias futuras. | D103: Vicerrectoría Administrativa y Financiera
A104: 5 | B104: Se agrupan necesidades iguales, se confirma la modalidad y se convierte el consolidado al formato de cargue de SECOP II. | D104: GIT de Contratación y Adquisiciones
A105: 6 | B105: Se aprueba y se publica el Plan Anual de Adquisiciones a más tardar el 31 de enero de 2027. | D105: Instancia de aprobación institucional
A106: 7 | B106: Toda necesidad nueva o modificada se tramita como actualización del plan durante 2027. | D106: GIT de Contratación y Adquisiciones
A108: Volver a la hoja PlandeNecesidades

Sheet Plan_Acción_2027
A1: ESTRUCTURA DEL PDI 2025 A 2032 | F1: FORMULACIÓN 2027 | Q1: IMPACTO SEGÚN LA GUÍA METODOLÓGICA PARA LA EVALUACIÓN DE IMPACTO INSTITUCIONAL | V1: SEGUIMIENTO
A2: EJE ESTRATÉGICO | B2: OBJETIVO ESTRATÉGICO DEL EJE | C2: LÍNEA DE ACCIÓN | D2: OBJETIVO ESTRATÉGICO | E2: META ESTRATÉGICA (PDI 2032) | F2: AJUSTE 2027 | G2: QUÉ CAMBIA FRENTE A 2026 | H2: INDICADOR DE LA META | I2: LÍNEA BASE | J2: META 2032 | K2: META 2027 | L2: FUENTE DE LA META 2027 | M2: ACCIONES 2027 (RESULTADOS QUE SE BUSCAN) | N2: ACTIVIDADES QUE COMPONEN CADA ACCIÓN Y SU PRODUCTO | O2: ÁREAS RESPONSABLES | P2: PRESUPUESTO 2027 (millones de pesos) | Q2: DIMENSIÓN DE IMPACTO | R2: CATEGORÍA DE IMPACTO (GUÍA METODOLÓGICA) | S2: INDICADOR DE IMPACTO (GUÍA METODOLÓGICA) | T2: CÓMO SE GENERA EL IMPACTO (CADENA DE VALOR) | U2: CÓMO SABREMOS QUE HUBO IMPACTO | V2: N.° DE ACCIONES | W2: N.° DE ACTIVIDADES | X2: RUTA DE ALINEACIÓN Y SEGUIMIENTO | Y2: ALERTAS PARA LA REVISIÓN
A3: 1. Formación y pedagogía de calidad | B3: 1. Consolidar a la ETITC como un referente educativo de excelencia, ampliando su oferta académica y garantizando la calidad en todos sus programas mediante una actualización continua y una estrecha vinculación con el entorno. | C3: 1.1 Ampliación de cobertura | D3: 1.1.1. Ampliar la cobertura de estudiantes en los programas de educación superior, asegurando el acceso equitativo y la calidad académica. | E3: 1.1.1.1. Contar con 11.000 estudiantes vinculados a programas de educación superior al 2032. | F3: Se mantiene | G3: Se mantiene el enunciado. Se agrega el crecimiento neto de primer curso (método MEN) como indicador de gestión y se suman las cohortes territoriales y la oferta híbrida y virtual (ver 1.4.1.1). | H3: N.° de estudiantes matriculados en programas de educación superior (SNIES) | I3: 3.925 estudiantes (2024, MPI, columna «Línea base 2024»); 4.219 matriculados en primer semestre de 2026 (Proyecciones de matrícula) | J3: 11.000 estudiantes | K3: 5.400 estudiantes | L3: MPI (meta 2027) y Proyecciones de matrícula 2020 a 2035 (columna Meta). Los programas nuevos aportan entre 650 (primer semestre de 2027) y 883 (segundo semestre de 2027) estudiantes según la misma proyección. | M3: AC27.01. Fortalecer la medición de la cobertura y de sus efectos, de modo que la Escuela sepa cuántos estudiantes nuevos gana cada año y qué pasa con ellos al egresar. AC27.02. Orientar la admisión 2027 hacia los programas con mayor demanda, con un calendario de admisiones armonizado con los recursos que asigna el Ministerio de Educación. AC27.03. Ampliar la cobertura en los territorios con cohortes nuevas en La Primavera (Vichada) y en Zipaquirá. | N3: AC27.01, actividades: 1. Adoptar el crecimiento neto de primer curso como indicador de meta, junto con nuevos atendidos (A27-001). Producto: ficha del indicador y serie SNIES por programa. 2. Iniciar el estudio de impacto de Egresados (A27-006). Producto: diseño del estudio aprobado. AC27.02, actividades: 1. Armonizar el calendario de admisiones con la asignación de recursos del MEN (A27-002). Producto: calendario de admisiones armonizado. 2. Concentrar cupos en programas con demanda creciente y revisar la oferta de programas en descenso (A27-003). Producto: informe de oferta y demanda por programa 2027. AC27.03, actividades: 1. Ejecutar la cohorte primer semestre de 2027 en La Primavera (Vichada) con 80 cupos adicionales (A27-004). Producto: matrícula de la cohorte en SNIES y acto del Consejo Directivo. 2. Ofertar y matricular en Zipaquirá bajo lugares de desarrollo transitorios (A27-005). Producto: matrícula por lugar de desarrollo en SNIES. | O3: Planeación y Plan de Acción (101) Egresados y Bolsa de Empleo (141) GIT Registro, Control y Admisiones (126) Despacho de la Vicerrectoría Académica (120) Sedes Tintal / Soacha-UPK / Viotá (120) | P3: A27-004: 295,8 (Res. MEN 019862) | Q3: Valor Público | R3: Transformaciones del territorio (condiciones del desarrollo, especialmente de cobertura y pertinencia en la oferta educativa). | S3: Porcentaje de jóvenes de la comunidad beneficiaria que se escolarizaron con la Institución. Proporción de programas académicos pertinentes (alineados con necesidades y vocación del territorio) ofrecidos por la Institución en el territorio. | T3: 1. Lo que hacemos: 3 acciones con 6 actividades (columnas M y N). 2. Lo que entregamos (productos): ficha del indicador y serie SNIES por programa; diseño del estudio aprobado; calendario de admisiones armonizado; informe de oferta y demanda por programa 2027; matrícula de la cohorte en SNIES y acto del Consejo Directivo; matrícula por lugar de desarrollo en SNIES. 3. Lo que cambia pronto (resultado): crece la matrícula de primer curso en Bogotá y en los territorios, y los cupos se concentran en programas con demanda. 4. La transformación que buscamos (impacto): más jóvenes de Bogotá y de regiones con poca oferta pública acceden y permanecen en educación superior pertinente con la vocación productiva de su territorio. 5. Tipo de impacto según la guía: externo. | U3: El porcentaje de jóvenes de las comunidades atendidas que se escolarizan con la Escuela sube frente a la línea base de 2024, y la proporción de programas pertinentes ofrecidos en cada territorio aumenta. Indicador de la guía con que se mide: porcentaje de jóvenes de la comunidad beneficiaria que se escolarizaron con la Institución. Punto de comparación: la línea base de la meta (3.925 estudiantes (2024, MPI, columna «Línea base 2024»); 4.219 matriculados en primer semestre de 2026 (Proyecciones de matrícula)) y, cuando el estudio lo permita, un grupo de referencia que no recibió la intervención. | V3: 3 | W3: 6 | X3: Dónde se ubica: eje 1, Formación y pedagogía de calidad, línea 1.1 Ampliación de cobertura, meta 1.1.1.1 del PDI 2025 a 2032. Qué cambió frente a 2026: se mantiene. Se mantiene el enunciado. Se agrega el crecimiento neto de primer curso (método MEN) como indicador de gestión y se suman las cohortes territoriales y la oferta híbrida y virtual (ver 1.4.1.1). Cómo se mide la meta: N.° de estudiantes matriculados en programas de educación superior (SNIES). Línea base: 3.925 estudiantes (2024, MPI, columna «Línea base 2024»); 4.219 matriculados en primer semestre de 2026 (Proyecciones de matrícula). Meta 2027: 5.400 estudiantes. Cómo se mide el impacto: porcentaje de jóvenes de la comunidad beneficiaria que se escolarizaron con la Institución. El indicador sale de la Guía Metodológica para la Evaluación de Impacto Institucional y se lee frente a la línea base. Qué esperamos obtener: más jóvenes de Bogotá y de regiones con poca oferta pública acceden y permanecen en educación superior pertinente con la vocación productiva de su territorio. Cómo se hace el seguimiento: cada trimestre las áreas reportan en el SUIE el avance de las actividades con su evidencia; la Oficina Asesora de Planeación verifica la pertinencia de los productos, consolida el avance de las acciones y de la meta y lo presenta al Comité Institucional de Gestión y Desempeño. Al cierre de 2027 se compara el indicador de la meta con su línea base. | Y3: El texto del PDI (pág. 39) habla de 12.000 estudiantes; la tabla de metas y la MPI, de 11.000. La proyección de matrícula llega a 9.675 en segundo semestre de 2032, por debajo de la meta.
E4: 1.1.1.2. Lograr que el 30% de los estudiantes del IBTI pasen a la educación superior de la ETITC. | F4: Se mantiene | G4: Se unifica el enunciado (el aplicativo tenía dos textos con y sin tilde). | H4: N.° y % de egresados del IBTI matriculados en programas de la ETITC | I4: 31 estudiantes (2024, MPI, columna «Línea base 2024») | J4: 30% (MPI: 250 estudiantes en 2032) | K4: 40 estudiantes | L4: MPI | M4: AC27.04. Consolidar la ruta de tránsito del IBTI a la educación superior de la ETITC, desde la alineación curricular hasta el acompañamiento de la cohorte que ingresa. | N4: AC27.04, actividades: 1. Alinear los currículos del IBTI con los programas técnicos profesionales por ciclos propedéuticos (A27-007). Producto: currículos alineados (ver 4.2.1.3). 2. Implementar la ruta de admisión y tránsito del IBTI a la educación superior (A27-008). Producto: procedimiento adoptado y estudiantes admitidos. 3. Hacer seguimiento a la cohorte que transita y a su permanencia en el primer año (A27-009). Producto: informe de seguimiento de la cohorte. | O4: Despacho de la Vicerrectoría Académica (120) IBTI (124) GIT Registro, Control y Admisiones (126) | P4: Sin presupuesto registrado en la matriz plurianual | Q4: Valor Público | R4: Transformaciones del territorio (condiciones del desarrollo, especialmente de cobertura y pertinencia en la oferta educativa). Cambios curriculares y mejoramiento de programas | S4: Porcentaje de jóvenes de la comunidad beneficiaria que se escolarizaron con la Institución. Reducción en la tasa de deserción atribuible a la intervención. | T4: 1. Lo que hacemos: 1 acción con 3 actividades (columnas M y N). 2. Lo que entregamos (productos): currículos alineados (ver 4.2.1.3); procedimiento adoptado y estudiantes admitidos; informe de seguimiento de la cohorte. 3. Lo que cambia pronto (resultado): más bachilleres técnicos del IBTI ingresan a los programas técnicos profesionales de la ETITC y terminan su primer año. 4. La transformación que buscamos (impacto): la ruta IBTI y educación superior se vuelve una trayectoria continua que reduce la deserción y mejora las oportunidades de estos jóvenes. 5. Tipo de impacto según la guía: externo e interno. | U4: La tasa de tránsito del IBTI a la ETITC supera los 31 estudiantes de la línea base y la deserción de esa cohorte en primer año es menor que la del resto de estudiantes nuevos. Indicador de la guía con que se mide: porcentaje de jóvenes de la comunidad beneficiaria que se escolarizaron con la Institución. Punto de comparación: la línea base de la meta (31 estudiantes (2024, MPI, columna «Línea base 2024»)) y, cuando el estudio lo permita, un grupo de referencia que no recibió la intervención. | V4: 1 | W4: 3 | X4: Dónde se ubica: eje 1, Formación y pedagogía de calidad, línea 1.1 Ampliación de cobertura, meta 1.1.1.2 del PDI 2025 a 2032. Qué cambió frente a 2026: se mantiene. Se unifica el enunciado (el aplicativo tenía dos textos con y sin tilde). Cómo se mide la meta: N.° y % de egresados del IBTI matriculados en programas de la ETITC. Línea base: 31 estudiantes (2024, MPI, columna «Línea base 2024»). Meta 2027: 40 estudiantes. Cómo se mide el impacto: porcentaje de jóvenes de la comunidad beneficiaria que se escolarizaron con la Institución. El indicador sale de la Guía Metodológica para la Evaluación de Impacto Institucional y se lee frente a la línea base. Qué esperamos obtener: la ruta IBTI y educación superior se vuelve una trayectoria continua que reduce la deserción y mejora las oportunidades de estos jóvenes. Cómo se hace el seguimiento: cada trimestre las áreas reportan en el SUIE el avance de las actividades con su evidencia; la Oficina Asesora de Planeación verifica la pertinencia de los productos, consolida el avance de las acciones y de la meta y lo presenta al Comité Institucional de Gestión y Desempeño. Al cierre de 2027 se compara el indicador de la meta con su línea base. | Y4: El PDI expresa la meta en porcentaje y la MPI en número de estudiantes: reportar ambos.
C5: 1.2 Oferta educativa | D5: 1.2.1. Fortalecer la oferta educativa mediante la creación y consolidación de programas de pregrado y posgrado, así como la ETDH, con modalidades virtuales que respondan a las demandas del entorno actual. | E5: 1.2.1.1. Ofrecer programas de educación superior: 5 pregrados nuevos, 3 especializaciones y 3 maestrías. | F5: Se corrige | G5: Se retira la adición de «2 programas nuevos de doctorado», que no está en el PDI (salvo acto del Consejo Directivo). Se integran los programas de IA comprometidos. | H5: N.° de programas nuevos con registro calificado y ofertados, por nivel | I5: 15 pregrados y 3 posgrados (2024, MPI, columna «Línea base 2024»); en 2025 se recibieron 4 visitas de verificación para 10 programas nuevos en modalidad distancia (RC 2025) | J5: 5 pregrados, 3 especializaciones, 3 maestrías | K5: Pregrado: 3 documentos maestros, 2 programas con registro calificado y 2 ofertados desde el II semestre. Posgrado: 2 especializaciones y 2 maestrías ofertadas en el II semestre. | L5: MPI; Acuerdos 04, 07 y 08 de 2026 y Oficio del 10/03/2026 (programas de IA). | M5: AC27.05. Completar el diseño y la aprobación de la nueva oferta de pregrado, con énfasis en inteligencia artificial y ciencia de datos. AC27.06. Poner en marcha la nueva oferta en el segundo semestre de 2027, incluidos los posgrados y los programas que se desarrollarán en Zipaquirá. | N5: AC27.05, actividades: 1. Reprogramar los productos 2026 vencidos de la meta (38 al 2 de septiembre de 2026) (A27-010). Producto: productos reprogramados. 2. Elaborar los documentos maestros de 3 programas de pregrado (A27-011). Producto: documentos maestros. 3. Diseñar 4 programas nuevos de IA: Tecnología en Análisis y Modelado de Datos con IA, TP en Ciencia de Datos Aplicada a la IA, Especialización en Gestión de Proyectos de IA y Maestría en Ciencia de Datos (A27-012). Producto: planes de estudio y acuerdos. 4. Obtener registro calificado de Ingeniería en IA, Ingeniería Robótica con IA y Especialización en Soluciones de IA (A27-013). Producto: radicados y resoluciones del MEN. AC27.06, actividades: 1. Tramitar la modificación del lugar de desarrollo de los programas de IA si se ofrecerán en Zipaquirá (A27-014). Producto: solicitud ante el MEN. 2. Ofertar 2 especializaciones y 2 maestrías en el II semestre (A27-015). Producto: programas ofertados y matrícula. | O5: Despacho de la Vicerrectoría Académica (120) Facultad de Inteligencia Artificial (Acuerdo 010 de 2025) (123) Aseguramiento de la Calidad, MIPG y Registros Calificados (101) Coordinación de Especializaciones (123) | P5: Sin presupuesto registrado en la matriz plurianual | Q5: Valor Público | R5: Transformaciones del territorio (condiciones del desarrollo, especialmente de cobertura y pertinencia en la oferta educativa). Transformaciones de vidas (condiciones de vida movilidad social) de las personas con las que se interactúa. | S5: Proporción de programas académicos pertinentes (alineados con necesidades y vocación del territorio) ofrecidos por la Institución en el territorio. Índice de empleabilidad en el corto plazo tras finalizar el programa formativo. | T5: 1. Lo que hacemos: 2 acciones con 6 actividades (columnas M y N). 2. Lo que entregamos (productos): productos reprogramados; documentos maestros; planes de estudio y acuerdos; radicados y resoluciones del MEN; solicitud ante el MEN; programas ofertados y matrícula. 3. Lo que cambia pronto (resultado): la Escuela cuenta con documentos maestros, registros calificados y programas nuevos ofertados, en especial en inteligencia artificial y datos. 4. La transformación que buscamos (impacto): la oferta responde a lo que el territorio y el sector productivo demandan, y sus egresados se vinculan rápidamente al empleo. 5. Tipo de impacto según la guía: interno y externo. | U5: Aumenta la proporción de programas pertinentes con la vocación del territorio y, cuando egresen las primeras cohortes, su índice de empleabilidad de corto plazo es igual o superior al promedio institucional. Indicador de la guía con que se mide: proporción de programas académicos pertinentes (alineados con necesidades y vocación del territorio) ofrecidos por la Institución en el territorio. Punto de comparación: la línea base de la meta (15 pregrados y 3 posgrados (2024, MPI, columna «Línea base 2024»); en 2025 se recibieron 4 visitas de verificación para 10 programas nuevos en modalidad distancia (RC 2025)) y, cuando el estudio lo permita, un grupo de referencia que no recibió la intervención. | V5: 2 | W5: 6 | X5: Dónde se ubica: eje 1, Formación y pedagogía de calidad, línea 1.2 Oferta educativa, meta 1.2.1.1 del PDI 2025 a 2032. Qué cambió frente a 2026: se corrige. Se retira la adición de «2 programas nuevos de doctorado», que no está en el PDI (salvo acto del Consejo Directivo). Se integran los programas de IA comprometidos. Cómo se mide la meta: N.° de programas nuevos con registro calificado y ofertados, por nivel. Línea base: 15 pregrados y 3 posgrados (2024, MPI, columna «Línea base 2024»); en 2025 se recibieron 4 visitas de verificación para 10 programas nuevos en modalidad distancia (RC 2025). Meta 2027: Pregrado: 3 documentos maestros, 2 programas con registro calificado y 2 ofertados desde el II semestre. Posgrado: 2 especializaciones y 2 maestrías ofertadas en el II semestre. Cómo se mide el impacto: proporción de programas académicos pertinentes (alineados con necesidades y vocación del territorio) ofrecidos por la Institución en el territorio. El indicador sale de la Guía Metodológica para la Evaluación de Impacto Institucional y se lee frente a la línea base. Qué esperamos obtener: la oferta responde a lo que el territorio y el sector productivo demandan, y sus egresados se vinculan rápidamente al empleo. Cómo se hace el seguimiento: cada trimestre las áreas reportan en el SUIE el avance de las actividades con su evidencia; la Oficina Asesora de Planeación verifica la pertinencia de los productos, consolida el avance de las acciones y de la meta y lo presenta al Comité Institucional de Gestión y Desempeño. Al cierre de 2027 se compara el indicador de la meta con su línea base. | Y5: La MPI incluye 2 doctorados que no están en la tabla de metas del PDI.
C6: 1.3 Calidad de los programas académicos | D6: 1.3.1. Garantizar la alta calidad de todos los programas de la ETITC. | E6: 1.3.1.1. Contar con la acreditación del 100% de los programas de la ETITC que sean acreditables. | F6: Se reformula | G6: Hito cumplido: la ETITC mantiene el 100% de sus programas acreditables acreditados y obtuvo la acreditación institucional en 2026. Para 2027 la meta pasa de «lograr» a «mantener y ampliar»: sostener las acreditaciones vigentes, renovar las que vencen y preparar los programas que cumplan requisitos. | H6: % de programas acreditables con acreditación vigente y N.° de programas acreditados | I6: 12 programas acreditados (2024, MPI, columna «Línea base 2024»); 100% de los programas acreditables acreditados y acreditación institucional obtenida en 2026 (RC 2025) | J6: 100% de los acreditables (MPI: 24 programas) | K6: Sugerida por la OAP: mantener el 100% de los programas acreditables acreditados, 18 programas con acreditación vigente, según la MPI, y radicar a tiempo las renovaciones que vencen en 2027 | L6: Sugerida por la OAP con base en la MPI (18 programas en 2027) y en el logro 2026. | M6: AC27.07. Asegurar la continuidad de las acreditaciones de programa, con un calendario de vencimientos y la radicación oportuna de las renovaciones de 2027. AC27.08. Cerrar el ciclo de mejoramiento de los programas acreditados, al día con los planes de mejoramiento y sin productos pendientes de 2026. | N6: AC27.07, actividades: 1. Construir el calendario de vencimientos de las acreditaciones de programa 2027 a 2029 (A27-016). Producto: calendario de vencimientos. 2. Radicar las renovaciones de acreditación que vencen en 2027 y atender las visitas de pares (A27-017). Producto: informes de autoevaluación radicados. AC27.08, actividades: 1. Hacer seguimiento a los planes de mejoramiento de los programas acreditados (A27-018). Producto: informe semestral de planes de mejoramiento. 2. Cerrar los 11 productos vencidos de acreditación de programas de 2026 (A27-019). Producto: productos reprogramados. | O6: Autoevaluación y Acreditación (101) Aseguramiento de la Calidad, MIPG y Registros Calificados (101) | P6: Sin presupuesto registrado en la matriz plurianual | Q6: Académica | R6: Cambios curriculares y mejoramiento de programas Impacto en las labores sustantivas: docencia y formación, investigación e innovación, extensión y proyección social. | S6: Resultados del valor agregado (diferencia entre el desarrollo de competencias antes de ingresar a la Escuela y lo que demuestra al egresar). Cantidad de procesos académicos y académico administrativos que mejoran. | T6: 1. Lo que hacemos: 2 acciones con 4 actividades (columnas M y N). 2. Lo que entregamos (productos): calendario de vencimientos; informes de autoevaluación radicados; informe semestral de planes de mejoramiento; productos reprogramados. 3. Lo que cambia pronto (resultado): ningún programa pierde su acreditación por vencimiento y los planes de mejoramiento quedan al día. 4. La transformación que buscamos (impacto): la calidad reconocida se traduce en mejores aprendizajes y en procesos académicos que mejoran de manera continua. 5. Tipo de impacto según la guía: interno. | U6: Los resultados de valor agregado de los programas acreditados mejoran frente a la medición anterior y crece el número de procesos académicos que reportan mejoras verificables. Indicador de la guía con que se mide: resultados del valor agregado (diferencia entre el desarrollo de competencias antes de ingresar a la Escuela y lo que demuestra al egresar). Punto de comparación: la línea base de la meta (12 programas acreditados (2024, MPI, columna «Línea base 2024»); 100% de los programas acreditables acreditados y acreditación institucional obtenida en 2026 (RC 2025)) y, cuando el estudio lo permita, un grupo de referencia que no recibió la intervención. | V6: 2 | W6: 4 | X6: Dónde se ubica: eje 1, Formación y pedagogía de calidad, línea 1.3 Calidad de los programas académicos, meta 1.3.1.1 del PDI 2025 a 2032. Qué cambió frente a 2026: se reformula. Hito cumplido: la ETITC mantiene el 100% de sus programas acreditables acreditados y obtuvo la acreditación institucional en 2026. Para 2027 la meta pasa de «lograr» a «mantener y ampliar»: sostener las acreditaciones vigentes, renovar las que vencen y preparar los programas que cumplan requisitos. Cómo se mide la meta: % de programas acreditables con acreditación vigente y N.° de programas acreditados. Línea base: 12 programas acreditados (2024, MPI, columna «Línea base 2024»); 100% de los programas acreditables acreditados y acreditación institucional obtenida en 2026 (RC 2025). Meta 2027: Sugerida por la OAP: mantener el 100% de los programas acreditables acreditados, 18 programas con acreditación vigente, según la MPI, y radicar a tiempo las renovaciones que vencen en 2027. Cómo se mide el impacto: resultados del valor agregado (diferencia entre el desarrollo de competencias antes de ingresar a la Escuela y lo que demuestra al egresar). El indicador sale de la Guía Metodológica para la Evaluación de Impacto Institucional y se lee frente a la línea base. Qué esperamos obtener: la calidad reconocida se traduce en mejores aprendizajes y en procesos académicos que mejoran de manera continua. Cómo se hace el seguimiento: cada trimestre las áreas reportan en el SUIE el avance de las actividades con su evidencia; la Oficina Asesora de Planeación verifica la pertinencia de los productos, consolida el avance de las acciones y de la meta y lo presenta al Comité Institucional de Gestión y Desempeño. Al cierre de 2027 se compara el indicador de la meta con su línea base. | Y6: Sin alertas.
E7: 1.3.1.2. Resultados de las Pruebas SABER por encima de la valoración de la media. | F7: Se corrige | G7: El 2026 decía «promedio 252 en el 2032»; según la MPI, 252 es la línea base de 2024, no la meta. | H7: Puntaje promedio institucional Saber PRO y TyT frente a la media nacional | I7: Promedio 252 (2024, MPI, columna «Línea base 2024») | J7: Por encima de la media nacional | K7: Sugerida por la OAP: promedio institucional de 254 puntos, mejora de 1 punto por año desde 252 en 2024, y por encima de la media nacional del grupo de referencia | L7: Sugerida por la OAP (trayectoria de mejora anual de 1 punto). | M7: AC27.09. Mejorar los resultados de las pruebas Saber PRO y TyT a partir del análisis por programa y competencia, con estrategias de preparación cuyo efecto se evalúa. | N7: AC27.09, actividades: 1. Analizar los resultados 2025 a 2026 por programa y competencia (A27-020). Producto: informe de análisis por programa. 2. Implementar estrategias de preparación para Saber PRO y TyT (talleres de ítems, simulacros) (A27-021). Producto: plan de preparación y simulacros aplicados. 3. Evaluar el efecto de las estrategias en los resultados 2027 (A27-022). Producto: informe de resultados 2027. | O7: Autoevaluación y Acreditación (101) Despacho de la Vicerrectoría Académica (120) | P7: Sin presupuesto registrado en la matriz plurianual | Q7: Académica | R7: Cambios curriculares y mejoramiento de programas Cambios en la formación integral y los aprendizajes del estudiantado. | S7: Resultados del valor agregado (diferencia entre el desarrollo de competencias antes de ingresar a la Escuela y lo que demuestra al egresar). Porcentaje de docentes que transforman la didáctica y la evaluación de los aprendizajes. | T7: 1. Lo que hacemos: 1 acción con 3 actividades (columnas M y N). 2. Lo que entregamos (productos): informe de análisis por programa; plan de preparación y simulacros aplicados; informe de resultados 2027. 3. Lo que cambia pronto (resultado): los estudiantes llegan mejor preparados a las pruebas Saber PRO y TyT y el promedio institucional sube. 4. La transformación que buscamos (impacto): los estudiantes egresan con más competencias de las que traían, y los docentes ajustan su didáctica con base en la evidencia. 5. Tipo de impacto según la guía: interno. | U7: El valor agregado entre el ingreso y la salida crece, el promedio supera los 252 puntos de la línea base y aumenta el porcentaje de docentes que transforma su didáctica y su evaluación. Indicador de la guía con que se mide: resultados del valor agregado (diferencia entre el desarrollo de competencias antes de ingresar a la Escuela y lo que demuestra al egresar). Punto de comparación: la línea base de la meta (Promedio 252 (2024, MPI, columna «Línea base 2024»)) y, cuando el estudio lo permita, un grupo de referencia que no recibió la intervención. | V7: 1 | W7: 3 | X7: Dónde se ubica: eje 1, Formación y pedagogía de calidad, línea 1.3 Calidad de los programas académicos, meta 1.3.1.2 del PDI 2025 a 2032. Qué cambió frente a 2026: se corrige. El 2026 decía «promedio 252 en el 2032»; según la MPI, 252 es la línea base de 2024, no la meta. Cómo se mide la meta: Puntaje promedio institucional Saber PRO y TyT frente a la media nacional. Línea base: Promedio 252 (2024, MPI, columna «Línea base 2024»). Meta 2027: Sugerida por la OAP: promedio institucional de 254 puntos, mejora de 1 punto por año desde 252 en 2024, y por encima de la media nacional del grupo de referencia. Cómo se mide el impacto: resultados del valor agregado (diferencia entre el desarrollo de competencias antes de ingresar a la Escuela y lo que demuestra al egresar). El indicador sale de la Guía Metodológica para la Evaluación de Impacto Institucional y se lee frente a la línea base. Qué esperamos obtener: los estudiantes egresan con más competencias de las que traían, y los docentes ajustan su didáctica con base en la evidencia. Cómo se hace el seguimiento: cada trimestre las áreas reportan en el SUIE el avance de las actividades con su evidencia; la Oficina Asesora de Planeación verifica la pertinencia de los productos, consolida el avance de las acciones y de la meta y lo presenta al Comité Institucional de Gestión y Desempeño. Al cierre de 2027 se compara el indicador de la meta con su línea base. | Y7: Sin alertas.
C8: 1.4 Acreditación internacional | D8: 1.4.1. Fortalecer la oferta educativa de la ETITC mediante la acreditación internacional de sus programas de educación superior, alineados con los estándares del Marco Común Europeo de Referencia. | E8: 1.4.1.1. Contar con 2 programas de acreditación internacional. | F8: Se corrige | G8: El 2026 la llamó «cualificación internacional MEC». El MEC es el Marco Europeo de Cualificaciones: 8 niveles que describen lo que una persona sabe, sabe hacer y con qué autonomía (técnico y tecnológico ≈ nivel 5; profesional universitario ≈ 6; especialización y maestría ≈ 7; doctorado = 8). Referenciar un programa al MEC hace legibles sus títulos en el exterior. Se aplica primero a los programas virtuales e híbridos, que pueden captar estudiantes fuera de Bogotá y del país y aportar a los 5.400 de 2027. | H8: N.° de programas con resultados de aprendizaje referenciados al MEC y con acreditación o reconocimiento internacional | I8: 0 programas (2024, MPI, columna «Línea base 2024»); 3 programas nuevos híbridos (presencial y virtual) diseñados en 2025 y 10 programas en modalidad distancia con visita de verificación (RC 2025) | J8: 2 programas | K8: Sugerida por la OAP: 2 programas, priorizando los híbridos y virtuales de IA, con resultados de aprendizaje referenciados a los 8 niveles del MEC y plan de cualificación internacional aprobado; 1 alianza con una IES o agencia extranjera para su reconocimiento | L8: Sugerida por la OAP. | M8: AC27.10. Referenciar dos programas al Marco Europeo de Cualificaciones para que sus títulos sean legibles en el exterior. AC27.11. Proyectar internacionalmente los programas referenciados mediante oferta virtual y una alianza de reconocimiento mutuo. | N8: AC27.10, actividades: 1. Elaborar el documento técnico de referenciación al MEC y al Marco Nacional de Cualificaciones (8 niveles) y seleccionar los 2 programas (A27-023). Producto: documento técnico aprobado. 2. Reescribir los resultados de aprendizaje de los 2 programas por nivel del MEC (conocimientos, destrezas, autonomía) (A27-024). Producto: matriz de resultados de aprendizaje referenciada. AC27.11, actividades: 1. Diseñar la oferta virtual de los programas referenciados para captar estudiantes de otras regiones (A27-025). Producto: plan de oferta virtual 2027 a 2028. 2. Firmar una alianza con una IES o agencia extranjera para reconocimiento mutuo y movilidad virtual (COIL) (A27-026). Producto: convenio suscrito. | O8: Autoevaluación y Acreditación (101) Unidad B-Learning (120) Internacionalización (ORII) (100) | P8: Sin presupuesto registrado en la matriz plurianual | Q8: Académica | R8: Impacto en las labores sustantivas: docencia y formación, investigación e innovación, extensión y proyección social. Cambios curriculares y mejoramiento de programas | S8: Cantidad de procesos académicos y académico administrativos que mejoran. Resultados del valor agregado (diferencia entre el desarrollo de competencias antes de ingresar a la Escuela y lo que demuestra al egresar). | T8: 1. Lo que hacemos: 2 acciones con 4 actividades (columnas M y N). 2. Lo que entregamos (productos): documento técnico aprobado; matriz de resultados de aprendizaje referenciada; plan de oferta virtual 2027 a 2028; convenio suscrito. 3. Lo que cambia pronto (resultado): dos programas tienen resultados de aprendizaje referenciados internacionalmente y una alianza de reconocimiento firmada. 4. La transformación que buscamos (impacto): los títulos de la ETITC son comparables en el exterior y la oferta virtual atrae estudiantes de otras regiones y países con calidad reconocida. 5. Tipo de impacto según la guía: interno. | U8: Aumentan los procesos académicos mejorados por la referenciación y los estudiantes de esos programas muestran mayor valor agregado en sus competencias. Indicador de la guía con que se mide: cantidad de procesos académicos y académico administrativos que mejoran. Punto de comparación: la línea base de la meta (0 programas (2024, MPI, columna «Línea base 2024»); 3 programas nuevos híbridos (presencial y virtual) diseñados en 2025 y 10 programas en modalidad distancia con visita de verificación (RC 2025)) y, cuando el estudio lo permita, un grupo de referencia que no recibió la intervención. | V8: 2 | W8: 4 | X8: Dónde se ubica: eje 1, Formación y pedagogía de calidad, línea 1.4 Acreditación internacional, meta 1.4.1.1 del PDI 2025 a 2032. Qué cambió frente a 2026: se corrige. El 2026 la llamó «cualificación internacional MEC». El MEC es el Marco Europeo de Cualificaciones: 8 niveles que describen lo que una persona sabe, sabe hacer y con qué autonomía (técnico y tecnológico ≈ nivel 5; profesional universitario ≈ 6; especialización y maestría ≈ 7; doctorado = 8). Referenciar un programa al MEC hace legibles sus títulos en el exterior. Se aplica primero a los programas virtuales e híbridos, que pueden captar estudiantes fuera de Bogotá y del país y aportar a los 5.400 de 2027. Cómo se mide la meta: N.° de programas con resultados de aprendizaje referenciados al MEC y con acreditación o reconocimiento internacional. Línea base: 0 programas (2024, MPI, columna «Línea base 2024»); 3 programas nuevos híbridos (presencial y virtual) diseñados en 2025 y 10 programas en modalidad distancia con visita de verificación (RC 2025). Meta 2027: Sugerida por la OAP: 2 programas, priorizando los híbridos y virtuales de IA, con resultados de aprendizaje referenciados a los 8 niveles del MEC y plan de cualificación internacional aprobado; 1 alianza con una IES o agencia extranjera para su reconocimiento. Cómo se mide el impacto: cantidad de procesos académicos y académico administrativos que mejoran. El indicador sale de la Guía Metodológica para la Evaluación de Impacto Institucional y se lee frente a la línea base. Qué esperamos obtener: los títulos de la ETITC son comparables en el exterior y la oferta virtual atrae estudiantes de otras regiones y países con calidad reconocida. Cómo se hace el seguimiento: cada trimestre las áreas reportan en el SUIE el avance de las actividades con su evidencia; la Oficina Asesora de Planeación verifica la pertinencia de los productos, consolida el avance de las acciones y de la meta y lo presenta al Comité Institucional de Gestión y Desempeño. Al cierre de 2027 se compara el indicador de la meta con su línea base. | Y8: El PDI menciona el «Marco Común Europeo de Referencia», que es el de lenguas (MCER), y el 2026 el MEC (cualificaciones): conviene precisarlo en la próxima revisión del PDI.
C9: 1.5 Fortalecimiento del cuerpo docente | D9: 1.5.1. Garantizar que la ETITC cuente con un cuerpo docente de alta calidad mediante la implementación de un plan integral de desarrollo profesoral, orientado a la excelencia académica y al fortalecimiento de sus capacidades. | E9: 1.5.1.1. Se mantienen 12 doctores en formación. | F9: Se corrige | G9: Vuelve al concepto de formación docente del PDI. El 2026 la reemplazó por «24 docentes con doctorado» con código mal formado (1.5.1. 4). | H9: N.° de docentes en formación doctoral | I9: 0 (2024, MPI, columna «Línea base 2024»); 3 docentes iniciaron doctorado en 2026 por la convocatoria posgradual 2025 (RC 2025) | J9: 12 doctores en formación (MPI: 10) | K9: 2 docentes nuevos en formación doctoral (acumulado sugerido: 5) | L9: MPI (2 nuevos en 2027); acumulado calculado por la OAP. | M9: AC27.12. Sostener la formación doctoral de los docentes mediante un plan profesoral actualizado, una convocatoria anual y los apoyos de estudio. | N9: AC27.12, actividades: 1. Actualizar el plan integral de desarrollo profesoral (A27-027). Producto: plan aprobado. 2. Abrir la convocatoria de formación posgradual 2027 (doctorado) (A27-028). Producto: convocatoria y docentes seleccionados. 3. Otorgar los apoyos para formación doctoral disciplinar (A27-029). Producto: comisiones de estudio o apoyos otorgados. | O9: GIT Talento Humano (133) Despacho de la Vicerrectoría Académica (120) | P9: A27-029: 640 (MPI) | Q9: Académica | R9: Cambios curriculares y mejoramiento de programas Cambios en la formación integral y los aprendizajes del estudiantado. | S9: Porcentaje de docentes que transforman o innovan sus prácticas tras su participación en actividades institucionales y de desarrollo docente. Porcentaje de docentes que transforman la didáctica y la evaluación de los aprendizajes. | T9: 1. Lo que hacemos: 1 acción con 3 actividades (columnas M y N). 2. Lo que entregamos (productos): plan aprobado; convocatoria y docentes seleccionados; comisiones de estudio o apoyos otorgados. 3. Lo que cambia pronto (resultado): más docentes inician y sostienen su formación doctoral con apoyo institucional. 4. La transformación que buscamos (impacto): los docentes con formación doctoral transforman sus prácticas y fortalecen la investigación y la docencia de sus programas. 5. Tipo de impacto según la guía: interno. | U9: Crece el porcentaje de docentes que innovan sus prácticas después de su formación, verificable en planes de curso, proyectos y productos de investigación. Indicador de la guía con que se mide: porcentaje de docentes que transforman o innovan sus prácticas tras su participación en actividades institucionales y de desarrollo docente. Punto de comparación: la línea base de la meta (0 (2024, MPI, columna «Línea base 2024»); 3 docentes iniciaron doctorado en 2026 por la convocatoria posgradual 2025 (RC 2025)) y, cuando el estudio lo permita, un grupo de referencia que no recibió la intervención. | V9: 1 | W9: 3 | X9: Dónde se ubica: eje 1, Formación y pedagogía de calidad, línea 1.5 Fortalecimiento del cuerpo docente, meta 1.5.1.1 del PDI 2025 a 2032. Qué cambió frente a 2026: se corrige. Vuelve al concepto de formación docente del PDI. El 2026 la reemplazó por «24 docentes con doctorado» con código mal formado (1.5.1. 4). Cómo se mide la meta: N.° de docentes en formación doctoral. Línea base: 0 (2024, MPI, columna «Línea base 2024»); 3 docentes iniciaron doctorado en 2026 por la convocatoria posgradual 2025 (RC 2025). Meta 2027: 2 docentes nuevos en formación doctoral (acumulado sugerido: 5). Cómo se mide el impacto: porcentaje de docentes que transforman o innovan sus prácticas tras su participación en actividades institucionales y de desarrollo docente. El indicador sale de la Guía Metodológica para la Evaluación de Impacto Institucional y se lee frente a la línea base. Qué esperamos obtener: los docentes con formación doctoral transforman sus prácticas y fortalecen la investigación y la docencia de sus programas. Cómo se hace el seguimiento: cada trimestre las áreas reportan en el SUIE el avance de las actividades con su evidencia; la Oficina Asesora de Planeación verifica la pertinencia de los productos, consolida el avance de las acciones y de la meta y lo presenta al Comité Institucional de Gestión y Desempeño. Al cierre de 2027 se compara el indicador de la meta con su línea base. | Y9: La hoja PROY dice 12 doctores; la tabla en imagen del PDI y la MPI dicen 10.
E10: 1.5.1.2. 80% en formación docentes de planta. | F10: Se corrige | G10: Se recogen aquí las metas de maestrías (48) y formación continuada (276) que el 2026 registró con códigos mal formados. La formalización laboral sale de esta línea. | H10: % de docentes de planta en formación avanzada o continuada | I10: 0 (2024, MPI, columna «Línea base 2024»); 4 docentes iniciaron maestría en 2026 por la convocatoria posgradual 2025 (RC 2025) | J10: 80% | K10: 6 docentes de planta en maestría y 40 docentes en formación continuada | L10: MPI | M10: AC27.13. Elevar la formación avanzada y continuada de los docentes de planta con base en las necesidades reales de cada facultad. | N10: AC27.13, actividades: 1. Identificar las necesidades de formación por facultad (A27-030). Producto: diagnóstico de necesidades. 2. Financiar la formación de docentes de planta en maestrías disciplinares (A27-031). Producto: docentes beneficiados. 3. Ofrecer cursos de formación continuada a docentes (A27-032). Producto: docentes certificados. | O10: Despacho de la Vicerrectoría Académica (120) GIT Talento Humano (133) | P10: A27-031: 240 (MPI) A27-032: 100 (MPI) | Q10: Académica | R10: Cambios curriculares y mejoramiento de programas Cambios en la formación integral y los aprendizajes del estudiantado. | S10: Porcentaje de docentes que transforman o innovan sus prácticas tras su participación en actividades institucionales y de desarrollo docente. Porcentaje de docentes que transforman la didáctica y la evaluación de los aprendizajes. | T10: 1. Lo que hacemos: 1 acción con 3 actividades (columnas M y N). 2. Lo que entregamos (productos): diagnóstico de necesidades; docentes beneficiados; docentes certificados. 3. Lo que cambia pronto (resultado): más docentes de planta cursan maestrías y formación continuada pertinente con las necesidades de su facultad. 4. La transformación que buscamos (impacto): la formación docente se refleja en cambios reales en la didáctica y en la evaluación de los aprendizajes. 5. Tipo de impacto según la guía: interno. | U10: Aumenta el porcentaje de docentes que transforman su didáctica y su evaluación, contrastado con los registros de seguimiento académico antes y después de la formación. Indicador de la guía con que se mide: porcentaje de docentes que transforman o innovan sus prácticas tras su participación en actividades institucionales y de desarrollo docente. Punto de comparación: la línea base de la meta (0 (2024, MPI, columna «Línea base 2024»); 4 docentes iniciaron maestría en 2026 por la convocatoria posgradual 2025 (RC 2025)) y, cuando el estudio lo permita, un grupo de referencia que no recibió la intervención. | V10: 1 | W10: 3 | X10: Dónde se ubica: eje 1, Formación y pedagogía de calidad, línea 1.5 Fortalecimiento del cuerpo docente, meta 1.5.1.2 del PDI 2025 a 2032. Qué cambió frente a 2026: se corrige. Se recogen aquí las metas de maestrías (48) y formación continuada (276) que el 2026 registró con códigos mal formados. La formalización laboral sale de esta línea. Cómo se mide la meta: % de docentes de planta en formación avanzada o continuada. Línea base: 0 (2024, MPI, columna «Línea base 2024»); 4 docentes iniciaron maestría en 2026 por la convocatoria posgradual 2025 (RC 2025). Meta 2027: 6 docentes de planta en maestría y 40 docentes en formación continuada. Cómo se mide el impacto: porcentaje de docentes que transforman o innovan sus prácticas tras su participación en actividades institucionales y de desarrollo docente. El indicador sale de la Guía Metodológica para la Evaluación de Impacto Institucional y se lee frente a la línea base. Qué esperamos obtener: la formación docente se refleja en cambios reales en la didáctica y en la evaluación de los aprendizajes. Cómo se hace el seguimiento: cada trimestre las áreas reportan en el SUIE el avance de las actividades con su evidencia; la Oficina Asesora de Planeación verifica la pertinencia de los productos, consolida el avance de las acciones y de la meta y lo presenta al Comité Institucional de Gestión y Desempeño. Al cierre de 2027 se compara el indicador de la meta con su línea base. | Y10: Sin alertas.
A11: 2. Investigación y producción técnico científica | B11: 2. Generar y fortalecer las capacidades técnico científica y de innovación de la ETITC mediante la consolidación de la investigación aplicada, la generación de alianzas estratégicas y la integración de la innovación con la formación académica. | C11: 2.1 Capacidades de investigación e innovación | D11: 2.1.1. Contar con una sólida capacidad de investigación. | E11: 2.1.1.1. Contar como mínimo por vigencia con un (1) grupo de investigación en clasificación A (en MinCiencias). | F11: Se mantiene | G11: Se mantiene. Se ordena la secuencia: en 2027 se consolidan B y C y se prepara el primer grupo para A. | H11: N.° de grupos categoría A y A1 en MinCiencias | I11: 9 grupos registrados en MinCiencias, ninguno en A; 2 en categoría C (Virtus y GEA) según la Convocatoria 957 de 2024 (RC 2025) | J11: 1 grupo A (MPI: 8 grupos A) | K11: Sugerida por la OAP: 1 grupo con ruta de ascenso a categoría A aprobada y con la producción de nuevo conocimiento requerida para la siguiente medición | L11: Sugerida por la OAP en secuencia: primero la categoría C, luego la B y después la A. | M11: AC27.14. Preparar el primer grupo de investigación para la categoría A, con diagnóstico de su producción, ruta de ascenso y medición del impacto de la investigación. | N11: AC27.14, actividades: 1. Diagnosticar la producción de cada grupo frente al modelo de medición de MinCiencias (A27-033). Producto: diagnóstico por grupo. 2. Definir la ruta de ascenso del grupo con mayor producción (metas de nuevo conocimiento y formación) (A27-034). Producto: ruta de ascenso aprobada. 3. Iniciar el estudio de impacto de Investigación (A27-035). Producto: diseño del estudio aprobado. | O11: Investigación (grupos, semilleros, revista, centro de pensamiento) (140) Despacho de la VIET (140) | P11: Sin presupuesto registrado en la matriz plurianual | Q11: Sector Productivo | R11: Contribución a la solución de problemas del contexto y la creación de nuevo conocimiento. | S11: Porcentaje de proyectos de investigación que transformaron un proceso, un producto o una problemática de una organización o sector. Porcentaje de proyectos de investigación que contribuyeron al desarrollo social y comunitario, económico, sostenibilidad ambiental, sector educativo, sector productivo y industrial, desarrollo tecnológico, nacional e internacional. | T11: 1. Lo que hacemos: 1 acción con 3 actividades (columnas M y N). 2. Lo que entregamos (productos): diagnóstico por grupo; ruta de ascenso aprobada; diseño del estudio aprobado. 3. Lo que cambia pronto (resultado): un grupo cuenta con diagnóstico de su producción y una ruta de ascenso aprobada hacia la categoría A. 4. La transformación que buscamos (impacto): la investigación de la Escuela resuelve problemas reales de organizaciones y sectores, y no solo cumple requisitos de medición. 5. Tipo de impacto según la guía: externo. | U11: Crece el porcentaje de proyectos de investigación que transformaron un proceso, un producto o una problemática de una organización o sector. Indicador de la guía con que se mide: porcentaje de proyectos de investigación que transformaron un proceso, un producto o una problemática de una organización o sector. Punto de comparación: la línea base de la meta (9 grupos registrados en MinCiencias, ninguno en A; 2 en categoría C (Virtus y GEA) según la Convocatoria 957 de 2024 (RC 2025)) y, cuando el estudio lo permita, un grupo de referencia que no recibió la intervención. | V11: 1 | W11: 3 | X11: Dónde se ubica: eje 2, Investigación y producción técnico científica, línea 2.1 Capacidades de investigación e innovación, meta 2.1.1.1 del PDI 2025 a 2032. Qué cambió frente a 2026: se mantiene. Se mantiene. Se ordena la secuencia: en 2027 se consolidan B y C y se prepara el primer grupo para A. Cómo se mide la meta: N.° de grupos categoría A y A1 en MinCiencias. Línea base: 9 grupos registrados en MinCiencias, ninguno en A; 2 en categoría C (Virtus y GEA) según la Convocatoria 957 de 2024 (RC 2025). Meta 2027: Sugerida por la OAP: 1 grupo con ruta de ascenso a categoría A aprobada y con la producción de nuevo conocimiento requerida para la siguiente medición. Cómo se mide el impacto: porcentaje de proyectos de investigación que transformaron un proceso, un producto o una problemática de una organización o sector. El indicador sale de la Guía Metodológica para la Evaluación de Impacto Institucional y se lee frente a la línea base. Qué esperamos obtener: la investigación de la Escuela resuelve problemas reales de organizaciones y sectores, y no solo cumple requisitos de medición. Cómo se hace el seguimiento: cada trimestre las áreas reportan en el SUIE el avance de las actividades con su evidencia; la Oficina Asesora de Planeación verifica la pertinencia de los productos, consolida el avance de las acciones y de la meta y lo presenta al Comité Institucional de Gestión y Desempeño. Al cierre de 2027 se compara el indicador de la meta con su línea base. | Y11: La MPI proyecta 8 grupos A, 16 B y 14 C; el PDI, 1 A, 3 B y 4 C. El informe de rendición de cuentas 2025 dice en un apartado que se mantienen grupos en A, B y C y en otro que solo 2 están en C.
E12: 2.1.1.2. Tres (3) grupos en B. | F12: Se mantiene | G12: Se mantiene. | H12: N.° de grupos categoría B en MinCiencias | I12: 0 grupos en B; 9 registrados y 2 en C (RC 2025) | J12: 3 grupos B (MPI: 16) | K12: Sugerida por la OAP: 1 grupo clasificado en B, ascenso de uno de los 2 grupos en C, | L12: Sugerida por la OAP. | M12: AC27.15. Llevar a categoría B los grupos que hoy están en C, mediante asesoría en productos de nuevo conocimiento y su postulación oportuna. | N12: AC27.15, actividades: 1. Asesorar a los grupos en C (Virtus y GEA) en productos de nuevo conocimiento y apropiación (A27-036). Producto: registro de asesorías y productos validados. 2. Postular los grupos en la convocatoria de medición vigente (A27-037). Producto: postulación radicada. | O12: Investigación (grupos, semilleros, revista, centro de pensamiento) (140) | P12: Sin presupuesto registrado en la matriz plurianual | Q12: Sector Productivo | R12: Contribución a la solución de problemas del contexto y la creación de nuevo conocimiento. | S12: Porcentaje de proyectos de investigación que transformaron un proceso, un producto o una problemática de una organización o sector. Porcentaje de proyectos de investigación que contribuyeron al desarrollo social y comunitario, económico, sostenibilidad ambiental, sector educativo, sector productivo y industrial, desarrollo tecnológico, nacional e internacional. | T12: 1. Lo que hacemos: 1 acción con 2 actividades (columnas M y N). 2. Lo que entregamos (productos): registro de asesorías y productos validados; postulación radicada. 3. Lo que cambia pronto (resultado): al menos un grupo pasa de la categoría C a la B en la siguiente medición de MinCiencias. 4. La transformación que buscamos (impacto): más proyectos de investigación transforman procesos o productos del sector productivo. 5. Tipo de impacto según la guía: externo. | U12: El grupo ascendido reporta proyectos con efectos verificables en organizaciones externas y aumenta el porcentaje institucional de proyectos transformadores. Indicador de la guía con que se mide: porcentaje de proyectos de investigación que transformaron un proceso, un producto o una problemática de una organización o sector. Punto de comparación: la línea base de la meta (0 grupos en B; 9 registrados y 2 en C (RC 2025)) y, cuando el estudio lo permita, un grupo de referencia que no recibió la intervención. | V12: 1 | W12: 2 | X12: Dónde se ubica: eje 2, Investigación y producción técnico científica, línea 2.1 Capacidades de investigación e innovación, meta 2.1.1.2 del PDI 2025 a 2032. Qué cambió frente a 2026: se mantiene. Se mantiene. Cómo se mide la meta: N.° de grupos categoría B en MinCiencias. Línea base: 0 grupos en B; 9 registrados y 2 en C (RC 2025). Meta 2027: Sugerida por la OAP: 1 grupo clasificado en B, ascenso de uno de los 2 grupos en C,. Cómo se mide el impacto: porcentaje de proyectos de investigación que transformaron un proceso, un producto o una problemática de una organización o sector. El indicador sale de la Guía Metodológica para la Evaluación de Impacto Institucional y se lee frente a la línea base. Qué esperamos obtener: más proyectos de investigación transforman procesos o productos del sector productivo. Cómo se hace el seguimiento: cada trimestre las áreas reportan en el SUIE el avance de las actividades con su evidencia; la Oficina Asesora de Planeación verifica la pertinencia de los productos, consolida el avance de las acciones y de la meta y lo presenta al Comité Institucional de Gestión y Desempeño. Al cierre de 2027 se compara el indicador de la meta con su línea base. | Y12: Sin alertas.
E13: 2.1.1.3. Cuatro (4) grupos en C. | F13: Se mantiene | G13: Se mantiene. | H13: N.° de grupos categoría C en MinCiencias | I13: 2 grupos en C (Virtus y GEA) de 9 registrados (RC 2025) | J13: 4 grupos C (MPI: 14) | K13: Sugerida por la OAP: 4 grupos en C: mantener Virtus y GEA y clasificar 2 de los 7 grupos registrados sin categoría | L13: Sugerida por la OAP. | M13: AC27.16. Ampliar la base de grupos clasificados, actualizando la información de los grupos sin categoría y acompañando a los de mayor producción. | N13: AC27.16, actividades: 1. Actualizar GrupLAC y CvLAC de los 7 grupos sin categoría (A27-038). Producto: aplicativos actualizados. 2. Acompañar a los 2 grupos con más producción para su clasificación en C (A27-039). Producto: grupos postulados. | O13: Investigación (grupos, semilleros, revista, centro de pensamiento) (140) | P13: Sin presupuesto registrado en la matriz plurianual | Q13: Sector Productivo | R13: Contribución a la solución de problemas del contexto y la creación de nuevo conocimiento. | S13: Porcentaje de proyectos de investigación que transformaron un proceso, un producto o una problemática de una organización o sector. Porcentaje de proyectos de investigación que contribuyeron al desarrollo social y comunitario, económico, sostenibilidad ambiental, sector educativo, sector productivo y industrial, desarrollo tecnológico, nacional e internacional. | T13: 1. Lo que hacemos: 1 acción con 2 actividades (columnas M y N). 2. Lo que entregamos (productos): aplicativos actualizados; grupos postulados. 3. Lo que cambia pronto (resultado): los grupos sin categoría actualizan su información y dos de ellos logran clasificación. 4. La transformación que buscamos (impacto): la base de investigación se amplía y se integra con la formación de los estudiantes. 5. Tipo de impacto según la guía: externo. | U13: Aumenta el número de proyectos con participación de estudiantes y con contribución verificable al desarrollo social, productivo o tecnológico. Indicador de la guía con que se mide: porcentaje de proyectos de investigación que transformaron un proceso, un producto o una problemática de una organización o sector. Punto de comparación: la línea base de la meta (2 grupos en C (Virtus y GEA) de 9 registrados (RC 2025)) y, cuando el estudio lo permita, un grupo de referencia que no recibió la intervención. | V13: 1 | W13: 2 | X13: Dónde se ubica: eje 2, Investigación y producción técnico científica, línea 2.1 Capacidades de investigación e innovación, meta 2.1.1.3 del PDI 2025 a 2032. Qué cambió frente a 2026: se mantiene. Se mantiene. Cómo se mide la meta: N.° de grupos categoría C en MinCiencias. Línea base: 2 grupos en C (Virtus y GEA) de 9 registrados (RC 2025). Meta 2027: Sugerida por la OAP: 4 grupos en C: mantener Virtus y GEA y clasificar 2 de los 7 grupos registrados sin categoría. Cómo se mide el impacto: porcentaje de proyectos de investigación que transformaron un proceso, un producto o una problemática de una organización o sector. El indicador sale de la Guía Metodológica para la Evaluación de Impacto Institucional y se lee frente a la línea base. Qué esperamos obtener: la base de investigación se amplía y se integra con la formación de los estudiantes. Cómo se hace el seguimiento: cada trimestre las áreas reportan en el SUIE el avance de las actividades con su evidencia; la Oficina Asesora de Planeación verifica la pertinencia de los productos, consolida el avance de las acciones y de la meta y lo presenta al Comité Institucional de Gestión y Desempeño. Al cierre de 2027 se compara el indicador de la meta con su línea base. | Y13: Sin alertas.
C14: 2.2 Producción técnico científica | D14: 2.2.1. Aumentar la producción científico técnica de calidad validable por su publicación en revistas indexadas nacionales e internacionales. | E14: 2.2.1.1. Lograr como mínimo por vigencia la publicación de dos (2) artículos en revistas internacionales indexadas. | F14: Se mantiene | G14: Se mantiene. Al 2 de septiembre de 2026 tenía 1 solo producto. | H14: N.° de artículos publicados en revistas internacionales indexadas | I14: 3 artículos registrados por los grupos en 2025 (GrupLAC, Convocatoria 957) (RC 2025) | J14: 2 por vigencia (16 en el periodo, según MPI) | K14: 2 artículos | L14: Hoja PROY («como mínimo por vigencia») y MPI. | M14: AC27.17. Aumentar la publicación en revistas internacionales indexadas con estímulos, traducción y acompañamiento al sometimiento. | N14: AC27.17, actividades: 1. Abrir la convocatoria de estímulos a la publicación 2027 (A27-040). Producto: convocatoria y artículos sometidos. 2. Acompañar la traducción y el sometimiento a revistas internacionales indexadas (A27-041). Producto: artículos sometidos. | O14: Investigación (grupos, semilleros, revista, centro de pensamiento) (140) | P14: Sin presupuesto registrado en la matriz plurianual | Q14: Sector Productivo | R14: Contribución a la solución de problemas del contexto y la creación de nuevo conocimiento. | S14: Porcentaje de proyectos de investigación que contribuyeron al desarrollo social y comunitario, económico, sostenibilidad ambiental, sector educativo, sector productivo y industrial, desarrollo tecnológico, nacional e internacional. Porcentaje de proyectos de investigación que transformaron un proceso, un producto o una problemática de una organización o sector. | T14: 1. Lo que hacemos: 1 acción con 2 actividades (columnas M y N). 2. Lo que entregamos (productos): convocatoria y artículos sometidos; artículos sometidos. 3. Lo que cambia pronto (resultado): se someten y publican artículos en revistas internacionales indexadas. 4. La transformación que buscamos (impacto): el conocimiento producido por la Escuela es usado por pares y por sectores fuera del país. 5. Tipo de impacto según la guía: externo. | U14: Los artículos publicados registran citaciones o usos y se asocian a proyectos que contribuyeron al desarrollo social, productivo o tecnológico. Indicador de la guía con que se mide: porcentaje de proyectos de investigación que contribuyeron al desarrollo social y comunitario, económico, sostenibilidad ambiental, sector educativo, sector productivo y industrial, desarrollo tecnológico, nacional e internacional. Punto de comparación: la línea base de la meta (3 artículos registrados por los grupos en 2025 (GrupLAC, Convocatoria 957) (RC 2025)) y, cuando el estudio lo permita, un grupo de referencia que no recibió la intervención. | V14: 1 | W14: 2 | X14: Dónde se ubica: eje 2, Investigación y producción técnico científica, línea 2.2 Producción técnico científica, meta 2.2.1.1 del PDI 2025 a 2032. Qué cambió frente a 2026: se mantiene. Se mantiene. Al 2 de septiembre de 2026 tenía 1 solo producto. Cómo se mide la meta: N.° de artículos publicados en revistas internacionales indexadas. Línea base: 3 artículos registrados por los grupos en 2025 (GrupLAC, Convocatoria 957) (RC 2025). Meta 2027: 2 artículos. Cómo se mide el impacto: porcentaje de proyectos de investigación que contribuyeron al desarrollo social y comunitario, económico, sostenibilidad ambiental, sector educativo, sector productivo y industrial, desarrollo tecnológico, nacional e internacional. El indicador sale de la Guía Metodológica para la Evaluación de Impacto Institucional y se lee frente a la línea base. Qué esperamos obtener: el conocimiento producido por la Escuela es usado por pares y por sectores fuera del país. Cómo se hace el seguimiento: cada trimestre las áreas reportan en el SUIE el avance de las actividades con su evidencia; la Oficina Asesora de Planeación verifica la pertinencia de los productos, consolida el avance de las acciones y de la meta y lo presenta al Comité Institucional de Gestión y Desempeño. Al cierre de 2027 se compara el indicador de la meta con su línea base. | Y14: Sin alertas.
E15: 2.2.1.2. Lograr la publicación de ocho (8) artículos en revistas nacionales indexadas. | F15: Se corrige | G15: Hay que precisar si es anual. La MPI dice 8 por año y 48 en total; con 8 vigencias serían 64. | H15: N.° de artículos publicados en revistas nacionales indexadas | I15: 3 artículos registrados por los grupos en 2025 (GrupLAC, Convocatoria 957) (RC 2025) | J15: 8 (MPI: 8 por año, 48 en total) | K15: 8 artículos [validar si es anual] | L15: MPI | M15: AC27.18. Aumentar la publicación en revistas nacionales indexadas, fortaleciendo las revistas propias y convirtiendo trabajos de grado y semilleros en artículos. | N15: AC27.18, actividades: 1. Fortalecer la Revista Letras ETITC y Cuadernos ETITC (pares, convocatorias) (A27-042). Producto: números publicados. 2. Vincular trabajos de grado y semilleros a artículos con docentes (A27-043). Producto: artículos sometidos. | O15: Investigación (grupos, semilleros, revista, centro de pensamiento) (140) | P15: Sin presupuesto registrado en la matriz plurianual | Q15: Sector Productivo | R15: Contribución a la solución de problemas del contexto y la creación de nuevo conocimiento. | S15: Porcentaje de proyectos de investigación que contribuyeron al desarrollo social y comunitario, económico, sostenibilidad ambiental, sector educativo, sector productivo y industrial, desarrollo tecnológico, nacional e internacional. Porcentaje de proyectos de investigación que transformaron un proceso, un producto o una problemática de una organización o sector. | T15: 1. Lo que hacemos: 1 acción con 2 actividades (columnas M y N). 2. Lo que entregamos (productos): números publicados; artículos sometidos. 3. Lo que cambia pronto (resultado): las revistas propias publican con regularidad y los trabajos de grado y semilleros se convierten en artículos. 4. La transformación que buscamos (impacto): la producción nacional aporta a la solución de problemas del país y fortalece la formación de los estudiantes. 5. Tipo de impacto según la guía: externo. | U15: Aumenta el porcentaje de proyectos con publicación que contribuyeron a resolver problemáticas del contexto nacional. Indicador de la guía con que se mide: porcentaje de proyectos de investigación que contribuyeron al desarrollo social y comunitario, económico, sostenibilidad ambiental, sector educativo, sector productivo y industrial, desarrollo tecnológico, nacional e internacional. Punto de comparación: la línea base de la meta (3 artículos registrados por los grupos en 2025 (GrupLAC, Convocatoria 957) (RC 2025)) y, cuando el estudio lo permita, un grupo de referencia que no recibió la intervención. | V15: 1 | W15: 2 | X15: Dónde se ubica: eje 2, Investigación y producción técnico científica, línea 2.2 Producción técnico científica, meta 2.2.1.2 del PDI 2025 a 2032. Qué cambió frente a 2026: se corrige. Hay que precisar si es anual. La MPI dice 8 por año y 48 en total; con 8 vigencias serían 64. Cómo se mide la meta: N.° de artículos publicados en revistas nacionales indexadas. Línea base: 3 artículos registrados por los grupos en 2025 (GrupLAC, Convocatoria 957) (RC 2025). Meta 2027: 8 artículos [validar si es anual]. Cómo se mide el impacto: porcentaje de proyectos de investigación que contribuyeron al desarrollo social y comunitario, económico, sostenibilidad ambiental, sector educativo, sector productivo y industrial, desarrollo tecnológico, nacional e internacional. El indicador sale de la Guía Metodológica para la Evaluación de Impacto Institucional y se lee frente a la línea base. Qué esperamos obtener: la producción nacional aporta a la solución de problemas del país y fortalece la formación de los estudiantes. Cómo se hace el seguimiento: cada trimestre las áreas reportan en el SUIE el avance de las actividades con su evidencia; la Oficina Asesora de Planeación verifica la pertinencia de los productos, consolida el avance de las acciones y de la meta y lo presenta al Comité Institucional de Gestión y Desempeño. Al cierre de 2027 se compara el indicador de la meta con su línea base. | Y15: Total de la MPI no cuadra con 8 por año.
C16: 2.3 Alianzas estratégicas para la investigación | D16: 2.3.1. Lograr el establecimiento y operación de alianzas estratégicas con instituciones de investigación en innovación en los campos de interés de la ETITC, que conduzca a la generación de patentes. | E16: 2.3.1.1. Contar con cuatro (4) patentes registradas sobre la base de los desarrollos logrados con las alianzas con el sector productivo o institucional. | F16: Se corrige | G16: Se recodifica (el 2026 la tenía como 2.3.1.6). Las 5 metas de alianzas del 2026 (2.3.1.1 a 2.3.1.5) salen como metas y pasan a indicadores de gestión de esta. | H16: N.° de solicitudes y de patentes registradas | I16: 1 patente concedida por la SIC (2017, «Prensa de alacrán con tensor de trinquete») y 4 solicitudes de registro de esquemas de trazado en trámite ante la SIC en 2025 (RC 2025) | J16: 4 patentes | K16: Sugerida por la OAP: 2 solicitudes de patente o modelo de utilidad radicadas ante la SIC, avance hacia 4 en 2032, y mantenimiento de la patente vigente | L16: Sugerida por la OAP. | M16: AC27.19. Convertir los desarrollos de la Escuela en propiedad intelectual protegida, desde la identificación de lo patentable hasta la radicación ante la SIC. AC27.20. Mantener vigente la patente concedida, al día con anualidades y requerimientos de la SIC. | N16: AC27.19, actividades: 1. Identificar desarrollos patentables aplicando el reglamento de propiedad intelectual (A27-044). Producto: inventario de desarrollos con potencial. 2. Formalizar alianzas de codesarrollo con IES, empresas, centros y entidades públicas (A27-045). Producto: convenios suscritos. 3. Radicar las solicitudes de patente o modelo de utilidad ante la SIC (A27-046). Producto: solicitudes radicadas. AC27.20, actividades: 1. Pagar la anualidad de la patente vigente y atender los requerimientos de la SIC (A27-047). Producto: soportes de pago y respuestas. | O16: Innovación y Laboratorio Inteligente (140) Despacho de la VIET (140) | P16: Sin presupuesto registrado en la matriz plurianual | Q16: Académica | R16: Impacto en las labores sustantivas: docencia y formación, investigación e innovación, extensión y proyección social. Contribución a la solución de problemas del contexto y la creación de nuevo conocimiento. | S16: Cantidad de ingresos por productos o servicios que son resultado de la implementación de la investigación, la innovación y el desarrollo tecnológico. Porcentaje de proyectos de investigación que transformaron un proceso, un producto o una problemática de una organización o sector. | T16: 1. Lo que hacemos: 2 acciones con 4 actividades (columnas M y N). 2. Lo que entregamos (productos): inventario de desarrollos con potencial; convenios suscritos; solicitudes radicadas; soportes de pago y respuestas. 3. Lo que cambia pronto (resultado): la Escuela identifica sus desarrollos patentables, firma alianzas de codesarrollo y radica solicitudes ante la SIC. 4. La transformación que buscamos (impacto): los desarrollos protegidos se transfieren al sector productivo y generan ingresos para la Institución. 5. Tipo de impacto según la guía: interno e externo. | U16: Aparecen ingresos por licenciamiento, servicios o productos derivados de la investigación y crece el porcentaje de proyectos que transformaron un proceso o un producto externo. Indicador de la guía con que se mide: cantidad de ingresos por productos o servicios que son resultado de la implementación de la investigación, la innovación y el desarrollo tecnológico. Punto de comparación: la línea base de la meta (1 patente concedida por la SIC (2017, «Prensa de alacrán con tensor de trinquete») y 4 solicitudes de registro de esquemas de trazado en trámite ante la SIC en 2025 (RC 2025)) y, cuando el estudio lo permita, un grupo de referencia que no recibió la intervención. | V16: 2 | W16: 4 | X16: Dónde se ubica: eje 2, Investigación y producción técnico científica, línea 2.3 Alianzas estratégicas para la investigación, meta 2.3.1.1 del PDI 2025 a 2032. Qué cambió frente a 2026: se corrige. Se recodifica (el 2026 la tenía como 2.3.1.6). Las 5 metas de alianzas del 2026 (2.3.1.1 a 2.3.1.5) salen como metas y pasan a indicadores de gestión de esta. Cómo se mide la meta: N.° de solicitudes y de patentes registradas. Línea base: 1 patente concedida por la SIC (2017, «Prensa de alacrán con tensor de trinquete») y 4 solicitudes de registro de esquemas de trazado en trámite ante la SIC en 2025 (RC 2025). Meta 2027: Sugerida por la OAP: 2 solicitudes de patente o modelo de utilidad radicadas ante la SIC, avance hacia 4 en 2032, y mantenimiento de la patente vigente. Cómo se mide el impacto: cantidad de ingresos por productos o servicios que son resultado de la implementación de la investigación, la innovación y el desarrollo tecnológico. El indicador sale de la Guía Metodológica para la Evaluación de Impacto Institucional y se lee frente a la línea base. Qué esperamos obtener: los desarrollos protegidos se transfieren al sector productivo y generan ingresos para la Institución. Cómo se hace el seguimiento: cada trimestre las áreas reportan en el SUIE el avance de las actividades con su evidencia; la Oficina Asesora de Planeación verifica la pertinencia de los productos, consolida el avance de las acciones y de la meta y lo presenta al Comité Institucional de Gestión y Desempeño. Al cierre de 2027 se compara el indicador de la meta con su línea base. | Y16: Sin alertas.
C17: 2.4 Vinculación de lo investigativo con lo académico | D17: 2.4.1. Establecer una integración entre los procesos de Investigación y los de Formación y Extensión de la ETITC. | E17: 2.4.1.1. Contar con un (1) centro de pensamiento y desarrollo tecnológico registrado en Colciencias (MinCiencias) y articulado con el Parque Tecnológico de Funza. | F17: Se mantiene | G17: Se mantiene. Reactivar Semilleros (0 de 23 productos al 2 de septiembre de 2026). | H17: Centro de pensamiento reconocido por MinCiencias (fase de avance) | I17: 0 centros (2024, MPI, columna «Línea base 2024»); solicitud de reconocimiento radicada en el portal de MinCiencias en 2026 (MPI) | J17: 1 centro reconocido | K17: Puesta en marcha del Centro de Pensamiento | L17: MPI | M17: AC27.21. Poner en marcha el Centro de Pensamiento y Desarrollo Tecnológico articulado con el Ecoparque de Funza, con reconocimiento de MinCiencias y semilleros activos. | N17: AC27.21, actividades: 1. Completar las etapas del proceso de reconocimiento ante MinCiencias (A27-048). Producto: solicitud y evaluación. 2. Poner en marcha el Centro de Pensamiento articulado con el Ecoparque de Funza (A27-049). Producto: acta de puesta en marcha y plan de trabajo. 3. Reprogramar los productos de Semilleros (A27-050). Producto: productos reprogramados. | O17: Investigación (grupos, semilleros, revista, centro de pensamiento) (140) | P17: Sin presupuesto registrado en la matriz plurianual | Q17: Sector Productivo | R17: Contribución a la solución de problemas del contexto y la creación de nuevo conocimiento. Contribución al desarrollo social y comunitario, económico, sostenibilidad ambiental, sector educativo, sector productivo y industrial, desarrollo tecnológico, nacional e internacional. | S17: Porcentaje de proyectos de investigación que transformaron un proceso, un producto o una problemática de una organización o sector. Tasas de productividad y competitividad después del proyecto. | T17: 1. Lo que hacemos: 1 acción con 3 actividades (columnas M y N). 2. Lo que entregamos (productos): solicitud y evaluación; acta de puesta en marcha y plan de trabajo; productos reprogramados. 3. Lo que cambia pronto (resultado): el Centro de Pensamiento queda reconocido o en evaluación por MinCiencias, opera con un plan de trabajo y los semilleros se reactivan. 4. La transformación que buscamos (impacto): el centro articula investigación, formación y extensión, y mejora la productividad de las organizaciones con las que trabaja. 5. Tipo de impacto según la guía: externo. | U17: Las organizaciones atendidas por el centro muestran mejoras en productividad o competitividad frente a su situación inicial. Indicador de la guía con que se mide: porcentaje de proyectos de investigación que transformaron un proceso, un producto o una problemática de una organización o sector. Punto de comparación: la línea base de la meta (0 centros (2024, MPI, columna «Línea base 2024»); solicitud de reconocimiento radicada en el portal de MinCiencias en 2026 (MPI)) y, cuando el estudio lo permita, un grupo de referencia que no recibió la intervención. | V17: 1 | W17: 3 | X17: Dónde se ubica: eje 2, Investigación y producción técnico científica, línea 2.4 Vinculación de lo investigativo con lo académico, meta 2.4.1.1 del PDI 2025 a 2032. Qué cambió frente a 2026: se mantiene. Se mantiene. Reactivar Semilleros (0 de 23 productos al 2 de septiembre de 2026). Cómo se mide la meta: Centro de pensamiento reconocido por MinCiencias (fase de avance). Línea base: 0 centros (2024, MPI, columna «Línea base 2024»); solicitud de reconocimiento radicada en el portal de MinCiencias en 2026 (MPI). Meta 2027: Puesta en marcha del Centro de Pensamiento. Cómo se mide el impacto: porcentaje de proyectos de investigación que transformaron un proceso, un producto o una problemática de una organización o sector. El indicador sale de la Guía Metodológica para la Evaluación de Impacto Institucional y se lee frente a la línea base. Qué esperamos obtener: el centro articula investigación, formación y extensión, y mejora la productividad de las organizaciones con las que trabaja. Cómo se hace el seguimiento: cada trimestre las áreas reportan en el SUIE el avance de las actividades con su evidencia; la Oficina Asesora de Planeación verifica la pertinencia de los productos, consolida el avance de las acciones y de la meta y lo presenta al Comité Institucional de Gestión y Desempeño. Al cierre de 2027 se compara el indicador de la meta con su línea base. | Y17: Sin alertas.
A18: 3. Extensión y proyección institucional | B18: 3. Ofrecer programas y servicios innovadores y de alta calidad que respondan eficazmente a las necesidades del sector productivo y social, promoviendo su bienestar y su desarrollo sostenible. | C18: 3.1 Autonomía y posicionamiento de la Extensión y Proyección Institucional | D18: 3.1.1. Fortalecer la autonomía en la gestión de actividades de extensión y proyección social mediante la implementación de una estructura institucional sólida que amplifique el impacto social y comunitario de la ETITC. | E18: 3.1.1.1. Disponer a mediano plazo de una vicerrectoría de extensión y proyección social. [Enunciado vigente del PDI. En 2027 se reorienta sin crear la vicerrectoría: ver la columna «Qué cambia frente a 2026».] | F18: Se reorienta | G18: La creación de la Vicerrectoría de Extensión se encuentra en análisis y aún no cuenta con una determinación definitiva. En la etapa actual, el objetivo de la línea 3.1 (autonomía de la extensión) se desarrolla a través del fortalecimiento del GIT de Extensión y Proyección Social en el marco de la estructura vigente. Por lo anterior, se recomienda proponer al Consejo Directivo, en la próxima revisión del PDI, el ajuste del enunciado de esta meta. | H18: Modelo de gestión autónoma de la extensión adoptado y operando (fase) | I18: La extensión opera como GIT de Extensión y Proyección Social (código 141) adscrito a la VIET; recaudó $515,47 millones en 2025 (RC 2025) | J18: Sugerida por la OAP: extensión con autonomía administrativa y financiera operando desde el GIT de Extensión y Proyección Social, sin crear una nueva vicerrectoría | K18: Sugerida por la OAP: modelo de gestión autónoma de la extensión adoptado por acto administrativo: estatuto de extensión actualizado, centro de costos propio del GIT y procedimientos de la extensión en el SGC | L18: Sugerida por la OAP. | M18: AC27.22. Dotar a la extensión de autonomía de gestión dentro de la estructura actual, con reglas, centro de costos y procedimientos propios. AC27.23. Ajustar el enunciado de la meta en la revisión del PDI para que refleje el modelo de autonomía adoptado. | N18: AC27.22, actividades: 1. Actualizar el estatuto o reglamento de extensión con las reglas de autonomía del GIT (contratación de servicios, precios, excedentes) (A27-051). Producto: acto administrativo adoptado. 2. Crear el centro de costos propio de la extensión con Gestión Financiera (A27-052). Producto: centro de costos operando. 3. Documentar y codificar en el SGC los procedimientos de la extensión (A27-053). Producto: procedimientos codificados. AC27.23, actividades: 1. Presentar al Consejo Directivo la propuesta de ajuste del enunciado de la meta 3.1.1.1 en la revisión del PDI (A27-054). Producto: propuesta presentada. | O18: GIT Extensión y Proyección Social (incluye ETDH) (141) Gestión Financiera (Presupuesto, Contabilidad, Tesorería) (130) Planeación y Plan de Acción (101) | P18: Sin presupuesto registrado en la matriz plurianual | Q18: Académica | R18: Impacto en las labores sustantivas: docencia y formación, investigación e innovación, extensión y proyección social. | S18: Cantidad de procesos académicos y académico administrativos que mejoran. Cantidad de ingresos por productos o servicios que son resultado de la implementación de la investigación, la innovación y el desarrollo tecnológico. | T18: 1. Lo que hacemos: 2 acciones con 4 actividades (columnas M y N). 2. Lo que entregamos (productos): acto administrativo adoptado; centro de costos operando; procedimientos codificados; propuesta presentada. 3. Lo que cambia pronto (resultado): la extensión opera con reglas, centro de costos y procedimientos propios, sin crear una nueva estructura. 4. La transformación que buscamos (impacto): la extensión gana autonomía de gestión, mejora sus procesos y aumenta los ingresos propios de la Escuela. 5. Tipo de impacto según la guía: interno. | U18: Aumenta el número de procesos de extensión mejorados y los ingresos propios por servicios crecen frente a los $515,47 millones de 2025. Indicador de la guía con que se mide: cantidad de procesos académicos y académico administrativos que mejoran. Punto de comparación: la línea base de la meta (La extensión opera como GIT de Extensión y Proyección Social (código 141) adscrito a la VIET; recaudó $515,47 millones en 2025 (RC 2025)) y, cuando el estudio lo permita, un grupo de referencia que no recibió la intervención. | V18: 2 | W18: 4 | X18: Dónde se ubica: eje 3, Extensión y proyección institucional, línea 3.1 Autonomía y posicionamiento de la Extensión y Proyección Institucional, meta 3.1.1.1 del PDI 2025 a 2032. Qué cambió frente a 2026: se reorienta. La creación de la Vicerrectoría de Extensión no es viable y no se hará. El objetivo de la línea 3.1 (autonomía de la extensión) se cumple fortaleciendo el GIT de Extensión y Proyección Social dentro de la estructura actual. Se recomienda proponer al Consejo Directivo, en la próxima revisión del PDI, ajustar el enunciado de esta meta. Cómo se mide la meta: Modelo de gestión autónoma de la extensión adoptado y operando (fase). Línea base: La extensión opera como GIT de Extensión y Proyección Social (código 141) adscrito a la VIET; recaudó $515,47 millones en 2025 (RC 2025). Meta 2027: Sugerida por la OAP: modelo de gestión autónoma de la extensión adoptado por acto administrativo: estatuto de extensión actualizado, centro de costos propio del GIT y procedimientos de la extensión en el SGC. Cómo se mide el impacto: cantidad de procesos académicos y académico administrativos que mejoran. El indicador sale de la Guía Metodológica para la Evaluación de Impacto Institucional y se lee frente a la línea base. Qué esperamos obtener: la extensión gana autonomía de gestión, mejora sus procesos y aumenta los ingresos propios de la Escuela. Cómo se hace el seguimiento: cada trimestre las áreas reportan en el SUIE el avance de las actividades con su evidencia; la Oficina Asesora de Planeación verifica la pertinencia de los productos, consolida el avance de las acciones y de la meta y lo presenta al Comité Institucional de Gestión y Desempeño. Al cierre de 2027 se compara el indicador de la meta con su línea base. | Y18: La meta del PDI sigue hablando de una vicerrectoría: mientras no se ajuste el PDI, se reporta el avance del modelo de autonomía.
C19: 3.2 Fortalecimiento de la innovación para la Proyección Institucional | D19: 3.2.1. Liderar iniciativas innovadoras en programas de extensión que contribuyan al bienestar y al desarrollo social, fortaleciendo la proyección institucional de la ETITC y avanzando hacia la meta de ampliar la cobertura educativa. | E19: 3.2.1.1. Diseñar y diversificar la oferta de programas de educación continuada y Educación para el Trabajo y el Desarrollo Humano. | F19: Se mantiene | G19: Se mantiene y se amplía con oferta virtual para llegar a egresados, empresas y regiones fuera de Bogotá. | H19: N.° de ofertas de educación continuada y ETDH, participantes y % en modalidad virtual | I19: 28 ofertas en 2025: 9 certificaciones (106 participantes), 5 cursos libres o a la medida y 14 cursos de lenguas (224 participantes); solo 1 en modalidad virtual (RC 2025) | J19: Sugerida por la OAP: 60 ofertas anuales, 30% en modalidad virtual o b learning | K19: Sugerida por la OAP: 34 ofertas, +20% sobre 2025, de las cuales al menos 8 en modalidad virtual o b learning, y 2 programas ETDH reactivados | L19: Sugerida por la OAP con base en la línea base 2025. | M19: AC27.24. Diversificar y virtualizar el portafolio de educación continuada y de Educación para el Trabajo y el Desarrollo Humano a partir de las necesidades de egresados, empresas y regiones. | N19: AC27.24, actividades: 1. Analizar necesidades y mercado (egresados, empresas, regiones) y actualizar el portafolio (A27-055). Producto: portafolio 2027 actualizado. 2. Virtualizar 8 ofertas con la Unidad B-Learning (certificaciones, diplomados, cursos de lenguas) (A27-056). Producto: ofertas virtuales publicadas. 3. Reactivar 2 programas ETDH con reglamento de formadores (A27-057). Producto: programas ETDH ofertados. 4. Ejecutar y evaluar la oferta 2027 (A27-058). Producto: informe de participantes y satisfacción. | O19: GIT Extensión y Proyección Social (incluye ETDH) (141) Unidad B-Learning (120) | P19: Sin presupuesto registrado en la matriz plurianual | Q19: Egresados | R19: Transformaciones de vidas (condiciones de vida movilidad social) de las personas con las que se interactúa. | S19: Porcentaje de beneficiarios que mejoraron las condiciones de empleo después de la intervención: nivel salarial, cargo, tipo de contrato, seguridad y salud, formalidad. Índice de empleabilidad en el corto plazo tras finalizar el programa formativo. | T19: 1. Lo que hacemos: 1 acción con 4 actividades (columnas M y N). 2. Lo que entregamos (productos): portafolio 2027 actualizado; ofertas virtuales publicadas; programas ETDH ofertados; informe de participantes y satisfacción. 3. Lo que cambia pronto (resultado): hay más ofertas de educación continuada y ETDH, varias de ellas virtuales, con mayor número de participantes. 4. La transformación que buscamos (impacto): egresados y trabajadores mejoran sus condiciones de empleo después de cursar la oferta. 5. Tipo de impacto según la guía: interno y externo. | U19: El seguimiento a participantes muestra mejoras en cargo, salario, tipo de contrato o formalidad, y crece su índice de empleabilidad. Indicador de la guía con que se mide: porcentaje de beneficiarios que mejoraron las condiciones de empleo después de la intervención: nivel salarial, cargo, tipo de contrato, seguridad y salud, formalidad. Punto de comparación: la línea base de la meta (28 ofertas en 2025: 9 certificaciones (106 participantes), 5 cursos libres o a la medida y 14 cursos de lenguas (224 participantes); solo 1 en modalidad virtual (RC 2025)) y, cuando el estudio lo permita, un grupo de referencia que no recibió la intervención. | V19: 1 | W19: 4 | X19: Dónde se ubica: eje 3, Extensión y proyección institucional, línea 3.2 Fortalecimiento de la innovación para la Proyección Institucional, meta 3.2.1.1 del PDI 2025 a 2032. Qué cambió frente a 2026: se mantiene. Se mantiene y se amplía con oferta virtual para llegar a egresados, empresas y regiones fuera de Bogotá. Cómo se mide la meta: N.° de ofertas de educación continuada y ETDH, participantes y % en modalidad virtual. Línea base: 28 ofertas en 2025: 9 certificaciones (106 participantes), 5 cursos libres o a la medida y 14 cursos de lenguas (224 participantes); solo 1 en modalidad virtual (RC 2025). Meta 2027: Sugerida por la OAP: 34 ofertas, +20% sobre 2025, de las cuales al menos 8 en modalidad virtual o b learning, y 2 programas ETDH reactivados. Cómo se mide el impacto: porcentaje de beneficiarios que mejoraron las condiciones de empleo después de la intervención: nivel salarial, cargo, tipo de contrato, seguridad y salud, formalidad. El indicador sale de la Guía Metodológica para la Evaluación de Impacto Institucional y se lee frente a la línea base. Qué esperamos obtener: egresados y trabajadores mejoran sus condiciones de empleo después de cursar la oferta. Cómo se hace el seguimiento: cada trimestre las áreas reportan en el SUIE el avance de las actividades con su evidencia; la Oficina Asesora de Planeación verifica la pertinencia de los productos, consolida el avance de las acciones y de la meta y lo presenta al Comité Institucional de Gestión y Desempeño. Al cierre de 2027 se compara el indicador de la meta con su línea base. | Y19: Sin alertas.
E20: 3.2.1.2. Generar ingresos para la ETITC mediante la comercialización de su portafolio de servicios, fortaleciendo su sostenibilidad financiera por vigencia. | F20: Se mantiene | G20: Se mantiene con meta financiera explícita. | H20: Ingresos por venta de servicios de extensión (millones $) | I20: $515,47 millones recaudados por el Centro de Extensión y Proyección Social en 2025 (Tabla 115) (RC 2025) | J20: Sugerida por la OAP: crecimiento sostenido del 7% anual | K20: Sugerida por la OAP: $590 millones, 7% anual sobre el recaudo 2025, | L20: Sugerida por la OAP. | M20: AC27.25. Aumentar los ingresos propios por venta de servicios con un plan comercial, una oferta empresarial y seguimiento trimestral del recaudo. | N20: AC27.25, actividades: 1. Definir precios y metas de venta por servicio (A27-059). Producto: plan comercial 2027. 2. Ofertar certificaciones, diplomados, consultorías y cursos a la medida para empresas (A27-060). Producto: contratos y ventas registradas. 3. Hacer seguimiento trimestral al recaudo con Gestión Financiera (A27-061). Producto: informe trimestral de recaudo. | O20: GIT Extensión y Proyección Social (incluye ETDH) (141) Gestión Financiera (Presupuesto, Contabilidad, Tesorería) (130) | P20: Sin presupuesto registrado en la matriz plurianual | Q20: Académica | R20: Impacto en las labores sustantivas: docencia y formación, investigación e innovación, extensión y proyección social. | S20: Cantidad de ingresos por productos o servicios que son resultado de la implementación de la investigación, la innovación y el desarrollo tecnológico. | T20: 1. Lo que hacemos: 1 acción con 3 actividades (columnas M y N). 2. Lo que entregamos (productos): plan comercial 2027; contratos y ventas registradas; informe trimestral de recaudo. 3. Lo que cambia pronto (resultado): la extensión vende más servicios a empresas y entidades, con un recaudo controlado cada trimestre. 4. La transformación que buscamos (impacto): los servicios derivados de la investigación y la extensión generan ingresos propios crecientes que fortalecen la sostenibilidad financiera. 5. Tipo de impacto según la guía: interno. | U20: Los ingresos por productos y servicios superan los $515,47 millones de 2025 y su crecimiento se sostiene en el tiempo. Indicador de la guía con que se mide: cantidad de ingresos por productos o servicios que son resultado de la implementación de la investigación, la innovación y el desarrollo tecnológico. Punto de comparación: la línea base de la meta ($515,47 millones recaudados por el Centro de Extensión y Proyección Social en 2025 (Tabla 115) (RC 2025)) y, cuando el estudio lo permita, un grupo de referencia que no recibió la intervención. | V20: 1 | W20: 3 | X20: Dónde se ubica: eje 3, Extensión y proyección institucional, línea 3.2 Fortalecimiento de la innovación para la Proyección Institucional, meta 3.2.1.2 del PDI 2025 a 2032. Qué cambió frente a 2026: se mantiene. Se mantiene con meta financiera explícita. Cómo se mide la meta: Ingresos por venta de servicios de extensión (millones $). Línea base: $515,47 millones recaudados por el Centro de Extensión y Proyección Social en 2025 (Tabla 115) (RC 2025). Meta 2027: Sugerida por la OAP: $590 millones, 7% anual sobre el recaudo 2025,. Cómo se mide el impacto: cantidad de ingresos por productos o servicios que son resultado de la implementación de la investigación, la innovación y el desarrollo tecnológico. El indicador sale de la Guía Metodológica para la Evaluación de Impacto Institucional y se lee frente a la línea base. Qué esperamos obtener: los servicios derivados de la investigación y la extensión generan ingresos propios crecientes que fortalecen la sostenibilidad financiera. Cómo se hace el seguimiento: cada trimestre las áreas reportan en el SUIE el avance de las actividades con su evidencia; la Oficina Asesora de Planeación verifica la pertinencia de los productos, consolida el avance de las acciones y de la meta y lo presenta al Comité Institucional de Gestión y Desempeño. Al cierre de 2027 se compara el indicador de la meta con su línea base. | Y20: Sin alertas.
E21: 3.2.1.3. Implementar mecanismos de retroalimentación continua de la oferta de programas de extensión y proyección social. | F21: Se mantiene | G21: Se mantiene. | H21: N.° de mecanismos aplicados y % de ofertas evaluadas | I21: Encuestas aplicadas por el Centro de Lenguas en 2026 (Hoja de Ruta); sin mecanismo institucional unificado | J21: Sugerida por la OAP: 100% de las ofertas evaluadas cada periodo | K21: Sugerida por la OAP: 1 mecanismo institucional de retroalimentación aplicado al 100% de las ofertas de extensión 2027, con informe semestral | L21: Sugerida por la OAP. | M21: AC27.26. Instalar un ciclo de mejora continua de la oferta de extensión basado en la opinión de los participantes. | N21: AC27.26, actividades: 1. Diseñar el instrumento único de retroalimentación (satisfacción, pertinencia, aplicación en el trabajo) (A27-062). Producto: instrumento aprobado. 2. Aplicarlo al cierre de cada oferta y consolidar resultados (A27-063). Producto: informe semestral. 3. Ajustar el portafolio con base en los resultados (A27-064). Producto: acta de ajustes. | O21: GIT Extensión y Proyección Social (incluye ETDH) (141) | P21: Sin presupuesto registrado en la matriz plurianual | Q21: Académica | R21: Impacto en las labores sustantivas: docencia y formación, investigación e innovación, extensión y proyección social. | S21: Cantidad de procesos académicos y académico administrativos que mejoran. | T21: 1. Lo que hacemos: 1 acción con 3 actividades (columnas M y N). 2. Lo que entregamos (productos): instrumento aprobado; informe semestral; acta de ajustes. 3. Lo que cambia pronto (resultado): todas las ofertas de extensión se evalúan con un instrumento único y sus resultados se usan para ajustar el portafolio. 4. La transformación que buscamos (impacto): la oferta de extensión mejora periodo a periodo con base en la voz de los participantes. 5. Tipo de impacto según la guía: interno. | U21: Aumenta el número de procesos de extensión ajustados con base en la retroalimentación y mejora la satisfacción y la aplicación en el trabajo reportada por los participantes. Indicador de la guía con que se mide: cantidad de procesos académicos y académico administrativos que mejoran. Punto de comparación: la línea base de la meta (Encuestas aplicadas por el Centro de Lenguas en 2026 (Hoja de Ruta); sin mecanismo institucional unificado) y, cuando el estudio lo permita, un grupo de referencia que no recibió la intervención. | V21: 1 | W21: 3 | X21: Dónde se ubica: eje 3, Extensión y proyección institucional, línea 3.2 Fortalecimiento de la innovación para la Proyección Institucional, meta 3.2.1.3 del PDI 2025 a 2032. Qué cambió frente a 2026: se mantiene. Se mantiene. Cómo se mide la meta: N.° de mecanismos aplicados y % de ofertas evaluadas. Línea base: Encuestas aplicadas por el Centro de Lenguas en 2026 (Hoja de Ruta); sin mecanismo institucional unificado. Meta 2027: Sugerida por la OAP: 1 mecanismo institucional de retroalimentación aplicado al 100% de las ofertas de extensión 2027, con informe semestral. Cómo se mide el impacto: cantidad de procesos académicos y académico administrativos que mejoran. El indicador sale de la Guía Metodológica para la Evaluación de Impacto Institucional y se lee frente a la línea base. Qué esperamos obtener: la oferta de extensión mejora periodo a periodo con base en la voz de los participantes. Cómo se hace el seguimiento: cada trimestre las áreas reportan en el SUIE el avance de las actividades con su evidencia; la Oficina Asesora de Planeación verifica la pertinencia de los productos, consolida el avance de las acciones y de la meta y lo presenta al Comité Institucional de Gestión y Desempeño. Al cierre de 2027 se compara el indicador de la meta con su línea base. | Y21: Sin alertas.
E22: 3.2.1.4. Alinear la formación en una segunda lengua en la ETITC con los estándares del Marco Común Europeo de Referencia para las Lenguas. | F22: Se mantiene | G22: Se mantiene. | H22: % de cursos de segunda lengua alineados al MCER | I22: 14 cursos de inglés y alemán ofertados en 2025 por niveles A1 a B2 (224 participantes en cursos libres y de lenguas) (RC 2025) | J22: Sugerida por la OAP: 100% de los cursos alineados y certificados por nivel MCER | K22: Sugerida por la OAP: 100% de los cursos con syllabus y evaluación alineados a niveles MCER A1-B2, prueba de clasificación institucional y 2 cursos virtuales | L22: Sugerida por la OAP. | M22: AC27.27. Alinear la formación en segunda lengua con el Marco Común Europeo de Referencia y ampliarla con oferta virtual. | N22: AC27.27, actividades: 1. Diagnosticar los cursos frente a los descriptores del MCER (A27-065). Producto: diagnóstico. 2. Ajustar syllabus, evaluación y prueba de clasificación (A27-066). Producto: syllabus y prueba aprobados. 3. Ofrecer 2 cursos virtuales de segunda lengua (A27-067). Producto: cursos virtuales ofertados. | O22: Centro de Lenguas (CEL) (141) | P22: Sin presupuesto registrado en la matriz plurianual | Q22: Egresados | R22: Transformaciones de vidas (condiciones de vida movilidad social) de las personas con las que se interactúa. Cambios curriculares y mejoramiento de programas | S22: Índice de empleabilidad en el corto plazo tras finalizar el programa formativo. Resultados del valor agregado (diferencia entre el desarrollo de competencias antes de ingresar a la Escuela y lo que demuestra al egresar). | T22: 1. Lo que hacemos: 1 acción con 3 actividades (columnas M y N). 2. Lo que entregamos (productos): diagnóstico; syllabus y prueba aprobados; cursos virtuales ofertados. 3. Lo que cambia pronto (resultado): los cursos de segunda lengua quedan alineados con los niveles del MCER y se ofrecen también de forma virtual. 4. La transformación que buscamos (impacto): el dominio certificado de una segunda lengua mejora la empleabilidad y la movilidad de estudiantes y egresados. 5. Tipo de impacto según la guía: interno y externo e interno. | U22: Crecen el valor agregado en competencias de segunda lengua y la empleabilidad de quienes certifican un nivel. Indicador de la guía con que se mide: índice de empleabilidad en el corto plazo tras finalizar el programa formativo. Punto de comparación: la línea base de la meta (14 cursos de inglés y alemán ofertados en 2025 por niveles A1 a B2 (224 participantes en cursos libres y de lenguas) (RC 2025)) y, cuando el estudio lo permita, un grupo de referencia que no recibió la intervención. | V22: 1 | W22: 3 | X22: Dónde se ubica: eje 3, Extensión y proyección institucional, línea 3.2 Fortalecimiento de la innovación para la Proyección Institucional, meta 3.2.1.4 del PDI 2025 a 2032. Qué cambió frente a 2026: se mantiene. Se mantiene. Cómo se mide la meta: % de cursos de segunda lengua alineados al MCER. Línea base: 14 cursos de inglés y alemán ofertados en 2025 por niveles A1 a B2 (224 participantes en cursos libres y de lenguas) (RC 2025). Meta 2027: Sugerida por la OAP: 100% de los cursos con syllabus y evaluación alineados a niveles MCER A1-B2, prueba de clasificación institucional y 2 cursos virtuales. Cómo se mide el impacto: índice de empleabilidad en el corto plazo tras finalizar el programa formativo. El indicador sale de la Guía Metodológica para la Evaluación de Impacto Institucional y se lee frente a la línea base. Qué esperamos obtener: el dominio certificado de una segunda lengua mejora la empleabilidad y la movilidad de estudiantes y egresados. Cómo se hace el seguimiento: cada trimestre las áreas reportan en el SUIE el avance de las actividades con su evidencia; la Oficina Asesora de Planeación verifica la pertinencia de los productos, consolida el avance de las acciones y de la meta y lo presenta al Comité Institucional de Gestión y Desempeño. Al cierre de 2027 se compara el indicador de la meta con su línea base. | Y22: Sin alertas.
C23: 3.3 Interacción con el sector productivo y social | D23: 3.3.1. Garantizar una sólida interacción con agentes del sector productivo y social, relacionados con el quehacer de la ETITC. | E23: 3.3.1.1. Garantizar la participación y representación del 100% de la programación de la ETITC en eventos académicos, empresariales y de proyección social, de acuerdo con disponibilidad de recursos. | F23: Se mantiene | G23: Se mantiene. | H23: % de la programación de eventos con participación institucional | I23: Participación en ferias universitarias en 2025 (EDUTECNIA, Expoestudiantes, colegios) (RC 2025) | J23: 100% | K23: 100% de la programación 2027 | L23: MPI | M23: AC27.28. Asegurar la presencia institucional en los eventos académicos, empresariales y sociales que aportan a la misión, con una agenda anual priorizada. | N23: AC27.28, actividades: 1. Construir la agenda anual de eventos 2027 con criterios de pertinencia (A27-068). Producto: agenda aprobada. 2. Participar en los eventos programados y promocionar la oferta institucional (A27-069). Producto: informe de participación. | O23: GIT Extensión y Proyección Social (incluye ETDH) (141) | P23: Sin presupuesto registrado en la matriz plurianual | Q23: Valor Público | R23: Contribución al desarrollo social y comunitario, económico, sostenibilidad ambiental, sector educativo, sector productivo y industrial, desarrollo tecnológico, nacional e internacional. Impacto a actores (estudiantes, docentes, administrativos, egresados) y organizaciones (sector externo y sociedad en general) en valores. | S23: Cantidad de grupos comunitarios establecidos o fortalecidos como resultado del proyecto. Porcentaje de actores que evidencian cambios significativos en sus valores y actitudes como consecuencia de las intervenciones institucionales. | T23: 1. Lo que hacemos: 1 acción con 2 actividades (columnas M y N). 2. Lo que entregamos (productos): agenda aprobada; informe de participación. 3. Lo que cambia pronto (resultado): la Escuela participa en los eventos priorizados de su agenda anual y promociona su oferta. 4. La transformación que buscamos (impacto): la presencia institucional crea vínculos duraderos con comunidades y empresas. 5. Tipo de impacto según la guía: externo. | U23: Aumenta la cantidad de grupos comunitarios o redes con los que la Escuela mantiene trabajo después de los eventos. Indicador de la guía con que se mide: cantidad de grupos comunitarios establecidos o fortalecidos como resultado del proyecto. Punto de comparación: la línea base de la meta (Participación en ferias universitarias en 2025 (EDUTECNIA, Expoestudiantes, colegios) (RC 2025)) y, cuando el estudio lo permita, un grupo de referencia que no recibió la intervención. | V23: 1 | W23: 2 | X23: Dónde se ubica: eje 3, Extensión y proyección institucional, línea 3.3 Interacción con el sector productivo y social, meta 3.3.1.1 del PDI 2025 a 2032. Qué cambió frente a 2026: se mantiene. Se mantiene. Cómo se mide la meta: % de la programación de eventos con participación institucional. Línea base: Participación en ferias universitarias en 2025 (EDUTECNIA, Expoestudiantes, colegios) (RC 2025). Meta 2027: 100% de la programación 2027. Cómo se mide el impacto: cantidad de grupos comunitarios establecidos o fortalecidos como resultado del proyecto. El indicador sale de la Guía Metodológica para la Evaluación de Impacto Institucional y se lee frente a la línea base. Qué esperamos obtener: la presencia institucional crea vínculos duraderos con comunidades y empresas. Cómo se hace el seguimiento: cada trimestre las áreas reportan en el SUIE el avance de las actividades con su evidencia; la Oficina Asesora de Planeación verifica la pertinencia de los productos, consolida el avance de las acciones y de la meta y lo presenta al Comité Institucional de Gestión y Desempeño. Al cierre de 2027 se compara el indicador de la meta con su línea base. | Y23: Sin alertas.
E24: 3.3.1.2. Ejecutar el 100% del Plan Estratégico de Comunicación de la Vicerrectoría de Extensión y Proyección Social, asegurando su efectividad y alcance. [Enunciado vigente del PDI. En 2027 se reorienta sin crear la vicerrectoría: ver la columna «Qué cambia frente a 2026».] | F24: Se reorienta | G24: Como no se creará la Vicerrectoría de Extensión, no habrá un plan propio de esa dependencia: la meta se cumple con un componente de comunicación de la extensión dentro del Plan Estratégico de Comunicaciones y Posicionamiento 2025 a 2032, a cargo de Comunicaciones con el GIT de Extensión. | H24: % de ejecución del componente de comunicación de la extensión dentro del plan institucional | I24: Plan Estratégico de Comunicaciones y Posicionamiento 2025 a 2032 institucional en ejecución (Contrato 350-2025); la extensión no tiene componente propio (RC 2025) | J24: 100% | K24: Sugerida por la OAP: componente de comunicación de la extensión incluido en el plan institucional 2025 a 2032 y 100% de lo programado para 2027 ejecutado | L24: Sugerida por la OAP. | M24: AC27.29. Posicionar la oferta de extensión con un componente propio dentro del Plan Estratégico de Comunicaciones y medición de su alcance. | N24: AC27.29, actividades: 1. Incluir el componente de comunicación de la extensión en el Plan Estratégico de Comunicaciones 2025 a 2032 (A27-070). Producto: componente aprobado. 2. Ejecutar las piezas y campañas de la oferta de extensión (A27-071). Producto: informe de ejecución. 3. Medir alcance y conversión (inscritos por campaña) (A27-072). Producto: informe de alcance. | O24: Comunicaciones y Mercadeo (100) GIT Extensión y Proyección Social (incluye ETDH) (141) | P24: Sin presupuesto registrado en la matriz plurianual | Q24: Valor Público | R24: Impacto a actores (estudiantes, docentes, administrativos, egresados) y organizaciones (sector externo y sociedad en general) en valores. | S24: Porcentaje de actores que evidencian cambios significativos en sus valores y actitudes como consecuencia de las intervenciones institucionales. | T24: 1. Lo que hacemos: 1 acción con 3 actividades (columnas M y N). 2. Lo que entregamos (productos): componente aprobado; informe de ejecución; informe de alcance. 3. Lo que cambia pronto (resultado): la oferta de extensión tiene campañas propias y su alcance se mide. 4. La transformación que buscamos (impacto): los públicos externos conocen la oferta de extensión y eso se refleja en más inscritos y en mejor percepción de la Escuela. 5. Tipo de impacto según la guía: externo. | U24: Crece el número de inscritos atribuible a las campañas y mejora la percepción de los públicos externos sobre la ETITC. Indicador de la guía con que se mide: porcentaje de actores que evidencian cambios significativos en sus valores y actitudes como consecuencia de las intervenciones institucionales. Punto de comparación: la línea base de la meta (Plan Estratégico de Comunicaciones y Posicionamiento 2025 a 2032 institucional en ejecución (Contrato 350-2025); la extensión no tiene componente propio (RC 2025)) y, cuando el estudio lo permita, un grupo de referencia que no recibió la intervención. | V24: 1 | W24: 3 | X24: Dónde se ubica: eje 3, Extensión y proyección institucional, línea 3.3 Interacción con el sector productivo y social, meta 3.3.1.2 del PDI 2025 a 2032. Qué cambió frente a 2026: se reorienta. Como no se creará la Vicerrectoría de Extensión, no habrá un plan propio de esa dependencia: la meta se cumple con un componente de comunicación de la extensión dentro del Plan Estratégico de Comunicaciones y Posicionamiento 2025 a 2032, a cargo de Comunicaciones con el GIT de Extensión. Cómo se mide la meta: % de ejecución del componente de comunicación de la extensión dentro del plan institucional. Línea base: Plan Estratégico de Comunicaciones y Posicionamiento 2025 a 2032 institucional en ejecución (Contrato 350-2025); la extensión no tiene componente propio (RC 2025). Meta 2027: Sugerida por la OAP: componente de comunicación de la extensión incluido en el plan institucional 2025 a 2032 y 100% de lo programado para 2027 ejecutado. Cómo se mide el impacto: porcentaje de actores que evidencian cambios significativos en sus valores y actitudes como consecuencia de las intervenciones institucionales. El indicador sale de la Guía Metodológica para la Evaluación de Impacto Institucional y se lee frente a la línea base. Qué esperamos obtener: los públicos externos conocen la oferta de extensión y eso se refleja en más inscritos y en mejor percepción de la Escuela. Cómo se hace el seguimiento: cada trimestre las áreas reportan en el SUIE el avance de las actividades con su evidencia; la Oficina Asesora de Planeación verifica la pertinencia de los productos, consolida el avance de las acciones y de la meta y lo presenta al Comité Institucional de Gestión y Desempeño. Al cierre de 2027 se compara el indicador de la meta con su línea base. | Y24: El enunciado del PDI menciona la vicerrectoría: se reporta como componente del plan institucional.
E25: 3.3.1.3. Establecer convenios y fortalecer redes de colaboración con sectores productivos, sociales y educativos, tanto públicos como privados. | F25: Se corrige | G25: Se recodifica (el 2026 la tenía como 3.1.1.3 dentro de la línea 3.3). | H25: N.° de convenios y redes activos | I25: 71 convenios activos en 2025 (31 marco nacionales, 22 específicos nacionales, 12 marco internacionales, 1 específico internacional, 5 administrativos) (RC 2025) | J25: Sugerida por la OAP: 90 convenios activos | K25: Sugerida por la OAP: 75 convenios activos, renovación de los que vencen y 4 nuevos, y 2 redes nuevas | L25: Sugerida por la OAP. | M25: AC27.30. Depurar, renovar y ampliar los convenios y las redes de colaboración, de modo que cada convenio vigente tenga uso real. | N25: AC27.30, actividades: 1. Revisar el vencimiento y el uso de los 71 convenios activos (A27-073). Producto: matriz de convenios con estado. 2. Renovar los convenios útiles que vencen y gestionar 4 nuevos (A27-074). Producto: convenios suscritos. 3. Afiliarse a 2 redes nuevas (por ejemplo, RIUC y renovación RCI ASCUN) (A27-075). Producto: actas de afiliación. | O25: GIT Extensión y Proyección Social (incluye ETDH) (141) Internacionalización (ORII) (100) | P25: Sin presupuesto registrado en la matriz plurianual | Q25: Sector Productivo | R25: Contribución al desarrollo social y comunitario, económico, sostenibilidad ambiental, sector educativo, sector productivo y industrial, desarrollo tecnológico, nacional e internacional. | S25: Tasas de productividad y competitividad después del proyecto. Cantidad de grupos comunitarios establecidos o fortalecidos como resultado del proyecto. | T25: 1. Lo que hacemos: 1 acción con 3 actividades (columnas M y N). 2. Lo que entregamos (productos): matriz de convenios con estado; convenios suscritos; actas de afiliación. 3. Lo que cambia pronto (resultado): los convenios quedan depurados, los útiles se renuevan y se suman convenios y redes nuevas. 4. La transformación que buscamos (impacto): los convenios se traducen en proyectos con efectos medibles en la productividad de las organizaciones y en las comunidades. 5. Tipo de impacto según la guía: externo. | U25: Aumenta el número de convenios con proyectos ejecutados y con mejoras verificables en productividad o en fortalecimiento comunitario. Indicador de la guía con que se mide: tasas de productividad y competitividad después del proyecto. Punto de comparación: la línea base de la meta (71 convenios activos en 2025 (31 marco nacionales, 22 específicos nacionales, 12 marco internacionales, 1 específico internacional, 5 administrativos) (RC 2025)) y, cuando el estudio lo permita, un grupo de referencia que no recibió la intervención. | V25: 1 | W25: 3 | X25: Dónde se ubica: eje 3, Extensión y proyección institucional, línea 3.3 Interacción con el sector productivo y social, meta 3.3.1.3 del PDI 2025 a 2032. Qué cambió frente a 2026: se corrige. Se recodifica (el 2026 la tenía como 3.1.1.3 dentro de la línea 3.3). Cómo se mide la meta: N.° de convenios y redes activos. Línea base: 71 convenios activos en 2025 (31 marco nacionales, 22 específicos nacionales, 12 marco internacionales, 1 específico internacional, 5 administrativos) (RC 2025). Meta 2027: Sugerida por la OAP: 75 convenios activos, renovación de los que vencen y 4 nuevos, y 2 redes nuevas. Cómo se mide el impacto: tasas de productividad y competitividad después del proyecto. El indicador sale de la Guía Metodológica para la Evaluación de Impacto Institucional y se lee frente a la línea base. Qué esperamos obtener: los convenios se traducen en proyectos con efectos medibles en la productividad de las organizaciones y en las comunidades. Cómo se hace el seguimiento: cada trimestre las áreas reportan en el SUIE el avance de las actividades con su evidencia; la Oficina Asesora de Planeación verifica la pertinencia de los productos, consolida el avance de las acciones y de la meta y lo presenta al Comité Institucional de Gestión y Desempeño. Al cierre de 2027 se compara el indicador de la meta con su línea base. | Y25: Sin alertas.
A26: 4. Transformación institucional | B26: 4. Pensar la ETITC mediante el desarrollo de sus horizontes de sentido, para que la comunidad contribuya en la transformación de vida de los integrantes de la institución, la sociedad y el planeta. | C26: 4.1 Dimensión estratégica | D26: 4.1.1. Consolidar las capacidades institucionales para soportar su posicionamiento como universidad tecnológica de alta calidad. | E26: 4.1.1.1. Cumplir al 2032 con el 90% en el Plan de Desarrollo Institucional 2025 a 2032 de la ETITC. | F26: Se mantiene | G26: Se mantiene. El «cambio de carácter a universidad» (4.1.1.4 en 2026) sale como meta y queda como hito transversal. | H26: % de avance acumulado del PDI | I26: 22% de avance acumulado previsto a 2026 (MPI); cumplimiento del plan de acción 2025: 70,7% (RC 2025) | J26: 90% | K26: 33% de avance acumulado del PDI | L26: MPI | M26: AC27.31. Fortalecer el seguimiento del PDI para que el avance reportado corresponda a productos pertinentes y verificables. AC27.32. Adelantar los trámites de transformación de la ETITC en universidad. | N26: AC27.31, actividades: 1. Adoptar el protocolo de mesas de trabajo en el SGC (A27-076). Producto: procedimiento adoptado. 2. Extender la revisión de pertinencia a todos los productos ejecutados (A27-077). Producto: matriz de aprobación. 3. Hacer seguimiento trimestral del PAA 2027 en el Navegador Estratégico (A27-078). Producto: informes trimestrales. AC27.32, actividades: 1. Adelantar los trámites de transformación a universidad (Ley 30 de 1992, Ley 749 de 2002) (A27-079). Producto: expediente radicado. | O26: Planeación y Plan de Acción (101) Despacho de Rectoría (100) | P26: Sin presupuesto registrado en la matriz plurianual | Q26: Académica | R26: Cambios en la cultura institucional (incluida la cultura de la calidad). Impacto en las labores sustantivas: docencia y formación, investigación e innovación, extensión y proyección social. | S26: Tasa de adopción de nuevos procesos atribuible a la implementación del sistema de calidad. Cantidad de procesos académicos y académico administrativos que mejoran. | T26: 1. Lo que hacemos: 2 acciones con 4 actividades (columnas M y N). 2. Lo que entregamos (productos): procedimiento adoptado; matriz de aprobación; informes trimestrales; expediente radicado. 3. Lo que cambia pronto (resultado): el seguimiento del PDI reporta productos pertinentes y verificables, y avanzan los trámites de transformación en universidad. 4. La transformación que buscamos (impacto): la planeación se convierte en práctica institucional: procesos nuevos adoptados y mejoras verificables en la gestión. 5. Tipo de impacto según la guía: interno. | U26: Crece la tasa de adopción de procesos nuevos y el avance acumulado del PDI llega al 33% en 2027 con evidencias validadas. Indicador de la guía con que se mide: tasa de adopción de nuevos procesos atribuible a la implementación del sistema de calidad. Punto de comparación: la línea base de la meta (22% de avance acumulado previsto a 2026 (MPI); cumplimiento del plan de acción 2025: 70,7% (RC 2025)) y, cuando el estudio lo permita, un grupo de referencia que no recibió la intervención. | V26: 2 | W26: 4 | X26: Dónde se ubica: eje 4, Transformación institucional, línea 4.1 Dimensión estratégica, meta 4.1.1.1 del PDI 2025 a 2032. Qué cambió frente a 2026: se mantiene. Se mantiene. El «cambio de carácter a universidad» (4.1.1.4 en 2026) sale como meta y queda como hito transversal. Cómo se mide la meta: % de avance acumulado del PDI. Línea base: 22% de avance acumulado previsto a 2026 (MPI); cumplimiento del plan de acción 2025: 70,7% (RC 2025). Meta 2027: 33% de avance acumulado del PDI. Cómo se mide el impacto: tasa de adopción de nuevos procesos atribuible a la implementación del sistema de calidad. El indicador sale de la Guía Metodológica para la Evaluación de Impacto Institucional y se lee frente a la línea base. Qué esperamos obtener: la planeación se convierte en práctica institucional: procesos nuevos adoptados y mejoras verificables en la gestión. Cómo se hace el seguimiento: cada trimestre las áreas reportan en el SUIE el avance de las actividades con su evidencia; la Oficina Asesora de Planeación verifica la pertinencia de los productos, consolida el avance de las acciones y de la meta y lo presenta al Comité Institucional de Gestión y Desempeño. Al cierre de 2027 se compara el indicador de la meta con su línea base. | Y26: Sin alertas.
E27: 4.1.1.2. Alcanzar el 92% en el Índice de Desempeño Institucional del FURAG. | F27: Se mantiene | G27: Se mantiene. Se agregan las acciones del Plan de Mejoramiento con la CGR y las debilidades del ECIC. | H27: Índice de Desempeño Institucional (FURAG) | I27: 87,73% en 2024 (88,24% en 2022 y 87,10% en 2023) (RC 2025) | J27: 92% | K27: Sugerida por la OAP: 90%, la trayectoria lineal de 87,7% en 2024 a 92% en 2032 da 89,3% en 2027, | L27: Sugerida por la OAP. Las dos versiones de la MPI dicen 89% y 92%. | M27: AC27.33. Mejorar el desempeño institucional en el FURAG con un plan de mejora por política del MIPG y el cumplimiento del plan suscrito con la Contraloría. AC27.34. Ordenar la gestión financiera y contable con cierres oportunos, indicadores propios, procedimientos documentados y capacitación. | N27: AC27.33, actividades: 1. Formular el plan de mejora por política MIPG con base en el último FURAG (A27-080). Producto: plan de mejora. 2. Ejecutar el Plan de Mejoramiento con la CGR (7 hallazgos, 24 metas) (A27-082). Producto: avance del plan reportado. AC27.34, actividades: 1. Fijar calendario de cierre con corte único y constituir el rezago a tiempo (A27-081). Producto: calendario y resolución de rezago. 2. Formular indicadores financieros y contables (razón corriente, margen, rotación de cartera) (A27-083). Producto: indicadores en el PAA. 3. Documentar y codificar los procedimientos de gratuidad (A27-084). Producto: procedimientos en el SGC. 4. Incluir capacitación contable en el Plan Institucional de Capacitación (A27-085). Producto: PIC 2027. | O27: Aseguramiento de la Calidad, MIPG y Registros Calificados (101) Gestión Financiera (Presupuesto, Contabilidad, Tesorería) (130) Despacho de la Vicerrectoría Administrativa y Financiera (130) GIT Talento Humano (133) | P27: Sin presupuesto registrado en la matriz plurianual | Q27: Académica | R27: Cambios en la cultura institucional (incluida la cultura de la calidad). | S27: Tasa de adopción de nuevos procesos atribuible a la implementación del sistema de calidad. Porcentaje de la comunidad académica satisfecha con el clima laboral después de la implementación del sistema de calidad. | T27: 1. Lo que hacemos: 2 acciones con 6 actividades (columnas M y N). 2. Lo que entregamos (productos): plan de mejora; avance del plan reportado; calendario y resolución de rezago; indicadores en el PAA; procedimientos en el SGC; PIC 2027. 3. Lo que cambia pronto (resultado): la Escuela cumple su plan de mejora del MIPG y el plan con la Contraloría, y ordena su gestión financiera. 4. La transformación que buscamos (impacto): la Escuela adopta procesos de gestión más eficientes y transparentes, y eso se refleja en el clima laboral y en la confianza de los entes de control. 5. Tipo de impacto según la guía: interno. | U27: El Índice de Desempeño Institucional supera el 87,73% de 2024, disminuyen los hallazgos de control y mejora la satisfacción con el clima laboral. Indicador de la guía con que se mide: tasa de adopción de nuevos procesos atribuible a la implementación del sistema de calidad. Punto de comparación: la línea base de la meta (87,73% en 2024 (88,24% en 2022 y 87,10% en 2023) (RC 2025)) y, cuando el estudio lo permita, un grupo de referencia que no recibió la intervención. | V27: 2 | W27: 6 | X27: Dónde se ubica: eje 4, Transformación institucional, línea 4.1 Dimensión estratégica, meta 4.1.1.2 del PDI 2025 a 2032. Qué cambió frente a 2026: se mantiene. Se mantiene. Se agregan las acciones del Plan de Mejoramiento con la CGR y las debilidades del ECIC. Cómo se mide la meta: Índice de Desempeño Institucional (FURAG). Línea base: 87,73% en 2024 (88,24% en 2022 y 87,10% en 2023) (RC 2025). Meta 2027: Sugerida por la OAP: 90%, la trayectoria lineal de 87,7% en 2024 a 92% en 2032 da 89,3% en 2027,. Cómo se mide el impacto: tasa de adopción de nuevos procesos atribuible a la implementación del sistema de calidad. El indicador sale de la Guía Metodológica para la Evaluación de Impacto Institucional y se lee frente a la línea base. Qué esperamos obtener: la Escuela adopta procesos de gestión más eficientes y transparentes, y eso se refleja en el clima laboral y en la confianza de los entes de control. Cómo se hace el seguimiento: cada trimestre las áreas reportan en el SUIE el avance de las actividades con su evidencia; la Oficina Asesora de Planeación verifica la pertinencia de los productos, consolida el avance de las acciones y de la meta y lo presenta al Comité Institucional de Gestión y Desempeño. Al cierre de 2027 se compara el indicador de la meta con su línea base. | Y27: Las dos versiones de la MPI difieren (92% frente a 89%) y la más reciente supera el 92% antes de 2032.
E28: 4.1.1.3. Lograr la renovación de la acreditación institucional a 8 años. | F28: Se reformula | G28: Hito cumplido en 2026: la ETITC obtuvo la acreditación institucional. Para 2027 la meta pasa a «mantener la acreditación»: ejecutar el plan de mejoramiento derivado de la evaluación y preparar la renovación. | H28: Acreditación institucional vigente y % de ejecución del plan de mejoramiento institucional | I28: Acreditación institucional en alta calidad obtenida en 2026; 1 visita de evaluación con fines de acreditación institucional en 2025 (RC 2025) | J28: Renovación a 8 años | K28: Sugerida por la OAP: 100% de las acciones del plan de mejoramiento institucional programadas para 2027 ejecutadas y sistema de seguimiento a las condiciones de calidad operando | L28: Sugerida por la OAP. | M28: AC27.35. Sostener la acreditación institucional mediante el plan de mejoramiento derivado de las recomendaciones del CNA y su seguimiento semestral. AC27.36. Divulgar la acreditación institucional ante la comunidad y los públicos externos. | N28: AC27.35, actividades: 1. Formular el plan de mejoramiento institucional derivado de las recomendaciones del CNA (A27-086). Producto: plan aprobado. 2. Ejecutar y hacer seguimiento semestral al plan de mejoramiento (A27-087). Producto: informes semestrales. 3. Cerrar los productos vencidos de Autoevaluación (32 al 2 de septiembre de 2026) (A27-089). Producto: productos reprogramados. AC27.36, actividades: 1. Divulgar la acreditación institucional (estrategia de divulgación) (A27-088). Producto: piezas y alcance. | O28: Autoevaluación y Acreditación (101) Comunicaciones y Mercadeo (100) | P28: Sin presupuesto registrado en la matriz plurianual | Q28: Académica | R28: Cambios en la cultura institucional (incluida la cultura de la calidad). Cambios curriculares y mejoramiento de programas | S28: Tasa de adopción de nuevos procesos atribuible a la implementación del sistema de calidad. Resultados del valor agregado (diferencia entre el desarrollo de competencias antes de ingresar a la Escuela y lo que demuestra al egresar). | T28: 1. Lo que hacemos: 2 acciones con 4 actividades (columnas M y N). 2. Lo que entregamos (productos): plan aprobado; informes semestrales; productos reprogramados; piezas y alcance. 3. Lo que cambia pronto (resultado): el plan de mejoramiento institucional se ejecuta con seguimiento semestral y la acreditación se divulga. 4. La transformación que buscamos (impacto): la cultura de la calidad se mantiene después de la acreditación y se ve en procesos que mejoran. 5. Tipo de impacto según la guía: interno. | U28: Aumenta la tasa de adopción de procesos de calidad y mejoran los resultados de valor agregado de los estudiantes. Indicador de la guía con que se mide: tasa de adopción de nuevos procesos atribuible a la implementación del sistema de calidad. Punto de comparación: la línea base de la meta (Acreditación institucional en alta calidad obtenida en 2026; 1 visita de evaluación con fines de acreditación institucional en 2025 (RC 2025)) y, cuando el estudio lo permita, un grupo de referencia que no recibió la intervención. | V28: 2 | W28: 4 | X28: Dónde se ubica: eje 4, Transformación institucional, línea 4.1 Dimensión estratégica, meta 4.1.1.3 del PDI 2025 a 2032. Qué cambió frente a 2026: se reformula. Hito cumplido en 2026: la ETITC obtuvo la acreditación institucional. Para 2027 la meta pasa a «mantener la acreditación»: ejecutar el plan de mejoramiento derivado de la evaluación y preparar la renovación. Cómo se mide la meta: Acreditación institucional vigente y % de ejecución del plan de mejoramiento institucional. Línea base: Acreditación institucional en alta calidad obtenida en 2026; 1 visita de evaluación con fines de acreditación institucional en 2025 (RC 2025). Meta 2027: Sugerida por la OAP: 100% de las acciones del plan de mejoramiento institucional programadas para 2027 ejecutadas y sistema de seguimiento a las condiciones de calidad operando. Cómo se mide el impacto: tasa de adopción de nuevos procesos atribuible a la implementación del sistema de calidad. El indicador sale de la Guía Metodológica para la Evaluación de Impacto Institucional y se lee frente a la línea base. Qué esperamos obtener: la cultura de la calidad se mantiene después de la acreditación y se ve en procesos que mejoran. Cómo se hace el seguimiento: cada trimestre las áreas reportan en el SUIE el avance de las actividades con su evidencia; la Oficina Asesora de Planeación verifica la pertinencia de los productos, consolida el avance de las acciones y de la meta y lo presenta al Comité Institucional de Gestión y Desempeño. Al cierre de 2027 se compara el indicador de la meta con su línea base. | Y28: Registrar en el plan el número de años otorgado por la resolución de acreditación.
C29: 4.2 Arquitectura institucional | D29: 4.2.1. Contar con una arquitectura institucional que garantice la gobernanza, efectividad y fluida comunicación entre todas las áreas de la Institución. | E29: 4.2.1.1. Contar con el 100% de la estructura organizacional académica y administrativa operando. | F29: Se corrige | G29: Se recodifica (el 2026 la tenía como 4.2.1.2). Recibe la formalización laboral (Decreto 391 de 2025), que el 2026 tenía en la línea 1.5. | H29: % de la estructura organizacional aprobada y operando | I29: Estructura del Decreto 902 de 2013 con 17 dependencias y GIT de la Resolución 215 de 2022; 124 cargos en el plan de formalización (75 docentes y 49 administrativos) (MPI) | J29: 100% | K29: 15 docentes de tiempo completo y 10 administrativos vinculados por formalización | L29: MPI | M29: AC27.37. Ajustar la estructura organizacional a la operación real de la Escuela y avanzar en la formalización laboral. | N29: AC27.37, actividades: 1. Elaborar el estudio técnico de rediseño institucional para el cambio de carácter (A27-090). Producto: estudio técnico. 2. Definir quién ejerce la jefatura de Control Interno, para que la Escuela pueda suscribir la evaluación del control interno contable (A27-091). Producto: acto administrativo. 3. Vincular 15 docentes de tiempo completo y 10 administrativos (formalización laboral) (A27-092). Producto: actos de vinculación. | O29: Planeación y Plan de Acción (101) Despacho de Rectoría (100) GIT Talento Humano (133) | P29: A27-092: 3.024 (MPI, docentes) | Q29: Académica | R29: Cambios en la cultura institucional (incluida la cultura de la calidad). Impacto en las labores sustantivas: docencia y formación, investigación e innovación, extensión y proyección social. | S29: Porcentaje de la comunidad académica satisfecha con el clima laboral después de la implementación del sistema de calidad. Cantidad de procesos académicos y académico administrativos que mejoran. | T29: 1. Lo que hacemos: 1 acción con 3 actividades (columnas M y N). 2. Lo que entregamos (productos): estudio técnico; acto administrativo; actos de vinculación. 3. Lo que cambia pronto (resultado): la estructura organizacional se ajusta a la operación y se vinculan 15 docentes de tiempo completo y 10 administrativos. 4. La transformación que buscamos (impacto): la estructura y la planta responden a la operación real y mejoran el clima laboral y la calidad del servicio. 5. Tipo de impacto según la guía: interno. | U29: Mejora la satisfacción con el clima laboral y crece el número de procesos que mejoran tras la formalización. Indicador de la guía con que se mide: porcentaje de la comunidad académica satisfecha con el clima laboral después de la implementación del sistema de calidad. Punto de comparación: la línea base de la meta (Estructura del Decreto 902 de 2013 con 17 dependencias y GIT de la Resolución 215 de 2022; 124 cargos en el plan de formalización (75 docentes y 49 administrativos) (MPI)) y, cuando el estudio lo permita, un grupo de referencia que no recibió la intervención. | V29: 1 | W29: 3 | X29: Dónde se ubica: eje 4, Transformación institucional, línea 4.2 Arquitectura institucional, meta 4.2.1.1 del PDI 2025 a 2032. Qué cambió frente a 2026: se corrige. Se recodifica (el 2026 la tenía como 4.2.1.2). Recibe la formalización laboral (Decreto 391 de 2025), que el 2026 tenía en la línea 1.5. Cómo se mide la meta: % de la estructura organizacional aprobada y operando. Línea base: Estructura del Decreto 902 de 2013 con 17 dependencias y GIT de la Resolución 215 de 2022; 124 cargos en el plan de formalización (75 docentes y 49 administrativos) (MPI). Meta 2027: 15 docentes de tiempo completo y 10 administrativos vinculados por formalización. Cómo se mide el impacto: porcentaje de la comunidad académica satisfecha con el clima laboral después de la implementación del sistema de calidad. El indicador sale de la Guía Metodológica para la Evaluación de Impacto Institucional y se lee frente a la línea base. Qué esperamos obtener: la estructura y la planta responden a la operación real y mejoran el clima laboral y la calidad del servicio. Cómo se hace el seguimiento: cada trimestre las áreas reportan en el SUIE el avance de las actividades con su evidencia; la Oficina Asesora de Planeación verifica la pertinencia de los productos, consolida el avance de las acciones y de la meta y lo presenta al Comité Institucional de Gestión y Desempeño. Al cierre de 2027 se compara el indicador de la meta con su línea base. | Y29: Sin alertas.
E30: 4.2.1.2. Contar con un (1) sistema de información estratégico. | F30: Se reformula | G30: Hito prácticamente cumplido en 2026: el SIUE está en marcha. Para 2027 la meta pasa de «contar con» a «consolidar y usar»: integración de módulos, uso por todas las dependencias y una sola cifra oficial. Se recodifica (el 2026 la tenía como 4.2.1.1). | H30: Sistema de información estratégico operando y % de dependencias que reportan en él | I30: SIUE en marcha y prácticamente implementado al cierre de 2026 (confirmado por la OAP); Hoja de Ruta Power Apps y Navegador Estratégico en uso | J30: 1 sistema | K30: Sugerida por la OAP: SIUE en operación plena: 100% de las dependencias reportando en él y 3 módulos integrados, Hoja de Ruta y Power BI, SNIES-HECAA y repositorio de evidencias, | L30: Sugerida por la OAP. | M30: AC27.38. Consolidar el SIUE como fuente única de información institucional, con módulos integrados y uso por todas las dependencias. AC27.39. Garantizar una sola cifra oficial en los reportes externos, con reporte SNIES certificado, repositorio de soportes y verificación de consistencia. | N30: AC27.38, actividades: 1. Formalizar el cierre de la implementación del SIUE y su manual de uso (A27-093). Producto: acta de entrega y manual. 2. Integrar la Hoja de Ruta Power Apps con el SIUE (A27-094). Producto: integración operando. AC27.39, actividades: 1. Completar el reporte SNIES en plantilla HECAA con certificación de veracidad (A27-095). Producto: reporte certificado. 2. Habilitar un repositorio de soportes de solo lectura para entes externos (A27-096). Producto: repositorio habilitado. 3. Verificar la consistencia de cifras entre MEN, SNIES, CGN y Congreso desde el SIUE (A27-097). Producto: acta de verificación. | O30: Gestión de Proyectos (101) GIT Registro, Control y Admisiones (126) GIT Informática y Telecomunicaciones (132) Planeación y Plan de Acción (101) | P30: Sin presupuesto registrado en la matriz plurianual | Q30: Académica | R30: Cambios en la cultura institucional (incluida la cultura de la calidad). Impacto en las labores sustantivas: docencia y formación, investigación e innovación, extensión y proyección social. | S30: Tasa de adopción de nuevos procesos atribuible a la implementación del sistema de calidad. Cantidad de procesos académicos y académico administrativos que mejoran. | T30: 1. Lo que hacemos: 2 acciones con 5 actividades (columnas M y N). 2. Lo que entregamos (productos): acta de entrega y manual; integración operando; reporte certificado; repositorio habilitado; acta de verificación. 3. Lo que cambia pronto (resultado): el SIUE opera con módulos integrados y todas las dependencias reportan en él. 4. La transformación que buscamos (impacto): las decisiones se toman con una sola cifra oficial y los reportes externos no se contradicen. 5. Tipo de impacto según la guía: interno. | U30: Desaparecen las diferencias de cifras entre MEN, SNIES, CGN y Congreso, y crece la adopción del sistema en las dependencias. Indicador de la guía con que se mide: tasa de adopción de nuevos procesos atribuible a la implementación del sistema de calidad. Punto de comparación: la línea base de la meta (SIUE en marcha y prácticamente implementado al cierre de 2026 (confirmado por la OAP); Hoja de Ruta Power Apps y Navegador Estratégico en uso) y, cuando el estudio lo permita, un grupo de referencia que no recibió la intervención. | V30: 2 | W30: 5 | X30: Dónde se ubica: eje 4, Transformación institucional, línea 4.2 Arquitectura institucional, meta 4.2.1.2 del PDI 2025 a 2032. Qué cambió frente a 2026: se reformula. Hito prácticamente cumplido en 2026: el SIUE está en marcha. Para 2027 la meta pasa de «contar con» a «consolidar y usar»: integración de módulos, uso por todas las dependencias y una sola cifra oficial. Se recodifica (el 2026 la tenía como 4.2.1.1). Cómo se mide la meta: Sistema de información estratégico operando y % de dependencias que reportan en él. Línea base: SIUE en marcha y prácticamente implementado al cierre de 2026 (confirmado por la OAP); Hoja de Ruta Power Apps y Navegador Estratégico en uso. Meta 2027: Sugerida por la OAP: SIUE en operación plena: 100% de las dependencias reportando en él y 3 módulos integrados, Hoja de Ruta y Power BI, SNIES-HECAA y repositorio de evidencias,. Cómo se mide el impacto: tasa de adopción de nuevos procesos atribuible a la implementación del sistema de calidad. El indicador sale de la Guía Metodológica para la Evaluación de Impacto Institucional y se lee frente a la línea base. Qué esperamos obtener: las decisiones se toman con una sola cifra oficial y los reportes externos no se contradicen. Cómo se hace el seguimiento: cada trimestre las áreas reportan en el SUIE el avance de las actividades con su evidencia; la Oficina Asesora de Planeación verifica la pertinencia de los productos, consolida el avance de las acciones y de la meta y lo presenta al Comité Institucional de Gestión y Desempeño. Al cierre de 2027 se compara el indicador de la meta con su línea base. | Y30: Sin alertas.
E31: 4.2.1.3. Consolidar el IBTI como unidad autónoma y adscrita a la Institución con un programa de tránsito inmediato a la educación superior. | F31: Se reincorpora | G31: En 2026 compartía código con otra meta y no tuvo productos en la sábana vigente. | H31: IBTI consolidado como unidad adscrita (fase) | I31: IBTI adscrito a la Vicerrectoría Académica (2024, MPI, columna «Línea base 2024») | J31: IBTI consolidado | K31: Currículos del IBTI y de los programas técnicos profesionales alineados; solicitud de adscripción ante el MEN | L31: MPI | M31: AC27.40. Consolidar el IBTI como unidad adscrita con tránsito inmediato a la educación superior, desde la alineación curricular hasta la aprobación ante el MEN. | N31: AC27.40, actividades: 1. Alinear los currículos del IBTI y de los programas técnicos profesionales (A27-098). Producto: currículos alineados. 2. Definir la propuesta de integración de estructuras (A27-099). Producto: propuesta aprobada. 3. Gestionar la aprobación de la adscripción ante el MEN (A27-100). Producto: solicitud radicada. | O31: IBTI (124) Despacho de la Vicerrectoría Académica (120) | P31: Sin presupuesto registrado en la matriz plurianual | Q31: Valor Público | R31: Transformaciones del territorio (condiciones del desarrollo, especialmente de cobertura y pertinencia en la oferta educativa). Cambios curriculares y mejoramiento de programas | S31: Porcentaje de jóvenes de la comunidad beneficiaria que se escolarizaron con la Institución. Reducción en la tasa de deserción atribuible a la intervención. | T31: 1. Lo que hacemos: 1 acción con 3 actividades (columnas M y N). 2. Lo que entregamos (productos): currículos alineados; propuesta aprobada; solicitud radicada. 3. Lo que cambia pronto (resultado): los currículos quedan alineados y la adscripción del IBTI se radica ante el MEN. 4. La transformación que buscamos (impacto): más jóvenes del IBTI ingresan a la educación superior y permanecen en ella. 5. Tipo de impacto según la guía: externo e interno. | U31: Aumentan la escolarización en la ETITC de los egresados del IBTI y la permanencia de esa cohorte. Indicador de la guía con que se mide: porcentaje de jóvenes de la comunidad beneficiaria que se escolarizaron con la Institución. Punto de comparación: la línea base de la meta (IBTI adscrito a la Vicerrectoría Académica (2024, MPI, columna «Línea base 2024»)) y, cuando el estudio lo permita, un grupo de referencia que no recibió la intervención. | V31: 1 | W31: 3 | X31: Dónde se ubica: eje 4, Transformación institucional, línea 4.2 Arquitectura institucional, meta 4.2.1.3 del PDI 2025 a 2032. Qué cambió frente a 2026: se reincorpora. En 2026 compartía código con otra meta y no tuvo productos en la sábana vigente. Cómo se mide la meta: IBTI consolidado como unidad adscrita (fase). Línea base: IBTI adscrito a la Vicerrectoría Académica (2024, MPI, columna «Línea base 2024»). Meta 2027: Currículos del IBTI y de los programas técnicos profesionales alineados; solicitud de adscripción ante el MEN. Cómo se mide el impacto: porcentaje de jóvenes de la comunidad beneficiaria que se escolarizaron con la Institución. El indicador sale de la Guía Metodológica para la Evaluación de Impacto Institucional y se lee frente a la línea base. Qué esperamos obtener: más jóvenes del IBTI ingresan a la educación superior y permanecen en ella. Cómo se hace el seguimiento: cada trimestre las áreas reportan en el SUIE el avance de las actividades con su evidencia; la Oficina Asesora de Planeación verifica la pertinencia de los productos, consolida el avance de las acciones y de la meta y lo presenta al Comité Institucional de Gestión y Desempeño. Al cierre de 2027 se compara el indicador de la meta con su línea base. | Y31: Sin alertas.
C32: 4.3 Gestión de la comunidad educativa | D32: 4.3.1. Consolidar un modelo de gestión de la [comunidad educativa] que posibilite a la institución como una universidad de alta calidad. | E32: 4.3.1.1. Contar con un (1) sistema estratégico de desarrollo de la comunidad educativa. | F32: Se mantiene | G32: Se mantiene. | H32: Sistema estratégico de desarrollo de la comunidad educativa (fase) | I32: Diagnóstico del modelo de operación flexible en 2026 (MPI) | J32: 1 sistema | K32: Modelo de operación flexible en funcionamiento | L32: MPI | M32: AC27.41. Poner en operación el modelo de operación flexible validado con la comunidad educativa y medir su adopción. | N32: AC27.41, actividades: 1. Validar el modelo de operación flexible con la comunidad educativa (A27-101). Producto: acta de validación. 2. Poner en operación el modelo y medir su adopción (A27-102). Producto: modelo adoptado e informe. | O32: Autoevaluación y Acreditación (101) | P32: Sin presupuesto registrado en la matriz plurianual | Q32: Académica | R32: Cambios curriculares y mejoramiento de programas Cambios en la cultura institucional (incluida la cultura de la calidad). | S32: Nivel de percepción de trabajo colaborativo y construcción de comunidad académica de estudiantes y docentes como consecuencia de su participación en proyectos institucionales. Porcentaje de la comunidad académica satisfecha con el clima laboral después de la implementación del sistema de calidad. | T32: 1. Lo que hacemos: 1 acción con 2 actividades (columnas M y N). 2. Lo que entregamos (productos): acta de validación; modelo adoptado e informe. 3. Lo que cambia pronto (resultado): el modelo de operación flexible funciona y se conoce su nivel de adopción. 4. La transformación que buscamos (impacto): estudiantes y docentes trabajan de manera más colaborativa y se sienten parte de una comunidad académica. 5. Tipo de impacto según la guía: interno. | U32: Mejora el nivel de percepción de trabajo colaborativo y de comunidad académica en la encuesta institucional. Indicador de la guía con que se mide: nivel de percepción de trabajo colaborativo y construcción de comunidad académica de estudiantes y docentes como consecuencia de su participación en proyectos institucionales. Punto de comparación: la línea base de la meta (Diagnóstico del modelo de operación flexible en 2026 (MPI)) y, cuando el estudio lo permita, un grupo de referencia que no recibió la intervención. | V32: 1 | W32: 2 | X32: Dónde se ubica: eje 4, Transformación institucional, línea 4.3 Gestión de la comunidad educativa, meta 4.3.1.1 del PDI 2025 a 2032. Qué cambió frente a 2026: se mantiene. Se mantiene. Cómo se mide la meta: Sistema estratégico de desarrollo de la comunidad educativa (fase). Línea base: Diagnóstico del modelo de operación flexible en 2026 (MPI). Meta 2027: Modelo de operación flexible en funcionamiento. Cómo se mide el impacto: nivel de percepción de trabajo colaborativo y construcción de comunidad académica de estudiantes y docentes como consecuencia de su participación en proyectos institucionales. El indicador sale de la Guía Metodológica para la Evaluación de Impacto Institucional y se lee frente a la línea base. Qué esperamos obtener: estudiantes y docentes trabajan de manera más colaborativa y se sienten parte de una comunidad académica. Cómo se hace el seguimiento: cada trimestre las áreas reportan en el SUIE el avance de las actividades con su evidencia; la Oficina Asesora de Planeación verifica la pertinencia de los productos, consolida el avance de las acciones y de la meta y lo presenta al Comité Institucional de Gestión y Desempeño. Al cierre de 2027 se compara el indicador de la meta con su línea base. | Y32: Sin alertas.
C33: 4.4 Relacionamiento dialógico | D33: 4.4.1. Lograr el reconocimiento y posicionamiento de la institución como una universidad de alta calidad, a través de un efectivo relacionamiento con el ecosistema (Estado, empresa, academia, sociedad y medio ambiente). | E33: 4.4.1.1. Posicionamiento en un indicador Top of Mind de universidades tecnológicas de carácter público en el país. | F33: Se mantiene | G33: Se mantiene. | H33: Posición en el indicador Top of Mind | I33: Sin medición de Top of Mind; Plan Estratégico de Comunicaciones y Posicionamiento 2025 a 2032 en ejecución (RC 2025) | J33: 1 indicador | K33: Sugerida por la OAP: medición de línea base Top of Mind aplicada y plan de posicionamiento ejecutado al 100% de lo programado para 2027 | L33: Sugerida por la OAP. | M33: AC27.42. Posicionar la marca ETITC con una medición de línea base y campañas de alcance nacional y regional. | N33: AC27.42, actividades: 1. Aplicar la medición de línea base de Top of Mind (A27-103). Producto: informe de medición. 2. Desarrollar campañas de branding con alcance nacional y regional (A27-104). Producto: informe de campañas y alcance. | O33: Comunicaciones y Mercadeo (100) | P33: Sin presupuesto registrado en la matriz plurianual | Q33: Valor Público | R33: Impacto a actores (estudiantes, docentes, administrativos, egresados) y organizaciones (sector externo y sociedad en general) en valores. | S33: Porcentaje de actores que evidencian cambios significativos en sus valores y actitudes como consecuencia de las intervenciones institucionales. | T33: 1. Lo que hacemos: 1 acción con 2 actividades (columnas M y N). 2. Lo que entregamos (productos): informe de medición; informe de campañas y alcance. 3. Lo que cambia pronto (resultado): la Escuela conoce su posición de partida en Top of Mind y ejecuta campañas de marca. 4. La transformación que buscamos (impacto): la ETITC es reconocida por su calidad y ese reconocimiento se refleja en la demanda de cupos. 5. Tipo de impacto según la guía: externo. | U33: Mejora la posición en la segunda medición de Top of Mind y aumenta la relación de inscritos por cupo. Indicador de la guía con que se mide: porcentaje de actores que evidencian cambios significativos en sus valores y actitudes como consecuencia de las intervenciones institucionales. Punto de comparación: la línea base de la meta (Sin medición de Top of Mind; Plan Estratégico de Comunicaciones y Posicionamiento 2025 a 2032 en ejecución (RC 2025)) y, cuando el estudio lo permita, un grupo de referencia que no recibió la intervención. | V33: 1 | W33: 2 | X33: Dónde se ubica: eje 4, Transformación institucional, línea 4.4 Relacionamiento dialógico, meta 4.4.1.1 del PDI 2025 a 2032. Qué cambió frente a 2026: se mantiene. Se mantiene. Cómo se mide la meta: Posición en el indicador Top of Mind. Línea base: Sin medición de Top of Mind; Plan Estratégico de Comunicaciones y Posicionamiento 2025 a 2032 en ejecución (RC 2025). Meta 2027: Sugerida por la OAP: medición de línea base Top of Mind aplicada y plan de posicionamiento ejecutado al 100% de lo programado para 2027. Cómo se mide el impacto: porcentaje de actores que evidencian cambios significativos en sus valores y actitudes como consecuencia de las intervenciones institucionales. El indicador sale de la Guía Metodológica para la Evaluación de Impacto Institucional y se lee frente a la línea base. Qué esperamos obtener: la ETITC es reconocida por su calidad y ese reconocimiento se refleja en la demanda de cupos. Cómo se hace el seguimiento: cada trimestre las áreas reportan en el SUIE el avance de las actividades con su evidencia; la Oficina Asesora de Planeación verifica la pertinencia de los productos, consolida el avance de las acciones y de la meta y lo presenta al Comité Institucional de Gestión y Desempeño. Al cierre de 2027 se compara el indicador de la meta con su línea base. | Y33: Sin alertas.
E34: 4.4.1.2. Cinco (5) alianzas estratégicas. | F34: Se corrige | G34: Se restituye la cifra de 5 (el 2026 la había eliminado). | H34: N.° de alianzas estratégicas formalizadas | I34: 71 convenios activos en 2025, sin clasificación de alianzas estratégicas del PDI (RC 2025) | J34: 5 alianzas | K34: 5 proyectos o alianzas estratégicas suscritos | L34: MPI | M34: AC27.43. Formalizar cinco alianzas estratégicas con criterios claros y medir su efecto en la internacionalización y la cooperación. | N34: AC27.43, actividades: 1. Definir los criterios de «alianza estratégica» y clasificar los convenios vigentes (A27-105). Producto: criterios y clasificación. 2. Suscribir como mínimo 5 proyectos con el sector empresarial, académico, ambiental y gubernamental (A27-106). Producto: convenios suscritos. 3. Iniciar el estudio de impacto de Internacionalización y cooperación (A27-107). Producto: diseño del estudio. | O34: Internacionalización (ORII) (100) | P34: Sin presupuesto registrado en la matriz plurianual | Q34: Sector Productivo | R34: Contribución al desarrollo social y comunitario, económico, sostenibilidad ambiental, sector educativo, sector productivo y industrial, desarrollo tecnológico, nacional e internacional. | S34: Tasas de productividad y competitividad después del proyecto. Cantidad de grupos comunitarios establecidos o fortalecidos como resultado del proyecto. | T34: 1. Lo que hacemos: 1 acción con 3 actividades (columnas M y N). 2. Lo que entregamos (productos): criterios y clasificación; convenios suscritos; diseño del estudio. 3. Lo que cambia pronto (resultado): existen criterios claros de alianza estratégica y cinco proyectos suscritos con el sector empresarial, académico, ambiental o gubernamental. 4. La transformación que buscamos (impacto): las alianzas producen proyectos con efectos en la productividad y en las comunidades. 5. Tipo de impacto según la guía: externo. | U34: Las organizaciones aliadas reportan mejoras en productividad o fortalecimiento comunitario atribuibles a los proyectos conjuntos. Indicador de la guía con que se mide: tasas de productividad y competitividad después del proyecto. Punto de comparación: la línea base de la meta (71 convenios activos en 2025, sin clasificación de alianzas estratégicas del PDI (RC 2025)) y, cuando el estudio lo permita, un grupo de referencia que no recibió la intervención. | V34: 1 | W34: 3 | X34: Dónde se ubica: eje 4, Transformación institucional, línea 4.4 Relacionamiento dialógico, meta 4.4.1.2 del PDI 2025 a 2032. Qué cambió frente a 2026: se corrige. Se restituye la cifra de 5 (el 2026 la había eliminado). Cómo se mide la meta: N.° de alianzas estratégicas formalizadas. Línea base: 71 convenios activos en 2025, sin clasificación de alianzas estratégicas del PDI (RC 2025). Meta 2027: 5 proyectos o alianzas estratégicas suscritos. Cómo se mide el impacto: tasas de productividad y competitividad después del proyecto. El indicador sale de la Guía Metodológica para la Evaluación de Impacto Institucional y se lee frente a la línea base. Qué esperamos obtener: las alianzas producen proyectos con efectos en la productividad y en las comunidades. Cómo se hace el seguimiento: cada trimestre las áreas reportan en el SUIE el avance de las actividades con su evidencia; la Oficina Asesora de Planeación verifica la pertinencia de los productos, consolida el avance de las acciones y de la meta y lo presenta al Comité Institucional de Gestión y Desempeño. Al cierre de 2027 se compara el indicador de la meta con su línea base. | Y34: Sin alertas.
E35: 4.4.1.3. 30 proyectos por cada una de las hélices: (1) sistema educativo; (2) sistema económico; (3) entorno natural; (4) el público (medios, cultura y sociedad civil) y (5) el sistema político. | F35: Se reincorpora | G35: No existía en el aplicativo 2026. | H35: N.° de proyectos por hélice | I35: Sin registro de proyectos por hélice en 2026 (no existía en el aplicativo) | J35: 30 proyectos por hélice | K35: Sugerida por la OAP: inventario de proyectos por hélice y 5 proyectos por hélice, 25 en total, en 2027, trayectoria hacia 30 por hélice en 2032 | L35: Sugerida por la OAP. | M35: AC27.44. Organizar el relacionamiento con las cinco hélices mediante un inventario de proyectos y la ejecución de proyectos nuevos en cada una. | N35: AC27.44, actividades: 1. Inventariar los proyectos vigentes y clasificarlos por hélice (A27-108). Producto: inventario. 2. Formular y ejecutar 5 proyectos por hélice (A27-109). Producto: proyectos en ejecución. | O35: Despacho de la VIET (140) GIT Extensión y Proyección Social (incluye ETDH) (141) | P35: Sin presupuesto registrado en la matriz plurianual | Q35: Valor Público | R35: Contribución al desarrollo social y comunitario, económico, sostenibilidad ambiental, sector educativo, sector productivo y industrial, desarrollo tecnológico, nacional e internacional. | S35: Tasas de productividad y competitividad después del proyecto. Cantidad de grupos comunitarios establecidos o fortalecidos como resultado del proyecto. | T35: 1. Lo que hacemos: 1 acción con 2 actividades (columnas M y N). 2. Lo que entregamos (productos): inventario; proyectos en ejecución. 3. Lo que cambia pronto (resultado): la Escuela sabe cuántos proyectos tiene con cada hélice y ejecuta proyectos nuevos en cada una. 4. La transformación que buscamos (impacto): la ETITC se relaciona con todo su ecosistema y genera proyectos con efectos medibles. 5. Tipo de impacto según la guía: externo. | U35: Aumenta el número de proyectos por hélice con resultados verificables en productividad o en fortalecimiento de grupos comunitarios. Indicador de la guía con que se mide: tasas de productividad y competitividad después del proyecto. Punto de comparación: la línea base de la meta (Sin registro de proyectos por hélice en 2026 (no existía en el aplicativo)) y, cuando el estudio lo permita, un grupo de referencia que no recibió la intervención. | V35: 1 | W35: 2 | X35: Dónde se ubica: eje 4, Transformación institucional, línea 4.4 Relacionamiento dialógico, meta 4.4.1.3 del PDI 2025 a 2032. Qué cambió frente a 2026: se reincorpora. No existía en el aplicativo 2026. Cómo se mide la meta: N.° de proyectos por hélice. Línea base: Sin registro de proyectos por hélice en 2026 (no existía en el aplicativo). Meta 2027: Sugerida por la OAP: inventario de proyectos por hélice y 5 proyectos por hélice, 25 en total, en 2027, trayectoria hacia 30 por hélice en 2032. Cómo se mide el impacto: tasas de productividad y competitividad después del proyecto. El indicador sale de la Guía Metodológica para la Evaluación de Impacto Institucional y se lee frente a la línea base. Qué esperamos obtener: la ETITC se relaciona con todo su ecosistema y genera proyectos con efectos medibles. Cómo se hace el seguimiento: cada trimestre las áreas reportan en el SUIE el avance de las actividades con su evidencia; la Oficina Asesora de Planeación verifica la pertinencia de los productos, consolida el avance de las acciones y de la meta y lo presenta al Comité Institucional de Gestión y Desempeño. Al cierre de 2027 se compara el indicador de la meta con su línea base. | Y35: Sin alertas.
C36: 4.5 Cultura organizacional | D36: 4.5.1. Contar con una cultura comprometida con la excelencia, el conocimiento, el pensamiento crítico y la vida que impacten el bienestar y desarrollo social. | E36: 4.5.1.1. Lograr un 90% de participación de los grupos de valor en las acciones de cultura organizacional. | F36: Se reincorpora | G36: El 2026 puso en este código el texto del modelo de cultura (4.5.1.2) y la meta del 90% desapareció. | H36: % de participación de los grupos de valor en acciones de cultura | I36: Sin medición de participación; «fortalecimiento de la cultura organizacional con participación de los grupos de valor» (RC 2025) | J36: 90% | K36: Sugerida por la OAP: 75% de participación de los grupos de valor, primera medición en 2027 y trayectoria hacia 90% en 2032, | L36: Sugerida por la OAP. | M36: AC27.45. Aumentar la participación de los grupos de valor en las acciones de cultura organizacional, con una medición confiable de esa participación. | N36: AC27.45, actividades: 1. Definir la población por grupo de valor y el método de medición de participación (A27-110). Producto: ficha del indicador. 2. Ejecutar el plan de bienestar e incentivos con participación de todos los servidores (A27-111). Producto: informe de participación. | O36: GIT Talento Humano (133) Bienestar Laboral (133) | P36: Sin presupuesto registrado en la matriz plurianual | Q36: Valor Público | R36: Impacto a actores (estudiantes, docentes, administrativos, egresados) y organizaciones (sector externo y sociedad en general) en valores. Cambios en la cultura institucional (incluida la cultura de la calidad). | S36: Porcentaje de actores que evidencian cambios significativos en sus valores y actitudes como consecuencia de las intervenciones institucionales. Porcentaje de la comunidad académica satisfecha con el clima laboral después de la implementación del sistema de calidad. | T36: 1. Lo que hacemos: 1 acción con 2 actividades (columnas M y N). 2. Lo que entregamos (productos): ficha del indicador; informe de participación. 3. Lo que cambia pronto (resultado): se mide por primera vez la participación de los grupos de valor y esta crece. 4. La transformación que buscamos (impacto): los valores institucionales se ven en las actitudes cotidianas y en un mejor clima laboral. 5. Tipo de impacto según la guía: externo e interno. | U36: Crecen el porcentaje de actores con cambios en valores y actitudes y la satisfacción con el clima laboral. Indicador de la guía con que se mide: porcentaje de actores que evidencian cambios significativos en sus valores y actitudes como consecuencia de las intervenciones institucionales. Punto de comparación: la línea base de la meta (Sin medición de participación; «fortalecimiento de la cultura organizacional con participación de los grupos de valor» (RC 2025)) y, cuando el estudio lo permita, un grupo de referencia que no recibió la intervención. | V36: 1 | W36: 2 | X36: Dónde se ubica: eje 4, Transformación institucional, línea 4.5 Cultura organizacional, meta 4.5.1.1 del PDI 2025 a 2032. Qué cambió frente a 2026: se reincorpora. El 2026 puso en este código el texto del modelo de cultura (4.5.1.2) y la meta del 90% desapareció. Cómo se mide la meta: % de participación de los grupos de valor en acciones de cultura. Línea base: Sin medición de participación; «fortalecimiento de la cultura organizacional con participación de los grupos de valor» (RC 2025). Meta 2027: Sugerida por la OAP: 75% de participación de los grupos de valor, primera medición en 2027 y trayectoria hacia 90% en 2032,. Cómo se mide el impacto: porcentaje de actores que evidencian cambios significativos en sus valores y actitudes como consecuencia de las intervenciones institucionales. El indicador sale de la Guía Metodológica para la Evaluación de Impacto Institucional y se lee frente a la línea base. Qué esperamos obtener: los valores institucionales se ven en las actitudes cotidianas y en un mejor clima laboral. Cómo se hace el seguimiento: cada trimestre las áreas reportan en el SUIE el avance de las actividades con su evidencia; la Oficina Asesora de Planeación verifica la pertinencia de los productos, consolida el avance de las acciones y de la meta y lo presenta al Comité Institucional de Gestión y Desempeño. Al cierre de 2027 se compara el indicador de la meta con su línea base. | Y36: Sin alertas.
E37: 4.5.1.2. Consolidar un (1) modelo de gestión de la cultura que contemple un (1) instrumento de evaluación permanente. | F37: Se corrige | G37: Se deja un solo enunciado (en 2026 estaba duplicado en 4.5.1.1 y 4.5.1.2). | H37: Modelo de gestión de la cultura con instrumento de evaluación (fase) | I37: Plan de bienestar e incentivos en ejecución (MPI); sin instrumento de evaluación de la cultura | J37: 1 modelo + 1 instrumento | K37: Instrumento de evaluación diseñado y aplicado | L37: Propuesta OAP con base en la MPI | M37: AC27.46. Gestionar la cultura organizacional con un instrumento de evaluación permanente cuyos resultados se presentan al CIGD. | N37: AC27.46, actividades: 1. Diseñar el instrumento de evaluación de la cultura organizacional (A27-112). Producto: instrumento aprobado. 2. Aplicarlo y presentar resultados al CIGD (A27-113). Producto: informe de resultados. | O37: GIT Talento Humano (133) | P37: Sin presupuesto registrado en la matriz plurianual | Q37: Académica | R37: Cambios en la cultura institucional (incluida la cultura de la calidad). | S37: Porcentaje de la comunidad académica satisfecha con el clima laboral después de la implementación del sistema de calidad. Tasa de adopción de nuevos procesos atribuible a la implementación del sistema de calidad. | T37: 1. Lo que hacemos: 1 acción con 2 actividades (columnas M y N). 2. Lo que entregamos (productos): instrumento aprobado; informe de resultados. 3. Lo que cambia pronto (resultado): existe un instrumento de evaluación de la cultura, se aplica y sus resultados llegan al CIGD. 4. La transformación que buscamos (impacto): la cultura organizacional se gestiona con datos y los procesos de calidad se adoptan de verdad. 5. Tipo de impacto según la guía: interno. | U37: Mejoran entre la primera y la segunda aplicación del instrumento los resultados de clima laboral y la adopción de procesos. Indicador de la guía con que se mide: porcentaje de la comunidad académica satisfecha con el clima laboral después de la implementación del sistema de calidad. Punto de comparación: la línea base de la meta (Plan de bienestar e incentivos en ejecución (MPI); sin instrumento de evaluación de la cultura) y, cuando el estudio lo permita, un grupo de referencia que no recibió la intervención. | V37: 1 | W37: 2 | X37: Dónde se ubica: eje 4, Transformación institucional, línea 4.5 Cultura organizacional, meta 4.5.1.2 del PDI 2025 a 2032. Qué cambió frente a 2026: se corrige. Se deja un solo enunciado (en 2026 estaba duplicado en 4.5.1.1 y 4.5.1.2). Cómo se mide la meta: Modelo de gestión de la cultura con instrumento de evaluación (fase). Línea base: Plan de bienestar e incentivos en ejecución (MPI); sin instrumento de evaluación de la cultura. Meta 2027: Instrumento de evaluación diseñado y aplicado. Cómo se mide el impacto: porcentaje de la comunidad académica satisfecha con el clima laboral después de la implementación del sistema de calidad. El indicador sale de la Guía Metodológica para la Evaluación de Impacto Institucional y se lee frente a la línea base. Qué esperamos obtener: la cultura organizacional se gestiona con datos y los procesos de calidad se adoptan de verdad. Cómo se hace el seguimiento: cada trimestre las áreas reportan en el SUIE el avance de las actividades con su evidencia; la Oficina Asesora de Planeación verifica la pertinencia de los productos, consolida el avance de las acciones y de la meta y lo presenta al Comité Institucional de Gestión y Desempeño. Al cierre de 2027 se compara el indicador de la meta con su línea base. | Y37: Sin alertas.
A38: 5. Ampliación y modernización de la infraestructura | B38: 5. Proveer la infraestructura física y tecnológica necesaria para la calidad en la oferta educativa. | C38: 5.1 Sedes propias | D38: 5.1.1. Poseer sedes a nivel distrital y departamental que permitan la ampliación de cobertura con principios de sostenibilidad. | E38: 5.1.1.1. Contar con 4 sedes: 1. Calle 18, 2. Funza, 3. Guaymaral, 4. Central, con infraestructura y dotación para la prestación de servicios educativos. | F38: Se corrige | G38: Vuelve a una sola meta de 4 sedes con hitos por sede (el 2026 la partió en 5.1.1.1 a 5.1.1.4). | H38: N.° de sedes propias habilitadas y operando | I38: 2 inmuebles (edificio y casa) y 6 predios en comodato con la SAE en Funza (2024, MPI, columna «Línea base 2024») | J38: 4 sedes | K38: Calle 18: fase III (licencias, estudios y diseños, vigencias futuras MEN). Funza: puesta en marcha fase I. Guaymaral: puesta en marcha de la sede de Bienestar. | L38: MPI | M38: AC27.47. Habilitar las sedes propias de Calle 18, Funza y Guaymaral con los trámites, estudios, licencias y puesta en marcha que corresponden a cada una. AC27.48. Adecuar los inmuebles nuevos con criterios de eficiencia energética y construcción sostenible desde su diseño. | N38: AC27.47, actividades: 1. Calle 18: gestionar licencias de construcción y demolición, estudios y diseños y vigencias futuras (A27-114). Producto: licencias y estudios. 2. Funza: adelantar trámites de notariado, registro e impuestos de los predios (A27-115). Producto: escrituras y certificados. 3. Funza (Ecoparque): contratar estudios y diseños, licencias e infraestructura modular (A27-116). Producto: contratos y licencias. 4. Guaymaral: poner en marcha la sede de Bienestar (espacios deportivos) (A27-117). Producto: sede en operación. AC27.48, actividades: 1. Adecuar los nuevos inmuebles adquiridos (estudios y diseños) (A27-118). Producto: estudios y diseños. 2. Incluir criterios de eficiencia energética y construcción sostenible en los estudios y diseños de las nuevas sedes (incluida Fusagasugá), para no generar sobrecostos futuros (A27-119). Producto: criterios incluidos en los términos de referencia. | O38: Recursos Físicos e Infraestructura (130) Gestión Jurídica (110) | P38: A27-114: 33.000 (MPI) A27-116: 1.000 ETITC + 7.300 MEN vigencias futuras (MPI) A27-117: 400 (MPI) A27-118: 1.000 (MPI) | Q38: Valor Público | R38: Transformaciones del territorio (condiciones del desarrollo, especialmente de cobertura y pertinencia en la oferta educativa). | S38: Porcentaje de jóvenes de la comunidad beneficiaria que se escolarizaron con la Institución. Proporción de programas académicos pertinentes (alineados con necesidades y vocación del territorio) ofrecidos por la Institución en el territorio. | T38: 1. Lo que hacemos: 2 acciones con 6 actividades (columnas M y N). 2. Lo que entregamos (productos): licencias y estudios; escrituras y certificados; contratos y licencias; sede en operación; estudios y diseños; criterios incluidos en los términos de referencia. 3. Lo que cambia pronto (resultado): las sedes avanzan en licencias, estudios, escrituras y puesta en marcha, con diseños sostenibles. 4. La transformación que buscamos (impacto): la nueva infraestructura permite recibir más estudiantes en programas pertinentes y con menor costo de operación. 5. Tipo de impacto según la guía: externo. | U38: Aumenta la matrícula atendida en las sedes nuevas y la proporción de programas pertinentes ofrecidos en ellas. Indicador de la guía con que se mide: porcentaje de jóvenes de la comunidad beneficiaria que se escolarizaron con la Institución. Punto de comparación: la línea base de la meta (2 inmuebles (edificio y casa) y 6 predios en comodato con la SAE en Funza (2024, MPI, columna «Línea base 2024»)) y, cuando el estudio lo permita, un grupo de referencia que no recibió la intervención. | V38: 2 | W38: 6 | X38: Dónde se ubica: eje 5, Ampliación y modernización de la infraestructura, línea 5.1 Sedes propias, meta 5.1.1.1 del PDI 2025 a 2032. Qué cambió frente a 2026: se corrige. Vuelve a una sola meta de 4 sedes con hitos por sede (el 2026 la partió en 5.1.1.1 a 5.1.1.4). Cómo se mide la meta: N.° de sedes propias habilitadas y operando. Línea base: 2 inmuebles (edificio y casa) y 6 predios en comodato con la SAE en Funza (2024, MPI, columna «Línea base 2024»). Meta 2027: Calle 18: fase III (licencias, estudios y diseños, vigencias futuras MEN). Funza: puesta en marcha fase I. Guaymaral: puesta en marcha de la sede de Bienestar. Cómo se mide el impacto: porcentaje de jóvenes de la comunidad beneficiaria que se escolarizaron con la Institución. El indicador sale de la Guía Metodológica para la Evaluación de Impacto Institucional y se lee frente a la línea base. Qué esperamos obtener: la nueva infraestructura permite recibir más estudiantes en programas pertinentes y con menor costo de operación. Cómo se hace el seguimiento: cada trimestre las áreas reportan en el SUIE el avance de las actividades con su evidencia; la Oficina Asesora de Planeación verifica la pertinencia de los productos, consolida el avance de las acciones y de la meta y lo presenta al Comité Institucional de Gestión y Desempeño. Al cierre de 2027 se compara el indicador de la meta con su línea base. | Y38: Confirmar si el «Ecoparque Tecnológico» corresponde a la sede Funza del PDI.
C39: 5.2 Modernización de la infraestructura | D39: 5.2.1. Fortalecer la infraestructura física y tecnológica de las sedes. | E39: 5.2.1.1. 3 bloques reforzados estructuralmente en la sede centro. | F39: Se corrige | G39: Se recodifica (en 2026 el reforzamiento estaba en la línea 5.1 como 5.1.1.2). | H39: N.° de bloques con reforzamiento estructural terminado | I39: 15 bloques en la sede centro; faltan 5 por reforzar (2024, MPI, columna «Línea base 2024») | J39: 3 bloques | K39: Viabilidad presupuestal y permisos para los bloques pendientes | L39: MPI | M39: AC27.49. Viabilizar el reforzamiento estructural de los bloques pendientes de la sede centro con permisos, viabilidad presupuestal y medidas de eficiencia energética. | N39: AC27.49, actividades: 1. Gestionar permisos y licencias ante el Ministerio de Cultura y la curaduría (A27-120). Producto: permisos y licencias. 2. Obtener la viabilidad presupuestal del reforzamiento estructural (A27-121). Producto: viabilidad del MEN. 3. Integrar al reforzamiento de los bloques F, G y H las medidas de la matriz de oportunidades de eficiencia energética (avance parcial PGEE 2026) (A27-122). Producto: medidas incluidas en el diseño. | O39: Recursos Físicos e Infraestructura (130) Despacho de la Vicerrectoría Administrativa y Financiera (130) | P39: A27-121: 17.000 MEN (MPI) | Q39: Académica | R39: Impacto en las labores sustantivas: docencia y formación, investigación e innovación, extensión y proyección social. | S39: Cantidad de procesos académicos y académico administrativos que mejoran. | T39: 1. Lo que hacemos: 1 acción con 3 actividades (columnas M y N). 2. Lo que entregamos (productos): permisos y licencias; viabilidad del MEN; medidas incluidas en el diseño. 3. Lo que cambia pronto (resultado): los bloques pendientes cuentan con permisos, viabilidad presupuestal y diseño con eficiencia energética. 4. La transformación que buscamos (impacto): la sede centro opera con seguridad estructural y con espacios adecuados para la academia. 5. Tipo de impacto según la guía: interno. | U39: Disminuyen los espacios restringidos por riesgo estructural y mejoran los procesos académicos que dependen de esos bloques. Indicador de la guía con que se mide: cantidad de procesos académicos y académico administrativos que mejoran. Punto de comparación: la línea base de la meta (15 bloques en la sede centro; faltan 5 por reforzar (2024, MPI, columna «Línea base 2024»)) y, cuando el estudio lo permita, un grupo de referencia que no recibió la intervención. | V39: 1 | W39: 3 | X39: Dónde se ubica: eje 5, Ampliación y modernización de la infraestructura, línea 5.2 Modernización de la infraestructura, meta 5.2.1.1 del PDI 2025 a 2032. Qué cambió frente a 2026: se corrige. Se recodifica (en 2026 el reforzamiento estaba en la línea 5.1 como 5.1.1.2). Cómo se mide la meta: N.° de bloques con reforzamiento estructural terminado. Línea base: 15 bloques en la sede centro; faltan 5 por reforzar (2024, MPI, columna «Línea base 2024»). Meta 2027: Viabilidad presupuestal y permisos para los bloques pendientes. Cómo se mide el impacto: cantidad de procesos académicos y académico administrativos que mejoran. El indicador sale de la Guía Metodológica para la Evaluación de Impacto Institucional y se lee frente a la línea base. Qué esperamos obtener: la sede centro opera con seguridad estructural y con espacios adecuados para la academia. Cómo se hace el seguimiento: cada trimestre las áreas reportan en el SUIE el avance de las actividades con su evidencia; la Oficina Asesora de Planeación verifica la pertinencia de los productos, consolida el avance de las acciones y de la meta y lo presenta al Comité Institucional de Gestión y Desempeño. Al cierre de 2027 se compara el indicador de la meta con su línea base. | Y39: El PDI dice 3 bloques; la MPI dice que faltan 5.
