Workbook
Name L_AREAS: Catalogos!$Q$5:$Q$51
Name L_ESTVF: Catalogos!$AF$5:$AF$8
Name L_FUENTE: Catalogos!$AC$5:$AC$12
Name L_GASTO: Catalogos!$AD$5:$AD$6
Name L_MESES: Catalogos!$Z$5:$Z$16
Name L_METAS: Catalogos!$I$5:$I$49
Name L_MOD: Catalogos!$AB$5:$AB$11
Name L_PRIOR: Catalogos!$AH$5:$AH$7
Name L_REG2026: '2026'!$A$5:$A$428
Name L_SINO: Catalogos!$AE$5:$AE$6
Name L_TIPO: Catalogos!$AG$5:$AG$15
Name L_UNIDAD: Catalogos!$AA$5:$AA$7
Name P_FECHA: Tablero_Consistencia!$B$9
Name P_SMMLV: Tablero_Consistencia!$B$8
Name P_TOPE_MENOR: Tablero_Consistencia!$B$6
Name P_TOPE_MINIMA: Tablero_Consistencia!$B$7

Sheet Instructivo
A1: Plan de Necesidades 2027 — Escuela Tecnológica Instituto Técnico Central (ETITC)
A2: Oficina Asesora de Planeación y Desarrollo Institucional (OAPDI) · Versión 1 · Complemento de la Plantilla de Formulación 2027 (versión 7) · Libro protegido: solo se diligencian las celdas amarillas.
A4: 1. Propósito
A5: Este libro es el instrumento con el que cada dependencia y área funcional de la ETITC registra los bienes, obras y servicios que necesita contratar en 2027 para ejecutar las acciones de su Plan de Acción. Es el complemento de la Plantilla de Formulación 2027: en la plantilla el área dice qué va a hacer (acción, producto, indicador); en este libro dice qué necesita adquirir para hacerlo. Cada necesidad se vincula a una acción del Plan de Acción 2027 y, por medio de ella, a una meta del Plan de Desarrollo Institucional (PDI) 2025-2032, de modo que ningún recurso se programe sin una meta que lo justifique. La OAPDI consolida el libro y lo entrega como insumo del Plan Anual de Adquisiciones que la ETITC publica en SECOP II. Convención de siglas: en este libro, como en la plantilla, la sigla PAA se reserva para el Plan de Acción Anual; el Plan Anual de Adquisiciones se escribe siempre completo para no confundirlos.
A7: 2. Marco normativo
A8: Ley 80 de 1993 (Estatuto General de Contratación de la Administración Pública) y Ley 1150 de 2007 (modalidades de selección, artículo 2). Ley 1474 de 2011, artículo 74: las entidades publican en su página web, a más tardar el 31 de enero de cada año, el plan de acción con los proyectos de inversión, el presupuesto y el plan general de compras. Decreto 1082 de 2015, artículos 2.2.1.1.1.4.1 a 2.2.1.1.1.4.4: el Plan Anual de Adquisiciones debe listar los bienes, obras y servicios que se pretende adquirir, identificados con el Clasificador de Bienes y Servicios (UNSPSC), con su valor estimado, la fuente de los recursos, la modalidad de selección y la fecha aproximada de inicio del proceso; se publica en la página web y en SECOP y se actualiza por lo menos una vez durante la vigencia. Guía para elaborar el Plan Anual de Adquisiciones de Colombia Compra Eficiente. Decreto 111 de 1996 (Estatuto Orgánico del Presupuesto): ninguna necesidad se contrata sin certificado de disponibilidad presupuestal. Ley 152 de 1994 y Modelo Integrado de Planeación y Gestión (MIPG): articulación entre planeación, presupuesto y contratación.
A10: 3. Del plan de necesidades al Plan Anual de Adquisiciones: la ruta
A11: Etapa 1 — El área formula sus acciones 2027 en la Plantilla de Formulación 2027.
A12: Etapa 2 — El área registra en la hoja "Formulación PDN 2027" cada bien, obra o servicio que requiere una de esas acciones, con su código UNSPSC, valor, fechas, modalidad estimada, fuente y responsable.
A13: Etapa 3 — La OAPDI revisa el Tablero_Consistencia: alineación con la meta y la acción, alertas, comparación con 2026 y acciones con presupuesto que no registran necesidades.
A14: Etapa 4 — La Vicerrectoría Administrativa y Financiera (presupuesto) confirma la fuente, el rubro o proyecto de inversión y la viabilidad de las vigencias futuras.
A15: Etapa 5 — El GIT de Contratación y Adquisiciones toma la hoja "Insumo_Plan_Adquisiciones", agrupa necesidades iguales, confirma la modalidad según los topes de la vigencia, asigna la unidad de contratación y convierte los textos a los códigos de la plantilla de cargue de SECOP II.
... A39: 6. Diccionario de campos de la hoja Formulación PDN 2027
A40: Columna | B40: Campo | C40: Qué registrar | D40: Obligatorio | E40: Uso en el Plan Anual de Adquisiciones (campo SECOP II)
A41: A | B41: N.° necesidad | C41: Automático (PN27-001, PN27-002…). Identifica la necesidad en toda la cadena: OAPDI, presupuesto y contratación. | D41: Automático | E41: Trazabilidad interna.
A42: B | B42: Área funcional que formula | C42: Seleccione su área de la lista (las mismas 47 áreas de la Plantilla de Formulación 2027). | D42: Sí | E42: Trazabilidad; define la unidad de contratación.
A43: C-D | B43: Dependencia y proceso | C43: Automáticos: dependencia del Decreto 902 de 2013 / Resolución 215 de 2022 y proceso del mapa GDC-DI-01 V9. | D43: Automático | E43: Trazabilidad interna.
A44: E | B44: Meta estratégica PDI | C44: Seleccione la meta (código eje.línea.objetivo.meta) a la que aporta la acción que requiere la necesidad. | D44: Sí | E44: Justificación estratégica de la adquisición.
A45: F-G | B45: Eje y línea | C45: Automáticos a partir de la meta. | D45: Automático | E45: Trazabilidad interna.
A46: H | B46: Acción del Plan de Acción 2027 | C46: Seleccione la acción A27-### de la lista (filtrada por la meta) o "PROPIA" si es una acción formulada por el área. | D46: Sí | E46: Vincula el gasto con la planeación (Ley 1474 de 2011, art. 74).
A47: I | B47: Nombre de la acción propia | C47: Solo si eligió PROPIA: el nombre de la acción tal como quedó en la Plantilla de Formulación 2027. | D47: Condicional | E47: Trazabilidad interna.
A48: J | B48: Tipo de necesidad | C48: Servicios profesionales, apoyo a la gestión, bienes, suministro, mantenimiento, obra, consultoría, interventoría, licencias, arrendamiento u otro. | D48: Sí | E48: Orienta la modalidad y la agrupación de procesos.
A49: K | B49: Justificación de la necesidad | C49: Qué problema resuelve y qué producto de la acción no podría lograrse sin ella. Sea concreto: es la base de los estudios previos. | D49: Sí | E49: Estudios previos.
A50: L | B50: Descripción del objeto contractual | C50: Qué se va a adquirir o contratar y para qué. Ejemplo: "Prestar servicios profesionales para…", "Adquirir equipos de cómputo para…". | D50: Sí | E50: Descripción.
A51: M | B51: Código UNSPSC principal | C51: Un solo código de 8 dígitos, como número, a nivel de clase (termina en 00) o de producto. Ver Guía UNSPSC. | D51: Sí | E51: Códigos UNSPSC.
... A66: AJ | B66: Alerta de consistencia | C66: Automática. Debe decir OK para que la necesidad pase al Insumo del Plan Anual de Adquisiciones. | D66: Automático | E66: Control de calidad.
A68: 7. Reglas de calidad
A69: Una necesidad por fila y un objeto por necesidad. Toda necesidad sirve a una acción del Plan de Acción 2027; si la acción no existe, primero se formula en la plantilla. El código UNSPSC se registra como número de 8 dígitos (clase o producto). Los valores se registran en pesos colombianos, sin puntos, signos ni texto, y el valor de la vigencia 2027 no supera el total. Si el contrato se paga en más de una vigencia, marque vigencias futuras y su estado. El mes de presentación de ofertas no es anterior al de inicio. El responsable se identifica con correo institucional @itc.edu.co, sin tildes ni espacios. No registre como necesidad algo que no se va a contratar (por ejemplo, actividades que el área ejecuta con su propio personal de planta).
A71: 8. Convenciones
A72: Gris: información automática o de la OAPDI (bloqueada). Amarillo: celdas habilitadas para diligenciar. Verde: control y anotaciones de la OAPDI. El marcador [PENDIENTE DE VERIFICAR] señala un dato que ningún documento fuente confirma y que debe validarse antes de usarlo. El libro está protegido; la hoja 2026 y la estructura del libro (crear, borrar u ocultar hojas) solo las puede desbloquear la OAPDI.
A74: 9. Ejemplo de fila diligenciada (solo ilustrativo; no corresponde a una necesidad aprobada)
A75: Área (B) | B75: A05 · Planeación y Plan de Acción (101)
A76: Meta PDI (E) | B76: 4.2.1.2 · Contar con un (1) sistema de información estratégico.
A77: Acción (H) | B77: A27-093 · Formalizar el cierre de la implementación del SIUE y su manual de uso
A78: Tipo / objeto (J, L) | B78: Prestación de servicios profesionales / Prestar servicios profesionales a la OAPDI para el mantenimiento y fortalecimiento del sistema de información estratégico y la analítica de datos institucional.
A79: UNSPSC (M) | B79: 80111600 (clase; verifique en el clasificador si existe un producto más preciso)
A80: Meses (O, P) / duración (Q, R) | B80: Enero / Enero — 11 Meses
A81: Modalidad / fuente / gasto (S, T, U) | B81: Contratación directa / Presupuesto General de la Nación – funcionamiento / Funcionamiento
A82: Valor total y 2027 (W, X) | B82: 60500000 y 60500000 (cifras ilustrativas tomadas de una necesidad similar de 2026)
A83: Vigencias futuras (Y, Z) | B83: No / No aplica
A84: Responsable (AB-AE) | B84: Nombre del supervisor previsto / Jefe de la Oficina Asesora de Planeación / extensión / planeacion@itc.edu.co
A85: Continuidad 2026 (AF, AG) | B85: Sí / el N.° PN26-### de la necesidad 2026 equivalente
A86: Alerta (AJ) | B86: OK
A88: 10. Advertencias de la OAPDI antes de remitir
A89: a) La formulación 2026 no permite trazar las necesidades al PDI: el instructivo 2026 pedía eje, línea, meta, estrategia y acción, pero la hoja de datos solo tenía diez columnas (código UNSPSC a ID) y ninguna de alineación. Este libro corrige esa brecha con las columnas E a I.
A90: b) Existían dos versiones del plan 2026. La versión "PROTEGIDO" (106 registros) está contenida en su totalidad en la versión "Modificado_2" (424 registros), que es la que se conserva en la hoja 2026.
A91: c) Calidad del dato 2026: 207 valores escritos como texto (con $, puntos, comas o apóstrofos), 12 registros sin valor, 43 códigos UNSPSC vacíos, en texto o múltiples en una celda, 20 códigos a nivel de segmento o familia, 152 duraciones en texto o vacías (incluidas cuatro filas con el encabezado pegado como dato), 23 formas distintas de escribir la modalidad (incluidas "ORII" y "Vicerrectoría Administrativa"), 42 registros sin correo y 301 sin ID; en un registro la justificación quedó en la columna ID. La columna O de la hoja 2026 señala cada caso.
A92: d) El valor 2026 normalizado por la OAPDI (columna M de la hoja 2026) suma $50.409.700.208; es una cifra de referencia: se excluyen los registros sin valor o no interpretables (marcados [PENDIENTE DE VERIFICAR]) y se mantienen tal cual valores atípicos como $25.800 (área protegida) que el área debe confirmar.
A93: e) La dependencia de cada registro 2026 se infirió a partir del correo del responsable y, cuando faltaba o no era institucional (por ejemplo, "academusoft@it.edu.co"), a partir del campo ENCARGADO; con ello todos los registros quedaron asignados, pero la asignación es una inferencia. Toda la columna L de la hoja 2026 debe validarse antes de usar el comparativo del tablero.
A94: f) Valores 2026 que deben revisarse antes de tomarlos como referencia: 3 contratos de prestación de servicios por $500 millones o más (por ejemplo. PN26-044 por $7.150 millones. PN26-101 por $3.023 millones y PN26-103 por $2.411 millones). que suman $12.583.827.400 y parecen errores de digitación; y 41 necesidades marcadas como mínima cuantía por encima del tope de $39.850.000 que citaba el propio instructivo 2026. con valores de hasta $1.200.000.000. En ambos casos la modalidad o el valor son incompatibles y deben aclararse con el área.
A95: g) El instructivo 2026 indicaba "Mínima cuantía: montos hasta $39.850.000" (cifra de 2025) y "Menor cuantía: desde $39.851.000 en adelante". Lo segundo es incompleto: la menor cuantía tiene un tope superior que depende del presupuesto anual de la entidad en salarios mínimos, y por encima de él aplica otra modalidad. Los topes 2027 se registran en el Tablero_Consistencia cuando Contratación los certifique [PENDIENTE DE VERIFICAR].
A96: h) Las fuentes de recursos de la lista son una agrupación institucional propuesta por la OAPDI; la Vicerrectoría Administrativa y Financiera debe validarlas y Contratación debe homologarlas a las fuentes de la plantilla de SECOP II.
A97: i) La lista de acciones proviene del Plan de acción 2027 (158 acciones A27-001 a A27-158, versión 7 sujeta a revisión del CIGD). Si el CIGD modifica, elimina o renumera acciones, la OAPDI debe actualizar la hoja Catálogos antes de distribuir este libro.
A98: j) La hoja Insumo_Plan_Adquisiciones sigue los campos de la plantilla de cargue de SECOP II descritos por Colombia Compra Eficiente; la versión vigente de esa plantilla debe confirmarse con el GIT de Contratación antes del cargue.

Sheet Guía UNSPSC
A1: Guía del Código Estándar de Productos y Servicios de las Naciones Unidas (UNSPSC)
A2: Cómo identificar el código de cada necesidad para que el Plan de Necesidades se convierta en el Plan Anual de Adquisiciones.
A4: 1. Qué es el UNSPSC y por qué es obligatorio
A5: El UNSPSC (United Nations Standard Products and Services Code, Código Estándar de Productos y Servicios de las Naciones Unidas) es un sistema de clasificación de cuatro niveles que asigna un código numérico de 8 dígitos a cada bien, obra o servicio. En Colombia se adoptó como el Clasificador de Bienes y Servicios que administra la Agencia Nacional de Contratación Pública – Colombia Compra Eficiente. El Decreto 1082 de 2015 (artículo 2.2.1.1.1.4.1) exige que cada adquisición del Plan Anual de Adquisiciones se identifique con este clasificador, y SECOP II no admite una adquisición sin código. El código tiene además tres efectos prácticos: (a) es el idioma común con los proveedores, porque los proponentes se inscriben en el Registro Único de Proponentes (RUP) con estos mismos códigos; (b) define qué proveedores reciben la alerta del proceso en SECOP II y quiénes pueden acreditar experiencia; y (c) permite a la ETITC agrupar compras iguales de varias áreas en un solo proceso. Un código mal elegido puede dejar por fuera a los proveedores idóneos o invalidar la verificación de experiencia.
A7: 2. Estructura del código: cuatro niveles, dos dígitos por nivel
A8: Nivel | B8: Dígitos que identifica | C8: Código de ejemplo | D8: Denominación de referencia del ejemplo | E8: ¿Sirve para SECOP II? | F8: Comentario
A9: 1. Segmento | B9: 2 primeros (80) | C9: 80000000 | D9: Servicios de gestión, servicios profesionales de empresa y servicios administrativos | E9: No | F9: Agrupa sectores completos; es demasiado general.
A10: 2. Familia | B10: 4 primeros (8011) | C10: 80110000 | D10: Servicios de recursos humanos | E10: No | F10: Sigue siendo general; SECOP II exige tercer o cuarto nivel.
A11: 3. Clase | B11: 6 primeros (801116) | C11: 80111600 | D11: Servicios de personal temporal | E11: Sí | F11: Termina en 00. Úsela cuando no exista un producto exacto o el objeto agrupe varios productos de la misma clase.
A12: 4. Producto | B12: 8 dígitos (80111601) | C12: 80111601 | D12: Asistencia de oficina o administrativa temporal | E12: Sí (preferible) | F12: Es el nivel más preciso; úselo siempre que exista.
A13: Nota: las denominaciones de esta guía son de referencia para explicar la estructura. La denominación oficial y vigente es la que muestra el clasificador de Colombia Compra Eficiente; verifíquela siempre allí antes de registrar el código.
A15: 3. Cómo encontrar el código correcto (paso a paso)
A16: Paso 1. Defina primero el objeto: qué se compra o contrata y para qué (columna L de la hoja de formulación). El código se escoge a partir del objeto, no al revés.
A17: Paso 2. Ingrese al Clasificador de Bienes y Servicios de Colombia Compra Eficiente: https://operaciones.colombiacompra.gov.co/clasificador-de-bienes-y-servicios (también puede usar el buscador de códigos del Registro Único de Proponentes en SECOP II).
A18: Paso 3. Busque por palabra clave del bien o servicio (por ejemplo: "mantenimiento", "licencia de software", "extintores") o navegue de lo general a lo particular: segmento → familia → clase → producto.
A19: Paso 4. Elija el producto (8 dígitos) que corresponda exactamente. Si el objeto agrupa varios productos de la misma clase, registre la clase (6 dígitos seguidos de 00).
A20: Paso 5. Registre en la columna M un solo código de 8 dígitos, como número, sin espacios, puntos ni texto. Si el objeto requiere códigos de otras clases (por ejemplo, suministro e instalación), regístrelos en la columna N separados por punto y coma (;).
A21: Paso 6. Verifique con el GIT de Contratación y Adquisiciones cuando dude entre dos códigos: el código debe ser coherente con los requisitos habilitantes que se pedirán en el RUP.
A22: Paso 7. Revise la columna "Alerta de consistencia": si dice "Código UNSPSC inválido" o "a nivel de segmento o familia", corrija antes de remitir.
A24: 4. Errores frecuentes encontrados en la formulación 2026 (hoja 2026)
A25: • De 424 registros 2026, 43 tienen el código vacío, escrito como texto o con varios códigos en la misma celda (por ejemplo, "39120000 39121700"); SECOP II solo lee un código por campo.
A26: • 20 registros usan códigos a nivel de segmento o familia (terminados en 0000, por ejemplo 41000000 o 60000000), que SECOP II no acepta como identificación de la adquisición.
... A31: 5. Segmentos usados por la ETITC en 2026 (orientación para buscar)
A32: Segmento | B32: N.° de códigos registrados en 2026 | D32: Denominación de referencia
A33: 11 | B33: 5 | D33: Material mineral, textil y vegetal y animal no comestible
A34: 12 | B34: 3 | D34: Material químico, incluidos bioquímicos y materiales de gas
A35: 13 | B35: 2 | D35: Materiales de resina, colofonia, caucho, espuma, película y elastómeros
A36: 14 | B36: 2 | D36: Materiales y productos de papel
A37: 20 | B37: 1 | D37: Maquinaria y accesorios de minería y perforación de pozos
A38: 22 | B38: 1 | D38: Maquinaria y accesorios para construcción y edificación
A39: 23 | B39: 17 | D39: Maquinaria y accesorios de manufactura y procesamiento industrial
A40: 24 | B40: 4 | D40: Maquinaria, accesorios y suministros para manejo, acondicionamiento y almacenamiento de materiales
A41: 25 | B41: 1 | D41: Vehículos comerciales, militares y particulares, accesorios y componentes
A42: 27 | B42: 6 | D42: Herramientas y maquinaria general
A43: 30 | B43: 6 | D43: Componentes y suministros para estructuras, edificación, construcción y obras civiles
A44: 31 | B44: 3 | D44: Componentes y suministros de manufactura
... A77: 95 | B77: 4 | D77: Terrenos, edificios, estructuras y vías
A79: 6. Códigos de 8 dígitos usados en 2026, con un ejemplo de objeto (consulta rápida; verifique siempre la denominación oficial)
A80: Código | B80: Nivel | C80: Veces en 2026 | D80: Ejemplo de objeto contractual 2026 | E80: N.° registro 2026 | F80: Área que lo registró (2026)
A81: 80111600 | B81: Clase | C81: 56 | D81: Prestar servicios profesionales para apoyar el diseño, implementación, conformación y seguimiento del Plan de Emergencias de la Escuela Tecnológica Instituto Técnico Central – ETITC y sus sedes, así como para realizar l… | E81: PN26-006 | F81: Talento humano - Seguridad y salud en el trabajo
A82: 80101600 | B82: Clase | C82: 29 | D82: Realizar la interventoría técnica, administrativa y financiera al contrato cuyo objeto es ejecutar la obra civil correspondiente a las soluciones arquitectónicas de la Etapa 1 del Plan de Movilidad Inclusiva y la interv… | E82: PN26-160 | F82: Vicerrectoria administrativa y financiera
A83: 81111600 | B83: Clase | C83: 26 | D83: Prestación de servicios profesionales para la gestión del giteps desarrollando acciones dirigidas a la proyección social a través de articulación de la comunidad con la institución durante la vigencia 2026. | E83: PN26-043 | F83: Proyección social
A84: 81112307 | B84: Producto | C84: 20 | D84: PRESTACIÓN DE SERVICIOS COMO TECNOLOGO EN EL ÁREA DE INFORMÁTICA Y TELECOMUNICACIONES PARA BRINDAR EL SOPORTE DE PRIMER NIVEL CON EL PROPÓSITO DE BRINDAR RESPUESTA Y SOLUCIÓN A LOS INCIDENTES, REQUERIMIENTOS Y SOLICITUD… | E84: PN26-377 | F84: Gestión Tecnología e Informática
A85: 81112501 | B85: Producto | C85: 18 | D85: Renovación de licenciamiento LevelBlue AlienVault USM Anywhere (Unified Security Management) & Threat Intelligent durante doce meses para el servicio de monitoreo de estado de compromisos e inteligencia de amenazas como… | E85: PN26-105 | F85: Planeación - Seguridad de la Información
A86: 81112210 | B86: Producto | C86: 8 | D86: Adquisición del soporte y las actualizaciones del sistema de información de gestión académico del bachillerato GNOSOFT de la escuela tecnológica instituto técnico central | E86: PN26-365 | F86: Vicerretoría académica-Sistemas de información Getión Académica
A87: 80111601 | B87: Producto | C87: 7 | D87: Prestación de servicios de apoyo a la gestión para realizar la gestión administrativa y logística de las actividades relacionadas con el seguimiento y la ejecución de los contratos a cargo de la vicerrectoría administra… | E87: PN26-059 | F87: Pendiente
A88: 81161507 | B88: Producto | C88: 7 | D88: ADQUISICION DE LICENCIAS PARA ACCEDER A LA PLATAFORMA VIRTUAL PRO COMO APOYO AL PROCESO DE FORMACION DE LOS ESTUDIANTES DE LOS PROGRAMAS DE EDUCACIÓN SUSPERIOR DE LA ESCUELA TECNOLOGICA INSTITUTO TECNICO CENTRAL | E88: PN26-197 | F88: Centro de Biblioteca y Recursos Educativos
A89: 41104503 | B89: Producto | C89: 6 | D89: ADQUISICIÓN DE UN HORNO DE SECADO POR CONVECCIÓN PARA LABORATORIO CON CONTROL DIGITAL DE TEMPERATURA Y SISTEMA DE CIRCULACIÓN DE AIRE UNIFORME. EL EQUIPO DEBE CONTAR CON INTERIOR EN ACERO INOXIDABLE DE ALTA RESISTENCIA,… | E89: PN26-289 | F89: Talleres y Laboratorios (Laboratorio física, química y biología)
A90: 41000000 | B90: Segmento | C90: 5 | D90: ADQUISICIÓN DE UN LOTE DE 15 KITS MULTIPARAMÉTRICOS Y DE REACCIÓN RÁPIDA PARA ANÁLISIS FISICOQUÍMICO Y AMBIENTAL, QUE INCLUYE KITS PARA ANÁLISIS DE CALIDAD DE AGUAS (DUREZA, CLORO, ALCALINIDAD, OXÍGENO DISUELTO), KITS D… | E90: PN26-279 | F90: Talleres y Laboratorios (Laboratorio física, química y biología)
A91: 43211503 | B91: Producto | C91: 5 | D91: Compra de 6 computadores equipos portátiles HP 512 G10, Intel Core I5 1334U, SSD 512GB, DDR4 8GB, NO DVD, Pantalla 15.6" HD. | E91: PN26-141 | F91: Bienestar Universitario
A92: 39120000 | B92: Familia | C92: 4 | D92: SUMINISTRO DE EQUIPOS, HERRAMIENTAS Y MATERIALES ELÉCTRICOS PARA LA ESCUELA TECNOLÓGICA INSTITUTO TÉCNICO CENTRAL Y EXTENSIONES (SUMINISTRO - ADQUISICIÓN) | E92: PN26-113 | F92: Infraestructura electrica
... A276: 95101807 | B276: Producto | C276: 1 | D276: Contratación del mantenimiento y adecuaciones de los escenarios deportivos (canchas) en los patios realizando mantenimiento general, reparación y adecuación de superficies de juego, ajustes necesarios para asegurar cond… | E276: PN26-122 | F276: Bienestar Universitario

Sheet Formulación PDN 2027
A1: Formulación del Plan de Necesidades 2027 — Escuela Tecnológica Instituto Técnico Central (ETITC)
A2: Una necesidad (bien, obra o servicio) por fila. Cada necesidad se vincula a una acción del Plan de Acción 2027 y, por ella, a una meta del PDI 2025-2032. Lo diligenciado aquí alimenta el Plan Anual de Adquisiciones.
A3: Gris: datos automáticos (no se editan). Amarillo: celdas que diligencia el área. Verde oscuro: control de la OAPDI. Diligencie en orden: área → meta → acción → necesidad. Consulte el Instructivo y la Guía UNSPSC.
A5: IDENTIFICACIÓN DEL ÁREA | E5: ALINEACIÓN CON EL PLAN DE ACCIÓN 2027 Y EL PDI | J5: LA NECESIDAD | M5: DATOS PARA EL PLAN ANUAL DE ADQUISICIONES (SECOP II) | AB5: RESPONSABLE | AF5: TRAZABILIDAD 2026 Y PRIORIDAD | AJ5: CONTROL
A6: N.° necesidad | B6: Área funcional que formula | C6: Dependencia (Decreto 902 de 2013) | D6: Proceso (mapa GDC-DI-01 V9) | E6: Meta estratégica PDI 2025-2032 | F6: Eje estratégico | G6: Línea de acción | H6: Acción del Plan de Acción 2027 a la que sirve la necesidad | I6: Nombre de la acción propia del área (solo si eligió PROPIA) | J6: Tipo de necesidad | K6: Justificación de la necesidad (qué problema resuelve y qué producto de la acción permite) | L6: Descripción del objeto contractual | M6: Código UNSPSC principal (8 dígitos) | N6: Códigos UNSPSC adicionales (separados por ;) | O6: Mes estimado de inicio del proceso de selección | P6: Mes estimado de presentación de ofertas | Q6: Duración del contrato (número) | R6: Unidad de duración | S6: Modalidad de selección | T6: Fuente de los recursos | U6: Tipo de gasto | V6: Rubro presupuestal o proyecto de inversión (BPIN) | W6: Valor total estimado ($, sin puntos) | X6: Valor estimado vigencia 2027 ($, sin puntos) | Y6: ¿Requiere vigencias futuras? | Z6: Estado de la solicitud de vigencias futuras | AA6: Sede o lugar de ejecución | AB6: Nombre del responsable (supervisor previsto) | AC6: Cargo del responsable | AD6: Teléfono / extensión | AE6: Correo institucional del responsable | AF6: ¿Continúa una necesidad 2026? | AG6: N.° de registro 2026 que continúa (hoja 2026) | AH6: Prioridad | AI6: Observaciones | AJ6: Alerta de consistencia | AK6: Aux. índice exportación
A7: ="PN27-"&TEXT(ROW()-6,"000") -> PN27-001 | C7: =IF(B7="","",IFERROR(INDEX(Catalogos!$R$5:$R$51,MATCH(B7,L_AREAS,0)),"")) | D7: =IF(B7="","",IFERROR(INDEX(Catalogos!$O$5:$O$51,MATCH(B7,L_AREAS,0)),"")) | F7: =IF(E7="","",IFERROR(INDEX(Catalogos!$C$5:$C$49,MATCH(E7,L_METAS,0)),"")) | G7: =IF(E7="","",IFERROR(INDEX(Catalogos!$E$5:$E$49,MATCH(E7,L_METAS,0)),"")) | AJ7: =IF(COUNTA(B7,E7,H7,I7,J7,K7,L7,M7,N7,O7,P7,Q7,R7,S7,T7,U7,V7,W7,X7,Y7,Z7,AA7,AB7,AC7,AD7,AE7,AF7,AG7,AH7,AI7)=0,"",IF(OR(B7="",E7="",H7="",J7="",K7="",L7="",M7="",O7="",P7="",Q7="",R7="",S7="",T7="",U7="",W7="",X7="",Y7="",AB7="",AC7="",AE7="",AF7=""),"Incompleta: faltan campos obligatorios",IF(AND(LEFT(H7,6)="PROPIA",I7=""),"Falta el nombre de la acción propia del área",IF(AND(LEFT(H7,3)="A27",IFERROR(INDEX(Catalogos!$T$5:$T$207,MATCH(H7,Catalogos!$U$5:$U$207,0)),"x")<>LEFT(E7,7)),"La acción no corresponde a la meta seleccionada",IF(OR(NOT(ISNUMBER(M7)),M7<10000000,M7>99999999),"Código UNSPSC inválido: registre 8 dígitos",IF(MOD(M7,10000)=0,"UNSPSC a nivel de segmento o familia: use clase o producto",IF(IFERROR(MATCH(P7,L_MESES,0)<MATCH(O7,L_MESES,0),TRUE()),"El mes de ofertas es anterior al de inicio del proceso",IF(OR(NOT(ISNUMBER(Q7)),Q7<=0),"Duración inválida",IF(OR(NOT(ISNUMBER(W7)),NOT(ISNUMBER(X7))),"Valor inválido: registre solo números",IF(OR(W7<=0,X7<=0),"Valor inválido: debe ser mayor que cero",IF(X7>W7,"El valor de la vigencia 2027 supera el valor total",IF(AND(X7<W7,Y7="No"),"El valor total supera el de 2027: requiere vigencias futuras",IF(AND(Y7="Sí",OR(Z7="",Z7="No aplica")),"Indique el estado de la solicitud de vigencias futuras",IF(IF(AND(S7="Mínima cuantía",ISNUMBER(P_TOPE_MINIMA)),W7>P_TOPE_MINIMA,FALSE()),"El valor supera el tope de mínima cuantía 2027",IF(IF(AND(S7="Selección abreviada de menor cuantía",ISNUMBER(P_TOPE_MENOR)),W7>P_TOPE_MENOR,FALSE()),"El valor supera el tope de menor cuantía 2027",IF(OR(ISERROR(SEARCH("@itc.edu.co",AE7)),SUMPRODUCT(--ISNUMBER(SEARCH({"á","é","í","ó","ú","ñ"," "},AE7)))>0),"El correo del responsable no es institucional válido",IF(AND(AF7="Sí",AG7=""),"Indique el N.° de registro 2026 que continúa","OK"))))))))))))))))) | AK7: =IF(AJ7="OK",COUNTIF($AJ$7:AJ7,"OK"),"")
A8: ="PN27-"&TEXT(ROW()-6,"000") -> PN27-002 | C8: =IF(B8="","",IFERROR(INDEX(Catalogos!$R$5:$R$51,MATCH(B8,L_AREAS,0)),"")) | D8: =IF(B8="","",IFERROR(INDEX(Catalogos!$O$5:$O$51,MATCH(B8,L_AREAS,0)),"")) | F8: =IF(E8="","",IFERROR(INDEX(Catalogos!$C$5:$C$49,MATCH(E8,L_METAS,0)),"")) | G8: =IF(E8="","",IFERROR(INDEX(Catalogos!$E$5:$E$49,MATCH(E8,L_METAS,0)),"")) | AJ8: =IF(COUNTA(B8,E8,H8,I8,J8,K8,L8,M8,N8,O8,P8,Q8,R8,S8,T8,U8,V8,W8,X8,Y8,Z8,AA8,AB8,AC8,AD8,AE8,AF8,AG8,AH8,AI8)=0,"",IF(OR(B8="",E8="",H8="",J8="",K8="",L8="",M8="",O8="",P8="",Q8="",R8="",S8="",T8="",U8="",W8="",X8="",Y8="",AB8="",AC8="",AE8="",AF8=""),"Incompleta: faltan campos obligatorios",IF(AND(LEFT(H8,6)="PROPIA",I8=""),"Falta el nombre de la acción propia del área",IF(AND(LEFT(H8,3)="A27",IFERROR(INDEX(Catalogos!$T$5:$T$207,MATCH(H8,Catalogos!$U$5:$U$207,0)),"x")<>LEFT(E8,7)),"La acción no corresponde a la meta seleccionada",IF(OR(NOT(ISNUMBER(M8)),M8<10000000,M8>99999999),"Código UNSPSC inválido: registre 8 dígitos",IF(MOD(M8,10000)=0,"UNSPSC a nivel de segmento o familia: use clase o producto",IF(IFERROR(MATCH(P8,L_MESES,0)<MATCH(O8,L_MESES,0),TRUE()),"El mes de ofertas es anterior al de inicio del proceso",IF(OR(NOT(ISNUMBER(Q8)),Q8<=0),"Duración inválida",IF(OR(NOT(ISNUMBER(W8)),NOT(ISNUMBER(X8))),"Valor inválido: registre solo números",IF(OR(W8<=0,X8<=0),"Valor inválido: debe ser mayor que cero",IF(X8>W8,"El valor de la vigencia 2027 supera el valor total",IF(AND(X8<W8,Y8="No"),"El valor total supera el de 2027: requiere vigencias futuras",IF(AND(Y8="Sí",OR(Z8="",Z8="No aplica")),"Indique el estado de la solicitud de vigencias futuras",IF(IF(AND(S8="Mínima cuantía",ISNUMBER(P_TOPE_MINIMA)),W8>P_TOPE_MINIMA,FALSE()),"El valor supera el tope de mínima cuantía 2027",IF(IF(AND(S8="Selección abreviada de menor cuantía",ISNUMBER(P_TOPE_MENOR)),W8>P_TOPE_MENOR,FALSE()),"El valor supera el tope de menor cuantía 2027",IF(OR(ISERROR(SEARCH("@itc.edu.co",AE8)),SUMPRODUCT(--ISNUMBER(SEARCH({"á","é","í","ó","ú","ñ"," "},AE8)))>0),"El correo del responsable no es institucional válido",IF(AND(AF8="Sí",AG8=""),"Indique el N.° de registro 2026 que continúa","OK"))))))))))))))))) | AK8: =IF(AJ8="OK",COUNTIF($AJ$7:AJ8,"OK"),"")
A9: ="PN27-"&TEXT(ROW()-6,"000") -> PN27-003 | C9: =IF(B9="","",IFERROR(INDEX(Catalogos!$R$5:$R$51,MATCH(B9,L_AREAS,0)),"")) | D9: =IF(B9="","",IFERROR(INDEX(Catalogos!$O$5:$O$51,MATCH(B9,L_AREAS,0)),"")) | F9: =IF(E9="","",IFERROR(INDEX(Catalogos!$C$5:$C$49,MATCH(E9,L_METAS,0)),"")) | G9: =IF(E9="","",IFERROR(INDEX(Catalogos!$E$5:$E$49,MATCH(E9,L_METAS,0)),"")) | AJ9: =IF(COUNTA(B9,E9,H9,I9,J9,K9,L9,M9,N9,O9,P9,Q9,R9,S9,T9,U9,V9,W9,X9,Y9,Z9,AA9,AB9,AC9,AD9,AE9,AF9,AG9,AH9,AI9)=0,"",IF(OR(B9="",E9="",H9="",J9="",K9="",L9="",M9="",O9="",P9="",Q9="",R9="",S9="",T9="",U9="",W9="",X9="",Y9="",AB9="",AC9="",AE9="",AF9=""),"Incompleta: faltan campos obligatorios",IF(AND(LEFT(H9,6)="PROPIA",I9=""),"Falta el nombre de la acción propia del área",IF(AND(LEFT(H9,3)="A27",IFERROR(INDEX(Catalogos!$T$5:$T$207,MATCH(H9,Catalogos!$U$5:$U$207,0)),"x")<>LEFT(E9,7)),"La acción no corresponde a la meta seleccionada",IF(OR(NOT(ISNUMBER(M9)),M9<10000000,M9>99999999),"Código UNSPSC inválido: registre 8 dígitos",IF(MOD(M9,10000)=0,"UNSPSC a nivel de segmento o familia: use clase o producto",IF(IFERROR(MATCH(P9,L_MESES,0)<MATCH(O9,L_MESES,0),TRUE()),"El mes de ofertas es anterior al de inicio del proceso",IF(OR(NOT(ISNUMBER(Q9)),Q9<=0),"Duración inválida",IF(OR(NOT(ISNUMBER(W9)),NOT(ISNUMBER(X9))),"Valor inválido: registre solo números",IF(OR(W9<=0,X9<=0),"Valor inválido: debe ser mayor que cero",IF(X9>W9,"El valor de la vigencia 2027 supera el valor total",IF(AND(X9<W9,Y9="No"),"El valor total supera el de 2027: requiere vigencias futuras",IF(AND(Y9="Sí",OR(Z9="",Z9="No aplica")),"Indique el estado de la solicitud de vigencias futuras",IF(IF(AND(S9="Mínima cuantía",ISNUMBER(P_TOPE_MINIMA)),W9>P_TOPE_MINIMA,FALSE()),"El valor supera el tope de mínima cuantía 2027",IF(IF(AND(S9="Selección abreviada de menor cuantía",ISNUMBER(P_TOPE_MENOR)),W9>P_TOPE_MENOR,FALSE()),"El valor supera el tope de menor cuantía 2027",IF(OR(ISERROR(SEARCH("@itc.edu.co",AE9)),SUMPRODUCT(--ISNUMBER(SEARCH({"á","é","í","ó","ú","ñ"," "},AE9)))>0),"El correo del responsable no es institucional válido",IF(AND(AF9="Sí",AG9=""),"Indique el N.° de registro 2026 que continúa","OK"))))))))))))))))) | AK9: =IF(AJ9="OK",COUNTIF($AJ$7:AJ9,"OK"),"")
A10: ="PN27-"&TEXT(ROW()-6,"000") -> PN27-004 | C10: =IF(B10="","",IFERROR(INDEX(Catalogos!$R$5:$R$51,MATCH(B10,L_AREAS,0)),"")) | D10: =IF(B10="","",IFERROR(INDEX(Catalogos!$O$5:$O$51,MATCH(B10,L_AREAS,0)),"")) | F10: =IF(E10="","",IFERROR(INDEX(Catalogos!$C$5:$C$49,MATCH(E10,L_METAS,0)),"")) | G10: =IF(E10="","",IFERROR(INDEX(Catalogos!$E$5:$E$49,MATCH(E10,L_METAS,0)),"")) | AJ10: =IF(COUNTA(B10,E10,H10,I10,J10,K10,L10,M10,N10,O10,P10,Q10,R10,S10,T10,U10,V10,W10,X10,Y10,Z10,AA10,AB10,AC10,AD10,AE10,AF10,AG10,AH10,AI10)=0,"",IF(OR(B10="",E10="",H10="",J10="",K10="",L10="",M10="",O10="",P10="",Q10="",R10="",S10="",T10="",U10="",W10="",X10="",Y10="",AB10="",AC10="",AE10="",AF10=""),"Incompleta: faltan campos obligatorios",IF(AND(LEFT(H10,6)="PROPIA",I10=""),"Falta el nombre de la acción propia del área",IF(AND(LEFT(H10,3)="A27",IFERROR(INDEX(Catalogos!$T$5:$T$207,MATCH(H10,Catalogos!$U$5:$U$207,0)),"x")<>LEFT(E10,7)),"La acción no corresponde a la meta seleccionada",IF(OR(NOT(ISNUMBER(M10)),M10<10000000,M10>99999999),"Código UNSPSC inválido: registre 8 dígitos",IF(MOD(M10,10000)=0,"UNSPSC a nivel de segmento o familia: use clase o producto",IF(IFERROR(MATCH(P10,L_MESES,0)<MATCH(O10,L_MESES,0),TRUE()),"El mes de ofertas es anterior al de inicio del proceso",IF(OR(NOT(ISNUMBER(Q10)),Q10<=0),"Duración inválida",IF(OR(NOT(ISNUMBER(W10)),NOT(ISNUMBER(X10))),"Valor inválido: registre solo números",IF(OR(W10<=0,X10<=0),"Valor inválido: debe ser mayor que cero",IF(X10>W10,"El valor de la vigencia 2027 supera el valor total",IF(AND(X10<W10,Y10="No"),"El valor total supera el de 2027: requiere vigencias futuras",IF(AND(Y10="Sí",OR(Z10="",Z10="No aplica")),"Indique el estado de la solicitud de vigencias futuras",IF(IF(AND(S10="Mínima cuantía",ISNUMBER(P_TOPE_MINIMA)),W10>P_TOPE_MINIMA,FALSE()),"El valor supera el tope de mínima cuantía 2027",IF(IF(AND(S10="Selección abreviada de menor cuantía",ISNUMBER(P_TOPE_MENOR)),W10>P_TOPE_MENOR,FALSE()),"El valor supera el tope de menor cuantía 2027",IF(OR(ISERROR(SEARCH("@itc.edu.co",AE10)),SUMPRODUCT(--ISNUMBER(SEARCH({"á","é","í","ó","ú","ñ"," "},AE10)))>0),"El correo del responsable no es institucional válido",IF(AND(AF10="Sí",AG10=""),"Indique el N.° de registro 2026 que continúa","OK"))))))))))))))))) | AK10: =IF(AJ10="OK",COUNTIF($AJ$7:AJ10,"OK"),"")
A11: ="PN27-"&TEXT(ROW()-6,"000") -> PN27-005 | C11: =IF(B11="","",IFERROR(INDEX(Catalogos!$R$5:$R$51,MATCH(B11,L_AREAS,0)),"")) | D11: =IF(B11="","",IFERROR(INDEX(Catalogos!$O$5:$O$51,MATCH(B11,L_AREAS,0)),"")) | F11: =IF(E11="","",IFERROR(INDEX(Catalogos!$C$5:$C$49,MATCH(E11,L_METAS,0)),"")) | G11: =IF(E11="","",IFERROR(INDEX(Catalogos!$E$5:$E$49,MATCH(E11,L_METAS,0)),"")) | AJ11: =IF(COUNTA(B11,E11,H11,I11,J11,K11,L11,M11,N11,O11,P11,Q11,R11,S11,T11,U11,V11,W11,X11,Y11,Z11,AA11,AB11,AC11,AD11,AE11,AF11,AG11,AH11,AI11)=0,"",IF(OR(B11="",E11="",H11="",J11="",K11="",L11="",M11="",O11="",P11="",Q11="",R11="",S11="",T11="",U11="",W11="",X11="",Y11="",AB11="",AC11="",AE11="",AF11=""),"Incompleta: faltan campos obligatorios",IF(AND(LEFT(H11,6)="PROPIA",I11=""),"Falta el nombre de la acción propia del área",IF(AND(LEFT(H11,3)="A27",IFERROR(INDEX(Catalogos!$T$5:$T$207,MATCH(H11,Catalogos!$U$5:$U$207,0)),"x")<>LEFT(E11,7)),"La acción no corresponde a la meta seleccionada",IF(OR(NOT(ISNUMBER(M11)),M11<10000000,M11>99999999),"Código UNSPSC inválido: registre 8 dígitos",IF(MOD(M11,10000)=0,"UNSPSC a nivel de segmento o familia: use clase o producto",IF(IFERROR(MATCH(P11,L_MESES,0)<MATCH(O11,L_MESES,0),TRUE()),"El mes de ofertas es anterior al de inicio del proceso",IF(OR(NOT(ISNUMBER(Q11)),Q11<=0),"Duración inválida",IF(OR(NOT(ISNUMBER(W11)),NOT(ISNUMBER(X11))),"Valor inválido: registre solo números",IF(OR(W11<=0,X11<=0),"Valor inválido: debe ser mayor que cero",IF(X11>W11,"El valor de la vigencia 2027 supera el valor total",IF(AND(X11<W11,Y11="No"),"El valor total supera el de 2027: requiere vigencias futuras",IF(AND(Y11="Sí",OR(Z11="",Z11="No aplica")),"Indique el estado de la solicitud de vigencias futuras",IF(IF(AND(S11="Mínima cuantía",ISNUMBER(P_TOPE_MINIMA)),W11>P_TOPE_MINIMA,FALSE()),"El valor supera el tope de mínima cuantía 2027",IF(IF(AND(S11="Selección abreviada de menor cuantía",ISNUMBER(P_TOPE_MENOR)),W11>P_TOPE_MENOR,FALSE()),"El valor supera el tope de menor cuantía 2027",IF(OR(ISERROR(SEARCH("@itc.edu.co",AE11)),SUMPRODUCT(--ISNUMBER(SEARCH({"á","é","í","ó","ú","ñ"," "},AE11)))>0),"El correo del responsable no es institucional válido",IF(AND(AF11="Sí",AG11=""),"Indique el N.° de registro 2026 que continúa","OK"))))))))))))))))) | AK11: =IF(AJ11="OK",COUNTIF($AJ$7:AJ11,"OK"),"")
A12: ="PN27-"&TEXT(ROW()-6,"000") -> PN27-006 | C12: =IF(B12="","",IFERROR(INDEX(Catalogos!$R$5:$R$51,MATCH(B12,L_AREAS,0)),"")) | D12: =IF(B12="","",IFERROR(INDEX(Catalogos!$O$5:$O$51,MATCH(B12,L_AREAS,0)),"")) | F12: =IF(E12="","",IFERROR(INDEX(Catalogos!$C$5:$C$49,MATCH(E12,L_METAS,0)),"")) | G12: =IF(E12="","",IFERROR(INDEX(Catalogos!$E$5:$E$49,MATCH(E12,L_METAS,0)),"")) | AJ12: =IF(COUNTA(B12,E12,H12,I12,J12,K12,L12,M12,N12,O12,P12,Q12,R12,S12,T12,U12,V12,W12,X12,Y12,Z12,AA12,AB12,AC12,AD12,AE12,AF12,AG12,AH12,AI12)=0,"",IF(OR(B12="",E12="",H12="",J12="",K12="",L12="",M12="",O12="",P12="",Q12="",R12="",S12="",T12="",U12="",W12="",X12="",Y12="",AB12="",AC12="",AE12="",AF12=""),"Incompleta: faltan campos obligatorios",IF(AND(LEFT(H12,6)="PROPIA",I12=""),"Falta el nombre de la acción propia del área",IF(AND(LEFT(H12,3)="A27",IFERROR(INDEX(Catalogos!$T$5:$T$207,MATCH(H12,Catalogos!$U$5:$U$207,0)),"x")<>LEFT(E12,7)),"La acción no corresponde a la meta seleccionada",IF(OR(NOT(ISNUMBER(M12)),M12<10000000,M12>99999999),"Código UNSPSC inválido: registre 8 dígitos",IF(MOD(M12,10000)=0,"UNSPSC a nivel de segmento o familia: use clase o producto",IF(IFERROR(MATCH(P12,L_MESES,0)<MATCH(O12,L_MESES,0),TRUE()),"El mes de ofertas es anterior al de inicio del proceso",IF(OR(NOT(ISNUMBER(Q12)),Q12<=0),"Duración inválida",IF(OR(NOT(ISNUMBER(W12)),NOT(ISNUMBER(X12))),"Valor inválido: registre solo números",IF(OR(W12<=0,X12<=0),"Valor inválido: debe ser mayor que cero",IF(X12>W12,"El valor de la vigencia 2027 supera el valor total",IF(AND(X12<W12,Y12="No"),"El valor total supera el de 2027: requiere vigencias futuras",IF(AND(Y12="Sí",OR(Z12="",Z12="No aplica")),"Indique el estado de la solicitud de vigencias futuras",IF(IF(AND(S12="Mínima cuantía",ISNUMBER(P_TOPE_MINIMA)),W12>P_TOPE_MINIMA,FALSE()),"El valor supera el tope de mínima cuantía 2027",IF(IF(AND(S12="Selección abreviada de menor cuantía",ISNUMBER(P_TOPE_MENOR)),W12>P_TOPE_MENOR,FALSE()),"El valor supera el tope de menor cuantía 2027",IF(OR(ISERROR(SEARCH("@itc.edu.co",AE12)),SUMPRODUCT(--ISNUMBER(SEARCH({"á","é","í","ó","ú","ñ"," "},AE12)))>0),"El correo del responsable no es institucional válido",IF(AND(AF12="Sí",AG12=""),"Indique el N.° de registro 2026 que continúa","OK"))))))))))))))))) | AK12: =IF(AJ12="OK",COUNTIF($AJ$7:AJ12,"OK"),"")
A13: ="PN27-"&TEXT(ROW()-6,"000") -> PN27-007 | C13: =IF(B13="","",IFERROR(INDEX(Catalogos!$R$5:$R$51,MATCH(B13,L_AREAS,0)),"")) | D13: =IF(B13="","",IFERROR(INDEX(Catalogos!$O$5:$O$51,MATCH(B13,L_AREAS,0)),"")) | F13: =IF(E13="","",IFERROR(INDEX(Catalogos!$C$5:$C$49,MATCH(E13,L_METAS,0)),"")) | G13: =IF(E13="","",IFERROR(INDEX(Catalogos!$E$5:$E$49,MATCH(E13,L_METAS,0)),"")) | AJ13: =IF(COUNTA(B13,E13,H13,I13,J13,K13,L13,M13,N13,O13,P13,Q13,R13,S13,T13,U13,V13,W13,X13,Y13,Z13,AA13,AB13,AC13,AD13,AE13,AF13,AG13,AH13,AI13)=0,"",IF(OR(B13="",E13="",H13="",J13="",K13="",L13="",M13="",O13="",P13="",Q13="",R13="",S13="",T13="",U13="",W13="",X13="",Y13="",AB13="",AC13="",AE13="",AF13=""),"Incompleta: faltan campos obligatorios",IF(AND(LEFT(H13,6)="PROPIA",I13=""),"Falta el nombre de la acción propia del área",IF(AND(LEFT(H13,3)="A27",IFERROR(INDEX(Catalogos!$T$5:$T$207,MATCH(H13,Catalogos!$U$5:$U$207,0)),"x")<>LEFT(E13,7)),"La acción no corresponde a la meta seleccionada",IF(OR(NOT(ISNUMBER(M13)),M13<10000000,M13>99999999),"Código UNSPSC inválido: registre 8 dígitos",IF(MOD(M13,10000)=0,"UNSPSC a nivel de segmento o familia: use clase o producto",IF(IFERROR(MATCH(P13,L_MESES,0)<MATCH(O13,L_MESES,0),TRUE()),"El mes de ofertas es anterior al de inicio del proceso",IF(OR(NOT(ISNUMBER(Q13)),Q13<=0),"Duración inválida",IF(OR(NOT(ISNUMBER(W13)),NOT(ISNUMBER(X13))),"Valor inválido: registre solo números",IF(OR(W13<=0,X13<=0),"Valor inválido: debe ser mayor que cero",IF(X13>W13,"El valor de la vigencia 2027 supera el valor total",IF(AND(X13<W13,Y13="No"),"El valor total supera el de 2027: requiere vigencias futuras",IF(AND(Y13="Sí",OR(Z13="",Z13="No aplica")),"Indique el estado de la solicitud de vigencias futuras",IF(IF(AND(S13="Mínima cuantía",ISNUMBER(P_TOPE_MINIMA)),W13>P_TOPE_MINIMA,FALSE()),"El valor supera el tope de mínima cuantía 2027",IF(IF(AND(S13="Selección abreviada de menor cuantía",ISNUMBER(P_TOPE_MENOR)),W13>P_TOPE_MENOR,FALSE()),"El valor supera el tope de menor cuantía 2027",IF(OR(ISERROR(SEARCH("@itc.edu.co",AE13)),SUMPRODUCT(--ISNUMBER(SEARCH({"á","é","í","ó","ú","ñ"," "},AE13)))>0),"El correo del responsable no es institucional válido",IF(AND(AF13="Sí",AG13=""),"Indique el N.° de registro 2026 que continúa","OK"))))))))))))))))) | AK13: =IF(AJ13="OK",COUNTIF($AJ$7:AJ13,"OK"),"")
A14: ="PN27-"&TEXT(ROW()-6,"000") -> PN27-008 | C14: =IF(B14="","",IFERROR(INDEX(Catalogos!$R$5:$R$51,MATCH(B14,L_AREAS,0)),"")) | D14: =IF(B14="","",IFERROR(INDEX(Catalogos!$O$5:$O$51,MATCH(B14,L_AREAS,0)),"")) | F14: =IF(E14="","",IFERROR(INDEX(Catalogos!$C$5:$C$49,MATCH(E14,L_METAS,0)),"")) | G14: =IF(E14="","",IFERROR(INDEX(Catalogos!$E$5:$E$49,MATCH(E14,L_METAS,0)),"")) | AJ14: =IF(COUNTA(B14,E14,H14,I14,J14,K14,L14,M14,N14,O14,P14,Q14,R14,S14,T14,U14,V14,W14,X14,Y14,Z14,AA14,AB14,AC14,AD14,AE14,AF14,AG14,AH14,AI14)=0,"",IF(OR(B14="",E14="",H14="",J14="",K14="",L14="",M14="",O14="",P14="",Q14="",R14="",S14="",T14="",U14="",W14="",X14="",Y14="",AB14="",AC14="",AE14="",AF14=""),"Incompleta: faltan campos obligatorios",IF(AND(LEFT(H14,6)="PROPIA",I14=""),"Falta el nombre de la acción propia del área",IF(AND(LEFT(H14,3)="A27",IFERROR(INDEX(Catalogos!$T$5:$T$207,MATCH(H14,Catalogos!$U$5:$U$207,0)),"x")<>LEFT(E14,7)),"La acción no corresponde a la meta seleccionada",IF(OR(NOT(ISNUMBER(M14)),M14<10000000,M14>99999999),"Código UNSPSC inválido: registre 8 dígitos",IF(MOD(M14,10000)=0,"UNSPSC a nivel de segmento o familia: use clase o producto",IF(IFERROR(MATCH(P14,L_MESES,0)<MATCH(O14,L_MESES,0),TRUE()),"El mes de ofertas es anterior al de inicio del proceso",IF(OR(NOT(ISNUMBER(Q14)),Q14<=0),"Duración inválida",IF(OR(NOT(ISNUMBER(W14)),NOT(ISNUMBER(X14))),"Valor inválido: registre solo números",IF(OR(W14<=0,X14<=0),"Valor inválido: debe ser mayor que cero",IF(X14>W14,"El valor de la vigencia 2027 supera el valor total",IF(AND(X14<W14,Y14="No"),"El valor total supera el de 2027: requiere vigencias futuras",IF(AND(Y14="Sí",OR(Z14="",Z14="No aplica")),"Indique el estado de la solicitud de vigencias futuras",IF(IF(AND(S14="Mínima cuantía",ISNUMBER(P_TOPE_MINIMA)),W14>P_TOPE_MINIMA,FALSE()),"El valor supera el tope de mínima cuantía 2027",IF(IF(AND(S14="Selección abreviada de menor cuantía",ISNUMBER(P_TOPE_MENOR)),W14>P_TOPE_MENOR,FALSE()),"El valor supera el tope de menor cuantía 2027",IF(OR(ISERROR(SEARCH("@itc.edu.co",AE14)),SUMPRODUCT(--ISNUMBER(SEARCH({"á","é","í","ó","ú","ñ"," "},AE14)))>0),"El correo del responsable no es institucional válido",IF(AND(AF14="Sí",AG14=""),"Indique el N.° de registro 2026 que continúa","OK"))))))))))))))))) | AK14: =IF(AJ14="OK",COUNTIF($AJ$7:AJ14,"OK"),"")
A15: ="PN27-"&TEXT(ROW()-6,"000") -> PN27-009 | C15: =IF(B15="","",IFERROR(INDEX(Catalogos!$R$5:$R$51,MATCH(B15,L_AREAS,0)),"")) | D15: =IF(B15="","",IFERROR(INDEX(Catalogos!$O$5:$O$51,MATCH(B15,L_AREAS,0)),"")) | F15: =IF(E15="","",IFERROR(INDEX(Catalogos!$C$5:$C$49,MATCH(E15,L_METAS,0)),"")) | G15: =IF(E15="","",IFERROR(INDEX(Catalogos!$E$5:$E$49,MATCH(E15,L_METAS,0)),"")) | AJ15: =IF(COUNTA(B15,E15,H15,I15,J15,K15,L15,M15,N15,O15,P15,Q15,R15,S15,T15,U15,V15,W15,X15,Y15,Z15,AA15,AB15,AC15,AD15,AE15,AF15,AG15,AH15,AI15)=0,"",IF(OR(B15="",E15="",H15="",J15="",K15="",L15="",M15="",O15="",P15="",Q15="",R15="",S15="",T15="",U15="",W15="",X15="",Y15="",AB15="",AC15="",AE15="",AF15=""),"Incompleta: faltan campos obligatorios",IF(AND(LEFT(H15,6)="PROPIA",I15=""),"Falta el nombre de la acción propia del área",IF(AND(LEFT(H15,3)="A27",IFERROR(INDEX(Catalogos!$T$5:$T$207,MATCH(H15,Catalogos!$U$5:$U$207,0)),"x")<>LEFT(E15,7)),"La acción no corresponde a la meta seleccionada",IF(OR(NOT(ISNUMBER(M15)),M15<10000000,M15>99999999),"Código UNSPSC inválido: registre 8 dígitos",IF(MOD(M15,10000)=0,"UNSPSC a nivel de segmento o familia: use clase o producto",IF(IFERROR(MATCH(P15,L_MESES,0)<MATCH(O15,L_MESES,0),TRUE()),"El mes de ofertas es anterior al de inicio del proceso",IF(OR(NOT(ISNUMBER(Q15)),Q15<=0),"Duración inválida",IF(OR(NOT(ISNUMBER(W15)),NOT(ISNUMBER(X15))),"Valor inválido: registre solo números",IF(OR(W15<=0,X15<=0),"Valor inválido: debe ser mayor que cero",IF(X15>W15,"El valor de la vigencia 2027 supera el valor total",IF(AND(X15<W15,Y15="No"),"El valor total supera el de 2027: requiere vigencias futuras",IF(AND(Y15="Sí",OR(Z15="",Z15="No aplica")),"Indique el estado de la solicitud de vigencias futuras",IF(IF(AND(S15="Mínima cuantía",ISNUMBER(P_TOPE_MINIMA)),W15>P_TOPE_MINIMA,FALSE()),"El valor supera el tope de mínima cuantía 2027",IF(IF(AND(S15="Selección abreviada de menor cuantía",ISNUMBER(P_TOPE_MENOR)),W15>P_TOPE_MENOR,FALSE()),"El valor supera el tope de menor cuantía 2027",IF(OR(ISERROR(SEARCH("@itc.edu.co",AE15)),SUMPRODUCT(--ISNUMBER(SEARCH({"á","é","í","ó","ú","ñ"," "},AE15)))>0),"El correo del responsable no es institucional válido",IF(AND(AF15="Sí",AG15=""),"Indique el N.° de registro 2026 que continúa","OK"))))))))))))))))) | AK15: =IF(AJ15="OK",COUNTIF($AJ$7:AJ15,"OK"),"")
A16: ="PN27-"&TEXT(ROW()-6,"000") -> PN27-010 | C16: =IF(B16="","",IFERROR(INDEX(Catalogos!$R$5:$R$51,MATCH(B16,L_AREAS,0)),"")) | D16: =IF(B16="","",IFERROR(INDEX(Catalogos!$O$5:$O$51,MATCH(B16,L_AREAS,0)),"")) | F16: =IF(E16="","",IFERROR(INDEX(Catalogos!$C$5:$C$49,MATCH(E16,L_METAS,0)),"")) | G16: =IF(E16="","",IFERROR(INDEX(Catalogos!$E$5:$E$49,MATCH(E16,L_METAS,0)),"")) | AJ16: =IF(COUNTA(B16,E16,H16,I16,J16,K16,L16,M16,N16,O16,P16,Q16,R16,S16,T16,U16,V16,W16,X16,Y16,Z16,AA16,AB16,AC16,AD16,AE16,AF16,AG16,AH16,AI16)=0,"",IF(OR(B16="",E16="",H16="",J16="",K16="",L16="",M16="",O16="",P16="",Q16="",R16="",S16="",T16="",U16="",W16="",X16="",Y16="",AB16="",AC16="",AE16="",AF16=""),"Incompleta: faltan campos obligatorios",IF(AND(LEFT(H16,6)="PROPIA",I16=""),"Falta el nombre de la acción propia del área",IF(AND(LEFT(H16,3)="A27",IFERROR(INDEX(Catalogos!$T$5:$T$207,MATCH(H16,Catalogos!$U$5:$U$207,0)),"x")<>LEFT(E16,7)),"La acción no corresponde a la meta seleccionada",IF(OR(NOT(ISNUMBER(M16)),M16<10000000,M16>99999999),"Código UNSPSC inválido: registre 8 dígitos",IF(MOD(M16,10000)=0,"UNSPSC a nivel de segmento o familia: use clase o producto",IF(IFERROR(MATCH(P16,L_MESES,0)<MATCH(O16,L_MESES,0),TRUE()),"El mes de ofertas es anterior al de inicio del proceso",IF(OR(NOT(ISNUMBER(Q16)),Q16<=0),"Duración inválida",IF(OR(NOT(ISNUMBER(W16)),NOT(ISNUMBER(X16))),"Valor inválido: registre solo números",IF(OR(W16<=0,X16<=0),"Valor inválido: debe ser mayor que cero",IF(X16>W16,"El valor de la vigencia 2027 supera el valor total",IF(AND(X16<W16,Y16="No"),"El valor total supera el de 2027: requiere vigencias futuras",IF(AND(Y16="Sí",OR(Z16="",Z16="No aplica")),"Indique el estado de la solicitud de vigencias futuras",IF(IF(AND(S16="Mínima cuantía",ISNUMBER(P_TOPE_MINIMA)),W16>P_TOPE_MINIMA,FALSE()),"El valor supera el tope de mínima cuantía 2027",IF(IF(AND(S16="Selección abreviada de menor cuantía",ISNUMBER(P_TOPE_MENOR)),W16>P_TOPE_MENOR,FALSE()),"El valor supera el tope de menor cuantía 2027",IF(OR(ISERROR(SEARCH("@itc.edu.co",AE16)),SUMPRODUCT(--ISNUMBER(SEARCH({"á","é","í","ó","ú","ñ"," "},AE16)))>0),"El correo del responsable no es institucional válido",IF(AND(AF16="Sí",AG16=""),"Indique el N.° de registro 2026 que continúa","OK"))))))))))))))))) | AK16: =IF(AJ16="OK",COUNTIF($AJ$7:AJ16,"OK"),"")
A17: ="PN27-"&TEXT(ROW()-6,"000") -> PN27-011 | C17: =IF(B17="","",IFERROR(INDEX(Catalogos!$R$5:$R$51,MATCH(B17,L_AREAS,0)),"")) | D17: =IF(B17="","",IFERROR(INDEX(Catalogos!$O$5:$O$51,MATCH(B17,L_AREAS,0)),"")) | F17: =IF(E17="","",IFERROR(INDEX(Catalogos!$C$5:$C$49,MATCH(E17,L_METAS,0)),"")) | G17: =IF(E17="","",IFERROR(INDEX(Catalogos!$E$5:$E$49,MATCH(E17,L_METAS,0)),"")) | AJ17: =IF(COUNTA(B17,E17,H17,I17,J17,K17,L17,M17,N17,O17,P17,Q17,R17,S17,T17,U17,V17,W17,X17,Y17,Z17,AA17,AB17,AC17,AD17,AE17,AF17,AG17,AH17,AI17)=0,"",IF(OR(B17="",E17="",H17="",J17="",K17="",L17="",M17="",O17="",P17="",Q17="",R17="",S17="",T17="",U17="",W17="",X17="",Y17="",AB17="",AC17="",AE17="",AF17=""),"Incompleta: faltan campos obligatorios",IF(AND(LEFT(H17,6)="PROPIA",I17=""),"Falta el nombre de la acción propia del área",IF(AND(LEFT(H17,3)="A27",IFERROR(INDEX(Catalogos!$T$5:$T$207,MATCH(H17,Catalogos!$U$5:$U$207,0)),"x")<>LEFT(E17,7)),"La acción no corresponde a la meta seleccionada",IF(OR(NOT(ISNUMBER(M17)),M17<10000000,M17>99999999),"Código UNSPSC inválido: registre 8 dígitos",IF(MOD(M17,10000)=0,"UNSPSC a nivel de segmento o familia: use clase o producto",IF(IFERROR(MATCH(P17,L_MESES,0)<MATCH(O17,L_MESES,0),TRUE()),"El mes de ofertas es anterior al de inicio del proceso",IF(OR(NOT(ISNUMBER(Q17)),Q17<=0),"Duración inválida",IF(OR(NOT(ISNUMBER(W17)),NOT(ISNUMBER(X17))),"Valor inválido: registre solo números",IF(OR(W17<=0,X17<=0),"Valor inválido: debe ser mayor que cero",IF(X17>W17,"El valor de la vigencia 2027 supera el valor total",IF(AND(X17<W17,Y17="No"),"El valor total supera el de 2027: requiere vigencias futuras",IF(AND(Y17="Sí",OR(Z17="",Z17="No aplica")),"Indique el estado de la solicitud de vigencias futuras",IF(IF(AND(S17="Mínima cuantía",ISNUMBER(P_TOPE_MINIMA)),W17>P_TOPE_MINIMA,FALSE()),"El valor supera el tope de mínima cuantía 2027",IF(IF(AND(S17="Selección abreviada de menor cuantía",ISNUMBER(P_TOPE_MENOR)),W17>P_TOPE_MENOR,FALSE()),"El valor supera el tope de menor cuantía 2027",IF(OR(ISERROR(SEARCH("@itc.edu.co",AE17)),SUMPRODUCT(--ISNUMBER(SEARCH({"á","é","í","ó","ú","ñ"," "},AE17)))>0),"El correo del responsable no es institucional válido",IF(AND(AF17="Sí",AG17=""),"Indique el N.° de registro 2026 que continúa","OK"))))))))))))))))) | AK17: =IF(AJ17="OK",COUNTIF($AJ$7:AJ17,"OK"),"")
A18: ="PN27-"&TEXT(ROW()-6,"000") -> PN27-012 | C18: =IF(B18="","",IFERROR(INDEX(Catalogos!$R$5:$R$51,MATCH(B18,L_AREAS,0)),"")) | D18: =IF(B18="","",IFERROR(INDEX(Catalogos!$O$5:$O$51,MATCH(B18,L_AREAS,0)),"")) | F18: =IF(E18="","",IFERROR(INDEX(Catalogos!$C$5:$C$49,MATCH(E18,L_METAS,0)),"")) | G18: =IF(E18="","",IFERROR(INDEX(Catalogos!$E$5:$E$49,MATCH(E18,L_METAS,0)),"")) | AJ18: =IF(COUNTA(B18,E18,H18,I18,J18,K18,L18,M18,N18,O18,P18,Q18,R18,S18,T18,U18,V18,W18,X18,Y18,Z18,AA18,AB18,AC18,AD18,AE18,AF18,AG18,AH18,AI18)=0,"",IF(OR(B18="",E18="",H18="",J18="",K18="",L18="",M18="",O18="",P18="",Q18="",R18="",S18="",T18="",U18="",W18="",X18="",Y18="",AB18="",AC18="",AE18="",AF18=""),"Incompleta: faltan campos obligatorios",IF(AND(LEFT(H18,6)="PROPIA",I18=""),"Falta el nombre de la acción propia del área",IF(AND(LEFT(H18,3)="A27",IFERROR(INDEX(Catalogos!$T$5:$T$207,MATCH(H18,Catalogos!$U$5:$U$207,0)),"x")<>LEFT(E18,7)),"La acción no corresponde a la meta seleccionada",IF(OR(NOT(ISNUMBER(M18)),M18<10000000,M18>99999999),"Código UNSPSC inválido: registre 8 dígitos",IF(MOD(M18,10000)=0,"UNSPSC a nivel de segmento o familia: use clase o producto",IF(IFERROR(MATCH(P18,L_MESES,0)<MATCH(O18,L_MESES,0),TRUE()),"El mes de ofertas es anterior al de inicio del proceso",IF(OR(NOT(ISNUMBER(Q18)),Q18<=0),"Duración inválida",IF(OR(NOT(ISNUMBER(W18)),NOT(ISNUMBER(X18))),"Valor inválido: registre solo números",IF(OR(W18<=0,X18<=0),"Valor inválido: debe ser mayor que cero",IF(X18>W18,"El valor de la vigencia 2027 supera el valor total",IF(AND(X18<W18,Y18="No"),"El valor total supera el de 2027: requiere vigencias futuras",IF(AND(Y18="Sí",OR(Z18="",Z18="No aplica")),"Indique el estado de la solicitud de vigencias futuras",IF(IF(AND(S18="Mínima cuantía",ISNUMBER(P_TOPE_MINIMA)),W18>P_TOPE_MINIMA,FALSE()),"El valor supera el tope de mínima cuantía 2027",IF(IF(AND(S18="Selección abreviada de menor cuantía",ISNUMBER(P_TOPE_MENOR)),W18>P_TOPE_MENOR,FALSE()),"El valor supera el tope de menor cuantía 2027",IF(OR(ISERROR(SEARCH("@itc.edu.co",AE18)),SUMPRODUCT(--ISNUMBER(SEARCH({"á","é","í","ó","ú","ñ"," "},AE18)))>0),"El correo del responsable no es institucional válido",IF(AND(AF18="Sí",AG18=""),"Indique el N.° de registro 2026 que continúa","OK"))))))))))))))))) | AK18: =IF(AJ18="OK",COUNTIF($AJ$7:AJ18,"OK"),"")
... A506: ="PN27-"&TEXT(ROW()-6,"000") -> PN27-500 | C506: =IF(B506="","",IFERROR(INDEX(Catalogos!$R$5:$R$51,MATCH(B506,L_AREAS,0)),"")) | D506: =IF(B506="","",IFERROR(INDEX(Catalogos!$O$5:$O$51,MATCH(B506,L_AREAS,0)),"")) | F506: =IF(E506="","",IFERROR(INDEX(Catalogos!$C$5:$C$49,MATCH(E506,L_METAS,0)),"")) | G506: =IF(E506="","",IFERROR(INDEX(Catalogos!$E$5:$E$49,MATCH(E506,L_METAS,0)),"")) | AJ506: =IF(COUNTA(B506,E506,H506,I506,J506,K506,L506,M506,N506,O506,P506,Q506,R506,S506,T506,U506,V506,W506,X506,Y506,Z506,AA506,AB506,AC506,AD506,AE506,AF506,AG506,AH506,AI506)=0,"",IF(OR(B506="",E506="",H506="",J506="",K506="",L506="",M506="",O506="",P506="",Q506="",R506="",S506="",T506="",U506="",W506="",X506="",Y506="",AB506="",AC506="",AE506="",AF506=""),"Incompleta: faltan campos obligatorios",IF(AND(LEFT(H506,6)="PROPIA",I506=""),"Falta el nombre de la acción propia del área",IF(AND(LEFT(H506,3)="A27",IFERROR(INDEX(Catalogos!$T$5:$T$207,MATCH(H506,Catalogos!$U$5:$U$207,0)),"x")<>LEFT(E506,7)),"La acción no corresponde a la meta seleccionada",IF(OR(NOT(ISNUMBER(M506)),M506<10000000,M506>99999999),"Código UNSPSC inválido: registre 8 dígitos",IF(MOD(M506,10000)=0,"UNSPSC a nivel de segmento o familia: use clase o producto",IF(IFERROR(MATCH(P506,L_MESES,0)<MATCH(O506,L_MESES,0),TRUE()),"El mes de ofertas es anterior al de inicio del proceso",IF(OR(NOT(ISNUMBER(Q506)),Q506<=0),"Duración inválida",IF(OR(NOT(ISNUMBER(W506)),NOT(ISNUMBER(X506))),"Valor inválido: registre solo números",IF(OR(W506<=0,X506<=0),"Valor inválido: debe ser mayor que cero",IF(X506>W506,"El valor de la vigencia 2027 supera el valor total",IF(AND(X506<W506,Y506="No"),"El valor total supera el de 2027: requiere vigencias futuras",IF(AND(Y506="Sí",OR(Z506="",Z506="No aplica")),"Indique el estado de la solicitud de vigencias futuras",IF(IF(AND(S506="Mínima cuantía",ISNUMBER(P_TOPE_MINIMA)),W506>P_TOPE_MINIMA,FALSE()),"El valor supera el tope de mínima cuantía 2027",IF(IF(AND(S506="Selección abreviada de menor cuantía",ISNUMBER(P_TOPE_MENOR)),W506>P_TOPE_MENOR,FALSE()),"El valor supera el tope de menor cuantía 2027",IF(OR(ISERROR(SEARCH("@itc.edu.co",AE506)),SUMPRODUCT(--ISNUMBER(SEARCH({"á","é","í","ó","ú","ñ"," "},AE506)))>0),"El correo del responsable no es institucional válido",IF(AND(AF506="Sí",AG506=""),"Indique el N.° de registro 2026 que continúa","OK"))))))))))))))))) | AK506: =IF(AJ506="OK",COUNTIF($AJ$7:AJ506,"OK"),"")

Sheet 2026
A1: Plan de Necesidades 2026 — registro histórico (solo consulta)
A2: Fuente: archivo "Plan_de_necesidades_PROTEGIDO_Modificado_2.xlsx", hoja "Plan de necesidades fin" (424 registros), que contiene íntegramente la versión "Plan_de_necesidades_PROTEGIDO.xlsx". Hoja protegida por la OAPDI: no se puede editar ni borrar; sí filtrar.
A3: Columnas B a K: información original de la formulación 2026, sin modificar. Columnas L a O (verde): anotaciones de la OAPDI para la consolidación 2027; las inferidas deben validarse.
A4: N.° registro 2026 | B4: CÓDIGO UNSPSC | C4: ENCARGADO | D4: DESCRIPCIÓN (OBJETO CONTRACTUAL) | E4: DURACIÓN DEL CONTRATO (NUMERO MESES) | F4: MODALIDAD DE SELECCIÓN EJEMPLO: -DIRECTA -MINIMA CUANTIA -MENOR CUANTIA | G4: VALOR TOTAL ESTIMADO, EN PESOS COLOMBIANOS | H4: NOMBRE DEL CARGO RESPONSABLE (SUPERVISOR DEL CONTRATO) | I4: TELÉFONO DEL RESPONSABLE | J4: CORREO ELECTRÓNICO DEL RESPONSABLE (SUPERVISOR DEL CONTRATO) | K4: ID | L4: Dependencia (Decreto 902) inferida por el correo o, en su defecto, por el campo ENCARGADO — validar | M4: Valor numérico normalizado por la OAPDI ($) | N4: Modalidad normalizada por la OAPDI | O4: Alerta de calidad del dato (OAPDI)
A5: PN26-001 | B5: 84131602 | C5: Talento humano - Seguridad y salud en el trabajo | D5: Prestar el servicio de área protegida para la atención prehospitalaria, atención médica de urgencias y emergencias, y el traslado asistencial de pacientes que lo requieran, dirigido a funcionarios, contratistas, estudiantes y visitantes, en las diferentes sedes de la Escuela Tecnológica Instituto Técnico Central – ETITC | E5: 11 | F5: MINIMA CUANTIA | G5: 25800 | H5: profesional universitario 2044-11 | J5: seguridadysalud@itc.edu.co | K5: 1 | L5: 133 · GIT Gestión de Talento Humano | M5: 25800 | N5: Mínima cuantía | O5: =IF(LEN(IF(OR(NOT(ISNUMBER(B5)),LEN(B5)<>8),"UNSPSC vacío, en texto, con varios códigos o sin 8 dígitos; ","")&IF(AND(ISNUMBER(B5),LEN(B5)=8),IF(MOD(B5,10000)=0,"UNSPSC a nivel de segmento o familia; ",""),"")&IF(NOT(ISNUMBER(E5)),"Duración vacía o en texto; ","")&IF(NOT(ISNUMBER(G5)),"Valor vacío o en texto; ","")&IF(ISNUMBER(M5),IF(M5<1000000,"Valor inferior a $1.000.000: verificar; ",""),"Valor no interpretable; ")&IF(N5="[PENDIENTE DE VERIFICAR]","Modalidad no identificable; ","")&IF(OR(ISERROR(SEARCH("@itc.edu.co",J5)),SUMPRODUCT(--ISNUMBER(SEARCH({"á","é","í","ó","ú","ñ"},J5)))>0),"Correo vacío o no institucional válido; ","")&IF(LEN(TRIM(D5))=0,"Sin objeto contractual; ","")&IF(AND(ISNUMBER(M5),N5="Mínima cuantía"),IF(M5>39850000,"Mínima cuantía con valor superior al tope citado en el instructivo 2026 ($39.850.000): verificar modalidad; ",""),"")&IF(AND(ISNUMBER(M5),OR(ISNUMBER(SEARCH("prestación de servicios",D5)),ISNUMBER(SEARCH("prestar servicios",D5)),ISNUMBER(SEARCH("prestar los servicios",D5)))),IF(M5>=500000000,"Prestación de servicios por $500 millones o más: posible error de digitación; ",""),""))=0,"Sin observaciones",IF(OR(NOT(ISNUMBER(B5)),LEN(B5)<>8),"UNSPSC vacío, en texto, con varios códigos o sin 8 dígitos; ","")&IF(AND(ISNUMBER(B5),LEN(B5)=8),IF(MOD(B5,10000)=0,"UNSPSC a nivel de segmento o familia; ",""),"")&IF(NOT(ISNUMBER(E5)),"Duración vacía o en texto; ","")&IF(NOT(ISNUMBER(G5)),"Valor vacío o en texto; ","")&IF(ISNUMBER(M5),IF(M5<1000000,"Valor inferior a $1.000.000: verificar; ",""),"Valor no interpretable; ")&IF(N5="[PENDIENTE DE VERIFICAR]","Modalidad no identificable; ","")&IF(OR(ISERROR(SEARCH("@itc.edu.co",J5)),SUMPRODUCT(--ISNUMBER(SEARCH({"á","é","í","ó","ú","ñ"},J5)))>0),"Correo vacío o no institucional válido; ","")&IF(LEN(TRIM(D5))=0,"Sin objeto contractual; ","")&IF(AND(ISNUMBER(M5),N5="Mínima cuantía"),IF(M5>39850000,"Mínima cuantía con valor superior al tope citado en el instructivo 2026 ($39.850.000): verificar modalidad; ",""),"")&IF(AND(ISNUMBER(M5),OR(ISNUMBER(SEARCH("prestación de servicios",D5)),ISNUMBER(SEARCH("prestar servicios",D5)),ISNUMBER(SEARCH("prestar los servicios",D5)))),IF(M5>=500000000,"Prestación de servicios por $500 millones o más: posible error de digitación; ",""),"")) -> Valor inferior a $1.000.000: verificar;
A6: PN26-002 | B6: 80101505 | C6: Talento humano - Seguridad y salud en el trabajo | D6: Ejecución del Programa de Vigilancia Epidemiológica de Riesgo Psicosocial en la Escuela Tecnológica Instituto Técnico Central, que incluya la planeación, la implementación, el seguimiento y la evaluación de las medidas de intervención organizacional, grupal e individual, orientadas a la prevención, mitigación y control de los factores de riesgo psicosocial identificados en la batería del 2025, conforme a la normatividad vigente. | E6: 10 | F6: MINIMA CUANTIA | G6: 25000000 | H6: profesional universitario 2044-11 | J6: seguridadysalud@itc.edu.co | K6: 2 | L6: 133 · GIT Gestión de Talento Humano | M6: 25000000 | N6: Mínima cuantía | O6: =IF(LEN(IF(OR(NOT(ISNUMBER(B6)),LEN(B6)<>8),"UNSPSC vacío, en texto, con varios códigos o sin 8 dígitos; ","")&IF(AND(ISNUMBER(B6),LEN(B6)=8),IF(MOD(B6,10000)=0,"UNSPSC a nivel de segmento o familia; ",""),"")&IF(NOT(ISNUMBER(E6)),"Duración vacía o en texto; ","")&IF(NOT(ISNUMBER(G6)),"Valor vacío o en texto; ","")&IF(ISNUMBER(M6),IF(M6<1000000,"Valor inferior a $1.000.000: verificar; ",""),"Valor no interpretable; ")&IF(N6="[PENDIENTE DE VERIFICAR]","Modalidad no identificable; ","")&IF(OR(ISERROR(SEARCH("@itc.edu.co",J6)),SUMPRODUCT(--ISNUMBER(SEARCH({"á","é","í","ó","ú","ñ"},J6)))>0),"Correo vacío o no institucional válido; ","")&IF(LEN(TRIM(D6))=0,"Sin objeto contractual; ","")&IF(AND(ISNUMBER(M6),N6="Mínima cuantía"),IF(M6>39850000,"Mínima cuantía con valor superior al tope citado en el instructivo 2026 ($39.850.000): verificar modalidad; ",""),"")&IF(AND(ISNUMBER(M6),OR(ISNUMBER(SEARCH("prestación de servicios",D6)),ISNUMBER(SEARCH("prestar servicios",D6)),ISNUMBER(SEARCH("prestar los servicios",D6)))),IF(M6>=500000000,"Prestación de servicios por $500 millones o más: posible error de digitación; ",""),""))=0,"Sin observaciones",IF(OR(NOT(ISNUMBER(B6)),LEN(B6)<>8),"UNSPSC vacío, en texto, con varios códigos o sin 8 dígitos; ","")&IF(AND(ISNUMBER(B6),LEN(B6)=8),IF(MOD(B6,10000)=0,"UNSPSC a nivel de segmento o familia; ",""),"")&IF(NOT(ISNUMBER(E6)),"Duración vacía o en texto; ","")&IF(NOT(ISNUMBER(G6)),"Valor vacío o en texto; ","")&IF(ISNUMBER(M6),IF(M6<1000000,"Valor inferior a $1.000.000: verificar; ",""),"Valor no interpretable; ")&IF(N6="[PENDIENTE DE VERIFICAR]","Modalidad no identificable; ","")&IF(OR(ISERROR(SEARCH("@itc.edu.co",J6)),SUMPRODUCT(--ISNUMBER(SEARCH({"á","é","í","ó","ú","ñ"},J6)))>0),"Correo vacío o no institucional válido; ","")&IF(LEN(TRIM(D6))=0,"Sin objeto contractual; ","")&IF(AND(ISNUMBER(M6),N6="Mínima cuantía"),IF(M6>39850000,"Mínima cuantía con valor superior al tope citado en el instructivo 2026 ($39.850.000): verificar modalidad; ",""),"")&IF(AND(ISNUMBER(M6),OR(ISNUMBER(SEARCH("prestación de servicios",D6)),ISNUMBER(SEARCH("prestar servicios",D6)),ISNUMBER(SEARCH("prestar los servicios",D6)))),IF(M6>=500000000,"Prestación de servicios por $500 millones o más: posible error de digitación; ",""),"")) -> Sin observaciones
A7: PN26-003 | B7: 76122406 | C7: Talento humano - Seguridad y salud en el trabajo | D7: Adquirir elementos de protección personal y contratar la certificación de los elementos de protección para trabajo en alturas, destinados al personal de la Escuela Tecnológica Instituto Técnico Central – ETITC, de conformidad con la normatividad vigente. | E7: 7 | F7: SUBASTA | G7: 100000000 | H7: profesional universitario 2044-11 | J7: seguridadysalud@itc.edu.co | K7: 3 | L7: 133 · GIT Gestión de Talento Humano | M7: 100000000 | N7: Selección abreviada – subasta inversa | O7: =IF(LEN(IF(OR(NOT(ISNUMBER(B7)),LEN(B7)<>8),"UNSPSC vacío, en texto, con varios códigos o sin 8 dígitos; ","")&IF(AND(ISNUMBER(B7),LEN(B7)=8),IF(MOD(B7,10000)=0,"UNSPSC a nivel de segmento o familia; ",""),"")&IF(NOT(ISNUMBER(E7)),"Duración vacía o en texto; ","")&IF(NOT(ISNUMBER(G7)),"Valor vacío o en texto; ","")&IF(ISNUMBER(M7),IF(M7<1000000,"Valor inferior a $1.000.000: verificar; ",""),"Valor no interpretable; ")&IF(N7="[PENDIENTE DE VERIFICAR]","Modalidad no identificable; ","")&IF(OR(ISERROR(SEARCH("@itc.edu.co",J7)),SUMPRODUCT(--ISNUMBER(SEARCH({"á","é","í","ó","ú","ñ"},J7)))>0),"Correo vacío o no institucional válido; ","")&IF(LEN(TRIM(D7))=0,"Sin objeto contractual; ","")&IF(AND(ISNUMBER(M7),N7="Mínima cuantía"),IF(M7>39850000,"Mínima cuantía con valor superior al tope citado en el instructivo 2026 ($39.850.000): verificar modalidad; ",""),"")&IF(AND(ISNUMBER(M7),OR(ISNUMBER(SEARCH("prestación de servicios",D7)),ISNUMBER(SEARCH("prestar servicios",D7)),ISNUMBER(SEARCH("prestar los servicios",D7)))),IF(M7>=500000000,"Prestación de servicios por $500 millones o más: posible error de digitación; ",""),""))=0,"Sin observaciones",IF(OR(NOT(ISNUMBER(B7)),LEN(B7)<>8),"UNSPSC vacío, en texto, con varios códigos o sin 8 dígitos; ","")&IF(AND(ISNUMBER(B7),LEN(B7)=8),IF(MOD(B7,10000)=0,"UNSPSC a nivel de segmento o familia; ",""),"")&IF(NOT(ISNUMBER(E7)),"Duración vacía o en texto; ","")&IF(NOT(ISNUMBER(G7)),"Valor vacío o en texto; ","")&IF(ISNUMBER(M7),IF(M7<1000000,"Valor inferior a $1.000.000: verificar; ",""),"Valor no interpretable; ")&IF(N7="[PENDIENTE DE VERIFICAR]","Modalidad no identificable; ","")&IF(OR(ISERROR(SEARCH("@itc.edu.co",J7)),SUMPRODUCT(--ISNUMBER(SEARCH({"á","é","í","ó","ú","ñ"},J7)))>0),"Correo vacío o no institucional válido; ","")&IF(LEN(TRIM(D7))=0,"Sin objeto contractual; ","")&IF(AND(ISNUMBER(M7),N7="Mínima cuantía"),IF(M7>39850000,"Mínima cuantía con valor superior al tope citado en el instructivo 2026 ($39.850.000): verificar modalidad; ",""),"")&IF(AND(ISNUMBER(M7),OR(ISNUMBER(SEARCH("prestación de servicios",D7)),ISNUMBER(SEARCH("prestar servicios",D7)),ISNUMBER(SEARCH("prestar los servicios",D7)))),IF(M7>=500000000,"Prestación de servicios por $500 millones o más: posible error de digitación; ",""),"")) -> Sin observaciones
A8: PN26-004 | B8: 85122201 | C8: Talento humano - Seguridad y salud en el trabajo | D8: Prestar los servicios médicos ocupacionales para la identificación y vigilancia de las condiciones de salud del personal, mediante la realización de exámenes médicos ocupacionales de ingreso, periódicos, de egreso, alturas, post-incapacidad, por cambio de ocupación o reubicación laboral, y demás evaluaciones médicas requeridas por la normatividad vigente en Seguridad y Salud en el Trabajo, en la Escuela Tecnológica Instituto Técnico Central – ETITC en todas sus sedes. | E8: 10 | F8: MINIMA CUANTIA | G8: 26750000 | H8: profesional universitario 2044-11 | J8: seguridadysalud@itc.edu.co | K8: 4 | L8: 133 · GIT Gestión de Talento Humano | M8: 26750000 | N8: Mínima cuantía | O8: =IF(LEN(IF(OR(NOT(ISNUMBER(B8)),LEN(B8)<>8),"UNSPSC vacío, en texto, con varios códigos o sin 8 dígitos; ","")&IF(AND(ISNUMBER(B8),LEN(B8)=8),IF(MOD(B8,10000)=0,"UNSPSC a nivel de segmento o familia; ",""),"")&IF(NOT(ISNUMBER(E8)),"Duración vacía o en texto; ","")&IF(NOT(ISNUMBER(G8)),"Valor vacío o en texto; ","")&IF(ISNUMBER(M8),IF(M8<1000000,"Valor inferior a $1.000.000: verificar; ",""),"Valor no interpretable; ")&IF(N8="[PENDIENTE DE VERIFICAR]","Modalidad no identificable; ","")&IF(OR(ISERROR(SEARCH("@itc.edu.co",J8)),SUMPRODUCT(--ISNUMBER(SEARCH({"á","é","í","ó","ú","ñ"},J8)))>0),"Correo vacío o no institucional válido; ","")&IF(LEN(TRIM(D8))=0,"Sin objeto contractual; ","")&IF(AND(ISNUMBER(M8),N8="Mínima cuantía"),IF(M8>39850000,"Mínima cuantía con valor superior al tope citado en el instructivo 2026 ($39.850.000): verificar modalidad; ",""),"")&IF(AND(ISNUMBER(M8),OR(ISNUMBER(SEARCH("prestación de servicios",D8)),ISNUMBER(SEARCH("prestar servicios",D8)),ISNUMBER(SEARCH("prestar los servicios",D8)))),IF(M8>=500000000,"Prestación de servicios por $500 millones o más: posible error de digitación; ",""),""))=0,"Sin observaciones",IF(OR(NOT(ISNUMBER(B8)),LEN(B8)<>8),"UNSPSC vacío, en texto, con varios códigos o sin 8 dígitos; ","")&IF(AND(ISNUMBER(B8),LEN(B8)=8),IF(MOD(B8,10000)=0,"UNSPSC a nivel de segmento o familia; ",""),"")&IF(NOT(ISNUMBER(E8)),"Duración vacía o en texto; ","")&IF(NOT(ISNUMBER(G8)),"Valor vacío o en texto; ","")&IF(ISNUMBER(M8),IF(M8<1000000,"Valor inferior a $1.000.000: verificar; ",""),"Valor no interpretable; ")&IF(N8="[PENDIENTE DE VERIFICAR]","Modalidad no identificable; ","")&IF(OR(ISERROR(SEARCH("@itc.edu.co",J8)),SUMPRODUCT(--ISNUMBER(SEARCH({"á","é","í","ó","ú","ñ"},J8)))>0),"Correo vacío o no institucional válido; ","")&IF(LEN(TRIM(D8))=0,"Sin objeto contractual; ","")&IF(AND(ISNUMBER(M8),N8="Mínima cuantía"),IF(M8>39850000,"Mínima cuantía con valor superior al tope citado en el instructivo 2026 ($39.850.000): verificar modalidad; ",""),"")&IF(AND(ISNUMBER(M8),OR(ISNUMBER(SEARCH("prestación de servicios",D8)),ISNUMBER(SEARCH("prestar servicios",D8)),ISNUMBER(SEARCH("prestar los servicios",D8)))),IF(M8>=500000000,"Prestación de servicios por $500 millones o más: posible error de digitación; ",""),"")) -> Sin observaciones
A9: PN26-005 | B9: 46191601 | C9: Talento humano - Seguridad y salud en el trabajo | D9: Adquirir el servicio de recarga y mantenimiento de extintores, la dotación y reposición de botiquines, y el suministro de elementos para la la atención de emergencias, para la Escuela Tecnológica Instituto Técnico Central – ETITC en todas sus sedes. | E9: 7 | F9: TIENDA VIRTUAL | G9: 33000000 | H9: profesional universitario 2044-11 | J9: seguridadysalud@itc.edu.co | K9: 5 | L9: 133 · GIT Gestión de Talento Humano | M9: 33000000 | N9: Acuerdo marco de precios / Tienda Virtual (validar) | O9: =IF(LEN(IF(OR(NOT(ISNUMBER(B9)),LEN(B9)<>8),"UNSPSC vacío, en texto, con varios códigos o sin 8 dígitos; ","")&IF(AND(ISNUMBER(B9),LEN(B9)=8),IF(MOD(B9,10000)=0,"UNSPSC a nivel de segmento o familia; ",""),"")&IF(NOT(ISNUMBER(E9)),"Duración vacía o en texto; ","")&IF(NOT(ISNUMBER(G9)),"Valor vacío o en texto; ","")&IF(ISNUMBER(M9),IF(M9<1000000,"Valor inferior a $1.000.000: verificar; ",""),"Valor no interpretable; ")&IF(N9="[PENDIENTE DE VERIFICAR]","Modalidad no identificable; ","")&IF(OR(ISERROR(SEARCH("@itc.edu.co",J9)),SUMPRODUCT(--ISNUMBER(SEARCH({"á","é","í","ó","ú","ñ"},J9)))>0),"Correo vacío o no institucional válido; ","")&IF(LEN(TRIM(D9))=0,"Sin objeto contractual; ","")&IF(AND(ISNUMBER(M9),N9="Mínima cuantía"),IF(M9>39850000,"Mínima cuantía con valor superior al tope citado en el instructivo 2026 ($39.850.000): verificar modalidad; ",""),"")&IF(AND(ISNUMBER(M9),OR(ISNUMBER(SEARCH("prestación de servicios",D9)),ISNUMBER(SEARCH("prestar servicios",D9)),ISNUMBER(SEARCH("prestar los servicios",D9)))),IF(M9>=500000000,"Prestación de servicios por $500 millones o más: posible error de digitación; ",""),""))=0,"Sin observaciones",IF(OR(NOT(ISNUMBER(B9)),LEN(B9)<>8),"UNSPSC vacío, en texto, con varios códigos o sin 8 dígitos; ","")&IF(AND(ISNUMBER(B9),LEN(B9)=8),IF(MOD(B9,10000)=0,"UNSPSC a nivel de segmento o familia; ",""),"")&IF(NOT(ISNUMBER(E9)),"Duración vacía o en texto; ","")&IF(NOT(ISNUMBER(G9)),"Valor vacío o en texto; ","")&IF(ISNUMBER(M9),IF(M9<1000000,"Valor inferior a $1.000.000: verificar; ",""),"Valor no interpretable; ")&IF(N9="[PENDIENTE DE VERIFICAR]","Modalidad no identificable; ","")&IF(OR(ISERROR(SEARCH("@itc.edu.co",J9)),SUMPRODUCT(--ISNUMBER(SEARCH({"á","é","í","ó","ú","ñ"},J9)))>0),"Correo vacío o no institucional válido; ","")&IF(LEN(TRIM(D9))=0,"Sin objeto contractual; ","")&IF(AND(ISNUMBER(M9),N9="Mínima cuantía"),IF(M9>39850000,"Mínima cuantía con valor superior al tope citado en el instructivo 2026 ($39.850.000): verificar modalidad; ",""),"")&IF(AND(ISNUMBER(M9),OR(ISNUMBER(SEARCH("prestación de servicios",D9)),ISNUMBER(SEARCH("prestar servicios",D9)),ISNUMBER(SEARCH("prestar los servicios",D9)))),IF(M9>=500000000,"Prestación de servicios por $500 millones o más: posible error de digitación; ",""),"")) -> Sin observaciones
A10: PN26-006 | B10: 80111600 | C10: Talento humano - Seguridad y salud en el trabajo | D10: Prestar servicios profesionales para apoyar el diseño, implementación, conformación y seguimiento del Plan de Emergencias de la Escuela Tecnológica Instituto Técnico Central – ETITC y sus sedes, así como para realizar la coordinación, control, verificación y aplicación del Programa de Protección contra Caídas, en calidad de coordinador de trabajo en alturas, de conformidad con la normatividad vigente. | E10: 10.5 | F10: DIRECTA | G10: 57500000 | H10: profesional universitario 2044-11 | J10: seguridadysalud@itc.edu.co | K10: 6 | L10: 133 · GIT Gestión de Talento Humano | M10: 57500000 | N10: Contratación directa | O10: =IF(LEN(IF(OR(NOT(ISNUMBER(B10)),LEN(B10)<>8),"UNSPSC vacío, en texto, con varios códigos o sin 8 dígitos; ","")&IF(AND(ISNUMBER(B10),LEN(B10)=8),IF(MOD(B10,10000)=0,"UNSPSC a nivel de segmento o familia; ",""),"")&IF(NOT(ISNUMBER(E10)),"Duración vacía o en texto; ","")&IF(NOT(ISNUMBER(G10)),"Valor vacío o en texto; ","")&IF(ISNUMBER(M10),IF(M10<1000000,"Valor inferior a $1.000.000: verificar; ",""),"Valor no interpretable; ")&IF(N10="[PENDIENTE DE VERIFICAR]","Modalidad no identificable; ","")&IF(OR(ISERROR(SEARCH("@itc.edu.co",J10)),SUMPRODUCT(--ISNUMBER(SEARCH({"á","é","í","ó","ú","ñ"},J10)))>0),"Correo vacío o no institucional válido; ","")&IF(LEN(TRIM(D10))=0,"Sin objeto contractual; ","")&IF(AND(ISNUMBER(M10),N10="Mínima cuantía"),IF(M10>39850000,"Mínima cuantía con valor superior al tope citado en el instructivo 2026 ($39.850.000): verificar modalidad; ",""),"")&IF(AND(ISNUMBER(M10),OR(ISNUMBER(SEARCH("prestación de servicios",D10)),ISNUMBER(SEARCH("prestar servicios",D10)),ISNUMBER(SEARCH("prestar los servicios",D10)))),IF(M10>=500000000,"Prestación de servicios por $500 millones o más: posible error de digitación; ",""),""))=0,"Sin observaciones",IF(OR(NOT(ISNUMBER(B10)),LEN(B10)<>8),"UNSPSC vacío, en texto, con varios códigos o sin 8 dígitos; ","")&IF(AND(ISNUMBER(B10),LEN(B10)=8),IF(MOD(B10,10000)=0,"UNSPSC a nivel de segmento o familia; ",""),"")&IF(NOT(ISNUMBER(E10)),"Duración vacía o en texto; ","")&IF(NOT(ISNUMBER(G10)),"Valor vacío o en texto; ","")&IF(ISNUMBER(M10),IF(M10<1000000,"Valor inferior a $1.000.000: verificar; ",""),"Valor no interpretable; ")&IF(N10="[PENDIENTE DE VERIFICAR]","Modalidad no identificable; ","")&IF(OR(ISERROR(SEARCH("@itc.edu.co",J10)),SUMPRODUCT(--ISNUMBER(SEARCH({"á","é","í","ó","ú","ñ"},J10)))>0),"Correo vacío o no institucional válido; ","")&IF(LEN(TRIM(D10))=0,"Sin objeto contractual; ","")&IF(AND(ISNUMBER(M10),N10="Mínima cuantía"),IF(M10>39850000,"Mínima cuantía con valor superior al tope citado en el instructivo 2026 ($39.850.000): verificar modalidad; ",""),"")&IF(AND(ISNUMBER(M10),OR(ISNUMBER(SEARCH("prestación de servicios",D10)),ISNUMBER(SEARCH("prestar servicios",D10)),ISNUMBER(SEARCH("prestar los servicios",D10)))),IF(M10>=500000000,"Prestación de servicios por $500 millones o más: posible error de digitación; ",""),"")) -> Sin observaciones
A11: PN26-007 | C11: Talento Humano-vicerrectoria Administrativa | D11: Prestación de servicios profesionales para el apoyo logístico, operativo y/o Técnico en la planeación, ejecución y seguimiento de las actividades misionales desarrolladas por la Escuela Tecnológica Instituto Técnico Central, en el marco del programa de Bienestar laboral e incentivos correspondiente a la vigencia de 2026. | E11: 10.5 | F11: DIRECTA | G11: 350000000 | H11: Profesional Especializado 2028-15 | J11: personal@itc.edu.co | L11: 133 · GIT Gestión de Talento Humano | M11: 350000000 | N11: Contratación directa | O11: =IF(LEN(IF(OR(NOT(ISNUMBER(B11)),LEN(B11)<>8),"UNSPSC vacío, en texto, con varios códigos o sin 8 dígitos; ","")&IF(AND(ISNUMBER(B11),LEN(B11)=8),IF(MOD(B11,10000)=0,"UNSPSC a nivel de segmento o familia; ",""),"")&IF(NOT(ISNUMBER(E11)),"Duración vacía o en texto; ","")&IF(NOT(ISNUMBER(G11)),"Valor vacío o en texto; ","")&IF(ISNUMBER(M11),IF(M11<1000000,"Valor inferior a $1.000.000: verificar; ",""),"Valor no interpretable; ")&IF(N11="[PENDIENTE DE VERIFICAR]","Modalidad no identificable; ","")&IF(OR(ISERROR(SEARCH("@itc.edu.co",J11)),SUMPRODUCT(--ISNUMBER(SEARCH({"á","é","í","ó","ú","ñ"},J11)))>0),"Correo vacío o no institucional válido; ","")&IF(LEN(TRIM(D11))=0,"Sin objeto contractual; ","")&IF(AND(ISNUMBER(M11),N11="Mínima cuantía"),IF(M11>39850000,"Mínima cuantía con valor superior al tope citado en el instructivo 2026 ($39.850.000): verificar modalidad; ",""),"")&IF(AND(ISNUMBER(M11),OR(ISNUMBER(SEARCH("prestación de servicios",D11)),ISNUMBER(SEARCH("prestar servicios",D11)),ISNUMBER(SEARCH("prestar los servicios",D11)))),IF(M11>=500000000,"Prestación de servicios por $500 millones o más: posible error de digitación; ",""),""))=0,"Sin observaciones",IF(OR(NOT(ISNUMBER(B11)),LEN(B11)<>8),"UNSPSC vacío, en texto, con varios códigos o sin 8 dígitos; ","")&IF(AND(ISNUMBER(B11),LEN(B11)=8),IF(MOD(B11,10000)=0,"UNSPSC a nivel de segmento o familia; ",""),"")&IF(NOT(ISNUMBER(E11)),"Duración vacía o en texto; ","")&IF(NOT(ISNUMBER(G11)),"Valor vacío o en texto; ","")&IF(ISNUMBER(M11),IF(M11<1000000,"Valor inferior a $1.000.000: verificar; ",""),"Valor no interpretable; ")&IF(N11="[PENDIENTE DE VERIFICAR]","Modalidad no identificable; ","")&IF(OR(ISERROR(SEARCH("@itc.edu.co",J11)),SUMPRODUCT(--ISNUMBER(SEARCH({"á","é","í","ó","ú","ñ"},J11)))>0),"Correo vacío o no institucional válido; ","")&IF(LEN(TRIM(D11))=0,"Sin objeto contractual; ","")&IF(AND(ISNUMBER(M11),N11="Mínima cuantía"),IF(M11>39850000,"Mínima cuantía con valor superior al tope citado en el instructivo 2026 ($39.850.000): verificar modalidad; ",""),"")&IF(AND(ISNUMBER(M11),OR(ISNUMBER(SEARCH("prestación de servicios",D11)),ISNUMBER(SEARCH("prestar servicios",D11)),ISNUMBER(SEARCH("prestar los servicios",D11)))),IF(M11>=500000000,"Prestación de servicios por $500 millones o más: posible error de digitación; ",""),"")) -> UNSPSC vacío, en texto, con varios códigos o sin 8 dígitos;
A12: PN26-008 | B12: 80111600 | C12: Planeación estratégica | D12: Prestar los servicios profesionales de apoyo a la oficina asesora de planeación en la formulación, seguimiento y evaluación de los planes institucionales y demás instrumentos de planeación estratégica, así como en la estructuración de proyectos, análisis de indicadores, elaboración de informes y cumplimiento de las obligaciones de reporte ante los entes de control, en el marco del modelo integrado de planeación y gestión (mipg) y las políticas institucionales vigentes. | E12: 11 | F12: DIRECTA | G12: 60500000 | H12: Jefe de la oficina asesora de planeacion | J12: planeacion@itc.edu.co | K12: 7 | L12: 101 · Oficina Asesora de Planeación y Desarrollo Institucional | M12: 60500000 | N12: Contratación directa | O12: =IF(LEN(IF(OR(NOT(ISNUMBER(B12)),LEN(B12)<>8),"UNSPSC vacío, en texto, con varios códigos o sin 8 dígitos; ","")&IF(AND(ISNUMBER(B12),LEN(B12)=8),IF(MOD(B12,10000)=0,"UNSPSC a nivel de segmento o familia; ",""),"")&IF(NOT(ISNUMBER(E12)),"Duración vacía o en texto; ","")&IF(NOT(ISNUMBER(G12)),"Valor vacío o en texto; ","")&IF(ISNUMBER(M12),IF(M12<1000000,"Valor inferior a $1.000.000: verificar; ",""),"Valor no interpretable; ")&IF(N12="[PENDIENTE DE VERIFICAR]","Modalidad no identificable; ","")&IF(OR(ISERROR(SEARCH("@itc.edu.co",J12)),SUMPRODUCT(--ISNUMBER(SEARCH({"á","é","í","ó","ú","ñ"},J12)))>0),"Correo vacío o no institucional válido; ","")&IF(LEN(TRIM(D12))=0,"Sin objeto contractual; ","")&IF(AND(ISNUMBER(M12),N12="Mínima cuantía"),IF(M12>39850000,"Mínima cuantía con valor superior al tope citado en el instructivo 2026 ($39.850.000): verificar modalidad; ",""),"")&IF(AND(ISNUMBER(M12),OR(ISNUMBER(SEARCH("prestación de servicios",D12)),ISNUMBER(SEARCH("prestar servicios",D12)),ISNUMBER(SEARCH("prestar los servicios",D12)))),IF(M12>=500000000,"Prestación de servicios por $500 millones o más: posible error de digitación; ",""),""))=0,"Sin observaciones",IF(OR(NOT(ISNUMBER(B12)),LEN(B12)<>8),"UNSPSC vacío, en texto, con varios códigos o sin 8 dígitos; ","")&IF(AND(ISNUMBER(B12),LEN(B12)=8),IF(MOD(B12,10000)=0,"UNSPSC a nivel de segmento o familia; ",""),"")&IF(NOT(ISNUMBER(E12)),"Duración vacía o en texto; ","")&IF(NOT(ISNUMBER(G12)),"Valor vacío o en texto; ","")&IF(ISNUMBER(M12),IF(M12<1000000,"Valor inferior a $1.000.000: verificar; ",""),"Valor no interpretable; ")&IF(N12="[PENDIENTE DE VERIFICAR]","Modalidad no identificable; ","")&IF(OR(ISERROR(SEARCH("@itc.edu.co",J12)),SUMPRODUCT(--ISNUMBER(SEARCH({"á","é","í","ó","ú","ñ"},J12)))>0),"Correo vacío o no institucional válido; ","")&IF(LEN(TRIM(D12))=0,"Sin objeto contractual; ","")&IF(AND(ISNUMBER(M12),N12="Mínima cuantía"),IF(M12>39850000,"Mínima cuantía con valor superior al tope citado en el instructivo 2026 ($39.850.000): verificar modalidad; ",""),"")&IF(AND(ISNUMBER(M12),OR(ISNUMBER(SEARCH("prestación de servicios",D12)),ISNUMBER(SEARCH("prestar servicios",D12)),ISNUMBER(SEARCH("prestar los servicios",D12)))),IF(M12>=500000000,"Prestación de servicios por $500 millones o más: posible error de digitación; ",""),"")) -> Sin observaciones
A13: PN26-009 | B13: 80111600 | C13: Planeacion financiera - proyectos de inversión | D13: Prestar servicios profesionales de apoyo a la oficina asesora de planeación en la formulación, seguimiento y evaluación de los proyectos de inversión institucional, garantizando su coherencia con el direccionamiento estratégico, la planeación presupuestal y los lineamientos del ministerio de hacienda y crédito público y del departamento nacional de planeación. asimismo, apoyar la gestión de recursos, la elaboración de informes y reportes en los sistemas oficiales, en el marco del modelo integrado de planeación y gestión (mipg) y las políticas institucionales vigentes. | E13: 11 | F13: DIRECTA | G13: 60500000 | H13: Jefe de la oficina asesora de planeacion | J13: planeacion@itc.edu.co | K13: 8 | L13: 101 · Oficina Asesora de Planeación y Desarrollo Institucional | M13: 60500000 | N13: Contratación directa | O13: =IF(LEN(IF(OR(NOT(ISNUMBER(B13)),LEN(B13)<>8),"UNSPSC vacío, en texto, con varios códigos o sin 8 dígitos; ","")&IF(AND(ISNUMBER(B13),LEN(B13)=8),IF(MOD(B13,10000)=0,"UNSPSC a nivel de segmento o familia; ",""),"")&IF(NOT(ISNUMBER(E13)),"Duración vacía o en texto; ","")&IF(NOT(ISNUMBER(G13)),"Valor vacío o en texto; ","")&IF(ISNUMBER(M13),IF(M13<1000000,"Valor inferior a $1.000.000: verificar; ",""),"Valor no interpretable; ")&IF(N13="[PENDIENTE DE VERIFICAR]","Modalidad no identificable; ","")&IF(OR(ISERROR(SEARCH("@itc.edu.co",J13)),SUMPRODUCT(--ISNUMBER(SEARCH({"á","é","í","ó","ú","ñ"},J13)))>0),"Correo vacío o no institucional válido; ","")&IF(LEN(TRIM(D13))=0,"Sin objeto contractual; ","")&IF(AND(ISNUMBER(M13),N13="Mínima cuantía"),IF(M13>39850000,"Mínima cuantía con valor superior al tope citado en el instructivo 2026 ($39.850.000): verificar modalidad; ",""),"")&IF(AND(ISNUMBER(M13),OR(ISNUMBER(SEARCH("prestación de servicios",D13)),ISNUMBER(SEARCH("prestar servicios",D13)),ISNUMBER(SEARCH("prestar los servicios",D13)))),IF(M13>=500000000,"Prestación de servicios por $500 millones o más: posible error de digitación; ",""),""))=0,"Sin observaciones",IF(OR(NOT(ISNUMBER(B13)),LEN(B13)<>8),"UNSPSC vacío, en texto, con varios códigos o sin 8 dígitos; ","")&IF(AND(ISNUMBER(B13),LEN(B13)=8),IF(MOD(B13,10000)=0,"UNSPSC a nivel de segmento o familia; ",""),"")&IF(NOT(ISNUMBER(E13)),"Duración vacía o en texto; ","")&IF(NOT(ISNUMBER(G13)),"Valor vacío o en texto; ","")&IF(ISNUMBER(M13),IF(M13<1000000,"Valor inferior a $1.000.000: verificar; ",""),"Valor no interpretable; ")&IF(N13="[PENDIENTE DE VERIFICAR]","Modalidad no identificable; ","")&IF(OR(ISERROR(SEARCH("@itc.edu.co",J13)),SUMPRODUCT(--ISNUMBER(SEARCH({"á","é","í","ó","ú","ñ"},J13)))>0),"Correo vacío o no institucional válido; ","")&IF(LEN(TRIM(D13))=0,"Sin objeto contractual; ","")&IF(AND(ISNUMBER(M13),N13="Mínima cuantía"),IF(M13>39850000,"Mínima cuantía con valor superior al tope citado en el instructivo 2026 ($39.850.000): verificar modalidad; ",""),"")&IF(AND(ISNUMBER(M13),OR(ISNUMBER(SEARCH("prestación de servicios",D13)),ISNUMBER(SEARCH("prestar servicios",D13)),ISNUMBER(SEARCH("prestar los servicios",D13)))),IF(M13>=500000000,"Prestación de servicios por $500 millones o más: posible error de digitación; ",""),"")) -> Sin observaciones
A14: PN26-010 | B14: 80111600 | C14: Analítica de datos institucional | D14: Prestar los servicios profesionales de apoyo a la oficina asesora de planeación en la implementación, mantenimiento y fortalecimiento del sistema unificado de información y estadística (suie), así como en la recolección, análisis y difusión de información estadística institucional. de igual forma, apoyar el desarrollo de soluciones informáticas y analíticas que faciliten la planeación, el seguimiento y la evaluación de la gestión institucional, promoviendo la toma de decisiones estratégicas y el mejoramiento continuo. | E14: 11 | F14: DIRECTA | G14: 93500000 | H14: Jefe de la oficina asesora de planeacion | J14: planeacion@itc.edu.co | K14: 9 | L14: 101 · Oficina Asesora de Planeación y Desarrollo Institucional | M14: 93500000 | N14: Contratación directa | O14: =IF(LEN(IF(OR(NOT(ISNUMBER(B14)),LEN(B14)<>8),"UNSPSC vacío, en texto, con varios códigos o sin 8 dígitos; ","")&IF(AND(ISNUMBER(B14),LEN(B14)=8),IF(MOD(B14,10000)=0,"UNSPSC a nivel de segmento o familia; ",""),"")&IF(NOT(ISNUMBER(E14)),"Duración vacía o en texto; ","")&IF(NOT(ISNUMBER(G14)),"Valor vacío o en texto; ","")&IF(ISNUMBER(M14),IF(M14<1000000,"Valor inferior a $1.000.000: verificar; ",""),"Valor no interpretable; ")&IF(N14="[PENDIENTE DE VERIFICAR]","Modalidad no identificable; ","")&IF(OR(ISERROR(SEARCH("@itc.edu.co",J14)),SUMPRODUCT(--ISNUMBER(SEARCH({"á","é","í","ó","ú","ñ"},J14)))>0),"Correo vacío o no institucional válido; ","")&IF(LEN(TRIM(D14))=0,"Sin objeto contractual; ","")&IF(AND(ISNUMBER(M14),N14="Mínima cuantía"),IF(M14>39850000,"Mínima cuantía con valor superior al tope citado en el instructivo 2026 ($39.850.000): verificar modalidad; ",""),"")&IF(AND(ISNUMBER(M14),OR(ISNUMBER(SEARCH("prestación de servicios",D14)),ISNUMBER(SEARCH("prestar servicios",D14)),ISNUMBER(SEARCH("prestar los servicios",D14)))),IF(M14>=500000000,"Prestación de servicios por $500 millones o más: posible error de digitación; ",""),""))=0,"Sin observaciones",IF(OR(NOT(ISNUMBER(B14)),LEN(B14)<>8),"UNSPSC vacío, en texto, con varios códigos o sin 8 dígitos; ","")&IF(AND(ISNUMBER(B14),LEN(B14)=8),IF(MOD(B14,10000)=0,"UNSPSC a nivel de segmento o familia; ",""),"")&IF(NOT(ISNUMBER(E14)),"Duración vacía o en texto; ","")&IF(NOT(ISNUMBER(G14)),"Valor vacío o en texto; ","")&IF(ISNUMBER(M14),IF(M14<1000000,"Valor inferior a $1.000.000: verificar; ",""),"Valor no interpretable; ")&IF(N14="[PENDIENTE DE VERIFICAR]","Modalidad no identificable; ","")&IF(OR(ISERROR(SEARCH("@itc.edu.co",J14)),SUMPRODUCT(--ISNUMBER(SEARCH({"á","é","í","ó","ú","ñ"},J14)))>0),"Correo vacío o no institucional válido; ","")&IF(LEN(TRIM(D14))=0,"Sin objeto contractual; ","")&IF(AND(ISNUMBER(M14),N14="Mínima cuantía"),IF(M14>39850000,"Mínima cuantía con valor superior al tope citado en el instructivo 2026 ($39.850.000): verificar modalidad; ",""),"")&IF(AND(ISNUMBER(M14),OR(ISNUMBER(SEARCH("prestación de servicios",D14)),ISNUMBER(SEARCH("prestar servicios",D14)),ISNUMBER(SEARCH("prestar los servicios",D14)))),IF(M14>=500000000,"Prestación de servicios por $500 millones o más: posible error de digitación; ",""),"")) -> Sin observaciones
A15: PN26-011 | B15: 80111600 | C15: Seguimiento al modelo y programa mipg y ptep | D15: Prestar servicios de apoyo profesional para la implementación, seguimiento y fortalecimiento del modelo integrado de planeación y gestión (mipg) y del programa de transparencia y ética pública (ptep), incluyendo la gestión del riesgo institucional, la transparencia, la rendición de cuentas y la participación ciudadana, conforme a los lineamientos del departamento administrativo de la función pública (dafp) y la normatividad vigente. | E15: 11 | F15: DIRECTA | G15: 60500000 | H15: Jefe de la oficina asesora de planeacion | J15: planeacion@itc.edu.co | K15: 10 | L15: 101 · Oficina Asesora de Planeación y Desarrollo Institucional | M15: 60500000 | N15: Contratación directa | O15: =IF(LEN(IF(OR(NOT(ISNUMBER(B15)),LEN(B15)<>8),"UNSPSC vacío, en texto, con varios códigos o sin 8 dígitos; ","")&IF(AND(ISNUMBER(B15),LEN(B15)=8),IF(MOD(B15,10000)=0,"UNSPSC a nivel de segmento o familia; ",""),"")&IF(NOT(ISNUMBER(E15)),"Duración vacía o en texto; ","")&IF(NOT(ISNUMBER(G15)),"Valor vacío o en texto; ","")&IF(ISNUMBER(M15),IF(M15<1000000,"Valor inferior a $1.000.000: verificar; ",""),"Valor no interpretable; ")&IF(N15="[PENDIENTE DE VERIFICAR]","Modalidad no identificable; ","")&IF(OR(ISERROR(SEARCH("@itc.edu.co",J15)),SUMPRODUCT(--ISNUMBER(SEARCH({"á","é","í","ó","ú","ñ"},J15)))>0),"Correo vacío o no institucional válido; ","")&IF(LEN(TRIM(D15))=0,"Sin objeto contractual; ","")&IF(AND(ISNUMBER(M15),N15="Mínima cuantía"),IF(M15>39850000,"Mínima cuantía con valor superior al tope citado en el instructivo 2026 ($39.850.000): verificar modalidad; ",""),"")&IF(AND(ISNUMBER(M15),OR(ISNUMBER(SEARCH("prestación de servicios",D15)),ISNUMBER(SEARCH("prestar servicios",D15)),ISNUMBER(SEARCH("prestar los servicios",D15)))),IF(M15>=500000000,"Prestación de servicios por $500 millones o más: posible error de digitación; ",""),""))=0,"Sin observaciones",IF(OR(NOT(ISNUMBER(B15)),LEN(B15)<>8),"UNSPSC vacío, en texto, con varios códigos o sin 8 dígitos; ","")&IF(AND(ISNUMBER(B15),LEN(B15)=8),IF(MOD(B15,10000)=0,"UNSPSC a nivel de segmento o familia; ",""),"")&IF(NOT(ISNUMBER(E15)),"Duración vacía o en texto; ","")&IF(NOT(ISNUMBER(G15)),"Valor vacío o en texto; ","")&IF(ISNUMBER(M15),IF(M15<1000000,"Valor inferior a $1.000.000: verificar; ",""),"Valor no interpretable; ")&IF(N15="[PENDIENTE DE VERIFICAR]","Modalidad no identificable; ","")&IF(OR(ISERROR(SEARCH("@itc.edu.co",J15)),SUMPRODUCT(--ISNUMBER(SEARCH({"á","é","í","ó","ú","ñ"},J15)))>0),"Correo vacío o no institucional válido; ","")&IF(LEN(TRIM(D15))=0,"Sin objeto contractual; ","")&IF(AND(ISNUMBER(M15),N15="Mínima cuantía"),IF(M15>39850000,"Mínima cuantía con valor superior al tope citado en el instructivo 2026 ($39.850.000): verificar modalidad; ",""),"")&IF(AND(ISNUMBER(M15),OR(ISNUMBER(SEARCH("prestación de servicios",D15)),ISNUMBER(SEARCH("prestar servicios",D15)),ISNUMBER(SEARCH("prestar los servicios",D15)))),IF(M15>=500000000,"Prestación de servicios por $500 millones o más: posible error de digitación; ",""),"")) -> Sin observaciones
A16: PN26-012 | B16: 80111600 | C16: Estrategia de regionalización | D16: Prestar servicios de apoyo profesional prestación de servicios profesionales a la oficina asesora de planeación para apoyar la implementación, fomento del desarrollo local de la estrategia de regionalización a través de la docencia, la investigación y extension realizando las acciones necesarias para establecer y fortalecer la oferta educativa en zonas geográficas determinadas, de acuerdo con las políticas vigentes y caracterización de la vocación local en coordinación con las dependencias de la escuela y su respectiva documentación. | E16: 11 | F16: DIRECTA | G16: 60500000 | H16: Jefe de la oficina asesora de planeacion | J16: planeacion@itc.edu.co | K16: 11 | L16: 101 · Oficina Asesora de Planeación y Desarrollo Institucional | M16: 60500000 | N16: Contratación directa | O16: =IF(LEN(IF(OR(NOT(ISNUMBER(B16)),LEN(B16)<>8),"UNSPSC vacío, en texto, con varios códigos o sin 8 dígitos; ","")&IF(AND(ISNUMBER(B16),LEN(B16)=8),IF(MOD(B16,10000)=0,"UNSPSC a nivel de segmento o familia; ",""),"")&IF(NOT(ISNUMBER(E16)),"Duración vacía o en texto; ","")&IF(NOT(ISNUMBER(G16)),"Valor vacío o en texto; ","")&IF(ISNUMBER(M16),IF(M16<1000000,"Valor inferior a $1.000.000: verificar; ",""),"Valor no interpretable; ")&IF(N16="[PENDIENTE DE VERIFICAR]","Modalidad no identificable; ","")&IF(OR(ISERROR(SEARCH("@itc.edu.co",J16)),SUMPRODUCT(--ISNUMBER(SEARCH({"á","é","í","ó","ú","ñ"},J16)))>0),"Correo vacío o no institucional válido; ","")&IF(LEN(TRIM(D16))=0,"Sin objeto contractual; ","")&IF(AND(ISNUMBER(M16),N16="Mínima cuantía"),IF(M16>39850000,"Mínima cuantía con valor superior al tope citado en el instructivo 2026 ($39.850.000): verificar modalidad; ",""),"")&IF(AND(ISNUMBER(M16),OR(ISNUMBER(SEARCH("prestación de servicios",D16)),ISNUMBER(SEARCH("prestar servicios",D16)),ISNUMBER(SEARCH("prestar los servicios",D16)))),IF(M16>=500000000,"Prestación de servicios por $500 millones o más: posible error de digitación; ",""),""))=0,"Sin observaciones",IF(OR(NOT(ISNUMBER(B16)),LEN(B16)<>8),"UNSPSC vacío, en texto, con varios códigos o sin 8 dígitos; ","")&IF(AND(ISNUMBER(B16),LEN(B16)=8),IF(MOD(B16,10000)=0,"UNSPSC a nivel de segmento o familia; ",""),"")&IF(NOT(ISNUMBER(E16)),"Duración vacía o en texto; ","")&IF(NOT(ISNUMBER(G16)),"Valor vacío o en texto; ","")&IF(ISNUMBER(M16),IF(M16<1000000,"Valor inferior a $1.000.000: verificar; ",""),"Valor no interpretable; ")&IF(N16="[PENDIENTE DE VERIFICAR]","Modalidad no identificable; ","")&IF(OR(ISERROR(SEARCH("@itc.edu.co",J16)),SUMPRODUCT(--ISNUMBER(SEARCH({"á","é","í","ó","ú","ñ"},J16)))>0),"Correo vacío o no institucional válido; ","")&IF(LEN(TRIM(D16))=0,"Sin objeto contractual; ","")&IF(AND(ISNUMBER(M16),N16="Mínima cuantía"),IF(M16>39850000,"Mínima cuantía con valor superior al tope citado en el instructivo 2026 ($39.850.000): verificar modalidad; ",""),"")&IF(AND(ISNUMBER(M16),OR(ISNUMBER(SEARCH("prestación de servicios",D16)),ISNUMBER(SEARCH("prestar servicios",D16)),ISNUMBER(SEARCH("prestar los servicios",D16)))),IF(M16>=500000000,"Prestación de servicios por $500 millones o más: posible error de digitación; ",""),"")) -> Sin observaciones
A17: PN26-013 | B17: 80111600 | C17: Gestion ambiental | D17: Prestación de servicios profesionales con autonomía técnica y administrativa para liderar, fortalecer, actualizar y dar continuidad al sistema de gestión ambiental (sga) institucional, asegurando el cumplimiento normativo, el mejoramiento continuo y la integración con los procesos institucionales para el periodo 2026 | E17: 11 | F17: DIRECTA | G17: 52800000 | H17: Jefe de la oficina asesora de planeacion | J17: planeacion@itc.edu.co | K17: 12 | L17: 101 · Oficina Asesora de Planeación y Desarrollo Institucional | M17: 52800000 | N17: Contratación directa | O17: =IF(LEN(IF(OR(NOT(ISNUMBER(B17)),LEN(B17)<>8),"UNSPSC vacío, en texto, con varios códigos o sin 8 dígitos; ","")&IF(AND(ISNUMBER(B17),LEN(B17)=8),IF(MOD(B17,10000)=0,"UNSPSC a nivel de segmento o familia; ",""),"")&IF(NOT(ISNUMBER(E17)),"Duración vacía o en texto; ","")&IF(NOT(ISNUMBER(G17)),"Valor vacío o en texto; ","")&IF(ISNUMBER(M17),IF(M17<1000000,"Valor inferior a $1.000.000: verificar; ",""),"Valor no interpretable; ")&IF(N17="[PENDIENTE DE VERIFICAR]","Modalidad no identificable; ","")&IF(OR(ISERROR(SEARCH("@itc.edu.co",J17)),SUMPRODUCT(--ISNUMBER(SEARCH({"á","é","í","ó","ú","ñ"},J17)))>0),"Correo vacío o no institucional válido; ","")&IF(LEN(TRIM(D17))=0,"Sin objeto contractual; ","")&IF(AND(ISNUMBER(M17),N17="Mínima cuantía"),IF(M17>39850000,"Mínima cuantía con valor superior al tope citado en el instructivo 2026 ($39.850.000): verificar modalidad; ",""),"")&IF(AND(ISNUMBER(M17),OR(ISNUMBER(SEARCH("prestación de servicios",D17)),ISNUMBER(SEARCH("prestar servicios",D17)),ISNUMBER(SEARCH("prestar los servicios",D17)))),IF(M17>=500000000,"Prestación de servicios por $500 millones o más: posible error de digitación; ",""),""))=0,"Sin observaciones",IF(OR(NOT(ISNUMBER(B17)),LEN(B17)<>8),"UNSPSC vacío, en texto, con varios códigos o sin 8 dígitos; ","")&IF(AND(ISNUMBER(B17),LEN(B17)=8),IF(MOD(B17,10000)=0,"UNSPSC a nivel de segmento o familia; ",""),"")&IF(NOT(ISNUMBER(E17)),"Duración vacía o en texto; ","")&IF(NOT(ISNUMBER(G17)),"Valor vacío o en texto; ","")&IF(ISNUMBER(M17),IF(M17<1000000,"Valor inferior a $1.000.000: verificar; ",""),"Valor no interpretable; ")&IF(N17="[PENDIENTE DE VERIFICAR]","Modalidad no identificable; ","")&IF(OR(ISERROR(SEARCH("@itc.edu.co",J17)),SUMPRODUCT(--ISNUMBER(SEARCH({"á","é","í","ó","ú","ñ"},J17)))>0),"Correo vacío o no institucional válido; ","")&IF(LEN(TRIM(D17))=0,"Sin objeto contractual; ","")&IF(AND(ISNUMBER(M17),N17="Mínima cuantía"),IF(M17>39850000,"Mínima cuantía con valor superior al tope citado en el instructivo 2026 ($39.850.000): verificar modalidad; ",""),"")&IF(AND(ISNUMBER(M17),OR(ISNUMBER(SEARCH("prestación de servicios",D17)),ISNUMBER(SEARCH("prestar servicios",D17)),ISNUMBER(SEARCH("prestar los servicios",D17)))),IF(M17>=500000000,"Prestación de servicios por $500 millones o más: posible error de digitación; ",""),"")) -> Sin observaciones
A18: PN26-014 | B18: 80111600 | C18: Gestion ambiental apoyo regionalizacion. | D18: Prestar servicios profesionales de apoyo a la ejecución, seguimiento y fortalecimiento de las actividades relacionadas con el sistema de gestión ambiental en las sedes y apoyo a los lugares de desarrollo donde se oferta educacion superior de la etitc | E18: 11 | F18: DIRECTA | G18: 41800000 | H18: Jefe de la oficina asesora de planeacion | J18: planeacion@itc.edu.co | K18: 13 | L18: 101 · Oficina Asesora de Planeación y Desarrollo Institucional | M18: 41800000 | N18: Contratación directa | O18: =IF(LEN(IF(OR(NOT(ISNUMBER(B18)),LEN(B18)<>8),"UNSPSC vacío, en texto, con varios códigos o sin 8 dígitos; ","")&IF(AND(ISNUMBER(B18),LEN(B18)=8),IF(MOD(B18,10000)=0,"UNSPSC a nivel de segmento o familia; ",""),"")&IF(NOT(ISNUMBER(E18)),"Duración vacía o en texto; ","")&IF(NOT(ISNUMBER(G18)),"Valor vacío o en texto; ","")&IF(ISNUMBER(M18),IF(M18<1000000,"Valor inferior a $1.000.000: verificar; ",""),"Valor no interpretable; ")&IF(N18="[PENDIENTE DE VERIFICAR]","Modalidad no identificable; ","")&IF(OR(ISERROR(SEARCH("@itc.edu.co",J18)),SUMPRODUCT(--ISNUMBER(SEARCH({"á","é","í","ó","ú","ñ"},J18)))>0),"Correo vacío o no institucional válido; ","")&IF(LEN(TRIM(D18))=0,"Sin objeto contractual; ","")&IF(AND(ISNUMBER(M18),N18="Mínima cuantía"),IF(M18>39850000,"Mínima cuantía con valor superior al tope citado en el instructivo 2026 ($39.850.000): verificar modalidad; ",""),"")&IF(AND(ISNUMBER(M18),OR(ISNUMBER(SEARCH("prestación de servicios",D18)),ISNUMBER(SEARCH("prestar servicios",D18)),ISNUMBER(SEARCH("prestar los servicios",D18)))),IF(M18>=500000000,"Prestación de servicios por $500 millones o más: posible error de digitación; ",""),""))=0,"Sin observaciones",IF(OR(NOT(ISNUMBER(B18)),LEN(B18)<>8),"UNSPSC vacío, en texto, con varios códigos o sin 8 dígitos; ","")&IF(AND(ISNUMBER(B18),LEN(B18)=8),IF(MOD(B18,10000)=0,"UNSPSC a nivel de segmento o familia; ",""),"")&IF(NOT(ISNUMBER(E18)),"Duración vacía o en texto; ","")&IF(NOT(ISNUMBER(G18)),"Valor vacío o en texto; ","")&IF(ISNUMBER(M18),IF(M18<1000000,"Valor inferior a $1.000.000: verificar; ",""),"Valor no interpretable; ")&IF(N18="[PENDIENTE DE VERIFICAR]","Modalidad no identificable; ","")&IF(OR(ISERROR(SEARCH("@itc.edu.co",J18)),SUMPRODUCT(--ISNUMBER(SEARCH({"á","é","í","ó","ú","ñ"},J18)))>0),"Correo vacío o no institucional válido; ","")&IF(LEN(TRIM(D18))=0,"Sin objeto contractual; ","")&IF(AND(ISNUMBER(M18),N18="Mínima cuantía"),IF(M18>39850000,"Mínima cuantía con valor superior al tope citado en el instructivo 2026 ($39.850.000): verificar modalidad; ",""),"")&IF(AND(ISNUMBER(M18),OR(ISNUMBER(SEARCH("prestación de servicios",D18)),ISNUMBER(SEARCH("prestar servicios",D18)),ISNUMBER(SEARCH("prestar los servicios",D18)))),IF(M18>=500000000,"Prestación de servicios por $500 millones o más: posible error de digitación; ",""),"")) -> Sin observaciones
A19: PN26-015 | B19: 80111600 | C19: Continuidad del servicio y datos personales. | D19: Prestar los servicios profesionales a la oficina asesora de planeación de la escuela tecnológica instituto técnico central – etic, para realizar el seguimiento, verificación y mejora continua del plan de continuidad del servicio y del tratamiento de protección de datos personales, asegurando su conformidad con la normativa vigente relacionada con la continuidad del servicio, la seguridad de la información y la protección de datos personales. | E19: 11 | F19: DIRECTA | G19: 52800000 | H19: Jefe de la oficina asesora de planeacion | J19: planeacion@itc.edu.co | K19: 14 | L19: 101 · Oficina Asesora de Planeación y Desarrollo Institucional | M19: 52800000 | N19: Contratación directa | O19: =IF(LEN(IF(OR(NOT(ISNUMBER(B19)),LEN(B19)<>8),"UNSPSC vacío, en texto, con varios códigos o sin 8 dígitos; ","")&IF(AND(ISNUMBER(B19),LEN(B19)=8),IF(MOD(B19,10000)=0,"UNSPSC a nivel de segmento o familia; ",""),"")&IF(NOT(ISNUMBER(E19)),"Duración vacía o en texto; ","")&IF(NOT(ISNUMBER(G19)),"Valor vacío o en texto; ","")&IF(ISNUMBER(M19),IF(M19<1000000,"Valor inferior a $1.000.000: verificar; ",""),"Valor no interpretable; ")&IF(N19="[PENDIENTE DE VERIFICAR]","Modalidad no identificable; ","")&IF(OR(ISERROR(SEARCH("@itc.edu.co",J19)),SUMPRODUCT(--ISNUMBER(SEARCH({"á","é","í","ó","ú","ñ"},J19)))>0),"Correo vacío o no institucional válido; ","")&IF(LEN(TRIM(D19))=0,"Sin objeto contractual; ","")&IF(AND(ISNUMBER(M19),N19="Mínima cuantía"),IF(M19>39850000,"Mínima cuantía con valor superior al tope citado en el instructivo 2026 ($39.850.000): verificar modalidad; ",""),"")&IF(AND(ISNUMBER(M19),OR(ISNUMBER(SEARCH("prestación de servicios",D19)),ISNUMBER(SEARCH("prestar servicios",D19)),ISNUMBER(SEARCH("prestar los servicios",D19)))),IF(M19>=500000000,"Prestación de servicios por $500 millones o más: posible error de digitación; ",""),""))=0,"Sin observaciones",IF(OR(NOT(ISNUMBER(B19)),LEN(B19)<>8),"UNSPSC vacío, en texto, con varios códigos o sin 8 dígitos; ","")&IF(AND(ISNUMBER(B19),LEN(B19)=8),IF(MOD(B19,10000)=0,"UNSPSC a nivel de segmento o familia; ",""),"")&IF(NOT(ISNUMBER(E19)),"Duración vacía o en texto; ","")&IF(NOT(ISNUMBER(G19)),"Valor vacío o en texto; ","")&IF(ISNUMBER(M19),IF(M19<1000000,"Valor inferior a $1.000.000: verificar; ",""),"Valor no interpretable; ")&IF(N19="[PENDIENTE DE VERIFICAR]","Modalidad no identificable; ","")&IF(OR(ISERROR(SEARCH("@itc.edu.co",J19)),SUMPRODUCT(--ISNUMBER(SEARCH({"á","é","í","ó","ú","ñ"},J19)))>0),"Correo vacío o no institucional válido; ","")&IF(LEN(TRIM(D19))=0,"Sin objeto contractual; ","")&IF(AND(ISNUMBER(M19),N19="Mínima cuantía"),IF(M19>39850000,"Mínima cuantía con valor superior al tope citado en el instructivo 2026 ($39.850.000): verificar modalidad; ",""),"")&IF(AND(ISNUMBER(M19),OR(ISNUMBER(SEARCH("prestación de servicios",D19)),ISNUMBER(SEARCH("prestar servicios",D19)),ISNUMBER(SEARCH("prestar los servicios",D19)))),IF(M19>=500000000,"Prestación de servicios por $500 millones o más: posible error de digitación; ",""),"")) -> Sin observaciones
A20: PN26-016 | B20: 811112208 | C20: Ciberseguridad y seguridad de la informacion. | D20: Prestación de servicios profesionales a la oficina asesora de planeación para ejecutar actividades orientadas al fortalecimiento de la seguridad de la información, incluyendo monitoreo, inteligencia de amenazas, documentación para garantizar cumplimiento normativo mipg, apoyo técnico al líder de seguridad de la información, gestión de incidentes y vulnerabilidades, concientización en ciberseguridad | E20: 11 | F20: DIRECTA | G20: 52800000 | H20: profesional universitario 2044-11 en Seguridad de la Información | J20: seguridaddigital@itc.edu.co | K20: 15 | L20: 132 · GIT Gestión de Informática y Telecomunicaciones | M20: 52800000 | N20: Contratación directa | O20: =IF(LEN(IF(OR(NOT(ISNUMBER(B20)),LEN(B20)<>8),"UNSPSC vacío, en texto, con varios códigos o sin 8 dígitos; ","")&IF(AND(ISNUMBER(B20),LEN(B20)=8),IF(MOD(B20,10000)=0,"UNSPSC a nivel de segmento o familia; ",""),"")&IF(NOT(ISNUMBER(E20)),"Duración vacía o en texto; ","")&IF(NOT(ISNUMBER(G20)),"Valor vacío o en texto; ","")&IF(ISNUMBER(M20),IF(M20<1000000,"Valor inferior a $1.000.000: verificar; ",""),"Valor no interpretable; ")&IF(N20="[PENDIENTE DE VERIFICAR]","Modalidad no identificable; ","")&IF(OR(ISERROR(SEARCH("@itc.edu.co",J20)),SUMPRODUCT(--ISNUMBER(SEARCH({"á","é","í","ó","ú","ñ"},J20)))>0),"Correo vacío o no institucional válido; ","")&IF(LEN(TRIM(D20))=0,"Sin objeto contractual; ","")&IF(AND(ISNUMBER(M20),N20="Mínima cuantía"),IF(M20>39850000,"Mínima cuantía con valor superior al tope citado en el instructivo 2026 ($39.850.000): verificar modalidad; ",""),"")&IF(AND(ISNUMBER(M20),OR(ISNUMBER(SEARCH("prestación de servicios",D20)),ISNUMBER(SEARCH("prestar servicios",D20)),ISNUMBER(SEARCH("prestar los servicios",D20)))),IF(M20>=500000000,"Prestación de servicios por $500 millones o más: posible error de digitación; ",""),""))=0,"Sin observaciones",IF(OR(NOT(ISNUMBER(B20)),LEN(B20)<>8),"UNSPSC vacío, en texto, con varios códigos o sin 8 dígitos; ","")&IF(AND(ISNUMBER(B20),LEN(B20)=8),IF(MOD(B20,10000)=0,"UNSPSC a nivel de segmento o familia; ",""),"")&IF(NOT(ISNUMBER(E20)),"Duración vacía o en texto; ","")&IF(NOT(ISNUMBER(G20)),"Valor vacío o en texto; ","")&IF(ISNUMBER(M20),IF(M20<1000000,"Valor inferior a $1.000.000: verificar; ",""),"Valor no interpretable; ")&IF(N20="[PENDIENTE DE VERIFICAR]","Modalidad no identificable; ","")&IF(OR(ISERROR(SEARCH("@itc.edu.co",J20)),SUMPRODUCT(--ISNUMBER(SEARCH({"á","é","í","ó","ú","ñ"},J20)))>0),"Correo vacío o no institucional válido; ","")&IF(LEN(TRIM(D20))=0,"Sin objeto contractual; ","")&IF(AND(ISNUMBER(M20),N20="Mínima cuantía"),IF(M20>39850000,"Mínima cuantía con valor superior al tope citado en el instructivo 2026 ($39.850.000): verificar modalidad; ",""),"")&IF(AND(ISNUMBER(M20),OR(ISNUMBER(SEARCH("prestación de servicios",D20)),ISNUMBER(SEARCH("prestar servicios",D20)),ISNUMBER(SEARCH("prestar los servicios",D20)))),IF(M20>=500000000,"Prestación de servicios por $500 millones o más: posible error de digitación; ",""),"")) -> UNSPSC vacío, en texto, con varios códigos o sin 8 dígitos;
A21: PN26-017 | B21: 80111600 | C21: Sistema de seguridad y salud en el trabajo - regionalizacion | D21: Prestación de servicios profesionales para apoyar las actividades, gestión, ejecución y/o acompañamiento para implementar y mantener un sistema de gestión de seguridad y salud en el trabajo (sgsst). en las sedes y lugar de desarrollo donde la etitc oferta programas de educacion superior en cumplimiento de la normativa vigente | E21: 11 | F21: DIRECTA | G21: 52800000 | H21: Jefe de la oficina asesora de planeacion | J21: planeacion@itc.edu.co | K21: 16 | L21: 101 · Oficina Asesora de Planeación y Desarrollo Institucional | M21: 52800000 | N21: Contratación directa | O21: =IF(LEN(IF(OR(NOT(ISNUMBER(B21)),LEN(B21)<>8),"UNSPSC vacío, en texto, con varios códigos o sin 8 dígitos; ","")&IF(AND(ISNUMBER(B21),LEN(B21)=8),IF(MOD(B21,10000)=0,"UNSPSC a nivel de segmento o familia; ",""),"")&IF(NOT(ISNUMBER(E21)),"Duración vacía o en texto; ","")&IF(NOT(ISNUMBER(G21)),"Valor vacío o en texto; ","")&IF(ISNUMBER(M21),IF(M21<1000000,"Valor inferior a $1.000.000: verificar; ",""),"Valor no interpretable; ")&IF(N21="[PENDIENTE DE VERIFICAR]","Modalidad no identificable; ","")&IF(OR(ISERROR(SEARCH("@itc.edu.co",J21)),SUMPRODUCT(--ISNUMBER(SEARCH({"á","é","í","ó","ú","ñ"},J21)))>0),"Correo vacío o no institucional válido; ","")&IF(LEN(TRIM(D21))=0,"Sin objeto contractual; ","")&IF(AND(ISNUMBER(M21),N21="Mínima cuantía"),IF(M21>39850000,"Mínima cuantía con valor superior al tope citado en el instructivo 2026 ($39.850.000): verificar modalidad; ",""),"")&IF(AND(ISNUMBER(M21),OR(ISNUMBER(SEARCH("prestación de servicios",D21)),ISNUMBER(SEARCH("prestar servicios",D21)),ISNUMBER(SEARCH("prestar los servicios",D21)))),IF(M21>=500000000,"Prestación de servicios por $500 millones o más: posible error de digitación; ",""),""))=0,"Sin observaciones",IF(OR(NOT(ISNUMBER(B21)),LEN(B21)<>8),"UNSPSC vacío, en texto, con varios códigos o sin 8 dígitos; ","")&IF(AND(ISNUMBER(B21),LEN(B21)=8),IF(MOD(B21,10000)=0,"UNSPSC a nivel de segmento o familia; ",""),"")&IF(NOT(ISNUMBER(E21)),"Duración vacía o en texto; ","")&IF(NOT(ISNUMBER(G21)),"Valor vacío o en texto; ","")&IF(ISNUMBER(M21),IF(M21<1000000,"Valor inferior a $1.000.000: verificar; ",""),"Valor no interpretable; ")&IF(N21="[PENDIENTE DE VERIFICAR]","Modalidad no identificable; ","")&IF(OR(ISERROR(SEARCH("@itc.edu.co",J21)),SUMPRODUCT(--ISNUMBER(SEARCH({"á","é","í","ó","ú","ñ"},J21)))>0),"Correo vacío o no institucional válido; ","")&IF(LEN(TRIM(D21))=0,"Sin objeto contractual; ","")&IF(AND(ISNUMBER(M21),N21="Mínima cuantía"),IF(M21>39850000,"Mínima cuantía con valor superior al tope citado en el instructivo 2026 ($39.850.000): verificar modalidad; ",""),"")&IF(AND(ISNUMBER(M21),OR(ISNUMBER(SEARCH("prestación de servicios",D21)),ISNUMBER(SEARCH("prestar servicios",D21)),ISNUMBER(SEARCH("prestar los servicios",D21)))),IF(M21>=500000000,"Prestación de servicios por $500 millones o más: posible error de digitación; ",""),"")) -> Sin observaciones
A22: PN26-018 | B22: 80111600 | C22: Conductor mecanico | D22: Prestar los servicios como conductor mecanico con el propósito de transportar personas y materiales a los diversos lugares al interior de la ciudad de bogota, otros municipios y departamentos en cumplimiento de las obligaciones inherentes al desarrollo de las actividades misionales y administrativas, en términos de oportunidad y eficiencia que le permitan a la etitc cumplir su misionalidad | E22: 11 | F22: DIRECTA | H22: Jefe de la oficina asesora de planeacion | J22: planeacion@itc.edu.co | K22: 17 | L22: 101 · Oficina Asesora de Planeación y Desarrollo Institucional | N22: Contratación directa | O22: =IF(LEN(IF(OR(NOT(ISNUMBER(B22)),LEN(B22)<>8),"UNSPSC vacío, en texto, con varios códigos o sin 8 dígitos; ","")&IF(AND(ISNUMBER(B22),LEN(B22)=8),IF(MOD(B22,10000)=0,"UNSPSC a nivel de segmento o familia; ",""),"")&IF(NOT(ISNUMBER(E22)),"Duración vacía o en texto; ","")&IF(NOT(ISNUMBER(G22)),"Valor vacío o en texto; ","")&IF(ISNUMBER(M22),IF(M22<1000000,"Valor inferior a $1.000.000: verificar; ",""),"Valor no interpretable; ")&IF(N22="[PENDIENTE DE VERIFICAR]","Modalidad no identificable; ","")&IF(OR(ISERROR(SEARCH("@itc.edu.co",J22)),SUMPRODUCT(--ISNUMBER(SEARCH({"á","é","í","ó","ú","ñ"},J22)))>0),"Correo vacío o no institucional válido; ","")&IF(LEN(TRIM(D22))=0,"Sin objeto contractual; ","")&IF(AND(ISNUMBER(M22),N22="Mínima cuantía"),IF(M22>39850000,"Mínima cuantía con valor superior al tope citado en el instructivo 2026 ($39.850.000): verificar modalidad; ",""),"")&IF(AND(ISNUMBER(M22),OR(ISNUMBER(SEARCH("prestación de servicios",D22)),ISNUMBER(SEARCH("prestar servicios",D22)),ISNUMBER(SEARCH("prestar los servicios",D22)))),IF(M22>=500000000,"Prestación de servicios por $500 millones o más: posible error de digitación; ",""),""))=0,"Sin observaciones",IF(OR(NOT(ISNUMBER(B22)),LEN(B22)<>8),"UNSPSC vacío, en texto, con varios códigos o sin 8 dígitos; ","")&IF(AND(ISNUMBER(B22),LEN(B22)=8),IF(MOD(B22,10000)=0,"UNSPSC a nivel de segmento o familia; ",""),"")&IF(NOT(ISNUMBER(E22)),"Duración vacía o en texto; ","")&IF(NOT(ISNUMBER(G22)),"Valor vacío o en texto; ","")&IF(ISNUMBER(M22),IF(M22<1000000,"Valor inferior a $1.000.000: verificar; ",""),"Valor no interpretable; ")&IF(N22="[PENDIENTE DE VERIFICAR]","Modalidad no identificable; ","")&IF(OR(ISERROR(SEARCH("@itc.edu.co",J22)),SUMPRODUCT(--ISNUMBER(SEARCH({"á","é","í","ó","ú","ñ"},J22)))>0),"Correo vacío o no institucional válido; ","")&IF(LEN(TRIM(D22))=0,"Sin objeto contractual; ","")&IF(AND(ISNUMBER(M22),N22="Mínima cuantía"),IF(M22>39850000,"Mínima cuantía con valor superior al tope citado en el instructivo 2026 ($39.850.000): verificar modalidad; ",""),"")&IF(AND(ISNUMBER(M22),OR(ISNUMBER(SEARCH("prestación de servicios",D22)),ISNUMBER(SEARCH("prestar servicios",D22)),ISNUMBER(SEARCH("prestar los servicios",D22)))),IF(M22>=500000000,"Prestación de servicios por $500 millones o más: posible error de digitación; ",""),"")) -> Valor vacío o en texto; Valor no interpretable;
A23: PN26-019 | B23: 80111607 | C23: Juridico de apoyo | D23: Prestación de servicios profesionales para apoyar jurídcamente la formulación, ejecución y seguimiento de los proyectos estratégicos y planes misionales de la escuela tecnológica instituto técnico central - etitc, mediante actividades de gestión jurídica, administrativa, coordinación interinstitucional y acompañamiento a la secretaria general, en los distintitos proyectos estratégicos adelantados por la institución que acompaña funcionalmente la secretaría general; así como el apoyo profesional en supervisión de contratos, suplencia de representación judicial y acompañamiento jurídico en actuaciones administrativas y en la gestión administrativa y jurídica para la elaboración de actos administrativos, conceptos jurídicos, entre otros asuntos de la secretaria general. | E23: 11 | F23: DIRECTA | G23: 69600000 | H23: Profesional Especializado de la ORII | K23: 18 | L23: 110 · Secretaría General | M23: 69600000 | N23: Contratación directa | O23: =IF(LEN(IF(OR(NOT(ISNUMBER(B23)),LEN(B23)<>8),"UNSPSC vacío, en texto, con varios códigos o sin 8 dígitos; ","")&IF(AND(ISNUMBER(B23),LEN(B23)=8),IF(MOD(B23,10000)=0,"UNSPSC a nivel de segmento o familia; ",""),"")&IF(NOT(ISNUMBER(E23)),"Duración vacía o en texto; ","")&IF(NOT(ISNUMBER(G23)),"Valor vacío o en texto; ","")&IF(ISNUMBER(M23),IF(M23<1000000,"Valor inferior a $1.000.000: verificar; ",""),"Valor no interpretable; ")&IF(N23="[PENDIENTE DE VERIFICAR]","Modalidad no identificable; ","")&IF(OR(ISERROR(SEARCH("@itc.edu.co",J23)),SUMPRODUCT(--ISNUMBER(SEARCH({"á","é","í","ó","ú","ñ"},J23)))>0),"Correo vacío o no institucional válido; ","")&IF(LEN(TRIM(D23))=0,"Sin objeto contractual; ","")&IF(AND(ISNUMBER(M23),N23="Mínima cuantía"),IF(M23>39850000,"Mínima cuantía con valor superior al tope citado en el instructivo 2026 ($39.850.000): verificar modalidad; ",""),"")&IF(AND(ISNUMBER(M23),OR(ISNUMBER(SEARCH("prestación de servicios",D23)),ISNUMBER(SEARCH("prestar servicios",D23)),ISNUMBER(SEARCH("prestar los servicios",D23)))),IF(M23>=500000000,"Prestación de servicios por $500 millones o más: posible error de digitación; ",""),""))=0,"Sin observaciones",IF(OR(NOT(ISNUMBER(B23)),LEN(B23)<>8),"UNSPSC vacío, en texto, con varios códigos o sin 8 dígitos; ","")&IF(AND(ISNUMBER(B23),LEN(B23)=8),IF(MOD(B23,10000)=0,"UNSPSC a nivel de segmento o familia; ",""),"")&IF(NOT(ISNUMBER(E23)),"Duración vacía o en texto; ","")&IF(NOT(ISNUMBER(G23)),"Valor vacío o en texto; ","")&IF(ISNUMBER(M23),IF(M23<1000000,"Valor inferior a $1.000.000: verificar; ",""),"Valor no interpretable; ")&IF(N23="[PENDIENTE DE VERIFICAR]","Modalidad no identificable; ","")&IF(OR(ISERROR(SEARCH("@itc.edu.co",J23)),SUMPRODUCT(--ISNUMBER(SEARCH({"á","é","í","ó","ú","ñ"},J23)))>0),"Correo vacío o no institucional válido; ","")&IF(LEN(TRIM(D23))=0,"Sin objeto contractual; ","")&IF(AND(ISNUMBER(M23),N23="Mínima cuantía"),IF(M23>39850000,"Mínima cuantía con valor superior al tope citado en el instructivo 2026 ($39.850.000): verificar modalidad; ",""),"")&IF(AND(ISNUMBER(M23),OR(ISNUMBER(SEARCH("prestación de servicios",D23)),ISNUMBER(SEARCH("prestar servicios",D23)),ISNUMBER(SEARCH("prestar los servicios",D23)))),IF(M23>=500000000,"Prestación de servicios por $500 millones o más: posible error de digitación; ",""),"")) -> Correo vacío o no institucional válido;
A24: PN26-020 | B24: 80111607 | C24: Juridico de apoyo | D24: Prestación de servicios profesionales de un abogado con especialización en derecho laboral administrativo para apoyar la gestión institucional de la escuela tecnológica instituto técnico central – etitc, mediante el acompañamiento técnico en la revisión y elaboración de actos administrativos, representación judicial, conceptos y demás documentos jurídicos relacionados con la administración del talento humano, y los procesos administrativos de la entidad, en el marco de la normativa vigente y de los objetivos institucionales orientados al fortalecimiento organizacional y la mejora normativa en el marco del reconocimiento como universidad y transformación como ente autónomo universitario de la entidad. | E24: 11 | F24: DIRECTA | G24: 69600000 | H24: Secretario general grado 0185-07 | K24: 19 | L24: 110 · Secretaría General | M24: 69600000 | N24: Contratación directa | O24: =IF(LEN(IF(OR(NOT(ISNUMBER(B24)),LEN(B24)<>8),"UNSPSC vacío, en texto, con varios códigos o sin 8 dígitos; ","")&IF(AND(ISNUMBER(B24),LEN(B24)=8),IF(MOD(B24,10000)=0,"UNSPSC a nivel de segmento o familia; ",""),"")&IF(NOT(ISNUMBER(E24)),"Duración vacía o en texto; ","")&IF(NOT(ISNUMBER(G24)),"Valor vacío o en texto; ","")&IF(ISNUMBER(M24),IF(M24<1000000,"Valor inferior a $1.000.000: verificar; ",""),"Valor no interpretable; ")&IF(N24="[PENDIENTE DE VERIFICAR]","Modalidad no identificable; ","")&IF(OR(ISERROR(SEARCH("@itc.edu.co",J24)),SUMPRODUCT(--ISNUMBER(SEARCH({"á","é","í","ó","ú","ñ"},J24)))>0),"Correo vacío o no institucional válido; ","")&IF(LEN(TRIM(D24))=0,"Sin objeto contractual; ","")&IF(AND(ISNUMBER(M24),N24="Mínima cuantía"),IF(M24>39850000,"Mínima cuantía con valor superior al tope citado en el instructivo 2026 ($39.850.000): verificar modalidad; ",""),"")&IF(AND(ISNUMBER(M24),OR(ISNUMBER(SEARCH("prestación de servicios",D24)),ISNUMBER(SEARCH("prestar servicios",D24)),ISNUMBER(SEARCH("prestar los servicios",D24)))),IF(M24>=500000000,"Prestación de servicios por $500 millones o más: posible error de digitación; ",""),""))=0,"Sin observaciones",IF(OR(NOT(ISNUMBER(B24)),LEN(B24)<>8),"UNSPSC vacío, en texto, con varios códigos o sin 8 dígitos; ","")&IF(AND(ISNUMBER(B24),LEN(B24)=8),IF(MOD(B24,10000)=0,"UNSPSC a nivel de segmento o familia; ",""),"")&IF(NOT(ISNUMBER(E24)),"Duración vacía o en texto; ","")&IF(NOT(ISNUMBER(G24)),"Valor vacío o en texto; ","")&IF(ISNUMBER(M24),IF(M24<1000000,"Valor inferior a $1.000.000: verificar; ",""),"Valor no interpretable; ")&IF(N24="[PENDIENTE DE VERIFICAR]","Modalidad no identificable; ","")&IF(OR(ISERROR(SEARCH("@itc.edu.co",J24)),SUMPRODUCT(--ISNUMBER(SEARCH({"á","é","í","ó","ú","ñ"},J24)))>0),"Correo vacío o no institucional válido; ","")&IF(LEN(TRIM(D24))=0,"Sin objeto contractual; ","")&IF(AND(ISNUMBER(M24),N24="Mínima cuantía"),IF(M24>39850000,"Mínima cuantía con valor superior al tope citado en el instructivo 2026 ($39.850.000): verificar modalidad; ",""),"")&IF(AND(ISNUMBER(M24),OR(ISNUMBER(SEARCH("prestación de servicios",D24)),ISNUMBER(SEARCH("prestar servicios",D24)),ISNUMBER(SEARCH("prestar los servicios",D24)))),IF(M24>=500000000,"Prestación de servicios por $500 millones o más: posible error de digitación; ",""),"")) -> Correo vacío o no institucional válido;
A25: PN26-021 | B25: 80111600 | C25: Oficina de relaciones interinstitucionales y de internacionalización | D25: Prestacion de servicios profesionales para desarrollar las actividades relacionadas con la movilidad académica y administrativa de la oficina de relaciones interinstitucionales y de internacionalización (orii) de la escuela tecnológica instituto técnico central. | E25: 11 | F25: DIRECTA | G25: 42928650 | H25: Profesional Especializado de la ORII | I25: 3443000 Ext 154 | J25: internacionalizacion@itc.edu.co | K25: 20 | L25: 100 · Rectoría | M25: 42928650 | N25: Contratación directa | O25: =IF(LEN(IF(OR(NOT(ISNUMBER(B25)),LEN(B25)<>8),"UNSPSC vacío, en texto, con varios códigos o sin 8 dígitos; ","")&IF(AND(ISNUMBER(B25),LEN(B25)=8),IF(MOD(B25,10000)=0,"UNSPSC a nivel de segmento o familia; ",""),"")&IF(NOT(ISNUMBER(E25)),"Duración vacía o en texto; ","")&IF(NOT(ISNUMBER(G25)),"Valor vacío o en texto; ","")&IF(ISNUMBER(M25),IF(M25<1000000,"Valor inferior a $1.000.000: verificar; ",""),"Valor no interpretable; ")&IF(N25="[PENDIENTE DE VERIFICAR]","Modalidad no identificable; ","")&IF(OR(ISERROR(SEARCH("@itc.edu.co",J25)),SUMPRODUCT(--ISNUMBER(SEARCH({"á","é","í","ó","ú","ñ"},J25)))>0),"Correo vacío o no institucional válido; ","")&IF(LEN(TRIM(D25))=0,"Sin objeto contractual; ","")&IF(AND(ISNUMBER(M25),N25="Mínima cuantía"),IF(M25>39850000,"Mínima cuantía con valor superior al tope citado en el instructivo 2026 ($39.850.000): verificar modalidad; ",""),"")&IF(AND(ISNUMBER(M25),OR(ISNUMBER(SEARCH("prestación de servicios",D25)),ISNUMBER(SEARCH("prestar servicios",D25)),ISNUMBER(SEARCH("prestar los servicios",D25)))),IF(M25>=500000000,"Prestación de servicios por $500 millones o más: posible error de digitación; ",""),""))=0,"Sin observaciones",IF(OR(NOT(ISNUMBER(B25)),LEN(B25)<>8),"UNSPSC vacío, en texto, con varios códigos o sin 8 dígitos; ","")&IF(AND(ISNUMBER(B25),LEN(B25)=8),IF(MOD(B25,10000)=0,"UNSPSC a nivel de segmento o familia; ",""),"")&IF(NOT(ISNUMBER(E25)),"Duración vacía o en texto; ","")&IF(NOT(ISNUMBER(G25)),"Valor vacío o en texto; ","")&IF(ISNUMBER(M25),IF(M25<1000000,"Valor inferior a $1.000.000: verificar; ",""),"Valor no interpretable; ")&IF(N25="[PENDIENTE DE VERIFICAR]","Modalidad no identificable; ","")&IF(OR(ISERROR(SEARCH("@itc.edu.co",J25)),SUMPRODUCT(--ISNUMBER(SEARCH({"á","é","í","ó","ú","ñ"},J25)))>0),"Correo vacío o no institucional válido; ","")&IF(LEN(TRIM(D25))=0,"Sin objeto contractual; ","")&IF(AND(ISNUMBER(M25),N25="Mínima cuantía"),IF(M25>39850000,"Mínima cuantía con valor superior al tope citado en el instructivo 2026 ($39.850.000): verificar modalidad; ",""),"")&IF(AND(ISNUMBER(M25),OR(ISNUMBER(SEARCH("prestación de servicios",D25)),ISNUMBER(SEARCH("prestar servicios",D25)),ISNUMBER(SEARCH("prestar los servicios",D25)))),IF(M25>=500000000,"Prestación de servicios por $500 millones o más: posible error de digitación; ",""),"")) -> Sin observaciones
A26: PN26-022 | B26: 80111600 | C26: Oficina de relaciones interinstitucionales y de internacionalización | D26: Prestacion de servicios profesionales con autonomía técnica y administrativa para la gestión administrativa, académica y operativa de los convenios nacionales e internacionales que desarrolla la oficina de relaciones interinstitucionales e internacionalización (orii) de la escuela tecnológica instituto técnico central. | E26: 11 | F26: DIRECTA | G26: 42928650 | H26: Profesional Especializado de la ORII | I26: 3443000 Ext 154 | J26: internacionalizacion@itc.edu.co | K26: 21 | L26: 100 · Rectoría | M26: 42928650 | N26: Contratación directa | O26: =IF(LEN(IF(OR(NOT(ISNUMBER(B26)),LEN(B26)<>8),"UNSPSC vacío, en texto, con varios códigos o sin 8 dígitos; ","")&IF(AND(ISNUMBER(B26),LEN(B26)=8),IF(MOD(B26,10000)=0,"UNSPSC a nivel de segmento o familia; ",""),"")&IF(NOT(ISNUMBER(E26)),"Duración vacía o en texto; ","")&IF(NOT(ISNUMBER(G26)),"Valor vacío o en texto; ","")&IF(ISNUMBER(M26),IF(M26<1000000,"Valor inferior a $1.000.000: verificar; ",""),"Valor no interpretable; ")&IF(N26="[PENDIENTE DE VERIFICAR]","Modalidad no identificable; ","")&IF(OR(ISERROR(SEARCH("@itc.edu.co",J26)),SUMPRODUCT(--ISNUMBER(SEARCH({"á","é","í","ó","ú","ñ"},J26)))>0),"Correo vacío o no institucional válido; ","")&IF(LEN(TRIM(D26))=0,"Sin objeto contractual; ","")&IF(AND(ISNUMBER(M26),N26="Mínima cuantía"),IF(M26>39850000,"Mínima cuantía con valor superior al tope citado en el instructivo 2026 ($39.850.000): verificar modalidad; ",""),"")&IF(AND(ISNUMBER(M26),OR(ISNUMBER(SEARCH("prestación de servicios",D26)),ISNUMBER(SEARCH("prestar servicios",D26)),ISNUMBER(SEARCH("prestar los servicios",D26)))),IF(M26>=500000000,"Prestación de servicios por $500 millones o más: posible error de digitación; ",""),""))=0,"Sin observaciones",IF(OR(NOT(ISNUMBER(B26)),LEN(B26)<>8),"UNSPSC vacío, en texto, con varios códigos o sin 8 dígitos; ","")&IF(AND(ISNUMBER(B26),LEN(B26)=8),IF(MOD(B26,10000)=0,"UNSPSC a nivel de segmento o familia; ",""),"")&IF(NOT(ISNUMBER(E26)),"Duración vacía o en texto; ","")&IF(NOT(ISNUMBER(G26)),"Valor vacío o en texto; ","")&IF(ISNUMBER(M26),IF(M26<1000000,"Valor inferior a $1.000.000: verificar; ",""),"Valor no interpretable; ")&IF(N26="[PENDIENTE DE VERIFICAR]","Modalidad no identificable; ","")&IF(OR(ISERROR(SEARCH("@itc.edu.co",J26)),SUMPRODUCT(--ISNUMBER(SEARCH({"á","é","í","ó","ú","ñ"},J26)))>0),"Correo vacío o no institucional válido; ","")&IF(LEN(TRIM(D26))=0,"Sin objeto contractual; ","")&IF(AND(ISNUMBER(M26),N26="Mínima cuantía"),IF(M26>39850000,"Mínima cuantía con valor superior al tope citado en el instructivo 2026 ($39.850.000): verificar modalidad; ",""),"")&IF(AND(ISNUMBER(M26),OR(ISNUMBER(SEARCH("prestación de servicios",D26)),ISNUMBER(SEARCH("prestar servicios",D26)),ISNUMBER(SEARCH("prestar los servicios",D26)))),IF(M26>=500000000,"Prestación de servicios por $500 millones o más: posible error de digitación; ",""),"")) -> Sin observaciones
A27: PN26-023 | B27: 80111600 | C27: Oficina de relaciones interinstitucionales y de internacionalización | D27: Prestación de servicios técnicos y tecnológicos para la gestión administrativa, operativa y de marketing relacionada con la internacionalización, y atención integral a estudiantes, docentes y administrativos en la oficina de relaciones interinstitucionales e internacionalización (orii) de la escuela tecnológica instituto técnico central. | E27: 5 | F27: DIRECTA | G27: 27514657 | H27: Profesional Especializado de la ORII | I27: 3443000 Ext 154 | J27: internacionalizacion@itc.edu.co | K27: 22 | L27: 100 · Rectoría | M27: 27514657 | N27: Contratación directa | O27: =IF(LEN(IF(OR(NOT(ISNUMBER(B27)),LEN(B27)<>8),"UNSPSC vacío, en texto, con varios códigos o sin 8 dígitos; ","")&IF(AND(ISNUMBER(B27),LEN(B27)=8),IF(MOD(B27,10000)=0,"UNSPSC a nivel de segmento o familia; ",""),"")&IF(NOT(ISNUMBER(E27)),"Duración vacía o en texto; ","")&IF(NOT(ISNUMBER(G27)),"Valor vacío o en texto; ","")&IF(ISNUMBER(M27),IF(M27<1000000,"Valor inferior a $1.000.000: verificar; ",""),"Valor no interpretable; ")&IF(N27="[PENDIENTE DE VERIFICAR]","Modalidad no identificable; ","")&IF(OR(ISERROR(SEARCH("@itc.edu.co",J27)),SUMPRODUCT(--ISNUMBER(SEARCH({"á","é","í","ó","ú","ñ"},J27)))>0),"Correo vacío o no institucional válido; ","")&IF(LEN(TRIM(D27))=0,"Sin objeto contractual; ","")&IF(AND(ISNUMBER(M27),N27="Mínima cuantía"),IF(M27>39850000,"Mínima cuantía con valor superior al tope citado en el instructivo 2026 ($39.850.000): verificar modalidad; ",""),"")&IF(AND(ISNUMBER(M27),OR(ISNUMBER(SEARCH("prestación de servicios",D27)),ISNUMBER(SEARCH("prestar servicios",D27)),ISNUMBER(SEARCH("prestar los servicios",D27)))),IF(M27>=500000000,"Prestación de servicios por $500 millones o más: posible error de digitación; ",""),""))=0,"Sin observaciones",IF(OR(NOT(ISNUMBER(B27)),LEN(B27)<>8),"UNSPSC vacío, en texto, con varios códigos o sin 8 dígitos; ","")&IF(AND(ISNUMBER(B27),LEN(B27)=8),IF(MOD(B27,10000)=0,"UNSPSC a nivel de segmento o familia; ",""),"")&IF(NOT(ISNUMBER(E27)),"Duración vacía o en texto; ","")&IF(NOT(ISNUMBER(G27)),"Valor vacío o en texto; ","")&IF(ISNUMBER(M27),IF(M27<1000000,"Valor inferior a $1.000.000: verificar; ",""),"Valor no interpretable; ")&IF(N27="[PENDIENTE DE VERIFICAR]","Modalidad no identificable; ","")&IF(OR(ISERROR(SEARCH("@itc.edu.co",J27)),SUMPRODUCT(--ISNUMBER(SEARCH({"á","é","í","ó","ú","ñ"},J27)))>0),"Correo vacío o no institucional válido; ","")&IF(LEN(TRIM(D27))=0,"Sin objeto contractual; ","")&IF(AND(ISNUMBER(M27),N27="Mínima cuantía"),IF(M27>39850000,"Mínima cuantía con valor superior al tope citado en el instructivo 2026 ($39.850.000): verificar modalidad; ",""),"")&IF(AND(ISNUMBER(M27),OR(ISNUMBER(SEARCH("prestación de servicios",D27)),ISNUMBER(SEARCH("prestar servicios",D27)),ISNUMBER(SEARCH("prestar los servicios",D27)))),IF(M27>=500000000,"Prestación de servicios por $500 millones o más: posible error de digitación; ",""),"")) -> Sin observaciones
A28: PN26-024 | B28: 80111600 | C28: Oficina de Comunicaciones - Multimedia | D28: Prestación de servicios profesionales para apoyar al área de comunicaciones en el desarrollo proyectos estratégicos de comunicación visual de la escuela tecnológica instituto técnico central | E28: 11 | F28: DIRECTA | G28: 37827272 | H28: Jefe de la oficina asesora de planeacion | J28: planeacion@itc.edu.co | K28: 23 | L28: 101 · Oficina Asesora de Planeación y Desarrollo Institucional | M28: 37827272 | N28: Contratación directa | O28: =IF(LEN(IF(OR(NOT(ISNUMBER(B28)),LEN(B28)<>8),"UNSPSC vacío, en texto, con varios códigos o sin 8 dígitos; ","")&IF(AND(ISNUMBER(B28),LEN(B28)=8),IF(MOD(B28,10000)=0,"UNSPSC a nivel de segmento o familia; ",""),"")&IF(NOT(ISNUMBER(E28)),"Duración vacía o en texto; ","")&IF(NOT(ISNUMBER(G28)),"Valor vacío o en texto; ","")&IF(ISNUMBER(M28),IF(M28<1000000,"Valor inferior a $1.000.000: verificar; ",""),"Valor no interpretable; ")&IF(N28="[PENDIENTE DE VERIFICAR]","Modalidad no identificable; ","")&IF(OR(ISERROR(SEARCH("@itc.edu.co",J28)),SUMPRODUCT(--ISNUMBER(SEARCH({"á","é","í","ó","ú","ñ"},J28)))>0),"Correo vacío o no institucional válido; ","")&IF(LEN(TRIM(D28))=0,"Sin objeto contractual; ","")&IF(AND(ISNUMBER(M28),N28="Mínima cuantía"),IF(M28>39850000,"Mínima cuantía con valor superior al tope citado en el instructivo 2026 ($39.850.000): verificar modalidad; ",""),"")&IF(AND(ISNUMBER(M28),OR(ISNUMBER(SEARCH("prestación de servicios",D28)),ISNUMBER(SEARCH("prestar servicios",D28)),ISNUMBER(SEARCH("prestar los servicios",D28)))),IF(M28>=500000000,"Prestación de servicios por $500 millones o más: posible error de digitación; ",""),""))=0,"Sin observaciones",IF(OR(NOT(ISNUMBER(B28)),LEN(B28)<>8),"UNSPSC vacío, en texto, con varios códigos o sin 8 dígitos; ","")&IF(AND(ISNUMBER(B28),LEN(B28)=8),IF(MOD(B28,10000)=0,"UNSPSC a nivel de segmento o familia; ",""),"")&IF(NOT(ISNUMBER(E28)),"Duración vacía o en texto; ","")&IF(NOT(ISNUMBER(G28)),"Valor vacío o en texto; ","")&IF(ISNUMBER(M28),IF(M28<1000000,"Valor inferior a $1.000.000: verificar; ",""),"Valor no interpretable; ")&IF(N28="[PENDIENTE DE VERIFICAR]","Modalidad no identificable; ","")&IF(OR(ISERROR(SEARCH("@itc.edu.co",J28)),SUMPRODUCT(--ISNUMBER(SEARCH({"á","é","í","ó","ú","ñ"},J28)))>0),"Correo vacío o no institucional válido; ","")&IF(LEN(TRIM(D28))=0,"Sin objeto contractual; ","")&IF(AND(ISNUMBER(M28),N28="Mínima cuantía"),IF(M28>39850000,"Mínima cuantía con valor superior al tope citado en el instructivo 2026 ($39.850.000): verificar modalidad; ",""),"")&IF(AND(ISNUMBER(M28),OR(ISNUMBER(SEARCH("prestación de servicios",D28)),ISNUMBER(SEARCH("prestar servicios",D28)),ISNUMBER(SEARCH("prestar los servicios",D28)))),IF(M28>=500000000,"Prestación de servicios por $500 millones o más: posible error de digitación; ",""),"")) -> Sin observaciones
A29: PN26-025 | B29: 80111600 | C29: Oficina de Comunicaciones - Comunicadora | D29: Prestación de servicios profesionales en comunicación social para el desarrollo de estrategias de comunicación institucional, generación de contenidos, manejo de prensa y apoyo a los procesos de divulgación de la de la escuela tecnológica instituto técnico central | E29: 11 | F29: DIRECTA | G29: 44405902 | H29: Jefe de la oficina asesora de planeacion | J29: planeacion@itc.edu.co | K29: 24 | L29: 101 · Oficina Asesora de Planeación y Desarrollo Institucional | M29: 44405902 | N29: Contratación directa | O29: =IF(LEN(IF(OR(NOT(ISNUMBER(B29)),LEN(B29)<>8),"UNSPSC vacío, en texto, con varios códigos o sin 8 dígitos; ","")&IF(AND(ISNUMBER(B29),LEN(B29)=8),IF(MOD(B29,10000)=0,"UNSPSC a nivel de segmento o familia; ",""),"")&IF(NOT(ISNUMBER(E29)),"Duración vacía o en texto; ","")&IF(NOT(ISNUMBER(G29)),"Valor vacío o en texto; ","")&IF(ISNUMBER(M29),IF(M29<1000000,"Valor inferior a $1.000.000: verificar; ",""),"Valor no interpretable; ")&IF(N29="[PENDIENTE DE VERIFICAR]","Modalidad no identificable; ","")&IF(OR(ISERROR(SEARCH("@itc.edu.co",J29)),SUMPRODUCT(--ISNUMBER(SEARCH({"á","é","í","ó","ú","ñ"},J29)))>0),"Correo vacío o no institucional válido; ","")&IF(LEN(TRIM(D29))=0,"Sin objeto contractual; ","")&IF(AND(ISNUMBER(M29),N29="Mínima cuantía"),IF(M29>39850000,"Mínima cuantía con valor superior al tope citado en el instructivo 2026 ($39.850.000): verificar modalidad; ",""),"")&IF(AND(ISNUMBER(M29),OR(ISNUMBER(SEARCH("prestación de servicios",D29)),ISNUMBER(SEARCH("prestar servicios",D29)),ISNUMBER(SEARCH("prestar los servicios",D29)))),IF(M29>=500000000,"Prestación de servicios por $500 millones o más: posible error de digitación; ",""),""))=0,"Sin observaciones",IF(OR(NOT(ISNUMBER(B29)),LEN(B29)<>8),"UNSPSC vacío, en texto, con varios códigos o sin 8 dígitos; ","")&IF(AND(ISNUMBER(B29),LEN(B29)=8),IF(MOD(B29,10000)=0,"UNSPSC a nivel de segmento o familia; ",""),"")&IF(NOT(ISNUMBER(E29)),"Duración vacía o en texto; ","")&IF(NOT(ISNUMBER(G29)),"Valor vacío o en texto; ","")&IF(ISNUMBER(M29),IF(M29<1000000,"Valor inferior a $1.000.000: verificar; ",""),"Valor no interpretable; ")&IF(N29="[PENDIENTE DE VERIFICAR]","Modalidad no identificable; ","")&IF(OR(ISERROR(SEARCH("@itc.edu.co",J29)),SUMPRODUCT(--ISNUMBER(SEARCH({"á","é","í","ó","ú","ñ"},J29)))>0),"Correo vacío o no institucional válido; ","")&IF(LEN(TRIM(D29))=0,"Sin objeto contractual; ","")&IF(AND(ISNUMBER(M29),N29="Mínima cuantía"),IF(M29>39850000,"Mínima cuantía con valor superior al tope citado en el instructivo 2026 ($39.850.000): verificar modalidad; ",""),"")&IF(AND(ISNUMBER(M29),OR(ISNUMBER(SEARCH("prestación de servicios",D29)),ISNUMBER(SEARCH("prestar servicios",D29)),ISNUMBER(SEARCH("prestar los servicios",D29)))),IF(M29>=500000000,"Prestación de servicios por $500 millones o más: posible error de digitación; ",""),"")) -> Sin observaciones
A30: PN26-026 | B30: 80111600 | C30: Oficina de Comunicaciones - Periodista | D30: Prestación de servicios profesionales como periodista de la emisora institucional emtic, para fortalecer los medios educativos que aportan al proceso formativo de la comunidad académica ​de la escuela tecnológica instituto técnico central | E30: 11 | F30: DIRECTA | G30: 44405902 | H30: Jefe de la oficina asesora de planeacion | J30: planeacion@itc.edu.co | K30: 25 | L30: 101 · Oficina Asesora de Planeación y Desarrollo Institucional | M30: 44405902 | N30: Contratación directa | O30: =IF(LEN(IF(OR(NOT(ISNUMBER(B30)),LEN(B30)<>8),"UNSPSC vacío, en texto, con varios códigos o sin 8 dígitos; ","")&IF(AND(ISNUMBER(B30),LEN(B30)=8),IF(MOD(B30,10000)=0,"UNSPSC a nivel de segmento o familia; ",""),"")&IF(NOT(ISNUMBER(E30)),"Duración vacía o en texto; ","")&IF(NOT(ISNUMBER(G30)),"Valor vacío o en texto; ","")&IF(ISNUMBER(M30),IF(M30<1000000,"Valor inferior a $1.000.000: verificar; ",""),"Valor no interpretable; ")&IF(N30="[PENDIENTE DE VERIFICAR]","Modalidad no identificable; ","")&IF(OR(ISERROR(SEARCH("@itc.edu.co",J30)),SUMPRODUCT(--ISNUMBER(SEARCH({"á","é","í","ó","ú","ñ"},J30)))>0),"Correo vacío o no institucional válido; ","")&IF(LEN(TRIM(D30))=0,"Sin objeto contractual; ","")&IF(AND(ISNUMBER(M30),N30="Mínima cuantía"),IF(M30>39850000,"Mínima cuantía con valor superior al tope citado en el instructivo 2026 ($39.850.000): verificar modalidad; ",""),"")&IF(AND(ISNUMBER(M30),OR(ISNUMBER(SEARCH("prestación de servicios",D30)),ISNUMBER(SEARCH("prestar servicios",D30)),ISNUMBER(SEARCH("prestar los servicios",D30)))),IF(M30>=500000000,"Prestación de servicios por $500 millones o más: posible error de digitación; ",""),""))=0,"Sin observaciones",IF(OR(NOT(ISNUMBER(B30)),LEN(B30)<>8),"UNSPSC vacío, en texto, con varios códigos o sin 8 dígitos; ","")&IF(AND(ISNUMBER(B30),LEN(B30)=8),IF(MOD(B30,10000)=0,"UNSPSC a nivel de segmento o familia; ",""),"")&IF(NOT(ISNUMBER(E30)),"Duración vacía o en texto; ","")&IF(NOT(ISNUMBER(G30)),"Valor vacío o en texto; ","")&IF(ISNUMBER(M30),IF(M30<1000000,"Valor inferior a $1.000.000: verificar; ",""),"Valor no interpretable; ")&IF(N30="[PENDIENTE DE VERIFICAR]","Modalidad no identificable; ","")&IF(OR(ISERROR(SEARCH("@itc.edu.co",J30)),SUMPRODUCT(--ISNUMBER(SEARCH({"á","é","í","ó","ú","ñ"},J30)))>0),"Correo vacío o no institucional válido; ","")&IF(LEN(TRIM(D30))=0,"Sin objeto contractual; ","")&IF(AND(ISNUMBER(M30),N30="Mínima cuantía"),IF(M30>39850000,"Mínima cuantía con valor superior al tope citado en el instructivo 2026 ($39.850.000): verificar modalidad; ",""),"")&IF(AND(ISNUMBER(M30),OR(ISNUMBER(SEARCH("prestación de servicios",D30)),ISNUMBER(SEARCH("prestar servicios",D30)),ISNUMBER(SEARCH("prestar los servicios",D30)))),IF(M30>=500000000,"Prestación de servicios por $500 millones o más: posible error de digitación; ",""),"")) -> Sin observaciones
A31: PN26-027 | B31: 80111600 | C31: Oficina de Comunicaciones - Fotografía y video | D31: Prestación de servicios profesionales para la realización y producción de contenido audiovisual y multimedia con el fin de promover los objetivos estrategicos y lograr un impacto positivo en la audiencia de la escuela tecnológica instituto técnico central | E31: 11 | F31: DIRECTA | G31: 41527766 | H31: Jefe de la oficina asesora de planeacion | J31: planeacion@itc.edu.co | K31: 26 | L31: 101 · Oficina Asesora de Planeación y Desarrollo Institucional | M31: 41527766 | N31: Contratación directa | O31: =IF(LEN(IF(OR(NOT(ISNUMBER(B31)),LEN(B31)<>8),"UNSPSC vacío, en texto, con varios códigos o sin 8 dígitos; ","")&IF(AND(ISNUMBER(B31),LEN(B31)=8),IF(MOD(B31,10000)=0,"UNSPSC a nivel de segmento o familia; ",""),"")&IF(NOT(ISNUMBER(E31)),"Duración vacía o en texto; ","")&IF(NOT(ISNUMBER(G31)),"Valor vacío o en texto; ","")&IF(ISNUMBER(M31),IF(M31<1000000,"Valor inferior a $1.000.000: verificar; ",""),"Valor no interpretable; ")&IF(N31="[PENDIENTE DE VERIFICAR]","Modalidad no identificable; ","")&IF(OR(ISERROR(SEARCH("@itc.edu.co",J31)),SUMPRODUCT(--ISNUMBER(SEARCH({"á","é","í","ó","ú","ñ"},J31)))>0),"Correo vacío o no institucional válido; ","")&IF(LEN(TRIM(D31))=0,"Sin objeto contractual; ","")&IF(AND(ISNUMBER(M31),N31="Mínima cuantía"),IF(M31>39850000,"Mínima cuantía con valor superior al tope citado en el instructivo 2026 ($39.850.000): verificar modalidad; ",""),"")&IF(AND(ISNUMBER(M31),OR(ISNUMBER(SEARCH("prestación de servicios",D31)),ISNUMBER(SEARCH("prestar servicios",D31)),ISNUMBER(SEARCH("prestar los servicios",D31)))),IF(M31>=500000000,"Prestación de servicios por $500 millones o más: posible error de digitación; ",""),""))=0,"Sin observaciones",IF(OR(NOT(ISNUMBER(B31)),LEN(B31)<>8),"UNSPSC vacío, en texto, con varios códigos o sin 8 dígitos; ","")&IF(AND(ISNUMBER(B31),LEN(B31)=8),IF(MOD(B31,10000)=0,"UNSPSC a nivel de segmento o familia; ",""),"")&IF(NOT(ISNUMBER(E31)),"Duración vacía o en texto; ","")&IF(NOT(ISNUMBER(G31)),"Valor vacío o en texto; ","")&IF(ISNUMBER(M31),IF(M31<1000000,"Valor inferior a $1.000.000: verificar; ",""),"Valor no interpretable; ")&IF(N31="[PENDIENTE DE VERIFICAR]","Modalidad no identificable; ","")&IF(OR(ISERROR(SEARCH("@itc.edu.co",J31)),SUMPRODUCT(--ISNUMBER(SEARCH({"á","é","í","ó","ú","ñ"},J31)))>0),"Correo vacío o no institucional válido; ","")&IF(LEN(TRIM(D31))=0,"Sin objeto contractual; ","")&IF(AND(ISNUMBER(M31),N31="Mínima cuantía"),IF(M31>39850000,"Mínima cuantía con valor superior al tope citado en el instructivo 2026 ($39.850.000): verificar modalidad; ",""),"")&IF(AND(ISNUMBER(M31),OR(ISNUMBER(SEARCH("prestación de servicios",D31)),ISNUMBER(SEARCH("prestar servicios",D31)),ISNUMBER(SEARCH("prestar los servicios",D31)))),IF(M31>=500000000,"Prestación de servicios por $500 millones o más: posible error de digitación; ",""),"")) -> Sin observaciones
A32: PN26-028 | B32: 80111600 | C32: Oficina de Comunicaciones - Presentación emisora | D32: Prestación de servicios como apoyo a la gestión para la operación de la emisora web, la rectoría y el área de comunicaciones de la escuela tecnológica instituto técnico central | E32: 11 | F32: DIRECTA | G32: 31103320 | H32: Jefe de la oficina asesora de planeacion | J32: planeacion@itc.edu.co | K32: 27 | L32: 101 · Oficina Asesora de Planeación y Desarrollo Institucional | M32: 31103320 | N32: Contratación directa | O32: =IF(LEN(IF(OR(NOT(ISNUMBER(B32)),LEN(B32)<>8),"UNSPSC vacío, en texto, con varios códigos o sin 8 dígitos; ","")&IF(AND(ISNUMBER(B32),LEN(B32)=8),IF(MOD(B32,10000)=0,"UNSPSC a nivel de segmento o familia; ",""),"")&IF(NOT(ISNUMBER(E32)),"Duración vacía o en texto; ","")&IF(NOT(ISNUMBER(G32)),"Valor vacío o en texto; ","")&IF(ISNUMBER(M32),IF(M32<1000000,"Valor inferior a $1.000.000: verificar; ",""),"Valor no interpretable; ")&IF(N32="[PENDIENTE DE VERIFICAR]","Modalidad no identificable; ","")&IF(OR(ISERROR(SEARCH("@itc.edu.co",J32)),SUMPRODUCT(--ISNUMBER(SEARCH({"á","é","í","ó","ú","ñ"},J32)))>0),"Correo vacío o no institucional válido; ","")&IF(LEN(TRIM(D32))=0,"Sin objeto contractual; ","")&IF(AND(ISNUMBER(M32),N32="Mínima cuantía"),IF(M32>39850000,"Mínima cuantía con valor superior al tope citado en el instructivo 2026 ($39.850.000): verificar modalidad; ",""),"")&IF(AND(ISNUMBER(M32),OR(ISNUMBER(SEARCH("prestación de servicios",D32)),ISNUMBER(SEARCH("prestar servicios",D32)),ISNUMBER(SEARCH("prestar los servicios",D32)))),IF(M32>=500000000,"Prestación de servicios por $500 millones o más: posible error de digitación; ",""),""))=0,"Sin observaciones",IF(OR(NOT(ISNUMBER(B32)),LEN(B32)<>8),"UNSPSC vacío, en texto, con varios códigos o sin 8 dígitos; ","")&IF(AND(ISNUMBER(B32),LEN(B32)=8),IF(MOD(B32,10000)=0,"UNSPSC a nivel de segmento o familia; ",""),"")&IF(NOT(ISNUMBER(E32)),"Duración vacía o en texto; ","")&IF(NOT(ISNUMBER(G32)),"Valor vacío o en texto; ","")&IF(ISNUMBER(M32),IF(M32<1000000,"Valor inferior a $1.000.000: verificar; ",""),"Valor no interpretable; ")&IF(N32="[PENDIENTE DE VERIFICAR]","Modalidad no identificable; ","")&IF(OR(ISERROR(SEARCH("@itc.edu.co",J32)),SUMPRODUCT(--ISNUMBER(SEARCH({"á","é","í","ó","ú","ñ"},J32)))>0),"Correo vacío o no institucional válido; ","")&IF(LEN(TRIM(D32))=0,"Sin objeto contractual; ","")&IF(AND(ISNUMBER(M32),N32="Mínima cuantía"),IF(M32>39850000,"Mínima cuantía con valor superior al tope citado en el instructivo 2026 ($39.850.000): verificar modalidad; ",""),"")&IF(AND(ISNUMBER(M32),OR(ISNUMBER(SEARCH("prestación de servicios",D32)),ISNUMBER(SEARCH("prestar servicios",D32)),ISNUMBER(SEARCH("prestar los servicios",D32)))),IF(M32>=500000000,"Prestación de servicios por $500 millones o más: posible error de digitación; ",""),"")) -> Sin observaciones
A33: PN26-029 | B33: 80111600 | C33: Oficina de Comunicaciones - Mercadeo y admisiones | D33: Prestación de servicios profesionales para el diseño y ejecución de estrategias de promoción académica y posicionamiento de la oferta institucional de la escuela tecnológica instituto técnico central | E33: 11 | F33: DIRECTA | H33: Jefe de la oficina asesora de planeacion | J33: planeacion@itc.edu.co | K33: 28 | L33: 101 · Oficina Asesora de Planeación y Desarrollo Institucional | N33: Contratación directa | O33: =IF(LEN(IF(OR(NOT(ISNUMBER(B33)),LEN(B33)<>8),"UNSPSC vacío, en texto, con varios códigos o sin 8 dígitos; ","")&IF(AND(ISNUMBER(B33),LEN(B33)=8),IF(MOD(B33,10000)=0,"UNSPSC a nivel de segmento o familia; ",""),"")&IF(NOT(ISNUMBER(E33)),"Duración vacía o en texto; ","")&IF(NOT(ISNUMBER(G33)),"Valor vacío o en texto; ","")&IF(ISNUMBER(M33),IF(M33<1000000,"Valor inferior a $1.000.000: verificar; ",""),"Valor no interpretable; ")&IF(N33="[PENDIENTE DE VERIFICAR]","Modalidad no identificable; ","")&IF(OR(ISERROR(SEARCH("@itc.edu.co",J33)),SUMPRODUCT(--ISNUMBER(SEARCH({"á","é","í","ó","ú","ñ"},J33)))>0),"Correo vacío o no institucional válido; ","")&IF(LEN(TRIM(D33))=0,"Sin objeto contractual; ","")&IF(AND(ISNUMBER(M33),N33="Mínima cuantía"),IF(M33>39850000,"Mínima cuantía con valor superior al tope citado en el instructivo 2026 ($39.850.000): verificar modalidad; ",""),"")&IF(AND(ISNUMBER(M33),OR(ISNUMBER(SEARCH("prestación de servicios",D33)),ISNUMBER(SEARCH("prestar servicios",D33)),ISNUMBER(SEARCH("prestar los servicios",D33)))),IF(M33>=500000000,"Prestación de servicios por $500 millones o más: posible error de digitación; ",""),""))=0,"Sin observaciones",IF(OR(NOT(ISNUMBER(B33)),LEN(B33)<>8),"UNSPSC vacío, en texto, con varios códigos o sin 8 dígitos; ","")&IF(AND(ISNUMBER(B33),LEN(B33)=8),IF(MOD(B33,10000)=0,"UNSPSC a nivel de segmento o familia; ",""),"")&IF(NOT(ISNUMBER(E33)),"Duración vacía o en texto; ","")&IF(NOT(ISNUMBER(G33)),"Valor vacío o en texto; ","")&IF(ISNUMBER(M33),IF(M33<1000000,"Valor inferior a $1.000.000: verificar; ",""),"Valor no interpretable; ")&IF(N33="[PENDIENTE DE VERIFICAR]","Modalidad no identificable; ","")&IF(OR(ISERROR(SEARCH("@itc.edu.co",J33)),SUMPRODUCT(--ISNUMBER(SEARCH({"á","é","í","ó","ú","ñ"},J33)))>0),"Correo vacío o no institucional válido; ","")&IF(LEN(TRIM(D33))=0,"Sin objeto contractual; ","")&IF(AND(ISNUMBER(M33),N33="Mínima cuantía"),IF(M33>39850000,"Mínima cuantía con valor superior al tope citado en el instructivo 2026 ($39.850.000): verificar modalidad; ",""),"")&IF(AND(ISNUMBER(M33),OR(ISNUMBER(SEARCH("prestación de servicios",D33)),ISNUMBER(SEARCH("prestar servicios",D33)),ISNUMBER(SEARCH("prestar los servicios",D33)))),IF(M33>=500000000,"Prestación de servicios por $500 millones o más: posible error de digitación; ",""),"")) -> Valor vacío o en texto; Valor no interpretable;
A34: PN26-030 | B34: 80111600 | C34: Oficina de Comunicaciones - Redes sociales | D34: Prestación de servicios profesionales para administrar los contenidos de los medios digitales (portal web, redes sociales, carteleras digitales, carnetización digital) y coordinar la emisora web de la escuela tecnológica instituto técnico central | E34: 11 | F34: DIRECTA | G34: 54209616 | H34: Jefe de la oficina asesora de planeacion | J34: planeacion@itc.edu.co | K34: 29 | L34: 101 · Oficina Asesora de Planeación y Desarrollo Institucional | M34: 54209616 | N34: Contratación directa | O34: =IF(LEN(IF(OR(NOT(ISNUMBER(B34)),LEN(B34)<>8),"UNSPSC vacío, en texto, con varios códigos o sin 8 dígitos; ","")&IF(AND(ISNUMBER(B34),LEN(B34)=8),IF(MOD(B34,10000)=0,"UNSPSC a nivel de segmento o familia; ",""),"")&IF(NOT(ISNUMBER(E34)),"Duración vacía o en texto; ","")&IF(NOT(ISNUMBER(G34)),"Valor vacío o en texto; ","")&IF(ISNUMBER(M34),IF(M34<1000000,"Valor inferior a $1.000.000: verificar; ",""),"Valor no interpretable; ")&IF(N34="[PENDIENTE DE VERIFICAR]","Modalidad no identificable; ","")&IF(OR(ISERROR(SEARCH("@itc.edu.co",J34)),SUMPRODUCT(--ISNUMBER(SEARCH({"á","é","í","ó","ú","ñ"},J34)))>0),"Correo vacío o no institucional válido; ","")&IF(LEN(TRIM(D34))=0,"Sin objeto contractual; ","")&IF(AND(ISNUMBER(M34),N34="Mínima cuantía"),IF(M34>39850000,"Mínima cuantía con valor superior al tope citado en el instructivo 2026 ($39.850.000): verificar modalidad; ",""),"")&IF(AND(ISNUMBER(M34),OR(ISNUMBER(SEARCH("prestación de servicios",D34)),ISNUMBER(SEARCH("prestar servicios",D34)),ISNUMBER(SEARCH("prestar los servicios",D34)))),IF(M34>=500000000,"Prestación de servicios por $500 millones o más: posible error de digitación; ",""),""))=0,"Sin observaciones",IF(OR(NOT(ISNUMBER(B34)),LEN(B34)<>8),"UNSPSC vacío, en texto, con varios códigos o sin 8 dígitos; ","")&IF(AND(ISNUMBER(B34),LEN(B34)=8),IF(MOD(B34,10000)=0,"UNSPSC a nivel de segmento o familia; ",""),"")&IF(NOT(ISNUMBER(E34)),"Duración vacía o en texto; ","")&IF(NOT(ISNUMBER(G34)),"Valor vacío o en texto; ","")&IF(ISNUMBER(M34),IF(M34<1000000,"Valor inferior a $1.000.000: verificar; ",""),"Valor no interpretable; ")&IF(N34="[PENDIENTE DE VERIFICAR]","Modalidad no identificable; ","")&IF(OR(ISERROR(SEARCH("@itc.edu.co",J34)),SUMPRODUCT(--ISNUMBER(SEARCH({"á","é","í","ó","ú","ñ"},J34)))>0),"Correo vacío o no institucional válido; ","")&IF(LEN(TRIM(D34))=0,"Sin objeto contractual; ","")&IF(AND(ISNUMBER(M34),N34="Mínima cuantía"),IF(M34>39850000,"Mínima cuantía con valor superior al tope citado en el instructivo 2026 ($39.850.000): verificar modalidad; ",""),"")&IF(AND(ISNUMBER(M34),OR(ISNUMBER(SEARCH("prestación de servicios",D34)),ISNUMBER(SEARCH("prestar servicios",D34)),ISNUMBER(SEARCH("prestar los servicios",D34)))),IF(M34>=500000000,"Prestación de servicios por $500 millones o más: posible error de digitación; ",""),"")) -> Sin observaciones
A35: PN26-031 | B35: 80111600 | C35: Oficina de Comunicaciones - Lider Comunicaciones | D35: Prestación de servicios profesionales para la planeación, dirección y seguimiento estratégico de las acciones de comunicación institucional, garantizando la articulación entre las áreas, la ejecución del plan estratégico de comunicación y el posicionamiento de la escuela tecnológica instituto técnico central | E35: 11 | F35: DIRECTA | G35: 54209616 | H35: Jefe de la oficina asesora de planeacion | J35: planeacion@itc.edu.co | K35: 30 | L35: 101 · Oficina Asesora de Planeación y Desarrollo Institucional | M35: 54209616 | N35: Contratación directa | O35: =IF(LEN(IF(OR(NOT(ISNUMBER(B35)),LEN(B35)<>8),"UNSPSC vacío, en texto, con varios códigos o sin 8 dígitos; ","")&IF(AND(ISNUMBER(B35),LEN(B35)=8),IF(MOD(B35,10000)=0,"UNSPSC a nivel de segmento o familia; ",""),"")&IF(NOT(ISNUMBER(E35)),"Duración vacía o en texto; ","")&IF(NOT(ISNUMBER(G35)),"Valor vacío o en texto; ","")&IF(ISNUMBER(M35),IF(M35<1000000,"Valor inferior a $1.000.000: verificar; ",""),"Valor no interpretable; ")&IF(N35="[PENDIENTE DE VERIFICAR]","Modalidad no identificable; ","")&IF(OR(ISERROR(SEARCH("@itc.edu.co",J35)),SUMPRODUCT(--ISNUMBER(SEARCH({"á","é","í","ó","ú","ñ"},J35)))>0),"Correo vacío o no institucional válido; ","")&IF(LEN(TRIM(D35))=0,"Sin objeto contractual; ","")&IF(AND(ISNUMBER(M35),N35="Mínima cuantía"),IF(M35>39850000,"Mínima cuantía con valor superior al tope citado en el instructivo 2026 ($39.850.000): verificar modalidad; ",""),"")&IF(AND(ISNUMBER(M35),OR(ISNUMBER(SEARCH("prestación de servicios",D35)),ISNUMBER(SEARCH("prestar servicios",D35)),ISNUMBER(SEARCH("prestar los servicios",D35)))),IF(M35>=500000000,"Prestación de servicios por $500 millones o más: posible error de digitación; ",""),""))=0,"Sin observaciones",IF(OR(NOT(ISNUMBER(B35)),LEN(B35)<>8),"UNSPSC vacío, en texto, con varios códigos o sin 8 dígitos; ","")&IF(AND(ISNUMBER(B35),LEN(B35)=8),IF(MOD(B35,10000)=0,"UNSPSC a nivel de segmento o familia; ",""),"")&IF(NOT(ISNUMBER(E35)),"Duración vacía o en texto; ","")&IF(NOT(ISNUMBER(G35)),"Valor vacío o en texto; ","")&IF(ISNUMBER(M35),IF(M35<1000000,"Valor inferior a $1.000.000: verificar; ",""),"Valor no interpretable; ")&IF(N35="[PENDIENTE DE VERIFICAR]","Modalidad no identificable; ","")&IF(OR(ISERROR(SEARCH("@itc.edu.co",J35)),SUMPRODUCT(--ISNUMBER(SEARCH({"á","é","í","ó","ú","ñ"},J35)))>0),"Correo vacío o no institucional válido; ","")&IF(LEN(TRIM(D35))=0,"Sin objeto contractual; ","")&IF(AND(ISNUMBER(M35),N35="Mínima cuantía"),IF(M35>39850000,"Mínima cuantía con valor superior al tope citado en el instructivo 2026 ($39.850.000): verificar modalidad; ",""),"")&IF(AND(ISNUMBER(M35),OR(ISNUMBER(SEARCH("prestación de servicios",D35)),ISNUMBER(SEARCH("prestar servicios",D35)),ISNUMBER(SEARCH("prestar los servicios",D35)))),IF(M35>=500000000,"Prestación de servicios por $500 millones o más: posible error de digitación; ",""),"")) -> Sin observaciones
A36: PN26-032 | B36: 80111600 | C36: Control interno - aspectos generales. | D36: Prestacion de servicios profesionales para desarrollar las actividades contables y fiancieras del proceso de control interno, con autonomia tecnica y administrativa, de acuerdo con el plan anual de auditoria de control interno 2026 para la escuela tecnologica instituto tecnico central | E36: 11 | F36: DIRECTA | G36: 52800000 | H36: Profesional especializado 2028-15 | K36: 31 | L36: 102 · Control Interno | M36: 52800000 | N36: Contratación directa | O36: =IF(LEN(IF(OR(NOT(ISNUMBER(B36)),LEN(B36)<>8),"UNSPSC vacío, en texto, con varios códigos o sin 8 dígitos; ","")&IF(AND(ISNUMBER(B36),LEN(B36)=8),IF(MOD(B36,10000)=0,"UNSPSC a nivel de segmento o familia; ",""),"")&IF(NOT(ISNUMBER(E36)),"Duración vacía o en texto; ","")&IF(NOT(ISNUMBER(G36)),"Valor vacío o en texto; ","")&IF(ISNUMBER(M36),IF(M36<1000000,"Valor inferior a $1.000.000: verificar; ",""),"Valor no interpretable; ")&IF(N36="[PENDIENTE DE VERIFICAR]","Modalidad no identificable; ","")&IF(OR(ISERROR(SEARCH("@itc.edu.co",J36)),SUMPRODUCT(--ISNUMBER(SEARCH({"á","é","í","ó","ú","ñ"},J36)))>0),"Correo vacío o no institucional válido; ","")&IF(LEN(TRIM(D36))=0,"Sin objeto contractual; ","")&IF(AND(ISNUMBER(M36),N36="Mínima cuantía"),IF(M36>39850000,"Mínima cuantía con valor superior al tope citado en el instructivo 2026 ($39.850.000): verificar modalidad; ",""),"")&IF(AND(ISNUMBER(M36),OR(ISNUMBER(SEARCH("prestación de servicios",D36)),ISNUMBER(SEARCH("prestar servicios",D36)),ISNUMBER(SEARCH("prestar los servicios",D36)))),IF(M36>=500000000,"Prestación de servicios por $500 millones o más: posible error de digitación; ",""),""))=0,"Sin observaciones",IF(OR(NOT(ISNUMBER(B36)),LEN(B36)<>8),"UNSPSC vacío, en texto, con varios códigos o sin 8 dígitos; ","")&IF(AND(ISNUMBER(B36),LEN(B36)=8),IF(MOD(B36,10000)=0,"UNSPSC a nivel de segmento o familia; ",""),"")&IF(NOT(ISNUMBER(E36)),"Duración vacía o en texto; ","")&IF(NOT(ISNUMBER(G36)),"Valor vacío o en texto; ","")&IF(ISNUMBER(M36),IF(M36<1000000,"Valor inferior a $1.000.000: verificar; ",""),"Valor no interpretable; ")&IF(N36="[PENDIENTE DE VERIFICAR]","Modalidad no identificable; ","")&IF(OR(ISERROR(SEARCH("@itc.edu.co",J36)),SUMPRODUCT(--ISNUMBER(SEARCH({"á","é","í","ó","ú","ñ"},J36)))>0),"Correo vacío o no institucional válido; ","")&IF(LEN(TRIM(D36))=0,"Sin objeto contractual; ","")&IF(AND(ISNUMBER(M36),N36="Mínima cuantía"),IF(M36>39850000,"Mínima cuantía con valor superior al tope citado en el instructivo 2026 ($39.850.000): verificar modalidad; ",""),"")&IF(AND(ISNUMBER(M36),OR(ISNUMBER(SEARCH("prestación de servicios",D36)),ISNUMBER(SEARCH("prestar servicios",D36)),ISNUMBER(SEARCH("prestar los servicios",D36)))),IF(M36>=500000000,"Prestación de servicios por $500 millones o más: posible error de digitación; ",""),"")) -> Correo vacío o no institucional válido;
A37: PN26-033 | B37: 80111600 | C37: Control interno - financiero | D37: Prestacion de servicios profesionales para el desarrollo de las actividades del proceso de control interno, con autonomia tecnica y administrativa, orientadas a la ejecucion del plan anual de auditoria incluyendo seguimientos, informes de ley, evaluación del modelo integrado de planeación y gestión (mipg), la aplicación del modelo estándar de control interno (meci), la verificación de los planes de mejoramiento y la gestión de riesgos de la escuela tecnológica instituto técnico central. | E37: 11 | F37: DIRECTA | G37: 52800000 | H37: Profesional especializado 2028-15 | K37: 32 | L37: 102 · Control Interno | M37: 52800000 | N37: Contratación directa | O37: =IF(LEN(IF(OR(NOT(ISNUMBER(B37)),LEN(B37)<>8),"UNSPSC vacío, en texto, con varios códigos o sin 8 dígitos; ","")&IF(AND(ISNUMBER(B37),LEN(B37)=8),IF(MOD(B37,10000)=0,"UNSPSC a nivel de segmento o familia; ",""),"")&IF(NOT(ISNUMBER(E37)),"Duración vacía o en texto; ","")&IF(NOT(ISNUMBER(G37)),"Valor vacío o en texto; ","")&IF(ISNUMBER(M37),IF(M37<1000000,"Valor inferior a $1.000.000: verificar; ",""),"Valor no interpretable; ")&IF(N37="[PENDIENTE DE VERIFICAR]","Modalidad no identificable; ","")&IF(OR(ISERROR(SEARCH("@itc.edu.co",J37)),SUMPRODUCT(--ISNUMBER(SEARCH({"á","é","í","ó","ú","ñ"},J37)))>0),"Correo vacío o no institucional válido; ","")&IF(LEN(TRIM(D37))=0,"Sin objeto contractual; ","")&IF(AND(ISNUMBER(M37),N37="Mínima cuantía"),IF(M37>39850000,"Mínima cuantía con valor superior al tope citado en el instructivo 2026 ($39.850.000): verificar modalidad; ",""),"")&IF(AND(ISNUMBER(M37),OR(ISNUMBER(SEARCH("prestación de servicios",D37)),ISNUMBER(SEARCH("prestar servicios",D37)),ISNUMBER(SEARCH("prestar los servicios",D37)))),IF(M37>=500000000,"Prestación de servicios por $500 millones o más: posible error de digitación; ",""),""))=0,"Sin observaciones",IF(OR(NOT(ISNUMBER(B37)),LEN(B37)<>8),"UNSPSC vacío, en texto, con varios códigos o sin 8 dígitos; ","")&IF(AND(ISNUMBER(B37),LEN(B37)=8),IF(MOD(B37,10000)=0,"UNSPSC a nivel de segmento o familia; ",""),"")&IF(NOT(ISNUMBER(E37)),"Duración vacía o en texto; ","")&IF(NOT(ISNUMBER(G37)),"Valor vacío o en texto; ","")&IF(ISNUMBER(M37),IF(M37<1000000,"Valor inferior a $1.000.000: verificar; ",""),"Valor no interpretable; ")&IF(N37="[PENDIENTE DE VERIFICAR]","Modalidad no identificable; ","")&IF(OR(ISERROR(SEARCH("@itc.edu.co",J37)),SUMPRODUCT(--ISNUMBER(SEARCH({"á","é","í","ó","ú","ñ"},J37)))>0),"Correo vacío o no institucional válido; ","")&IF(LEN(TRIM(D37))=0,"Sin objeto contractual; ","")&IF(AND(ISNUMBER(M37),N37="Mínima cuantía"),IF(M37>39850000,"Mínima cuantía con valor superior al tope citado en el instructivo 2026 ($39.850.000): verificar modalidad; ",""),"")&IF(AND(ISNUMBER(M37),OR(ISNUMBER(SEARCH("prestación de servicios",D37)),ISNUMBER(SEARCH("prestar servicios",D37)),ISNUMBER(SEARCH("prestar los servicios",D37)))),IF(M37>=500000000,"Prestación de servicios por $500 millones o más: posible error de digitación; ",""),"")) -> Correo vacío o no institucional válido;
A38: PN26-034 | B38: 80111600 | C38: Apoyo registros calificados | D38: Apoyar el sistema integrado de aseguramiento de la calidad con procesos de calidad nacional y regional para los programas de educación superior vigentes y la institución, y en obtención de ofertas académicas en diversas áreas de formación. | E38: 11 | F38: DIRECTA | G38: 52800000 | H38: Autoevaluación Institucional | J38: autoevaluacion@itc.edu.co | K38: 33 | L38: 101 · Oficina Asesora de Planeación y Desarrollo Institucional | M38: 52800000 | N38: Contratación directa | O38: =IF(LEN(IF(OR(NOT(ISNUMBER(B38)),LEN(B38)<>8),"UNSPSC vacío, en texto, con varios códigos o sin 8 dígitos; ","")&IF(AND(ISNUMBER(B38),LEN(B38)=8),IF(MOD(B38,10000)=0,"UNSPSC a nivel de segmento o familia; ",""),"")&IF(NOT(ISNUMBER(E38)),"Duración vacía o en texto; ","")&IF(NOT(ISNUMBER(G38)),"Valor vacío o en texto; ","")&IF(ISNUMBER(M38),IF(M38<1000000,"Valor inferior a $1.000.000: verificar; ",""),"Valor no interpretable; ")&IF(N38="[PENDIENTE DE VERIFICAR]","Modalidad no identificable; ","")&IF(OR(ISERROR(SEARCH("@itc.edu.co",J38)),SUMPRODUCT(--ISNUMBER(SEARCH({"á","é","í","ó","ú","ñ"},J38)))>0),"Correo vacío o no institucional válido; ","")&IF(LEN(TRIM(D38))=0,"Sin objeto contractual; ","")&IF(AND(ISNUMBER(M38),N38="Mínima cuantía"),IF(M38>39850000,"Mínima cuantía con valor superior al tope citado en el instructivo 2026 ($39.850.000): verificar modalidad; ",""),"")&IF(AND(ISNUMBER(M38),OR(ISNUMBER(SEARCH("prestación de servicios",D38)),ISNUMBER(SEARCH("prestar servicios",D38)),ISNUMBER(SEARCH("prestar los servicios",D38)))),IF(M38>=500000000,"Prestación de servicios por $500 millones o más: posible error de digitación; ",""),""))=0,"Sin observaciones",IF(OR(NOT(ISNUMBER(B38)),LEN(B38)<>8),"UNSPSC vacío, en texto, con varios códigos o sin 8 dígitos; ","")&IF(AND(ISNUMBER(B38),LEN(B38)=8),IF(MOD(B38,10000)=0,"UNSPSC a nivel de segmento o familia; ",""),"")&IF(NOT(ISNUMBER(E38)),"Duración vacía o en texto; ","")&IF(NOT(ISNUMBER(G38)),"Valor vacío o en texto; ","")&IF(ISNUMBER(M38),IF(M38<1000000,"Valor inferior a $1.000.000: verificar; ",""),"Valor no interpretable; ")&IF(N38="[PENDIENTE DE VERIFICAR]","Modalidad no identificable; ","")&IF(OR(ISERROR(SEARCH("@itc.edu.co",J38)),SUMPRODUCT(--ISNUMBER(SEARCH({"á","é","í","ó","ú","ñ"},J38)))>0),"Correo vacío o no institucional válido; ","")&IF(LEN(TRIM(D38))=0,"Sin objeto contractual; ","")&IF(AND(ISNUMBER(M38),N38="Mínima cuantía"),IF(M38>39850000,"Mínima cuantía con valor superior al tope citado en el instructivo 2026 ($39.850.000): verificar modalidad; ",""),"")&IF(AND(ISNUMBER(M38),OR(ISNUMBER(SEARCH("prestación de servicios",D38)),ISNUMBER(SEARCH("prestar servicios",D38)),ISNUMBER(SEARCH("prestar los servicios",D38)))),IF(M38>=500000000,"Prestación de servicios por $500 millones o más: posible error de digitación; ",""),"")) -> Sin observaciones
A39: PN26-035 | B39: 80111600 | C39: Apoyo proceso de articulacion | D39: Apoyar el sistema integrado de aseguramiento de la calidad con procesos de articulación de condiciones de calidad de programas e institucional, factores de alta calidad y lineamientos internacionales en coherencia con la información estadística de la escuela. | E39: 11 | F39: DIRECTA | G39: 52800000 | H39: Autoevaluación Institucional | J39: autoevaluacion@itc.edu.co | K39: 34 | L39: 101 · Oficina Asesora de Planeación y Desarrollo Institucional | M39: 52800000 | N39: Contratación directa | O39: =IF(LEN(IF(OR(NOT(ISNUMBER(B39)),LEN(B39)<>8),"UNSPSC vacío, en texto, con varios códigos o sin 8 dígitos; ","")&IF(AND(ISNUMBER(B39),LEN(B39)=8),IF(MOD(B39,10000)=0,"UNSPSC a nivel de segmento o familia; ",""),"")&IF(NOT(ISNUMBER(E39)),"Duración vacía o en texto; ","")&IF(NOT(ISNUMBER(G39)),"Valor vacío o en texto; ","")&IF(ISNUMBER(M39),IF(M39<1000000,"Valor inferior a $1.000.000: verificar; ",""),"Valor no interpretable; ")&IF(N39="[PENDIENTE DE VERIFICAR]","Modalidad no identificable; ","")&IF(OR(ISERROR(SEARCH("@itc.edu.co",J39)),SUMPRODUCT(--ISNUMBER(SEARCH({"á","é","í","ó","ú","ñ"},J39)))>0),"Correo vacío o no institucional válido; ","")&IF(LEN(TRIM(D39))=0,"Sin objeto contractual; ","")&IF(AND(ISNUMBER(M39),N39="Mínima cuantía"),IF(M39>39850000,"Mínima cuantía con valor superior al tope citado en el instructivo 2026 ($39.850.000): verificar modalidad; ",""),"")&IF(AND(ISNUMBER(M39),OR(ISNUMBER(SEARCH("prestación de servicios",D39)),ISNUMBER(SEARCH("prestar servicios",D39)),ISNUMBER(SEARCH("prestar los servicios",D39)))),IF(M39>=500000000,"Prestación de servicios por $500 millones o más: posible error de digitación; ",""),""))=0,"Sin observaciones",IF(OR(NOT(ISNUMBER(B39)),LEN(B39)<>8),"UNSPSC vacío, en texto, con varios códigos o sin 8 dígitos; ","")&IF(AND(ISNUMBER(B39),LEN(B39)=8),IF(MOD(B39,10000)=0,"UNSPSC a nivel de segmento o familia; ",""),"")&IF(NOT(ISNUMBER(E39)),"Duración vacía o en texto; ","")&IF(NOT(ISNUMBER(G39)),"Valor vacío o en texto; ","")&IF(ISNUMBER(M39),IF(M39<1000000,"Valor inferior a $1.000.000: verificar; ",""),"Valor no interpretable; ")&IF(N39="[PENDIENTE DE VERIFICAR]","Modalidad no identificable; ","")&IF(OR(ISERROR(SEARCH("@itc.edu.co",J39)),SUMPRODUCT(--ISNUMBER(SEARCH({"á","é","í","ó","ú","ñ"},J39)))>0),"Correo vacío o no institucional válido; ","")&IF(LEN(TRIM(D39))=0,"Sin objeto contractual; ","")&IF(AND(ISNUMBER(M39),N39="Mínima cuantía"),IF(M39>39850000,"Mínima cuantía con valor superior al tope citado en el instructivo 2026 ($39.850.000): verificar modalidad; ",""),"")&IF(AND(ISNUMBER(M39),OR(ISNUMBER(SEARCH("prestación de servicios",D39)),ISNUMBER(SEARCH("prestar servicios",D39)),ISNUMBER(SEARCH("prestar los servicios",D39)))),IF(M39>=500000000,"Prestación de servicios por $500 millones o más: posible error de digitación; ",""),"")) -> Sin observaciones
A40: PN26-036 | B40: 80111600 | C40: Apoyo proceso de acreditacion | D40: Apoyar el sistema integrado de aseguramiento de la calidad con procesos de alta calidad nacional e internacional para los programas de educación superior vigentes y la institución, y en obtención de ofertas académicas. | E40: 11 | F40: DIRECTA | G40: 52800000 | H40: Autoevaluación Institucional | J40: autoevaluacion@itc.edu.co | K40: 35 | L40: 101 · Oficina Asesora de Planeación y Desarrollo Institucional | M40: 52800000 | N40: Contratación directa | O40: =IF(LEN(IF(OR(NOT(ISNUMBER(B40)),LEN(B40)<>8),"UNSPSC vacío, en texto, con varios códigos o sin 8 dígitos; ","")&IF(AND(ISNUMBER(B40),LEN(B40)=8),IF(MOD(B40,10000)=0,"UNSPSC a nivel de segmento o familia; ",""),"")&IF(NOT(ISNUMBER(E40)),"Duración vacía o en texto; ","")&IF(NOT(ISNUMBER(G40)),"Valor vacío o en texto; ","")&IF(ISNUMBER(M40),IF(M40<1000000,"Valor inferior a $1.000.000: verificar; ",""),"Valor no interpretable; ")&IF(N40="[PENDIENTE DE VERIFICAR]","Modalidad no identificable; ","")&IF(OR(ISERROR(SEARCH("@itc.edu.co",J40)),SUMPRODUCT(--ISNUMBER(SEARCH({"á","é","í","ó","ú","ñ"},J40)))>0),"Correo vacío o no institucional válido; ","")&IF(LEN(TRIM(D40))=0,"Sin objeto contractual; ","")&IF(AND(ISNUMBER(M40),N40="Mínima cuantía"),IF(M40>39850000,"Mínima cuantía con valor superior al tope citado en el instructivo 2026 ($39.850.000): verificar modalidad; ",""),"")&IF(AND(ISNUMBER(M40),OR(ISNUMBER(SEARCH("prestación de servicios",D40)),ISNUMBER(SEARCH("prestar servicios",D40)),ISNUMBER(SEARCH("prestar los servicios",D40)))),IF(M40>=500000000,"Prestación de servicios por $500 millones o más: posible error de digitación; ",""),""))=0,"Sin observaciones",IF(OR(NOT(ISNUMBER(B40)),LEN(B40)<>8),"UNSPSC vacío, en texto, con varios códigos o sin 8 dígitos; ","")&IF(AND(ISNUMBER(B40),LEN(B40)=8),IF(MOD(B40,10000)=0,"UNSPSC a nivel de segmento o familia; ",""),"")&IF(NOT(ISNUMBER(E40)),"Duración vacía o en texto; ","")&IF(NOT(ISNUMBER(G40)),"Valor vacío o en texto; ","")&IF(ISNUMBER(M40),IF(M40<1000000,"Valor inferior a $1.000.000: verificar; ",""),"Valor no interpretable; ")&IF(N40="[PENDIENTE DE VERIFICAR]","Modalidad no identificable; ","")&IF(OR(ISERROR(SEARCH("@itc.edu.co",J40)),SUMPRODUCT(--ISNUMBER(SEARCH({"á","é","í","ó","ú","ñ"},J40)))>0),"Correo vacío o no institucional válido; ","")&IF(LEN(TRIM(D40))=0,"Sin objeto contractual; ","")&IF(AND(ISNUMBER(M40),N40="Mínima cuantía"),IF(M40>39850000,"Mínima cuantía con valor superior al tope citado en el instructivo 2026 ($39.850.000): verificar modalidad; ",""),"")&IF(AND(ISNUMBER(M40),OR(ISNUMBER(SEARCH("prestación de servicios",D40)),ISNUMBER(SEARCH("prestar servicios",D40)),ISNUMBER(SEARCH("prestar los servicios",D40)))),IF(M40>=500000000,"Prestación de servicios por $500 millones o más: posible error de digitación; ",""),"")) -> Sin observaciones
A41: PN26-037 | B41: 80111600 | C41: Laboratorio inteligente | D41: Prestación de servicios profesionales para el desarrollo de actividades del laboratorio inteligente de ciencia, tencología, innovación y emprendimiento, formulación y ejecución de proyectos de emprendimiento del centro de pensamiento y desarrollo tecnológico para la vicerrectoría de investigación, extensión y transferencia de la escuela tecnológica instituto técnico central y sus sedes. | E41: 11 | F41: DIRECTA | G41: 39504668 | H41: Vicerrector de Investigación 0065-09 | J41: viceinvestigacion@itc.edu.co | K41: 36 | L41: 140 · Vicerrectoría de Investigación, Extensión y Transferencia | M41: 39504668 | N41: Contratación directa | O41: =IF(LEN(IF(OR(NOT(ISNUMBER(B41)),LEN(B41)<>8),"UNSPSC vacío, en texto, con varios códigos o sin 8 dígitos; ","")&IF(AND(ISNUMBER(B41),LEN(B41)=8),IF(MOD(B41,10000)=0,"UNSPSC a nivel de segmento o familia; ",""),"")&IF(NOT(ISNUMBER(E41)),"Duración vacía o en texto; ","")&IF(NOT(ISNUMBER(G41)),"Valor vacío o en texto; ","")&IF(ISNUMBER(M41),IF(M41<1000000,"Valor inferior a $1.000.000: verificar; ",""),"Valor no interpretable; ")&IF(N41="[PENDIENTE DE VERIFICAR]","Modalidad no identificable; ","")&IF(OR(ISERROR(SEARCH("@itc.edu.co",J41)),SUMPRODUCT(--ISNUMBER(SEARCH({"á","é","í","ó","ú","ñ"},J41)))>0),"Correo vacío o no institucional válido; ","")&IF(LEN(TRIM(D41))=0,"Sin objeto contractual; ","")&IF(AND(ISNUMBER(M41),N41="Mínima cuantía"),IF(M41>39850000,"Mínima cuantía con valor superior al tope citado en el instructivo 2026 ($39.850.000): verificar modalidad; ",""),"")&IF(AND(ISNUMBER(M41),OR(ISNUMBER(SEARCH("prestación de servicios",D41)),ISNUMBER(SEARCH("prestar servicios",D41)),ISNUMBER(SEARCH("prestar los servicios",D41)))),IF(M41>=500000000,"Prestación de servicios por $500 millones o más: posible error de digitación; ",""),""))=0,"Sin observaciones",IF(OR(NOT(ISNUMBER(B41)),LEN(B41)<>8),"UNSPSC vacío, en texto, con varios códigos o sin 8 dígitos; ","")&IF(AND(ISNUMBER(B41),LEN(B41)=8),IF(MOD(B41,10000)=0,"UNSPSC a nivel de segmento o familia; ",""),"")&IF(NOT(ISNUMBER(E41)),"Duración vacía o en texto; ","")&IF(NOT(ISNUMBER(G41)),"Valor vacío o en texto; ","")&IF(ISNUMBER(M41),IF(M41<1000000,"Valor inferior a $1.000.000: verificar; ",""),"Valor no interpretable; ")&IF(N41="[PENDIENTE DE VERIFICAR]","Modalidad no identificable; ","")&IF(OR(ISERROR(SEARCH("@itc.edu.co",J41)),SUMPRODUCT(--ISNUMBER(SEARCH({"á","é","í","ó","ú","ñ"},J41)))>0),"Correo vacío o no institucional válido; ","")&IF(LEN(TRIM(D41))=0,"Sin objeto contractual; ","")&IF(AND(ISNUMBER(M41),N41="Mínima cuantía"),IF(M41>39850000,"Mínima cuantía con valor superior al tope citado en el instructivo 2026 ($39.850.000): verificar modalidad; ",""),"")&IF(AND(ISNUMBER(M41),OR(ISNUMBER(SEARCH("prestación de servicios",D41)),ISNUMBER(SEARCH("prestar servicios",D41)),ISNUMBER(SEARCH("prestar los servicios",D41)))),IF(M41>=500000000,"Prestación de servicios por $500 millones o más: posible error de digitación; ",""),"")) -> Sin observaciones
A42: PN26-038 | B42: 80111600 | C42: Proceso de innovacion desarrollo y transferencia tecnologica | D42: Prestación de servicios profesionales para liderar el proceso de innovación, desarrollo y transferencia tecnológica de la escuela tecnológica instituto técnico central y sus sedes. | E42: 11 | F42: DIRECTA | G42: 45672007 | H42: Vicerrector de Investigación 0065-09 | J42: viceinvestigacion@itc.edu.co | K42: 37 | L42: 140 · Vicerrectoría de Investigación, Extensión y Transferencia | M42: 45672007 | N42: Contratación directa | O42: =IF(LEN(IF(OR(NOT(ISNUMBER(B42)),LEN(B42)<>8),"UNSPSC vacío, en texto, con varios códigos o sin 8 dígitos; ","")&IF(AND(ISNUMBER(B42),LEN(B42)=8),IF(MOD(B42,10000)=0,"UNSPSC a nivel de segmento o familia; ",""),"")&IF(NOT(ISNUMBER(E42)),"Duración vacía o en texto; ","")&IF(NOT(ISNUMBER(G42)),"Valor vacío o en texto; ","")&IF(ISNUMBER(M42),IF(M42<1000000,"Valor inferior a $1.000.000: verificar; ",""),"Valor no interpretable; ")&IF(N42="[PENDIENTE DE VERIFICAR]","Modalidad no identificable; ","")&IF(OR(ISERROR(SEARCH("@itc.edu.co",J42)),SUMPRODUCT(--ISNUMBER(SEARCH({"á","é","í","ó","ú","ñ"},J42)))>0),"Correo vacío o no institucional válido; ","")&IF(LEN(TRIM(D42))=0,"Sin objeto contractual; ","")&IF(AND(ISNUMBER(M42),N42="Mínima cuantía"),IF(M42>39850000,"Mínima cuantía con valor superior al tope citado en el instructivo 2026 ($39.850.000): verificar modalidad; ",""),"")&IF(AND(ISNUMBER(M42),OR(ISNUMBER(SEARCH("prestación de servicios",D42)),ISNUMBER(SEARCH("prestar servicios",D42)),ISNUMBER(SEARCH("prestar los servicios",D42)))),IF(M42>=500000000,"Prestación de servicios por $500 millones o más: posible error de digitación; ",""),""))=0,"Sin observaciones",IF(OR(NOT(ISNUMBER(B42)),LEN(B42)<>8),"UNSPSC vacío, en texto, con varios códigos o sin 8 dígitos; ","")&IF(AND(ISNUMBER(B42),LEN(B42)=8),IF(MOD(B42,10000)=0,"UNSPSC a nivel de segmento o familia; ",""),"")&IF(NOT(ISNUMBER(E42)),"Duración vacía o en texto; ","")&IF(NOT(ISNUMBER(G42)),"Valor vacío o en texto; ","")&IF(ISNUMBER(M42),IF(M42<1000000,"Valor inferior a $1.000.000: verificar; ",""),"Valor no interpretable; ")&IF(N42="[PENDIENTE DE VERIFICAR]","Modalidad no identificable; ","")&IF(OR(ISERROR(SEARCH("@itc.edu.co",J42)),SUMPRODUCT(--ISNUMBER(SEARCH({"á","é","í","ó","ú","ñ"},J42)))>0),"Correo vacío o no institucional válido; ","")&IF(LEN(TRIM(D42))=0,"Sin objeto contractual; ","")&IF(AND(ISNUMBER(M42),N42="Mínima cuantía"),IF(M42>39850000,"Mínima cuantía con valor superior al tope citado en el instructivo 2026 ($39.850.000): verificar modalidad; ",""),"")&IF(AND(ISNUMBER(M42),OR(ISNUMBER(SEARCH("prestación de servicios",D42)),ISNUMBER(SEARCH("prestar servicios",D42)),ISNUMBER(SEARCH("prestar los servicios",D42)))),IF(M42>=500000000,"Prestación de servicios por $500 millones o más: posible error de digitación; ",""),"")) -> Sin observaciones
A43: PN26-039 | B43: 80111600 | C43: Apoyo investigacion | D43: Prestación de servicios profesionales para apoyar la categorización de grupos de investigación e investigadores de la escuela tecnológica instituto técnico central, mediante la gestión y registro de productos en plataformas cvlac y gruplac, el análisis estadístico y documental de la producción académica, y la elaboración de reportes e informes que respalden los procesos de reconocimiento y visibilidad institucional conforme a la normatividad vigente. | E43: 11 | F43: DIRECTA | G43: 49181250 | H43: Vicerrector de Investigación 0065-09 | J43: viceinvestigacion@itc.edu.co | K43: 38 | L43: 140 · Vicerrectoría de Investigación, Extensión y Transferencia | M43: 49181250 | N43: Contratación directa | O43: =IF(LEN(IF(OR(NOT(ISNUMBER(B43)),LEN(B43)<>8),"UNSPSC vacío, en texto, con varios códigos o sin 8 dígitos; ","")&IF(AND(ISNUMBER(B43),LEN(B43)=8),IF(MOD(B43,10000)=0,"UNSPSC a nivel de segmento o familia; ",""),"")&IF(NOT(ISNUMBER(E43)),"Duración vacía o en texto; ","")&IF(NOT(ISNUMBER(G43)),"Valor vacío o en texto; ","")&IF(ISNUMBER(M43),IF(M43<1000000,"Valor inferior a $1.000.000: verificar; ",""),"Valor no interpretable; ")&IF(N43="[PENDIENTE DE VERIFICAR]","Modalidad no identificable; ","")&IF(OR(ISERROR(SEARCH("@itc.edu.co",J43)),SUMPRODUCT(--ISNUMBER(SEARCH({"á","é","í","ó","ú","ñ"},J43)))>0),"Correo vacío o no institucional válido; ","")&IF(LEN(TRIM(D43))=0,"Sin objeto contractual; ","")&IF(AND(ISNUMBER(M43),N43="Mínima cuantía"),IF(M43>39850000,"Mínima cuantía con valor superior al tope citado en el instructivo 2026 ($39.850.000): verificar modalidad; ",""),"")&IF(AND(ISNUMBER(M43),OR(ISNUMBER(SEARCH("prestación de servicios",D43)),ISNUMBER(SEARCH("prestar servicios",D43)),ISNUMBER(SEARCH("prestar los servicios",D43)))),IF(M43>=500000000,"Prestación de servicios por $500 millones o más: posible error de digitación; ",""),""))=0,"Sin observaciones",IF(OR(NOT(ISNUMBER(B43)),LEN(B43)<>8),"UNSPSC vacío, en texto, con varios códigos o sin 8 dígitos; ","")&IF(AND(ISNUMBER(B43),LEN(B43)=8),IF(MOD(B43,10000)=0,"UNSPSC a nivel de segmento o familia; ",""),"")&IF(NOT(ISNUMBER(E43)),"Duración vacía o en texto; ","")&IF(NOT(ISNUMBER(G43)),"Valor vacío o en texto; ","")&IF(ISNUMBER(M43),IF(M43<1000000,"Valor inferior a $1.000.000: verificar; ",""),"Valor no interpretable; ")&IF(N43="[PENDIENTE DE VERIFICAR]","Modalidad no identificable; ","")&IF(OR(ISERROR(SEARCH("@itc.edu.co",J43)),SUMPRODUCT(--ISNUMBER(SEARCH({"á","é","í","ó","ú","ñ"},J43)))>0),"Correo vacío o no institucional válido; ","")&IF(LEN(TRIM(D43))=0,"Sin objeto contractual; ","")&IF(AND(ISNUMBER(M43),N43="Mínima cuantía"),IF(M43>39850000,"Mínima cuantía con valor superior al tope citado en el instructivo 2026 ($39.850.000): verificar modalidad; ",""),"")&IF(AND(ISNUMBER(M43),OR(ISNUMBER(SEARCH("prestación de servicios",D43)),ISNUMBER(SEARCH("prestar servicios",D43)),ISNUMBER(SEARCH("prestar los servicios",D43)))),IF(M43>=500000000,"Prestación de servicios por $500 millones o más: posible error de digitación; ",""),"")) -> Sin observaciones
A44: PN26-040 | B44: 80111600 | C44: Centro de pensamiento | D44: Prestación de servicios profesionales para liderar el proyecto del centro de pensamiento y desarrollo tecnológico de la vicerrectoría de investigación, extensión y transferencia de la escuela tecnologica instituto tecnico central y sus sedes, de acuerdo con los requerimientos establecidos. | E44: 11 | F44: DIRECTA | G44: 49181250 | H44: Vicerrector de Investigación 0065-09 | J44: viceinvestigacion@itc.edu.co | K44: 39 | L44: 140 · Vicerrectoría de Investigación, Extensión y Transferencia | M44: 49181250 | N44: Contratación directa | O44: =IF(LEN(IF(OR(NOT(ISNUMBER(B44)),LEN(B44)<>8),"UNSPSC vacío, en texto, con varios códigos o sin 8 dígitos; ","")&IF(AND(ISNUMBER(B44),LEN(B44)=8),IF(MOD(B44,10000)=0,"UNSPSC a nivel de segmento o familia; ",""),"")&IF(NOT(ISNUMBER(E44)),"Duración vacía o en texto; ","")&IF(NOT(ISNUMBER(G44)),"Valor vacío o en texto; ","")&IF(ISNUMBER(M44),IF(M44<1000000,"Valor inferior a $1.000.000: verificar; ",""),"Valor no interpretable; ")&IF(N44="[PENDIENTE DE VERIFICAR]","Modalidad no identificable; ","")&IF(OR(ISERROR(SEARCH("@itc.edu.co",J44)),SUMPRODUCT(--ISNUMBER(SEARCH({"á","é","í","ó","ú","ñ"},J44)))>0),"Correo vacío o no institucional válido; ","")&IF(LEN(TRIM(D44))=0,"Sin objeto contractual; ","")&IF(AND(ISNUMBER(M44),N44="Mínima cuantía"),IF(M44>39850000,"Mínima cuantía con valor superior al tope citado en el instructivo 2026 ($39.850.000): verificar modalidad; ",""),"")&IF(AND(ISNUMBER(M44),OR(ISNUMBER(SEARCH("prestación de servicios",D44)),ISNUMBER(SEARCH("prestar servicios",D44)),ISNUMBER(SEARCH("prestar los servicios",D44)))),IF(M44>=500000000,"Prestación de servicios por $500 millones o más: posible error de digitación; ",""),""))=0,"Sin observaciones",IF(OR(NOT(ISNUMBER(B44)),LEN(B44)<>8),"UNSPSC vacío, en texto, con varios códigos o sin 8 dígitos; ","")&IF(AND(ISNUMBER(B44),LEN(B44)=8),IF(MOD(B44,10000)=0,"UNSPSC a nivel de segmento o familia; ",""),"")&IF(NOT(ISNUMBER(E44)),"Duración vacía o en texto; ","")&IF(NOT(ISNUMBER(G44)),"Valor vacío o en texto; ","")&IF(ISNUMBER(M44),IF(M44<1000000,"Valor inferior a $1.000.000: verificar; ",""),"Valor no interpretable; ")&IF(N44="[PENDIENTE DE VERIFICAR]","Modalidad no identificable; ","")&IF(OR(ISERROR(SEARCH("@itc.edu.co",J44)),SUMPRODUCT(--ISNUMBER(SEARCH({"á","é","í","ó","ú","ñ"},J44)))>0),"Correo vacío o no institucional válido; ","")&IF(LEN(TRIM(D44))=0,"Sin objeto contractual; ","")&IF(AND(ISNUMBER(M44),N44="Mínima cuantía"),IF(M44>39850000,"Mínima cuantía con valor superior al tope citado en el instructivo 2026 ($39.850.000): verificar modalidad; ",""),"")&IF(AND(ISNUMBER(M44),OR(ISNUMBER(SEARCH("prestación de servicios",D44)),ISNUMBER(SEARCH("prestar servicios",D44)),ISNUMBER(SEARCH("prestar los servicios",D44)))),IF(M44>=500000000,"Prestación de servicios por $500 millones o más: posible error de digitación; ",""),"")) -> Sin observaciones
A45: PN26-041 | B45: 80111600 | C45: Apoyo semilleros | D45: Prestación de servicios profesionales para gestionar y promover los diferentes procesos relacionados con la investigación de los estudiantes, garantizando la calidad académica y generando transferencia del conocimiento a través de la investigación formativa en la escuela tecnológica instituto técnico central. | E45: 11 | F45: DIRECTA | G45: 49181250 | H45: Vicerrector de Investigación 0065-09 | J45: viceinvestigacion@itc.edu.co | K45: 40 | L45: 140 · Vicerrectoría de Investigación, Extensión y Transferencia | M45: 49181250 | N45: Contratación directa | O45: =IF(LEN(IF(OR(NOT(ISNUMBER(B45)),LEN(B45)<>8),"UNSPSC vacío, en texto, con varios códigos o sin 8 dígitos; ","")&IF(AND(ISNUMBER(B45),LEN(B45)=8),IF(MOD(B45,10000)=0,"UNSPSC a nivel de segmento o familia; ",""),"")&IF(NOT(ISNUMBER(E45)),"Duración vacía o en texto; ","")&IF(NOT(ISNUMBER(G45)),"Valor vacío o en texto; ","")&IF(ISNUMBER(M45),IF(M45<1000000,"Valor inferior a $1.000.000: verificar; ",""),"Valor no interpretable; ")&IF(N45="[PENDIENTE DE VERIFICAR]","Modalidad no identificable; ","")&IF(OR(ISERROR(SEARCH("@itc.edu.co",J45)),SUMPRODUCT(--ISNUMBER(SEARCH({"á","é","í","ó","ú","ñ"},J45)))>0),"Correo vacío o no institucional válido; ","")&IF(LEN(TRIM(D45))=0,"Sin objeto contractual; ","")&IF(AND(ISNUMBER(M45),N45="Mínima cuantía"),IF(M45>39850000,"Mínima cuantía con valor superior al tope citado en el instructivo 2026 ($39.850.000): verificar modalidad; ",""),"")&IF(AND(ISNUMBER(M45),OR(ISNUMBER(SEARCH("prestación de servicios",D45)),ISNUMBER(SEARCH("prestar servicios",D45)),ISNUMBER(SEARCH("prestar los servicios",D45)))),IF(M45>=500000000,"Prestación de servicios por $500 millones o más: posible error de digitación; ",""),""))=0,"Sin observaciones",IF(OR(NOT(ISNUMBER(B45)),LEN(B45)<>8),"UNSPSC vacío, en texto, con varios códigos o sin 8 dígitos; ","")&IF(AND(ISNUMBER(B45),LEN(B45)=8),IF(MOD(B45,10000)=0,"UNSPSC a nivel de segmento o familia; ",""),"")&IF(NOT(ISNUMBER(E45)),"Duración vacía o en texto; ","")&IF(NOT(ISNUMBER(G45)),"Valor vacío o en texto; ","")&IF(ISNUMBER(M45),IF(M45<1000000,"Valor inferior a $1.000.000: verificar; ",""),"Valor no interpretable; ")&IF(N45="[PENDIENTE DE VERIFICAR]","Modalidad no identificable; ","")&IF(OR(ISERROR(SEARCH("@itc.edu.co",J45)),SUMPRODUCT(--ISNUMBER(SEARCH({"á","é","í","ó","ú","ñ"},J45)))>0),"Correo vacío o no institucional válido; ","")&IF(LEN(TRIM(D45))=0,"Sin objeto contractual; ","")&IF(AND(ISNUMBER(M45),N45="Mínima cuantía"),IF(M45>39850000,"Mínima cuantía con valor superior al tope citado en el instructivo 2026 ($39.850.000): verificar modalidad; ",""),"")&IF(AND(ISNUMBER(M45),OR(ISNUMBER(SEARCH("prestación de servicios",D45)),ISNUMBER(SEARCH("prestar servicios",D45)),ISNUMBER(SEARCH("prestar los servicios",D45)))),IF(M45>=500000000,"Prestación de servicios por $500 millones o más: posible error de digitación; ",""),"")) -> Sin observaciones
A46: PN26-042 | B46: 80111600 | C46: Revista letras | D46: Prestación de servicios profesionales para apoyar la gestión del proceso editorial, garantizando la calidad académica y generando transferencia del conocimiento a través de los productos editoriales en cumplimiento de los criterios de clidad científica de conformidad con la normatividad vigente en la escuela tecnológica instituto técnico central. | E46: 11 | F46: DIRECTA | G46: 42525357 | H46: Vicerrector de Investigación 0065-09 | J46: viceinvestigacion@itc.edu.co | K46: 41 | L46: 140 · Vicerrectoría de Investigación, Extensión y Transferencia | M46: 42525357 | N46: Contratación directa | O46: =IF(LEN(IF(OR(NOT(ISNUMBER(B46)),LEN(B46)<>8),"UNSPSC vacío, en texto, con varios códigos o sin 8 dígitos; ","")&IF(AND(ISNUMBER(B46),LEN(B46)=8),IF(MOD(B46,10000)=0,"UNSPSC a nivel de segmento o familia; ",""),"")&IF(NOT(ISNUMBER(E46)),"Duración vacía o en texto; ","")&IF(NOT(ISNUMBER(G46)),"Valor vacío o en texto; ","")&IF(ISNUMBER(M46),IF(M46<1000000,"Valor inferior a $1.000.000: verificar; ",""),"Valor no interpretable; ")&IF(N46="[PENDIENTE DE VERIFICAR]","Modalidad no identificable; ","")&IF(OR(ISERROR(SEARCH("@itc.edu.co",J46)),SUMPRODUCT(--ISNUMBER(SEARCH({"á","é","í","ó","ú","ñ"},J46)))>0),"Correo vacío o no institucional válido; ","")&IF(LEN(TRIM(D46))=0,"Sin objeto contractual; ","")&IF(AND(ISNUMBER(M46),N46="Mínima cuantía"),IF(M46>39850000,"Mínima cuantía con valor superior al tope citado en el instructivo 2026 ($39.850.000): verificar modalidad; ",""),"")&IF(AND(ISNUMBER(M46),OR(ISNUMBER(SEARCH("prestación de servicios",D46)),ISNUMBER(SEARCH("prestar servicios",D46)),ISNUMBER(SEARCH("prestar los servicios",D46)))),IF(M46>=500000000,"Prestación de servicios por $500 millones o más: posible error de digitación; ",""),""))=0,"Sin observaciones",IF(OR(NOT(ISNUMBER(B46)),LEN(B46)<>8),"UNSPSC vacío, en texto, con varios códigos o sin 8 dígitos; ","")&IF(AND(ISNUMBER(B46),LEN(B46)=8),IF(MOD(B46,10000)=0,"UNSPSC a nivel de segmento o familia; ",""),"")&IF(NOT(ISNUMBER(E46)),"Duración vacía o en texto; ","")&IF(NOT(ISNUMBER(G46)),"Valor vacío o en texto; ","")&IF(ISNUMBER(M46),IF(M46<1000000,"Valor inferior a $1.000.000: verificar; ",""),"Valor no interpretable; ")&IF(N46="[PENDIENTE DE VERIFICAR]","Modalidad no identificable; ","")&IF(OR(ISERROR(SEARCH("@itc.edu.co",J46)),SUMPRODUCT(--ISNUMBER(SEARCH({"á","é","í","ó","ú","ñ"},J46)))>0),"Correo vacío o no institucional válido; ","")&IF(LEN(TRIM(D46))=0,"Sin objeto contractual; ","")&IF(AND(ISNUMBER(M46),N46="Mínima cuantía"),IF(M46>39850000,"Mínima cuantía con valor superior al tope citado en el instructivo 2026 ($39.850.000): verificar modalidad; ",""),"")&IF(AND(ISNUMBER(M46),OR(ISNUMBER(SEARCH("prestación de servicios",D46)),ISNUMBER(SEARCH("prestar servicios",D46)),ISNUMBER(SEARCH("prestar los servicios",D46)))),IF(M46>=500000000,"Prestación de servicios por $500 millones o más: posible error de digitación; ",""),"")) -> Sin observaciones
A47: PN26-043 | B47: 81111600 | C47: Proyección social | D47: Prestación de servicios profesionales para la gestión del giteps desarrollando acciones dirigidas a la proyección social a través de articulación de la comunidad con la institución durante la vigencia 2026. | E47: 11 | F47: DIRECTA | G47: 48337317 | H47: Profesional de Gestión Coordinador del Grupo Interno de Trabajo de Extensión y Proyección social 2165-13 | K47: 42 | L47: 141 · GIT Extensión y Proyección Social | M47: 48337317 | N47: Contratación directa | O47: =IF(LEN(IF(OR(NOT(ISNUMBER(B47)),LEN(B47)<>8),"UNSPSC vacío, en texto, con varios códigos o sin 8 dígitos; ","")&IF(AND(ISNUMBER(B47),LEN(B47)=8),IF(MOD(B47,10000)=0,"UNSPSC a nivel de segmento o familia; ",""),"")&IF(NOT(ISNUMBER(E47)),"Duración vacía o en texto; ","")&IF(NOT(ISNUMBER(G47)),"Valor vacío o en texto; ","")&IF(ISNUMBER(M47),IF(M47<1000000,"Valor inferior a $1.000.000: verificar; ",""),"Valor no interpretable; ")&IF(N47="[PENDIENTE DE VERIFICAR]","Modalidad no identificable; ","")&IF(OR(ISERROR(SEARCH("@itc.edu.co",J47)),SUMPRODUCT(--ISNUMBER(SEARCH({"á","é","í","ó","ú","ñ"},J47)))>0),"Correo vacío o no institucional válido; ","")&IF(LEN(TRIM(D47))=0,"Sin objeto contractual; ","")&IF(AND(ISNUMBER(M47),N47="Mínima cuantía"),IF(M47>39850000,"Mínima cuantía con valor superior al tope citado en el instructivo 2026 ($39.850.000): verificar modalidad; ",""),"")&IF(AND(ISNUMBER(M47),OR(ISNUMBER(SEARCH("prestación de servicios",D47)),ISNUMBER(SEARCH("prestar servicios",D47)),ISNUMBER(SEARCH("prestar los servicios",D47)))),IF(M47>=500000000,"Prestación de servicios por $500 millones o más: posible error de digitación; ",""),""))=0,"Sin observaciones",IF(OR(NOT(ISNUMBER(B47)),LEN(B47)<>8),"UNSPSC vacío, en texto, con varios códigos o sin 8 dígitos; ","")&IF(AND(ISNUMBER(B47),LEN(B47)=8),IF(MOD(B47,10000)=0,"UNSPSC a nivel de segmento o familia; ",""),"")&IF(NOT(ISNUMBER(E47)),"Duración vacía o en texto; ","")&IF(NOT(ISNUMBER(G47)),"Valor vacío o en texto; ","")&IF(ISNUMBER(M47),IF(M47<1000000,"Valor inferior a $1.000.000: verificar; ",""),"Valor no interpretable; ")&IF(N47="[PENDIENTE DE VERIFICAR]","Modalidad no identificable; ","")&IF(OR(ISERROR(SEARCH("@itc.edu.co",J47)),SUMPRODUCT(--ISNUMBER(SEARCH({"á","é","í","ó","ú","ñ"},J47)))>0),"Correo vacío o no institucional válido; ","")&IF(LEN(TRIM(D47))=0,"Sin objeto contractual; ","")&IF(AND(ISNUMBER(M47),N47="Mínima cuantía"),IF(M47>39850000,"Mínima cuantía con valor superior al tope citado en el instructivo 2026 ($39.850.000): verificar modalidad; ",""),"")&IF(AND(ISNUMBER(M47),OR(ISNUMBER(SEARCH("prestación de servicios",D47)),ISNUMBER(SEARCH("prestar servicios",D47)),ISNUMBER(SEARCH("prestar los servicios",D47)))),IF(M47>=500000000,"Prestación de servicios por $500 millones o más: posible error de digitación; ",""),"")) -> Correo vacío o no institucional válido;
A48: PN26-044 | B48: 81111600 | C48: Apoyo profesional centro de lenguas | D48: Prestación de servicios profesionales especializado para apoyar las actividades del centro de extensión y proyección social y centro de lenguas, en el marco de la gestion de visibilidad institucional y oferta de servicios a nivel oficial y privado. | E48: 11 | F48: DIRECTA | G48: 7150000000 | H48: Profesional de Gestión Coordinador del Grupo Interno de Trabajo de Extensión y Proyección social 2165-13 | K48: 43 | L48: 141 · GIT Extensión y Proyección Social | M48: 7150000000 | N48: Contratación directa | O48: =IF(LEN(IF(OR(NOT(ISNUMBER(B48)),LEN(B48)<>8),"UNSPSC vacío, en texto, con varios códigos o sin 8 dígitos; ","")&IF(AND(ISNUMBER(B48),LEN(B48)=8),IF(MOD(B48,10000)=0,"UNSPSC a nivel de segmento o familia; ",""),"")&IF(NOT(ISNUMBER(E48)),"Duración vacía o en texto; ","")&IF(NOT(ISNUMBER(G48)),"Valor vacío o en texto; ","")&IF(ISNUMBER(M48),IF(M48<1000000,"Valor inferior a $1.000.000: verificar; ",""),"Valor no interpretable; ")&IF(N48="[PENDIENTE DE VERIFICAR]","Modalidad no identificable; ","")&IF(OR(ISERROR(SEARCH("@itc.edu.co",J48)),SUMPRODUCT(--ISNUMBER(SEARCH({"á","é","í","ó","ú","ñ"},J48)))>0),"Correo vacío o no institucional válido; ","")&IF(LEN(TRIM(D48))=0,"Sin objeto contractual; ","")&IF(AND(ISNUMBER(M48),N48="Mínima cuantía"),IF(M48>39850000,"Mínima cuantía con valor superior al tope citado en el instructivo 2026 ($39.850.000): verificar modalidad; ",""),"")&IF(AND(ISNUMBER(M48),OR(ISNUMBER(SEARCH("prestación de servicios",D48)),ISNUMBER(SEARCH("prestar servicios",D48)),ISNUMBER(SEARCH("prestar los servicios",D48)))),IF(M48>=500000000,"Prestación de servicios por $500 millones o más: posible error de digitación; ",""),""))=0,"Sin observaciones",IF(OR(NOT(ISNUMBER(B48)),LEN(B48)<>8),"UNSPSC vacío, en texto, con varios códigos o sin 8 dígitos; ","")&IF(AND(ISNUMBER(B48),LEN(B48)=8),IF(MOD(B48,10000)=0,"UNSPSC a nivel de segmento o familia; ",""),"")&IF(NOT(ISNUMBER(E48)),"Duración vacía o en texto; ","")&IF(NOT(ISNUMBER(G48)),"Valor vacío o en texto; ","")&IF(ISNUMBER(M48),IF(M48<1000000,"Valor inferior a $1.000.000: verificar; ",""),"Valor no interpretable; ")&IF(N48="[PENDIENTE DE VERIFICAR]","Modalidad no identificable; ","")&IF(OR(ISERROR(SEARCH("@itc.edu.co",J48)),SUMPRODUCT(--ISNUMBER(SEARCH({"á","é","í","ó","ú","ñ"},J48)))>0),"Correo vacío o no institucional válido; ","")&IF(LEN(TRIM(D48))=0,"Sin objeto contractual; ","")&IF(AND(ISNUMBER(M48),N48="Mínima cuantía"),IF(M48>39850000,"Mínima cuantía con valor superior al tope citado en el instructivo 2026 ($39.850.000): verificar modalidad; ",""),"")&IF(AND(ISNUMBER(M48),OR(ISNUMBER(SEARCH("prestación de servicios",D48)),ISNUMBER(SEARCH("prestar servicios",D48)),ISNUMBER(SEARCH("prestar los servicios",D48)))),IF(M48>=500000000,"Prestación de servicios por $500 millones o más: posible error de digitación; ",""),"")) -> Correo vacío o no institucional válido; Prestación de servicios por $500 millones o más: posible error de digitación;
A49: PN26-045 | B49: 81111600 | C49: Etdh | D49: Prestación de servicios profesionales especializados para apoyar las actividades del grupo interno de trabajo extensión y proyección social – giteps, en el marco de la constitución, organización, y registro de la oferta académica de educación para el trabajo y el desarrollo humano - etdh, gestionando de esta forma visibilidad institucional y oferta de servicios para el sector público y privado | E49: 11 | F49: DIRECTA | G49: 58283333 | H49: Profesional de Gestión Coordinador del Grupo Interno de Trabajo de Extensión y Proyección social 2165-13 | K49: 44 | L49: 141 · GIT Extensión y Proyección Social | M49: 58283333 | N49: Contratación directa | O49: =IF(LEN(IF(OR(NOT(ISNUMBER(B49)),LEN(B49)<>8),"UNSPSC vacío, en texto, con varios códigos o sin 8 dígitos; ","")&IF(AND(ISNUMBER(B49),LEN(B49)=8),IF(MOD(B49,10000)=0,"UNSPSC a nivel de segmento o familia; ",""),"")&IF(NOT(ISNUMBER(E49)),"Duración vacía o en texto; ","")&IF(NOT(ISNUMBER(G49)),"Valor vacío o en texto; ","")&IF(ISNUMBER(M49),IF(M49<1000000,"Valor inferior a $1.000.000: verificar; ",""),"Valor no interpretable; ")&IF(N49="[PENDIENTE DE VERIFICAR]","Modalidad no identificable; ","")&IF(OR(ISERROR(SEARCH("@itc.edu.co",J49)),SUMPRODUCT(--ISNUMBER(SEARCH({"á","é","í","ó","ú","ñ"},J49)))>0),"Correo vacío o no institucional válido; ","")&IF(LEN(TRIM(D49))=0,"Sin objeto contractual; ","")&IF(AND(ISNUMBER(M49),N49="Mínima cuantía"),IF(M49>39850000,"Mínima cuantía con valor superior al tope citado en el instructivo 2026 ($39.850.000): verificar modalidad; ",""),"")&IF(AND(ISNUMBER(M49),OR(ISNUMBER(SEARCH("prestación de servicios",D49)),ISNUMBER(SEARCH("prestar servicios",D49)),ISNUMBER(SEARCH("prestar los servicios",D49)))),IF(M49>=500000000,"Prestación de servicios por $500 millones o más: posible error de digitación; ",""),""))=0,"Sin observaciones",IF(OR(NOT(ISNUMBER(B49)),LEN(B49)<>8),"UNSPSC vacío, en texto, con varios códigos o sin 8 dígitos; ","")&IF(AND(ISNUMBER(B49),LEN(B49)=8),IF(MOD(B49,10000)=0,"UNSPSC a nivel de segmento o familia; ",""),"")&IF(NOT(ISNUMBER(E49)),"Duración vacía o en texto; ","")&IF(NOT(ISNUMBER(G49)),"Valor vacío o en texto; ","")&IF(ISNUMBER(M49),IF(M49<1000000,"Valor inferior a $1.000.000: verificar; ",""),"Valor no interpretable; ")&IF(N49="[PENDIENTE DE VERIFICAR]","Modalidad no identificable; ","")&IF(OR(ISERROR(SEARCH("@itc.edu.co",J49)),SUMPRODUCT(--ISNUMBER(SEARCH({"á","é","í","ó","ú","ñ"},J49)))>0),"Correo vacío o no institucional válido; ","")&IF(LEN(TRIM(D49))=0,"Sin objeto contractual; ","")&IF(AND(ISNUMBER(M49),N49="Mínima cuantía"),IF(M49>39850000,"Mínima cuantía con valor superior al tope citado en el instructivo 2026 ($39.850.000): verificar modalidad; ",""),"")&IF(AND(ISNUMBER(M49),OR(ISNUMBER(SEARCH("prestación de servicios",D49)),ISNUMBER(SEARCH("prestar servicios",D49)),ISNUMBER(SEARCH("prestar los servicios",D49)))),IF(M49>=500000000,"Prestación de servicios por $500 millones o más: posible error de digitación; ",""),"")) -> Correo vacío o no institucional válido;
A50: PN26-046 | B50: 81111600 | C50: Profesional de apoyo extension | D50: Prestación de servicios profesionales para realizar apoyo administrativo del área, seguimiento a la ejecución de los programas y coordinacion de la oferta académica del giteps en la escuela tecnologica instituto tecnico central durante la vigencia 2026. | E50: 11 | F50: DIRECTA | G50: 40098480 | H50: Profesional de Gestión Coordinador del Grupo Interno de Trabajo de Extensión y Proyección social 2165-13 | K50: 45 | L50: 141 · GIT Extensión y Proyección Social | M50: 40098480 | N50: Contratación directa | O50: =IF(LEN(IF(OR(NOT(ISNUMBER(B50)),LEN(B50)<>8),"UNSPSC vacío, en texto, con varios códigos o sin 8 dígitos; ","")&IF(AND(ISNUMBER(B50),LEN(B50)=8),IF(MOD(B50,10000)=0,"UNSPSC a nivel de segmento o familia; ",""),"")&IF(NOT(ISNUMBER(E50)),"Duración vacía o en texto; ","")&IF(NOT(ISNUMBER(G50)),"Valor vacío o en texto; ","")&IF(ISNUMBER(M50),IF(M50<1000000,"Valor inferior a $1.000.000: verificar; ",""),"Valor no interpretable; ")&IF(N50="[PENDIENTE DE VERIFICAR]","Modalidad no identificable; ","")&IF(OR(ISERROR(SEARCH("@itc.edu.co",J50)),SUMPRODUCT(--ISNUMBER(SEARCH({"á","é","í","ó","ú","ñ"},J50)))>0),"Correo vacío o no institucional válido; ","")&IF(LEN(TRIM(D50))=0,"Sin objeto contractual; ","")&IF(AND(ISNUMBER(M50),N50="Mínima cuantía"),IF(M50>39850000,"Mínima cuantía con valor superior al tope citado en el instructivo 2026 ($39.850.000): verificar modalidad; ",""),"")&IF(AND(ISNUMBER(M50),OR(ISNUMBER(SEARCH("prestación de servicios",D50)),ISNUMBER(SEARCH("prestar servicios",D50)),ISNUMBER(SEARCH("prestar los servicios",D50)))),IF(M50>=500000000,"Prestación de servicios por $500 millones o más: posible error de digitación; ",""),""))=0,"Sin observaciones",IF(OR(NOT(ISNUMBER(B50)),LEN(B50)<>8),"UNSPSC vacío, en texto, con varios códigos o sin 8 dígitos; ","")&IF(AND(ISNUMBER(B50),LEN(B50)=8),IF(MOD(B50,10000)=0,"UNSPSC a nivel de segmento o familia; ",""),"")&IF(NOT(ISNUMBER(E50)),"Duración vacía o en texto; ","")&IF(NOT(ISNUMBER(G50)),"Valor vacío o en texto; ","")&IF(ISNUMBER(M50),IF(M50<1000000,"Valor inferior a $1.000.000: verificar; ",""),"Valor no interpretable; ")&IF(N50="[PENDIENTE DE VERIFICAR]","Modalidad no identificable; ","")&IF(OR(ISERROR(SEARCH("@itc.edu.co",J50)),SUMPRODUCT(--ISNUMBER(SEARCH({"á","é","í","ó","ú","ñ"},J50)))>0),"Correo vacío o no institucional válido; ","")&IF(LEN(TRIM(D50))=0,"Sin objeto contractual; ","")&IF(AND(ISNUMBER(M50),N50="Mínima cuantía"),IF(M50>39850000,"Mínima cuantía con valor superior al tope citado en el instructivo 2026 ($39.850.000): verificar modalidad; ",""),"")&IF(AND(ISNUMBER(M50),OR(ISNUMBER(SEARCH("prestación de servicios",D50)),ISNUMBER(SEARCH("prestar servicios",D50)),ISNUMBER(SEARCH("prestar los servicios",D50)))),IF(M50>=500000000,"Prestación de servicios por $500 millones o más: posible error de digitación; ",""),"")) -> Correo vacío o no institucional válido;
A51: PN26-047 | B51: 81111600 | C51: Apoyo tecnico centro de lenguas | D51: Prestación de servicios de apoyo técnico a la gestión para realizar actividades administrativas y de seguimiento a la oferta académica del giteps y del centro de lenguas en la escuela tecnologica instituto tecnico central durante la vigencia 2026. | E51: 11 | F51: DIRECTA | G51: 25514657 | H51: Profesional de Gestión Coordinador del Grupo Interno de Trabajo de Extensión y Proyección social 2165-13 | K51: 46 | L51: 141 · GIT Extensión y Proyección Social | M51: 25514657 | N51: Contratación directa | O51: =IF(LEN(IF(OR(NOT(ISNUMBER(B51)),LEN(B51)<>8),"UNSPSC vacío, en texto, con varios códigos o sin 8 dígitos; ","")&IF(AND(ISNUMBER(B51),LEN(B51)=8),IF(MOD(B51,10000)=0,"UNSPSC a nivel de segmento o familia; ",""),"")&IF(NOT(ISNUMBER(E51)),"Duración vacía o en texto; ","")&IF(NOT(ISNUMBER(G51)),"Valor vacío o en texto; ","")&IF(ISNUMBER(M51),IF(M51<1000000,"Valor inferior a $1.000.000: verificar; ",""),"Valor no interpretable; ")&IF(N51="[PENDIENTE DE VERIFICAR]","Modalidad no identificable; ","")&IF(OR(ISERROR(SEARCH("@itc.edu.co",J51)),SUMPRODUCT(--ISNUMBER(SEARCH({"á","é","í","ó","ú","ñ"},J51)))>0),"Correo vacío o no institucional válido; ","")&IF(LEN(TRIM(D51))=0,"Sin objeto contractual; ","")&IF(AND(ISNUMBER(M51),N51="Mínima cuantía"),IF(M51>39850000,"Mínima cuantía con valor superior al tope citado en el instructivo 2026 ($39.850.000): verificar modalidad; ",""),"")&IF(AND(ISNUMBER(M51),OR(ISNUMBER(SEARCH("prestación de servicios",D51)),ISNUMBER(SEARCH("prestar servicios",D51)),ISNUMBER(SEARCH("prestar los servicios",D51)))),IF(M51>=500000000,"Prestación de servicios por $500 millones o más: posible error de digitación; ",""),""))=0,"Sin observaciones",IF(OR(NOT(ISNUMBER(B51)),LEN(B51)<>8),"UNSPSC vacío, en texto, con varios códigos o sin 8 dígitos; ","")&IF(AND(ISNUMBER(B51),LEN(B51)=8),IF(MOD(B51,10000)=0,"UNSPSC a nivel de segmento o familia; ",""),"")&IF(NOT(ISNUMBER(E51)),"Duración vacía o en texto; ","")&IF(NOT(ISNUMBER(G51)),"Valor vacío o en texto; ","")&IF(ISNUMBER(M51),IF(M51<1000000,"Valor inferior a $1.000.000: verificar; ",""),"Valor no interpretable; ")&IF(N51="[PENDIENTE DE VERIFICAR]","Modalidad no identificable; ","")&IF(OR(ISERROR(SEARCH("@itc.edu.co",J51)),SUMPRODUCT(--ISNUMBER(SEARCH({"á","é","í","ó","ú","ñ"},J51)))>0),"Correo vacío o no institucional válido; ","")&IF(LEN(TRIM(D51))=0,"Sin objeto contractual; ","")&IF(AND(ISNUMBER(M51),N51="Mínima cuantía"),IF(M51>39850000,"Mínima cuantía con valor superior al tope citado en el instructivo 2026 ($39.850.000): verificar modalidad; ",""),"")&IF(AND(ISNUMBER(M51),OR(ISNUMBER(SEARCH("prestación de servicios",D51)),ISNUMBER(SEARCH("prestar servicios",D51)),ISNUMBER(SEARCH("prestar los servicios",D51)))),IF(M51>=500000000,"Prestación de servicios por $500 millones o más: posible error de digitación; ",""),"")) -> Correo vacío o no institucional válido;
