Workbook

Sheet Instructivo
A1: Plantilla de Formulación del Plan de Acción Anual (PAA) 2027 — Escuela Tecnológica Instituto Técnico Central (ETITC)
A2: Oficina Asesora de Planeación y Desarrollo Institucional (OAPDI) · Versión 7 · Instrumento para las áreas funcionales · Libro protegido: solo se diligencian las celdas amarillas.
A4: 1. Propósito
A5: Este libro es el instrumento con el que cada dependencia y área funcional de la ETITC formula sus acciones para la vigencia 2027. La OAPDI entrega la ruta: las metas del Plan de Desarrollo Institucional (PDI) 2025-2032 que corresponden a cada área, lo que la institución espera alcanzar en 2027, las acciones que propone la OAPDI y los compromisos pendientes de 2026. Cada área responde con las acciones, productos, fechas, indicadores y evidencias con los que contribuirá a esas metas. La propuesta completa de la OAPDI, con los cambios frente a 2026, está en el libro 'Plan de acción 2027'.
A7: 2. Marco de referencia
A8: La formulación se rige por la Ley 152 de 1994 (Ley Orgánica del Plan de Desarrollo), el Modelo Integrado de Planeación y Gestión (MIPG), la estructura orgánica del Decreto 902 de 2013 y los grupos internos de trabajo de la Resolución 215 de 2022, el Mapa de Procesos GDC-DI-01 versión 9 (13 de junio de 2024), el Sistema Nacional de Acreditación (Acuerdos del Consejo Nacional de Educación Superior —CESU— 02 de 2020 y 01 de 2025) y la Guía Metodológica para la Evaluación de Impacto de la ETITC.
A10: 3. Arquitectura del PDI
A11: El PDI 2025-2032 se organiza en 6 ejes estratégicos, 24 líneas de acción y 45 metas estratégicas con horizonte 2032. Cada meta se identifica con un código de cuatro niveles (eje.línea.objetivo.meta), por ejemplo 1.1.1.1. Para 2027 se retoma la codificación del PDI: el diagnóstico de la OAPDI encontró que en 2026 varias metas cambiaron de código, de enunciado o de cifra, y esta plantilla las devuelve a su forma original.
A13: 4. Hojas del libro
A14: Buscador_Formulacion: el área selecciona su nombre en la lista desplegable (celda amarilla C4) y consulta sus metas, la meta institucional 2027, el aporte esperado (con las acciones que propone la OAPDI), los productos 2026 pendientes, los indicadores de impacto sugeridos, la hoja donde debe formular y sus compromisos 2026; en la parte inferior registra acciones adicionales. Eje1 a Eje6: una hoja por eje estratégico; cada fila es una meta asignada a un área y en ella el área formula su acción principal (columnas amarillas Q a AE). Compromisos_2026: hitos, compromisos vinculantes y tareas pendientes de los proyectos estructurantes (Convenio Zipazgo, Informe al Congreso 2025, Requerimiento MEN PIC/PG/PFB, Plan de Acción 2026) y del Acta CIGD 6-2026 sobre gestión energética; el área registra su decisión en las columnas amarillas. Las tablas de soporte (metas, áreas e indicadores) están ocultas y protegidas.
A16: 5. Cómo diligenciar
A17: Paso 1. Vaya a Buscador_Formulacion y seleccione su área en la celda amarilla C4. Paso 2. Revise las metas asignadas, el aporte esperado para 2027 y las acciones propuestas por la OAPDI, los productos 2026 pendientes y los compromisos que le corresponden (a la derecha); registre su decisión sobre cada compromiso en la hoja Compromisos_2026. Paso 3. Abra la hoja del eje que indica la columna 'Formular en la hoja', filtre por su área (columna J) y diligencie las columnas amarillas de cada fila. Paso 4. Si una meta requiere más de una acción, o si su área quiere contribuir a una meta que no tiene asignada, regístrela en la sección 'Acciones adicionales' del buscador, eligiendo el área y la meta en las listas. Paso 5. Verifique que la columna 'Alerta de consistencia' diga OK en todas sus filas y envíe el archivo a la OAPDI.
... A28: 9. Ejemplo de fila diligenciada (solo ilustrativo; no corresponde a una acción real)
A29: Hoja / fila | B29: Eje1_Formacion, fila de la meta 1.2.1.1 asignada a la Facultad de Sistemas (A26)
A30: Nombre de la acción | B30: Radicar en SACES el documento maestro de un programa nuevo de pregrado
A31: Producto esperado | B31: Constancia de radicación del documento maestro en SACES
A32: Fecha de inicio / fin | B32: 01/02/2027 — 30/06/2027
A33: Responsable | B33: sistemas@itc.edu.co
A34: Indicador de seguimiento / meta / unidad | B34: Documentos maestros radicados / 1 / documento
A35: Dimensión / indicador de impacto | B35: Valor Público / IMP-13 · Proporción de programas académicos pertinentes (alineados con necesidades y vocación del territorio)
A36: ¿Retoma compromiso 2026? | B36: Sí — continúa el documento maestro iniciado en 2026
A37: Evidencia verificable | B37: Radicado SACES y acta del Consejo Académico

Sheet Compromisos_2026
A1: Compromisos pendientes 2026 de los proyectos estructurantes para retomar o cerrar en el PAA 2027
A3: Id | B3: Proyecto estructurante | C3: Tipo | D3: Compromiso o tarea | E3: Responsable según la fuente | F3: Id área (propuesta) | G3: Área funcional | H3: Dependencia | I3: Meta PDI vinculada (propuesta) | J3: Eje | K3: Estado según la fuente | L3: Periodo 2027 | M3: Evidencia esperada | N3: Soporte normativo o documental | O3: Archivo fuente | P3: Decisión del área | Q3: Id asignación o fila donde se formula | R3: Observaciones | S3: Aux. | U3: Decisiones
A4: CP-001 | B4: Convenio ETITC-MinTIC / CIA Zipazgo | C4: Hito pendiente | D4: Suscribir el convenio interadministrativo ETITC-MinTIC (eventualmente tripartito con el municipio de Zipaquirá). | E4: Rectoría; MinTIC | F4: A01 | G4: =IFERROR(INDEX(Dependencias!$H$5:$H$51,MATCH(F4,Dependencias!$E$5:$E$51,0)),"") -> Despacho de Rectoría | H4: =IFERROR(INDEX(Dependencias!$F$5:$F$51,MATCH(F4,Dependencias!$E$5:$E$51,0))&" · "&INDEX(Dependencias!$G$5:$G$51,MATCH(F4,Dependencias!$E$5:$E$51,0)),"") -> 100 · Rectoría | I4: 5.3.1.1 | J4: =LEFT(I4,1) -> 5 | K4: En trámite; sin respuesta de MinTIC documentada | L4: Sugerido: (I semestre de 2027) | M4: Convenio suscrito | N4: Oficio 21/07/2026 | O4: Insumo Hoja de Ruta ETITC 2027 Convenio ETITC-MinTIC CIA Zipazgo.docx | S4: =IF(F4=LEFT(Buscador_Formulacion!$C$4,3),COUNTIF($F$4:F4,LEFT(Buscador_Formulacion!$C$4,3)),"") | U4: Se retoma en 2027
A5: CP-002 | B5: Convenio ETITC-MinTIC / CIA Zipazgo | C5: Hito pendiente | D5: Legalizar el convenio (perfeccionamiento, aprobaciones y designación de supervisión). | E5: Secretaría General; Rectoría | F5: A11 | G5: =IFERROR(INDEX(Dependencias!$H$5:$H$51,MATCH(F5,Dependencias!$E$5:$E$51,0)),"") -> Despacho de Secretaría General | H5: =IFERROR(INDEX(Dependencias!$F$5:$F$51,MATCH(F5,Dependencias!$E$5:$E$51,0))&" · "&INDEX(Dependencias!$G$5:$G$51,MATCH(F5,Dependencias!$E$5:$E$51,0)),"") -> 110 · Secretaría General | I5: 5.3.1.1 | J5: =LEFT(I5,1) -> 5 | K5: Sin iniciar: depende de la suscripción del convenio | L5: Posterior a la suscripción | M5: Actas de perfeccionamiento y designación de supervisor | N5: n.d. | O5: Insumo Hoja de Ruta ETITC 2027 Convenio ETITC-MinTIC CIA Zipazgo.docx | S5: =IF(F5=LEFT(Buscador_Formulacion!$C$4,3),COUNTIF($F$4:F5,LEFT(Buscador_Formulacion!$C$4,3)),"") | U5: Se cierra en 2026
A6: CP-003 | B6: Convenio ETITC-MinTIC / CIA Zipazgo | C6: Hito pendiente | D6: Iniciar la operación académica del Centro de IA Zipazgo una vez MinTIC entregue la obra y la dotación. | E6: MinTIC (obra y dotación); ETITC (operación) | F6: A15 | G6: =IFERROR(INDEX(Dependencias!$H$5:$H$51,MATCH(F6,Dependencias!$E$5:$E$51,0)),"") -> Despacho de la Vicerrectoría Académica | H6: =IFERROR(INDEX(Dependencias!$F$5:$F$51,MATCH(F6,Dependencias!$E$5:$E$51,0))&" · "&INDEX(Dependencias!$G$5:$G$51,MATCH(F6,Dependencias!$E$5:$E$51,0)),"") -> 120 · Vicerrectoría Académica | I6: 5.3.1.1 | J6: =LEFT(I6,1) -> 5 | K6: Pendiente; infraestructura en construcción al 31/03/2026 | L6: Sugerido: (2027-2, sujeto a la entrega de la obra por MinTIC) | M6: Acta de inicio de operación | N6: MEN 2026-EE-116789; Acuerdo 010/2025 | O6: Insumo Hoja de Ruta ETITC 2027 Convenio ETITC-MinTIC CIA Zipazgo.docx | S6: =IF(F6=LEFT(Buscador_Formulacion!$C$4,3),COUNTIF($F$4:F6,LEFT(Buscador_Formulacion!$C$4,3)),"") | U6: Se reasigna a otra área
A7: CP-004 | B7: Convenio ETITC-MinTIC / CIA Zipazgo | C7: Hito pendiente | D7: Definir la ruta de permanencia de la oferta en Zipaquirá antes del cierre de la ventana de lugares transitorios (admite nuevas cohortes por 2 años consecutivos). | E7: Vicerrectoría Académica | F7: A15 | G7: =IFERROR(INDEX(Dependencias!$H$5:$H$51,MATCH(F7,Dependencias!$E$5:$E$51,0)),"") -> Despacho de la Vicerrectoría Académica | H7: =IFERROR(INDEX(Dependencias!$F$5:$F$51,MATCH(F7,Dependencias!$E$5:$E$51,0))&" · "&INDEX(Dependencias!$G$5:$G$51,MATCH(F7,Dependencias!$E$5:$E$51,0)),"") -> 120 · Vicerrectoría Académica | I7: 1.1.1.1 | J7: =LEFT(I7,1) -> 1 | K7: Vigente desde las resoluciones del 16/04/2026; inicio del conteo por verificar | L7: 2027 | M7: Decisión documentada y trámite ante el MEN | N7: Res. 010369, 010371, 010377, 010378, 010379 y 010417 de 2026 | O7: Insumo Hoja de Ruta ETITC 2027 Convenio ETITC-MinTIC CIA Zipazgo.docx | S7: =IF(F7=LEFT(Buscador_Formulacion!$C$4,3),COUNTIF($F$4:F7,LEFT(Buscador_Formulacion!$C$4,3)),"") | U7: No aplica (justificar)
A8: CP-005 | B8: Convenio ETITC-MinTIC / CIA Zipazgo | C8: Compromiso vinculante | D8: Mantener designado un Coordinador del Convenio Marco de nivel directivo. | E8: Vicerrectoría Académica | F8: A15 | G8: =IFERROR(INDEX(Dependencias!$H$5:$H$51,MATCH(F8,Dependencias!$E$5:$E$51,0)),"") -> Despacho de la Vicerrectoría Académica | H8: =IFERROR(INDEX(Dependencias!$F$5:$F$51,MATCH(F8,Dependencias!$E$5:$E$51,0))&" · "&INDEX(Dependencias!$G$5:$G$51,MATCH(F8,Dependencias!$E$5:$E$51,0)),"") -> 120 · Vicerrectoría Académica | I8: 5.3.1.1 | J8: =LEFT(I8,1) -> 5 | K8: Vigente | L8: 2027 | M8: Acto de designación | N8: Convenio Marco 27/03/2025, cláusula 6, num. 7 | O8: Insumo Hoja de Ruta ETITC 2027 Convenio ETITC-MinTIC CIA Zipazgo.docx | S8: =IF(F8=LEFT(Buscador_Formulacion!$C$4,3),COUNTIF($F$4:F8,LEFT(Buscador_Formulacion!$C$4,3)),"")
A9: CP-006 | B9: Convenio ETITC-MinTIC / CIA Zipazgo | C9: Compromiso vinculante | D9: Presentar la programación académica semestral o anual del convenio. | E9: Vicerrectoría Académica; Decanaturas | F9: A15 | G9: =IFERROR(INDEX(Dependencias!$H$5:$H$51,MATCH(F9,Dependencias!$E$5:$E$51,0)),"") -> Despacho de la Vicerrectoría Académica | H9: =IFERROR(INDEX(Dependencias!$F$5:$F$51,MATCH(F9,Dependencias!$E$5:$E$51,0))&" · "&INDEX(Dependencias!$G$5:$G$51,MATCH(F9,Dependencias!$E$5:$E$51,0)),"") -> 120 · Vicerrectoría Académica | I9: 1.1.1.1 | J9: =LEFT(I9,1) -> 1 | K9: Vigente | L9: Cada periodo 2027 | M9: Documento de programación | N9: Convenio Marco, cláusula 6, num. 8 | O9: Insumo Hoja de Ruta ETITC 2027 Convenio ETITC-MinTIC CIA Zipazgo.docx | S9: =IF(F9=LEFT(Buscador_Formulacion!$C$4,3),COUNTIF($F$4:F9,LEFT(Buscador_Formulacion!$C$4,3)),"")
A10: CP-007 | B10: Convenio ETITC-MinTIC / CIA Zipazgo | C10: Compromiso vinculante | D10: Presentar el plan anual de trabajo 2027 del convenio. | E10: Vicerrectoría Académica | F10: A15 | G10: =IFERROR(INDEX(Dependencias!$H$5:$H$51,MATCH(F10,Dependencias!$E$5:$E$51,0)),"") -> Despacho de la Vicerrectoría Académica | H10: =IFERROR(INDEX(Dependencias!$F$5:$F$51,MATCH(F10,Dependencias!$E$5:$E$51,0))&" · "&INDEX(Dependencias!$G$5:$G$51,MATCH(F10,Dependencias!$E$5:$E$51,0)),"") -> 120 · Vicerrectoría Académica | I10: 5.3.1.1 | J10: =LEFT(I10,1) -> 5 | K10: Vigente | L10: Anual | M10: Plan de trabajo 2027 | N10: Convenio Marco, cláusula 6, num. 9 | O10: Insumo Hoja de Ruta ETITC 2027 Convenio ETITC-MinTIC CIA Zipazgo.docx | S10: =IF(F10=LEFT(Buscador_Formulacion!$C$4,3),COUNTIF($F$4:F10,LEFT(Buscador_Formulacion!$C$4,3)),"")
A11: CP-008 | B11: Convenio ETITC-MinTIC / CIA Zipazgo | C11: Compromiso vinculante | D11: Ejercer la Secretaría Técnica del Comité de Operación y Articulación. | E11: Vicerrectoría Académica | F11: A15 | G11: =IFERROR(INDEX(Dependencias!$H$5:$H$51,MATCH(F11,Dependencias!$E$5:$E$51,0)),"") -> Despacho de la Vicerrectoría Académica | H11: =IFERROR(INDEX(Dependencias!$F$5:$F$51,MATCH(F11,Dependencias!$E$5:$E$51,0))&" · "&INDEX(Dependencias!$G$5:$G$51,MATCH(F11,Dependencias!$E$5:$E$51,0)),"") -> 120 · Vicerrectoría Académica | I11: 5.3.1.1 | J11: =LEFT(I11,1) -> 5 | K11: Vigente; frecuencia por verificar | L11: Periódico | M11: Actas del comité | N11: Convenio Marco, cláusulas 9 y 10 | O11: Insumo Hoja de Ruta ETITC 2027 Convenio ETITC-MinTIC CIA Zipazgo.docx | S11: =IF(F11=LEFT(Buscador_Formulacion!$C$4,3),COUNTIF($F$4:F11,LEFT(Buscador_Formulacion!$C$4,3)),"")
A12: CP-009 | B12: Convenio ETITC-MinTIC / CIA Zipazgo | C12: Compromiso vinculante | D12: Aplicar la admisión especial y las rutas con homologación de créditos para estudiantes del convenio. | E12: Admisiones; Registro | F12: A29 | G12: =IFERROR(INDEX(Dependencias!$H$5:$H$51,MATCH(F12,Dependencias!$E$5:$E$51,0)),"") -> GIT Registro, Control y Admisiones | H12: =IFERROR(INDEX(Dependencias!$F$5:$F$51,MATCH(F12,Dependencias!$E$5:$E$51,0))&" · "&INDEX(Dependencias!$G$5:$G$51,MATCH(F12,Dependencias!$E$5:$E$51,0)),"") -> 126 · GIT Registro y Control | I12: 1.1.1.1 | J12: =LEFT(I12,1) -> 1 | K12: Vigente | L12: 2027-1 y 2027-2 | M12: Estudiantes admitidos y homologaciones | N12: Convenio Marco, cláusula 6, nums. 10 y 11 | O12: Insumo Hoja de Ruta ETITC 2027 Convenio ETITC-MinTIC CIA Zipazgo.docx | S12: =IF(F12=LEFT(Buscador_Formulacion!$C$4,3),COUNTIF($F$4:F12,LEFT(Buscador_Formulacion!$C$4,3)),"")
A13: CP-010 | B13: Convenio ETITC-MinTIC / CIA Zipazgo | C13: Compromiso vinculante | D13: Reportar en SNIES a los estudiantes del convenio. | E13: Registro y Control Académico; OAPDI | F13: A29 | G13: =IFERROR(INDEX(Dependencias!$H$5:$H$51,MATCH(F13,Dependencias!$E$5:$E$51,0)),"") -> GIT Registro, Control y Admisiones | H13: =IFERROR(INDEX(Dependencias!$F$5:$F$51,MATCH(F13,Dependencias!$E$5:$E$51,0))&" · "&INDEX(Dependencias!$G$5:$G$51,MATCH(F13,Dependencias!$E$5:$E$51,0)),"") -> 126 · GIT Registro y Control | I13: 1.1.1.1 | J13: =LEFT(I13,1) -> 1 | K13: Vigente | L13: Según calendario SNIES | M13: Reporte SNIES | N13: Convenio Marco, cláusula 6, num. 12 | O13: Insumo Hoja de Ruta ETITC 2027 Convenio ETITC-MinTIC CIA Zipazgo.docx | S13: =IF(F13=LEFT(Buscador_Formulacion!$C$4,3),COUNTIF($F$4:F13,LEFT(Buscador_Formulacion!$C$4,3)),"")
A14: CP-011 | B14: Convenio ETITC-MinTIC / CIA Zipazgo | C14: Compromiso institucional | D14: Obtener y cargar el Plan de Acción de la Facultad de IA y Zipazgo aprobado (debió presentarse en 3 meses desde el 16/05/2025; es anexo del oficio del 10/03/2026 y no está en la carpeta). | E14: Rectoría; OAPDI | F14: A05 | G14: =IFERROR(INDEX(Dependencias!$H$5:$H$51,MATCH(F14,Dependencias!$E$5:$E$51,0)),"") -> Planeación y Plan de Acción | H14: =IFERROR(INDEX(Dependencias!$F$5:$F$51,MATCH(F14,Dependencias!$E$5:$E$51,0))&" · "&INDEX(Dependencias!$G$5:$G$51,MATCH(F14,Dependencias!$E$5:$E$51,0)),"") -> 101 · Oficina Asesora de Planeación y Desarrollo Institucional | I14: 1.2.1.1 | J14: =LEFT(I14,1) -> 1 | K14: Aprobado por el Consejo Directivo según el oficio del 10/03/2026; el documento no está en la carpeta de trabajo | L14: Antes de cerrar la formulación 2027 | M14: Plan aprobado | N14: Acuerdo 010/2025, art. 2 | O14: Insumo Hoja de Ruta ETITC 2027 Convenio ETITC-MinTIC CIA Zipazgo.docx | S14: =IF(F14=LEFT(Buscador_Formulacion!$C$4,3),COUNTIF($F$4:F14,LEFT(Buscador_Formulacion!$C$4,3)),"")
A15: CP-012 | B15: Convenio ETITC-MinTIC / CIA Zipazgo | C15: Compromiso institucional | D15: Priorizar la sostenibilidad del Centro con recursos propios y gestionar convenios de financiación. | E15: Rectoría; Vicerrectoría Administrativa y Financiera | F15: A30 | G15: =IFERROR(INDEX(Dependencias!$H$5:$H$51,MATCH(F15,Dependencias!$E$5:$E$51,0)),"") -> Despacho de la Vicerrectoría Administrativa y Financiera | H15: =IFERROR(INDEX(Dependencias!$F$5:$F$51,MATCH(F15,Dependencias!$E$5:$E$51,0))&" · "&INDEX(Dependencias!$G$5:$G$51,MATCH(F15,Dependencias!$E$5:$E$51,0)),"") -> 130 · Vicerrectoría Administrativa y Financiera | I15: 5.3.1.1 | J15: =LEFT(I15,1) -> 5 | K15: Sin montos documentados | L15: 2027 | M15: Certificación presupuestal | N15: Acuerdo 010/2025, art. 3 | O15: Insumo Hoja de Ruta ETITC 2027 Convenio ETITC-MinTIC CIA Zipazgo.docx | S15: =IF(F15=LEFT(Buscador_Formulacion!$C$4,3),COUNTIF($F$4:F15,LEFT(Buscador_Formulacion!$C$4,3)),"")
A16: CP-013 | B16: Convenio ETITC-MinTIC / CIA Zipazgo | C16: Compromiso institucional | D16: Diseñar en 2027 cuatro programas: Tecnología en Análisis y Modelado de Datos con IA, Técnico Profesional en Ciencia de Datos Aplicada a la IA, Especialización en Gestión de Proyectos de IA y Maestría en Ciencia de Datos. | E16: Facultad de IA; Autoevaluación | F16: A46 | G16: =IFERROR(INDEX(Dependencias!$H$5:$H$51,MATCH(F16,Dependencias!$E$5:$E$51,0)),"") -> Facultad de Inteligencia Artificial (Acuerdo 010 de 2025) | H16: =IFERROR(INDEX(Dependencias!$F$5:$F$51,MATCH(F16,Dependencias!$E$5:$E$51,0))&" · "&INDEX(Dependencias!$G$5:$G$51,MATCH(F16,Dependencias!$E$5:$E$51,0)),"") -> 123 · Facultades | I16: 1.2.1.1 | J16: =LEFT(I16,1) -> 1 | K16: Proyectado | L16: 2027 | M16: Planes de estudio y acuerdos | N16: Oficio 10/03/2026, sección III | O16: Insumo Hoja de Ruta ETITC 2027 Convenio ETITC-MinTIC CIA Zipazgo.docx | S16: =IF(F16=LEFT(Buscador_Formulacion!$C$4,3),COUNTIF($F$4:F16,LEFT(Buscador_Formulacion!$C$4,3)),"")
A17: CP-014 | B17: Convenio ETITC-MinTIC / CIA Zipazgo | C17: Compromiso institucional | D17: Obtener registro calificado de Ingeniería en IA, Ingeniería Robótica con IA y Especialización en Soluciones de IA. | E17: Vicerrectoría Académica; Autoevaluación | F17: A15 | G17: =IFERROR(INDEX(Dependencias!$H$5:$H$51,MATCH(F17,Dependencias!$E$5:$E$51,0)),"") -> Despacho de la Vicerrectoría Académica | H17: =IFERROR(INDEX(Dependencias!$F$5:$F$51,MATCH(F17,Dependencias!$E$5:$E$51,0))&" · "&INDEX(Dependencias!$G$5:$G$51,MATCH(F17,Dependencias!$E$5:$E$51,0)),"") -> 120 · Vicerrectoría Académica | I17: 1.2.1.1 | J17: =LEFT(I17,1) -> 1 | K17: Ing. en IA radicada el 09/03/2026; las otras dos sin radicación documentada | L17: 2027 | M17: Radicados y resoluciones del MEN | N17: Acuerdos 04, 07 y 08 de 2026 | O17: Insumo Hoja de Ruta ETITC 2027 Convenio ETITC-MinTIC CIA Zipazgo.docx | S17: =IF(F17=LEFT(Buscador_Formulacion!$C$4,3),COUNTIF($F$4:F17,LEFT(Buscador_Formulacion!$C$4,3)),"")
A18: CP-015 | B18: Convenio ETITC-MinTIC / CIA Zipazgo | C18: Compromiso institucional | D18: Ofertar y matricular en Zipaquirá bajo lugares transitorios (por ejemplo, 60 estudiantes por periodo en Ingeniería de Sistemas). | E18: Vicerrectoría Académica | F18: A15 | G18: =IFERROR(INDEX(Dependencias!$H$5:$H$51,MATCH(F18,Dependencias!$E$5:$E$51,0)),"") -> Despacho de la Vicerrectoría Académica | H18: =IFERROR(INDEX(Dependencias!$F$5:$F$51,MATCH(F18,Dependencias!$E$5:$E$51,0))&" · "&INDEX(Dependencias!$G$5:$G$51,MATCH(F18,Dependencias!$E$5:$E$51,0)),"") -> 120 · Vicerrectoría Académica | I18: 1.1.1.1 | J18: =LEFT(I18,1) -> 1 | K18: Vigente | L18: Dentro de la ventana de 2 años | M18: Matrícula por lugar de desarrollo en SNIES | N18: Res. 010417 de 2026 | O18: Insumo Hoja de Ruta ETITC 2027 Convenio ETITC-MinTIC CIA Zipazgo.docx | S18: =IF(F18=LEFT(Buscador_Formulacion!$C$4,3),COUNTIF($F$4:F18,LEFT(Buscador_Formulacion!$C$4,3)),"")
A19: CP-016 | B19: Convenio ETITC-MinTIC / CIA Zipazgo | C19: Alerta a resolver | D19: Tramitar la modificación del lugar de desarrollo de los programas de IA si el Centro será su sede (los Acuerdos 04, 07 y 08 fijan Bogotá). | E19: Vicerrectoría Académica; Autoevaluación | F19: A08 | G19: =IFERROR(INDEX(Dependencias!$H$5:$H$51,MATCH(F19,Dependencias!$E$5:$E$51,0)),"") -> Aseguramiento de la Calidad, MIPG y Registros Calificados | H19: =IFERROR(INDEX(Dependencias!$F$5:$F$51,MATCH(F19,Dependencias!$E$5:$E$51,0))&" · "&INDEX(Dependencias!$G$5:$G$51,MATCH(F19,Dependencias!$E$5:$E$51,0)),"") -> 101 · Oficina Asesora de Planeación y Desarrollo Institucional | I19: 1.2.1.1 | J19: =LEFT(I19,1) -> 1 | K19: Sin trámite | L19: 2027 | M19: Solicitud de modificación ante el MEN | N19: Alerta 2 del insumo | O19: Insumo Hoja de Ruta ETITC 2027 Convenio ETITC-MinTIC CIA Zipazgo.docx | S19: =IF(F19=LEFT(Buscador_Formulacion!$C$4,3),COUNTIF($F$4:F19,LEFT(Buscador_Formulacion!$C$4,3)),"")
... A77: CP-074 | B77: Acta CIGD 6-2026 (07-10-2026) — Gestión energética | C77: Compromiso vinculante | D77: Reportar cada año a la UPME los resultados de la gestión energética (línea base, medidas y ahorro) en el Sistema Único de Usuarios. | E77: Gestión Ambiental; Gestor Energético | F77: A10 | G77: =IFERROR(INDEX(Dependencias!$H$5:$H$51,MATCH(F77,Dependencias!$E$5:$E$51,0)),"") -> Gestión Ambiental | H77: =IFERROR(INDEX(Dependencias!$F$5:$F$51,MATCH(F77,Dependencias!$E$5:$E$51,0))&" · "&INDEX(Dependencias!$G$5:$G$51,MATCH(F77,Dependencias!$E$5:$E$51,0)),"") -> 101 · Oficina Asesora de Planeación y Desarrollo Institucional | I77: 6.1.1.2 | J77: =LEFT(I77,1) -> 6 | K77: Incumplido a la fecha según el acta | L77: Sugerido: (primer reporte completo en 2027) | M77: Reporte radicado en el SUU | N77: Ley 2294 de 2023, art. 237; Circular UPME 000089 de 2025 | O77: Acta_de_Reunion_CIGD_6_2026_-_Borrador2_1.docx (punto 5 y numeral 4.2) | S77: =IF(F77=LEFT(Buscador_Formulacion!$C$4,3),COUNTIF($F$4:F77,LEFT(Buscador_Formulacion!$C$4,3)),"")

Sheet Buscador_Formulacion
A1: Buscador por área funcional y formulación de acciones adicionales 2027
A2: 1) Seleccione su área en la celda amarilla: la tabla muestra las metas que la OAPDI le asignó y lo que debe aportar en 2027. 2) Formule esas acciones en la hoja del eje indicada. 3) Si necesita acciones adicionales, regístrelas en la sección inferior.
B4: Área funcional: | C4: A27 · IBTI (124) | G4: Dependencia: | H4: =IFERROR(INDEX(Dependencias!$F$5:$F$51,MATCH(LEFT($C$4,3),Dependencias!$E$5:$E$51,0))&" · "&INDEX(Dependencias!$G$5:$G$51,MATCH(LEFT($C$4,3),Dependencias!$E$5:$E$51,0)),"") -> 124 · Instituto de Bachillerato Técnico Industrial (IBTI)
B5: Metas asignadas: | C5: =COUNTIF(Base_OAPDI!$I$5:$I$187,LEFT($C$4,3)) -> 2 | G5: Proceso: | H5: =IFERROR(INDEX(Dependencias!$I$5:$I$51,MATCH(LEFT($C$4,3),Dependencias!$E$5:$E$51,0)),"") -> Docencia IBTI
B6: Compromisos 2026: | C6: =COUNTIF(Compromisos_2026!$F$4:$F$77,LEFT($C$4,3)) -> 0
A7: N.° | B7: Id asignación | C7: Eje | D7: Código meta | E7: Meta estratégica (PDI) | F7: Meta institucional 2027 | G7: Aporte esperado del área 2027 | H7: Productos 2026 | I7: Pendientes 2026 | J7: Indicadores de impacto sugeridos | K7: Formular en la hoja | L7: Compromisos de proyectos | N7: N.° | O7: Id | P7: Proyecto estructurante | Q7: Compromiso pendiente 2026 | R7: Meta PDI | S7: Decisión del área
A8: 1 | B8: =IFERROR(INDEX(Base_OAPDI!$A$5:$A$187,MATCH($A8,Base_OAPDI!$U$5:$U$187,0)),"") -> E1-022 | C8: =IFERROR(INDEX(Base_OAPDI!$C$5:$C$187,MATCH($A8,Base_OAPDI!$U$5:$U$187,0)),"") -> Formación y pedagogía de calidad | D8: =IFERROR(INDEX(Base_OAPDI!$B$5:$B$187,MATCH($A8,Base_OAPDI!$U$5:$U$187,0)),"") -> 1.1.1.2 | E8: =IFERROR(INDEX(Base_OAPDI!$E$5:$E$187,MATCH($A8,Base_OAPDI!$U$5:$U$187,0)),"") -> Lograr que el 30% de los estudiantes del IBTI pasen a la educación superior de la ETITC. | F8: =IFERROR(INDEX(Base_OAPDI!$H$5:$H$187,MATCH($A8,Base_OAPDI!$U$5:$U$187,0)),"") -> 40 estudiantes | G8: =IFERROR(INDEX(Base_OAPDI!$R$5:$R$187,MATCH($A8,Base_OAPDI!$U$5:$U$187,0)),"") -> Acciones propuestas por la OAPDI (valídelas y formúlelas en esta fila o en Acciones adicionales): A27-008 Implementar la ruta de admisión y tránsito IBTI → educación superior. Cerrar o reprogramar 1 producto(s) 2026 pendiente(s) de esta meta. | H8: =IFERROR(INDEX(Base_OAPDI!$N$5:$N$187,MATCH($A8,Base_OAPDI!$U$5:$U$187,0)),"") -> 3 | I8: =IFERROR(INDEX(Base_OAPDI!$P$5:$P$187,MATCH($A8,Base_OAPDI!$U$5:$U$187,0)),"") -> 1 | J8: =IFERROR(INDEX(Base_OAPDI!$S$5:$S$187,MATCH($A8,Base_OAPDI!$U$5:$U$187,0)),"") -> IMP-12; IMP-06 | K8: =IFERROR(INDEX(Base_OAPDI!$T$5:$T$187,MATCH($A8,Base_OAPDI!$U$5:$U$187,0)),"") -> Eje1_Formacion | L8: =IFERROR(INDEX(Base_OAPDI!$Q$5:$Q$187,MATCH($A8,Base_OAPDI!$U$5:$U$187,0)),"") -> 0 | N8: 1 | O8: =IFERROR(INDEX(Compromisos_2026!$A$4:$A$77,MATCH($N8,Compromisos_2026!$S$4:$S$77,0))&"","") | P8: =IFERROR(INDEX(Compromisos_2026!$B$4:$B$77,MATCH($N8,Compromisos_2026!$S$4:$S$77,0))&"","") | Q8: =IFERROR(INDEX(Compromisos_2026!$D$4:$D$77,MATCH($N8,Compromisos_2026!$S$4:$S$77,0))&"","") | R8: =IFERROR(INDEX(Compromisos_2026!$I$4:$I$77,MATCH($N8,Compromisos_2026!$S$4:$S$77,0))&"","") | S8: =IFERROR(INDEX(Compromisos_2026!$P$4:$P$77,MATCH($N8,Compromisos_2026!$S$4:$S$77,0))&"","")
A9: 2 | B9: =IFERROR(INDEX(Base_OAPDI!$A$5:$A$187,MATCH($A9,Base_OAPDI!$U$5:$U$187,0)),"") -> E4-028 | C9: =IFERROR(INDEX(Base_OAPDI!$C$5:$C$187,MATCH($A9,Base_OAPDI!$U$5:$U$187,0)),"") -> Transformación institucional | D9: =IFERROR(INDEX(Base_OAPDI!$B$5:$B$187,MATCH($A9,Base_OAPDI!$U$5:$U$187,0)),"") -> 4.2.1.3 | E9: =IFERROR(INDEX(Base_OAPDI!$E$5:$E$187,MATCH($A9,Base_OAPDI!$U$5:$U$187,0)),"") -> Consolidar el IBTI como unidad autónoma y adscrita a la Institución con un programa de tránsito inmediato a la educación superior. | F9: =IFERROR(INDEX(Base_OAPDI!$H$5:$H$187,MATCH($A9,Base_OAPDI!$U$5:$U$187,0)),"") -> Currículos del IBTI y de los programas técnicos profesionales alineados; solicitud de adscripción ante el MEN | G9: =IFERROR(INDEX(Base_OAPDI!$R$5:$R$187,MATCH($A9,Base_OAPDI!$U$5:$U$187,0)),"") -> Acciones propuestas por la OAPDI (valídelas y formúlelas en esta fila o en Acciones adicionales): A27-098 Alinear los currículos del IBTI y de los programas técnicos profesionales. | H9: =IFERROR(INDEX(Base_OAPDI!$N$5:$N$187,MATCH($A9,Base_OAPDI!$U$5:$U$187,0)),"") -> 0 | I9: =IFERROR(INDEX(Base_OAPDI!$P$5:$P$187,MATCH($A9,Base_OAPDI!$U$5:$U$187,0)),"") -> 0 | J9: =IFERROR(INDEX(Base_OAPDI!$S$5:$S$187,MATCH($A9,Base_OAPDI!$U$5:$U$187,0)),"") -> IMP-12; IMP-06 | K9: =IFERROR(INDEX(Base_OAPDI!$T$5:$T$187,MATCH($A9,Base_OAPDI!$U$5:$U$187,0)),"") -> Eje4_Transformacion | L9: =IFERROR(INDEX(Base_OAPDI!$Q$5:$Q$187,MATCH($A9,Base_OAPDI!$U$5:$U$187,0)),"") -> 0 | N9: 2 | O9: =IFERROR(INDEX(Compromisos_2026!$A$4:$A$77,MATCH($N9,Compromisos_2026!$S$4:$S$77,0))&"","") | P9: =IFERROR(INDEX(Compromisos_2026!$B$4:$B$77,MATCH($N9,Compromisos_2026!$S$4:$S$77,0))&"","") | Q9: =IFERROR(INDEX(Compromisos_2026!$D$4:$D$77,MATCH($N9,Compromisos_2026!$S$4:$S$77,0))&"","") | R9: =IFERROR(INDEX(Compromisos_2026!$I$4:$I$77,MATCH($N9,Compromisos_2026!$S$4:$S$77,0))&"","") | S9: =IFERROR(INDEX(Compromisos_2026!$P$4:$P$77,MATCH($N9,Compromisos_2026!$S$4:$S$77,0))&"","")
A10: 3 | B10: =IFERROR(INDEX(Base_OAPDI!$A$5:$A$187,MATCH($A10,Base_OAPDI!$U$5:$U$187,0)),"") | C10: =IFERROR(INDEX(Base_OAPDI!$C$5:$C$187,MATCH($A10,Base_OAPDI!$U$5:$U$187,0)),"") | D10: =IFERROR(INDEX(Base_OAPDI!$B$5:$B$187,MATCH($A10,Base_OAPDI!$U$5:$U$187,0)),"") | E10: =IFERROR(INDEX(Base_OAPDI!$E$5:$E$187,MATCH($A10,Base_OAPDI!$U$5:$U$187,0)),"") | F10: =IFERROR(INDEX(Base_OAPDI!$H$5:$H$187,MATCH($A10,Base_OAPDI!$U$5:$U$187,0)),"") | G10: =IFERROR(INDEX(Base_OAPDI!$R$5:$R$187,MATCH($A10,Base_OAPDI!$U$5:$U$187,0)),"") | H10: =IFERROR(INDEX(Base_OAPDI!$N$5:$N$187,MATCH($A10,Base_OAPDI!$U$5:$U$187,0)),"") | I10: =IFERROR(INDEX(Base_OAPDI!$P$5:$P$187,MATCH($A10,Base_OAPDI!$U$5:$U$187,0)),"") | J10: =IFERROR(INDEX(Base_OAPDI!$S$5:$S$187,MATCH($A10,Base_OAPDI!$U$5:$U$187,0)),"") | K10: =IFERROR(INDEX(Base_OAPDI!$T$5:$T$187,MATCH($A10,Base_OAPDI!$U$5:$U$187,0)),"") | L10: =IFERROR(INDEX(Base_OAPDI!$Q$5:$Q$187,MATCH($A10,Base_OAPDI!$U$5:$U$187,0)),"") | N10: 3 | O10: =IFERROR(INDEX(Compromisos_2026!$A$4:$A$77,MATCH($N10,Compromisos_2026!$S$4:$S$77,0))&"","") | P10: =IFERROR(INDEX(Compromisos_2026!$B$4:$B$77,MATCH($N10,Compromisos_2026!$S$4:$S$77,0))&"","") | Q10: =IFERROR(INDEX(Compromisos_2026!$D$4:$D$77,MATCH($N10,Compromisos_2026!$S$4:$S$77,0))&"","") | R10: =IFERROR(INDEX(Compromisos_2026!$I$4:$I$77,MATCH($N10,Compromisos_2026!$S$4:$S$77,0))&"","") | S10: =IFERROR(INDEX(Compromisos_2026!$P$4:$P$77,MATCH($N10,Compromisos_2026!$S$4:$S$77,0))&"","")
A11: 4 | B11: =IFERROR(INDEX(Base_OAPDI!$A$5:$A$187,MATCH($A11,Base_OAPDI!$U$5:$U$187,0)),"") | C11: =IFERROR(INDEX(Base_OAPDI!$C$5:$C$187,MATCH($A11,Base_OAPDI!$U$5:$U$187,0)),"") | D11: =IFERROR(INDEX(Base_OAPDI!$B$5:$B$187,MATCH($A11,Base_OAPDI!$U$5:$U$187,0)),"") | E11: =IFERROR(INDEX(Base_OAPDI!$E$5:$E$187,MATCH($A11,Base_OAPDI!$U$5:$U$187,0)),"") | F11: =IFERROR(INDEX(Base_OAPDI!$H$5:$H$187,MATCH($A11,Base_OAPDI!$U$5:$U$187,0)),"") | G11: =IFERROR(INDEX(Base_OAPDI!$R$5:$R$187,MATCH($A11,Base_OAPDI!$U$5:$U$187,0)),"") | H11: =IFERROR(INDEX(Base_OAPDI!$N$5:$N$187,MATCH($A11,Base_OAPDI!$U$5:$U$187,0)),"") | I11: =IFERROR(INDEX(Base_OAPDI!$P$5:$P$187,MATCH($A11,Base_OAPDI!$U$5:$U$187,0)),"") | J11: =IFERROR(INDEX(Base_OAPDI!$S$5:$S$187,MATCH($A11,Base_OAPDI!$U$5:$U$187,0)),"") | K11: =IFERROR(INDEX(Base_OAPDI!$T$5:$T$187,MATCH($A11,Base_OAPDI!$U$5:$U$187,0)),"") | L11: =IFERROR(INDEX(Base_OAPDI!$Q$5:$Q$187,MATCH($A11,Base_OAPDI!$U$5:$U$187,0)),"") | N11: 4 | O11: =IFERROR(INDEX(Compromisos_2026!$A$4:$A$77,MATCH($N11,Compromisos_2026!$S$4:$S$77,0))&"","") | P11: =IFERROR(INDEX(Compromisos_2026!$B$4:$B$77,MATCH($N11,Compromisos_2026!$S$4:$S$77,0))&"","") | Q11: =IFERROR(INDEX(Compromisos_2026!$D$4:$D$77,MATCH($N11,Compromisos_2026!$S$4:$S$77,0))&"","") | R11: =IFERROR(INDEX(Compromisos_2026!$I$4:$I$77,MATCH($N11,Compromisos_2026!$S$4:$S$77,0))&"","") | S11: =IFERROR(INDEX(Compromisos_2026!$P$4:$P$77,MATCH($N11,Compromisos_2026!$S$4:$S$77,0))&"","")
A12: 5 | B12: =IFERROR(INDEX(Base_OAPDI!$A$5:$A$187,MATCH($A12,Base_OAPDI!$U$5:$U$187,0)),"") | C12: =IFERROR(INDEX(Base_OAPDI!$C$5:$C$187,MATCH($A12,Base_OAPDI!$U$5:$U$187,0)),"") | D12: =IFERROR(INDEX(Base_OAPDI!$B$5:$B$187,MATCH($A12,Base_OAPDI!$U$5:$U$187,0)),"") | E12: =IFERROR(INDEX(Base_OAPDI!$E$5:$E$187,MATCH($A12,Base_OAPDI!$U$5:$U$187,0)),"") | F12: =IFERROR(INDEX(Base_OAPDI!$H$5:$H$187,MATCH($A12,Base_OAPDI!$U$5:$U$187,0)),"") | G12: =IFERROR(INDEX(Base_OAPDI!$R$5:$R$187,MATCH($A12,Base_OAPDI!$U$5:$U$187,0)),"") | H12: =IFERROR(INDEX(Base_OAPDI!$N$5:$N$187,MATCH($A12,Base_OAPDI!$U$5:$U$187,0)),"") | I12: =IFERROR(INDEX(Base_OAPDI!$P$5:$P$187,MATCH($A12,Base_OAPDI!$U$5:$U$187,0)),"") | J12: =IFERROR(INDEX(Base_OAPDI!$S$5:$S$187,MATCH($A12,Base_OAPDI!$U$5:$U$187,0)),"") | K12: =IFERROR(INDEX(Base_OAPDI!$T$5:$T$187,MATCH($A12,Base_OAPDI!$U$5:$U$187,0)),"") | L12: =IFERROR(INDEX(Base_OAPDI!$Q$5:$Q$187,MATCH($A12,Base_OAPDI!$U$5:$U$187,0)),"") | N12: 5 | O12: =IFERROR(INDEX(Compromisos_2026!$A$4:$A$77,MATCH($N12,Compromisos_2026!$S$4:$S$77,0))&"","") | P12: =IFERROR(INDEX(Compromisos_2026!$B$4:$B$77,MATCH($N12,Compromisos_2026!$S$4:$S$77,0))&"","") | Q12: =IFERROR(INDEX(Compromisos_2026!$D$4:$D$77,MATCH($N12,Compromisos_2026!$S$4:$S$77,0))&"","") | R12: =IFERROR(INDEX(Compromisos_2026!$I$4:$I$77,MATCH($N12,Compromisos_2026!$S$4:$S$77,0))&"","") | S12: =IFERROR(INDEX(Compromisos_2026!$P$4:$P$77,MATCH($N12,Compromisos_2026!$S$4:$S$77,0))&"","")
A13: 6 | B13: =IFERROR(INDEX(Base_OAPDI!$A$5:$A$187,MATCH($A13,Base_OAPDI!$U$5:$U$187,0)),"") | C13: =IFERROR(INDEX(Base_OAPDI!$C$5:$C$187,MATCH($A13,Base_OAPDI!$U$5:$U$187,0)),"") | D13: =IFERROR(INDEX(Base_OAPDI!$B$5:$B$187,MATCH($A13,Base_OAPDI!$U$5:$U$187,0)),"") | E13: =IFERROR(INDEX(Base_OAPDI!$E$5:$E$187,MATCH($A13,Base_OAPDI!$U$5:$U$187,0)),"") | F13: =IFERROR(INDEX(Base_OAPDI!$H$5:$H$187,MATCH($A13,Base_OAPDI!$U$5:$U$187,0)),"") | G13: =IFERROR(INDEX(Base_OAPDI!$R$5:$R$187,MATCH($A13,Base_OAPDI!$U$5:$U$187,0)),"") | H13: =IFERROR(INDEX(Base_OAPDI!$N$5:$N$187,MATCH($A13,Base_OAPDI!$U$5:$U$187,0)),"") | I13: =IFERROR(INDEX(Base_OAPDI!$P$5:$P$187,MATCH($A13,Base_OAPDI!$U$5:$U$187,0)),"") | J13: =IFERROR(INDEX(Base_OAPDI!$S$5:$S$187,MATCH($A13,Base_OAPDI!$U$5:$U$187,0)),"") | K13: =IFERROR(INDEX(Base_OAPDI!$T$5:$T$187,MATCH($A13,Base_OAPDI!$U$5:$U$187,0)),"") | L13: =IFERROR(INDEX(Base_OAPDI!$Q$5:$Q$187,MATCH($A13,Base_OAPDI!$U$5:$U$187,0)),"") | N13: 6 | O13: =IFERROR(INDEX(Compromisos_2026!$A$4:$A$77,MATCH($N13,Compromisos_2026!$S$4:$S$77,0))&"","") | P13: =IFERROR(INDEX(Compromisos_2026!$B$4:$B$77,MATCH($N13,Compromisos_2026!$S$4:$S$77,0))&"","") | Q13: =IFERROR(INDEX(Compromisos_2026!$D$4:$D$77,MATCH($N13,Compromisos_2026!$S$4:$S$77,0))&"","") | R13: =IFERROR(INDEX(Compromisos_2026!$I$4:$I$77,MATCH($N13,Compromisos_2026!$S$4:$S$77,0))&"","") | S13: =IFERROR(INDEX(Compromisos_2026!$P$4:$P$77,MATCH($N13,Compromisos_2026!$S$4:$S$77,0))&"","")
A14: 7 | B14: =IFERROR(INDEX(Base_OAPDI!$A$5:$A$187,MATCH($A14,Base_OAPDI!$U$5:$U$187,0)),"") | C14: =IFERROR(INDEX(Base_OAPDI!$C$5:$C$187,MATCH($A14,Base_OAPDI!$U$5:$U$187,0)),"") | D14: =IFERROR(INDEX(Base_OAPDI!$B$5:$B$187,MATCH($A14,Base_OAPDI!$U$5:$U$187,0)),"") | E14: =IFERROR(INDEX(Base_OAPDI!$E$5:$E$187,MATCH($A14,Base_OAPDI!$U$5:$U$187,0)),"") | F14: =IFERROR(INDEX(Base_OAPDI!$H$5:$H$187,MATCH($A14,Base_OAPDI!$U$5:$U$187,0)),"") | G14: =IFERROR(INDEX(Base_OAPDI!$R$5:$R$187,MATCH($A14,Base_OAPDI!$U$5:$U$187,0)),"") | H14: =IFERROR(INDEX(Base_OAPDI!$N$5:$N$187,MATCH($A14,Base_OAPDI!$U$5:$U$187,0)),"") | I14: =IFERROR(INDEX(Base_OAPDI!$P$5:$P$187,MATCH($A14,Base_OAPDI!$U$5:$U$187,0)),"") | J14: =IFERROR(INDEX(Base_OAPDI!$S$5:$S$187,MATCH($A14,Base_OAPDI!$U$5:$U$187,0)),"") | K14: =IFERROR(INDEX(Base_OAPDI!$T$5:$T$187,MATCH($A14,Base_OAPDI!$U$5:$U$187,0)),"") | L14: =IFERROR(INDEX(Base_OAPDI!$Q$5:$Q$187,MATCH($A14,Base_OAPDI!$U$5:$U$187,0)),"") | N14: 7 | O14: =IFERROR(INDEX(Compromisos_2026!$A$4:$A$77,MATCH($N14,Compromisos_2026!$S$4:$S$77,0))&"","") | P14: =IFERROR(INDEX(Compromisos_2026!$B$4:$B$77,MATCH($N14,Compromisos_2026!$S$4:$S$77,0))&"","") | Q14: =IFERROR(INDEX(Compromisos_2026!$D$4:$D$77,MATCH($N14,Compromisos_2026!$S$4:$S$77,0))&"","") | R14: =IFERROR(INDEX(Compromisos_2026!$I$4:$I$77,MATCH($N14,Compromisos_2026!$S$4:$S$77,0))&"","") | S14: =IFERROR(INDEX(Compromisos_2026!$P$4:$P$77,MATCH($N14,Compromisos_2026!$S$4:$S$77,0))&"","")
A15: 8 | B15: =IFERROR(INDEX(Base_OAPDI!$A$5:$A$187,MATCH($A15,Base_OAPDI!$U$5:$U$187,0)),"") | C15: =IFERROR(INDEX(Base_OAPDI!$C$5:$C$187,MATCH($A15,Base_OAPDI!$U$5:$U$187,0)),"") | D15: =IFERROR(INDEX(Base_OAPDI!$B$5:$B$187,MATCH($A15,Base_OAPDI!$U$5:$U$187,0)),"") | E15: =IFERROR(INDEX(Base_OAPDI!$E$5:$E$187,MATCH($A15,Base_OAPDI!$U$5:$U$187,0)),"") | F15: =IFERROR(INDEX(Base_OAPDI!$H$5:$H$187,MATCH($A15,Base_OAPDI!$U$5:$U$187,0)),"") | G15: =IFERROR(INDEX(Base_OAPDI!$R$5:$R$187,MATCH($A15,Base_OAPDI!$U$5:$U$187,0)),"") | H15: =IFERROR(INDEX(Base_OAPDI!$N$5:$N$187,MATCH($A15,Base_OAPDI!$U$5:$U$187,0)),"") | I15: =IFERROR(INDEX(Base_OAPDI!$P$5:$P$187,MATCH($A15,Base_OAPDI!$U$5:$U$187,0)),"") | J15: =IFERROR(INDEX(Base_OAPDI!$S$5:$S$187,MATCH($A15,Base_OAPDI!$U$5:$U$187,0)),"") | K15: =IFERROR(INDEX(Base_OAPDI!$T$5:$T$187,MATCH($A15,Base_OAPDI!$U$5:$U$187,0)),"") | L15: =IFERROR(INDEX(Base_OAPDI!$Q$5:$Q$187,MATCH($A15,Base_OAPDI!$U$5:$U$187,0)),"") | N15: 8 | O15: =IFERROR(INDEX(Compromisos_2026!$A$4:$A$77,MATCH($N15,Compromisos_2026!$S$4:$S$77,0))&"","") | P15: =IFERROR(INDEX(Compromisos_2026!$B$4:$B$77,MATCH($N15,Compromisos_2026!$S$4:$S$77,0))&"","") | Q15: =IFERROR(INDEX(Compromisos_2026!$D$4:$D$77,MATCH($N15,Compromisos_2026!$S$4:$S$77,0))&"","") | R15: =IFERROR(INDEX(Compromisos_2026!$I$4:$I$77,MATCH($N15,Compromisos_2026!$S$4:$S$77,0))&"","") | S15: =IFERROR(INDEX(Compromisos_2026!$P$4:$P$77,MATCH($N15,Compromisos_2026!$S$4:$S$77,0))&"","")
A16: 9 | B16: =IFERROR(INDEX(Base_OAPDI!$A$5:$A$187,MATCH($A16,Base_OAPDI!$U$5:$U$187,0)),"") | C16: =IFERROR(INDEX(Base_OAPDI!$C$5:$C$187,MATCH($A16,Base_OAPDI!$U$5:$U$187,0)),"") | D16: =IFERROR(INDEX(Base_OAPDI!$B$5:$B$187,MATCH($A16,Base_OAPDI!$U$5:$U$187,0)),"") | E16: =IFERROR(INDEX(Base_OAPDI!$E$5:$E$187,MATCH($A16,Base_OAPDI!$U$5:$U$187,0)),"") | F16: =IFERROR(INDEX(Base_OAPDI!$H$5:$H$187,MATCH($A16,Base_OAPDI!$U$5:$U$187,0)),"") | G16: =IFERROR(INDEX(Base_OAPDI!$R$5:$R$187,MATCH($A16,Base_OAPDI!$U$5:$U$187,0)),"") | H16: =IFERROR(INDEX(Base_OAPDI!$N$5:$N$187,MATCH($A16,Base_OAPDI!$U$5:$U$187,0)),"") | I16: =IFERROR(INDEX(Base_OAPDI!$P$5:$P$187,MATCH($A16,Base_OAPDI!$U$5:$U$187,0)),"") | J16: =IFERROR(INDEX(Base_OAPDI!$S$5:$S$187,MATCH($A16,Base_OAPDI!$U$5:$U$187,0)),"") | K16: =IFERROR(INDEX(Base_OAPDI!$T$5:$T$187,MATCH($A16,Base_OAPDI!$U$5:$U$187,0)),"") | L16: =IFERROR(INDEX(Base_OAPDI!$Q$5:$Q$187,MATCH($A16,Base_OAPDI!$U$5:$U$187,0)),"") | N16: 9 | O16: =IFERROR(INDEX(Compromisos_2026!$A$4:$A$77,MATCH($N16,Compromisos_2026!$S$4:$S$77,0))&"","") | P16: =IFERROR(INDEX(Compromisos_2026!$B$4:$B$77,MATCH($N16,Compromisos_2026!$S$4:$S$77,0))&"","") | Q16: =IFERROR(INDEX(Compromisos_2026!$D$4:$D$77,MATCH($N16,Compromisos_2026!$S$4:$S$77,0))&"","") | R16: =IFERROR(INDEX(Compromisos_2026!$I$4:$I$77,MATCH($N16,Compromisos_2026!$S$4:$S$77,0))&"","") | S16: =IFERROR(INDEX(Compromisos_2026!$P$4:$P$77,MATCH($N16,Compromisos_2026!$S$4:$S$77,0))&"","")
A17: 10 | B17: =IFERROR(INDEX(Base_OAPDI!$A$5:$A$187,MATCH($A17,Base_OAPDI!$U$5:$U$187,0)),"") | C17: =IFERROR(INDEX(Base_OAPDI!$C$5:$C$187,MATCH($A17,Base_OAPDI!$U$5:$U$187,0)),"") | D17: =IFERROR(INDEX(Base_OAPDI!$B$5:$B$187,MATCH($A17,Base_OAPDI!$U$5:$U$187,0)),"") | E17: =IFERROR(INDEX(Base_OAPDI!$E$5:$E$187,MATCH($A17,Base_OAPDI!$U$5:$U$187,0)),"") | F17: =IFERROR(INDEX(Base_OAPDI!$H$5:$H$187,MATCH($A17,Base_OAPDI!$U$5:$U$187,0)),"") | G17: =IFERROR(INDEX(Base_OAPDI!$R$5:$R$187,MATCH($A17,Base_OAPDI!$U$5:$U$187,0)),"") | H17: =IFERROR(INDEX(Base_OAPDI!$N$5:$N$187,MATCH($A17,Base_OAPDI!$U$5:$U$187,0)),"") | I17: =IFERROR(INDEX(Base_OAPDI!$P$5:$P$187,MATCH($A17,Base_OAPDI!$U$5:$U$187,0)),"") | J17: =IFERROR(INDEX(Base_OAPDI!$S$5:$S$187,MATCH($A17,Base_OAPDI!$U$5:$U$187,0)),"") | K17: =IFERROR(INDEX(Base_OAPDI!$T$5:$T$187,MATCH($A17,Base_OAPDI!$U$5:$U$187,0)),"") | L17: =IFERROR(INDEX(Base_OAPDI!$Q$5:$Q$187,MATCH($A17,Base_OAPDI!$U$5:$U$187,0)),"") | N17: 10 | O17: =IFERROR(INDEX(Compromisos_2026!$A$4:$A$77,MATCH($N17,Compromisos_2026!$S$4:$S$77,0))&"","") | P17: =IFERROR(INDEX(Compromisos_2026!$B$4:$B$77,MATCH($N17,Compromisos_2026!$S$4:$S$77,0))&"","") | Q17: =IFERROR(INDEX(Compromisos_2026!$D$4:$D$77,MATCH($N17,Compromisos_2026!$S$4:$S$77,0))&"","") | R17: =IFERROR(INDEX(Compromisos_2026!$I$4:$I$77,MATCH($N17,Compromisos_2026!$S$4:$S$77,0))&"","") | S17: =IFERROR(INDEX(Compromisos_2026!$P$4:$P$77,MATCH($N17,Compromisos_2026!$S$4:$S$77,0))&"","")
A18: 11 | B18: =IFERROR(INDEX(Base_OAPDI!$A$5:$A$187,MATCH($A18,Base_OAPDI!$U$5:$U$187,0)),"") | C18: =IFERROR(INDEX(Base_OAPDI!$C$5:$C$187,MATCH($A18,Base_OAPDI!$U$5:$U$187,0)),"") | D18: =IFERROR(INDEX(Base_OAPDI!$B$5:$B$187,MATCH($A18,Base_OAPDI!$U$5:$U$187,0)),"") | E18: =IFERROR(INDEX(Base_OAPDI!$E$5:$E$187,MATCH($A18,Base_OAPDI!$U$5:$U$187,0)),"") | F18: =IFERROR(INDEX(Base_OAPDI!$H$5:$H$187,MATCH($A18,Base_OAPDI!$U$5:$U$187,0)),"") | G18: =IFERROR(INDEX(Base_OAPDI!$R$5:$R$187,MATCH($A18,Base_OAPDI!$U$5:$U$187,0)),"") | H18: =IFERROR(INDEX(Base_OAPDI!$N$5:$N$187,MATCH($A18,Base_OAPDI!$U$5:$U$187,0)),"") | I18: =IFERROR(INDEX(Base_OAPDI!$P$5:$P$187,MATCH($A18,Base_OAPDI!$U$5:$U$187,0)),"") | J18: =IFERROR(INDEX(Base_OAPDI!$S$5:$S$187,MATCH($A18,Base_OAPDI!$U$5:$U$187,0)),"") | K18: =IFERROR(INDEX(Base_OAPDI!$T$5:$T$187,MATCH($A18,Base_OAPDI!$U$5:$U$187,0)),"") | L18: =IFERROR(INDEX(Base_OAPDI!$Q$5:$Q$187,MATCH($A18,Base_OAPDI!$U$5:$U$187,0)),"") | N18: 11 | O18: =IFERROR(INDEX(Compromisos_2026!$A$4:$A$77,MATCH($N18,Compromisos_2026!$S$4:$S$77,0))&"","") | P18: =IFERROR(INDEX(Compromisos_2026!$B$4:$B$77,MATCH($N18,Compromisos_2026!$S$4:$S$77,0))&"","") | Q18: =IFERROR(INDEX(Compromisos_2026!$D$4:$D$77,MATCH($N18,Compromisos_2026!$S$4:$S$77,0))&"","") | R18: =IFERROR(INDEX(Compromisos_2026!$I$4:$I$77,MATCH($N18,Compromisos_2026!$S$4:$S$77,0))&"","") | S18: =IFERROR(INDEX(Compromisos_2026!$P$4:$P$77,MATCH($N18,Compromisos_2026!$S$4:$S$77,0))&"","")
A19: 12 | B19: =IFERROR(INDEX(Base_OAPDI!$A$5:$A$187,MATCH($A19,Base_OAPDI!$U$5:$U$187,0)),"") | C19: =IFERROR(INDEX(Base_OAPDI!$C$5:$C$187,MATCH($A19,Base_OAPDI!$U$5:$U$187,0)),"") | D19: =IFERROR(INDEX(Base_OAPDI!$B$5:$B$187,MATCH($A19,Base_OAPDI!$U$5:$U$187,0)),"") | E19: =IFERROR(INDEX(Base_OAPDI!$E$5:$E$187,MATCH($A19,Base_OAPDI!$U$5:$U$187,0)),"") | F19: =IFERROR(INDEX(Base_OAPDI!$H$5:$H$187,MATCH($A19,Base_OAPDI!$U$5:$U$187,0)),"") | G19: =IFERROR(INDEX(Base_OAPDI!$R$5:$R$187,MATCH($A19,Base_OAPDI!$U$5:$U$187,0)),"") | H19: =IFERROR(INDEX(Base_OAPDI!$N$5:$N$187,MATCH($A19,Base_OAPDI!$U$5:$U$187,0)),"") | I19: =IFERROR(INDEX(Base_OAPDI!$P$5:$P$187,MATCH($A19,Base_OAPDI!$U$5:$U$187,0)),"") | J19: =IFERROR(INDEX(Base_OAPDI!$S$5:$S$187,MATCH($A19,Base_OAPDI!$U$5:$U$187,0)),"") | K19: =IFERROR(INDEX(Base_OAPDI!$T$5:$T$187,MATCH($A19,Base_OAPDI!$U$5:$U$187,0)),"") | L19: =IFERROR(INDEX(Base_OAPDI!$Q$5:$Q$187,MATCH($A19,Base_OAPDI!$U$5:$U$187,0)),"") | N19: 12 | O19: =IFERROR(INDEX(Compromisos_2026!$A$4:$A$77,MATCH($N19,Compromisos_2026!$S$4:$S$77,0))&"","") | P19: =IFERROR(INDEX(Compromisos_2026!$B$4:$B$77,MATCH($N19,Compromisos_2026!$S$4:$S$77,0))&"","") | Q19: =IFERROR(INDEX(Compromisos_2026!$D$4:$D$77,MATCH($N19,Compromisos_2026!$S$4:$S$77,0))&"","") | R19: =IFERROR(INDEX(Compromisos_2026!$I$4:$I$77,MATCH($N19,Compromisos_2026!$S$4:$S$77,0))&"","") | S19: =IFERROR(INDEX(Compromisos_2026!$P$4:$P$77,MATCH($N19,Compromisos_2026!$S$4:$S$77,0))&"","")
... A32: 25 | B32: =IFERROR(INDEX(Base_OAPDI!$A$5:$A$187,MATCH($A32,Base_OAPDI!$U$5:$U$187,0)),"") | C32: =IFERROR(INDEX(Base_OAPDI!$C$5:$C$187,MATCH($A32,Base_OAPDI!$U$5:$U$187,0)),"") | D32: =IFERROR(INDEX(Base_OAPDI!$B$5:$B$187,MATCH($A32,Base_OAPDI!$U$5:$U$187,0)),"") | E32: =IFERROR(INDEX(Base_OAPDI!$E$5:$E$187,MATCH($A32,Base_OAPDI!$U$5:$U$187,0)),"") | F32: =IFERROR(INDEX(Base_OAPDI!$H$5:$H$187,MATCH($A32,Base_OAPDI!$U$5:$U$187,0)),"") | G32: =IFERROR(INDEX(Base_OAPDI!$R$5:$R$187,MATCH($A32,Base_OAPDI!$U$5:$U$187,0)),"") | H32: =IFERROR(INDEX(Base_OAPDI!$N$5:$N$187,MATCH($A32,Base_OAPDI!$U$5:$U$187,0)),"") | I32: =IFERROR(INDEX(Base_OAPDI!$P$5:$P$187,MATCH($A32,Base_OAPDI!$U$5:$U$187,0)),"") | J32: =IFERROR(INDEX(Base_OAPDI!$S$5:$S$187,MATCH($A32,Base_OAPDI!$U$5:$U$187,0)),"") | K32: =IFERROR(INDEX(Base_OAPDI!$T$5:$T$187,MATCH($A32,Base_OAPDI!$U$5:$U$187,0)),"") | L32: =IFERROR(INDEX(Base_OAPDI!$Q$5:$Q$187,MATCH($A32,Base_OAPDI!$U$5:$U$187,0)),"") | N32: 25 | O32: =IFERROR(INDEX(Compromisos_2026!$A$4:$A$77,MATCH($N32,Compromisos_2026!$S$4:$S$77,0))&"","") | P32: =IFERROR(INDEX(Compromisos_2026!$B$4:$B$77,MATCH($N32,Compromisos_2026!$S$4:$S$77,0))&"","") | Q32: =IFERROR(INDEX(Compromisos_2026!$D$4:$D$77,MATCH($N32,Compromisos_2026!$S$4:$S$77,0))&"","") | R32: =IFERROR(INDEX(Compromisos_2026!$I$4:$I$77,MATCH($N32,Compromisos_2026!$S$4:$S$77,0))&"","") | S32: =IFERROR(INDEX(Compromisos_2026!$P$4:$P$77,MATCH($N32,Compromisos_2026!$S$4:$S$77,0))&"","")
A33: 26 | B33: =IFERROR(INDEX(Base_OAPDI!$A$5:$A$187,MATCH($A33,Base_OAPDI!$U$5:$U$187,0)),"") | C33: =IFERROR(INDEX(Base_OAPDI!$C$5:$C$187,MATCH($A33,Base_OAPDI!$U$5:$U$187,0)),"") | D33: =IFERROR(INDEX(Base_OAPDI!$B$5:$B$187,MATCH($A33,Base_OAPDI!$U$5:$U$187,0)),"") | E33: =IFERROR(INDEX(Base_OAPDI!$E$5:$E$187,MATCH($A33,Base_OAPDI!$U$5:$U$187,0)),"") | F33: =IFERROR(INDEX(Base_OAPDI!$H$5:$H$187,MATCH($A33,Base_OAPDI!$U$5:$U$187,0)),"") | G33: =IFERROR(INDEX(Base_OAPDI!$R$5:$R$187,MATCH($A33,Base_OAPDI!$U$5:$U$187,0)),"") | H33: =IFERROR(INDEX(Base_OAPDI!$N$5:$N$187,MATCH($A33,Base_OAPDI!$U$5:$U$187,0)),"") | I33: =IFERROR(INDEX(Base_OAPDI!$P$5:$P$187,MATCH($A33,Base_OAPDI!$U$5:$U$187,0)),"") | J33: =IFERROR(INDEX(Base_OAPDI!$S$5:$S$187,MATCH($A33,Base_OAPDI!$U$5:$U$187,0)),"") | K33: =IFERROR(INDEX(Base_OAPDI!$T$5:$T$187,MATCH($A33,Base_OAPDI!$U$5:$U$187,0)),"") | L33: =IFERROR(INDEX(Base_OAPDI!$Q$5:$Q$187,MATCH($A33,Base_OAPDI!$U$5:$U$187,0)),"") | N33: La decisión sobre cada compromiso se registra en la hoja Compromisos_2026.
A34: 27 | B34: =IFERROR(INDEX(Base_OAPDI!$A$5:$A$187,MATCH($A34,Base_OAPDI!$U$5:$U$187,0)),"") | C34: =IFERROR(INDEX(Base_OAPDI!$C$5:$C$187,MATCH($A34,Base_OAPDI!$U$5:$U$187,0)),"") | D34: =IFERROR(INDEX(Base_OAPDI!$B$5:$B$187,MATCH($A34,Base_OAPDI!$U$5:$U$187,0)),"") | E34: =IFERROR(INDEX(Base_OAPDI!$E$5:$E$187,MATCH($A34,Base_OAPDI!$U$5:$U$187,0)),"") | F34: =IFERROR(INDEX(Base_OAPDI!$H$5:$H$187,MATCH($A34,Base_OAPDI!$U$5:$U$187,0)),"") | G34: =IFERROR(INDEX(Base_OAPDI!$R$5:$R$187,MATCH($A34,Base_OAPDI!$U$5:$U$187,0)),"") | H34: =IFERROR(INDEX(Base_OAPDI!$N$5:$N$187,MATCH($A34,Base_OAPDI!$U$5:$U$187,0)),"") | I34: =IFERROR(INDEX(Base_OAPDI!$P$5:$P$187,MATCH($A34,Base_OAPDI!$U$5:$U$187,0)),"") | J34: =IFERROR(INDEX(Base_OAPDI!$S$5:$S$187,MATCH($A34,Base_OAPDI!$U$5:$U$187,0)),"") | K34: =IFERROR(INDEX(Base_OAPDI!$T$5:$T$187,MATCH($A34,Base_OAPDI!$U$5:$U$187,0)),"") | L34: =IFERROR(INDEX(Base_OAPDI!$Q$5:$Q$187,MATCH($A34,Base_OAPDI!$U$5:$U$187,0)),"")
A35: 28 | B35: =IFERROR(INDEX(Base_OAPDI!$A$5:$A$187,MATCH($A35,Base_OAPDI!$U$5:$U$187,0)),"") | C35: =IFERROR(INDEX(Base_OAPDI!$C$5:$C$187,MATCH($A35,Base_OAPDI!$U$5:$U$187,0)),"") | D35: =IFERROR(INDEX(Base_OAPDI!$B$5:$B$187,MATCH($A35,Base_OAPDI!$U$5:$U$187,0)),"") | E35: =IFERROR(INDEX(Base_OAPDI!$E$5:$E$187,MATCH($A35,Base_OAPDI!$U$5:$U$187,0)),"") | F35: =IFERROR(INDEX(Base_OAPDI!$H$5:$H$187,MATCH($A35,Base_OAPDI!$U$5:$U$187,0)),"") | G35: =IFERROR(INDEX(Base_OAPDI!$R$5:$R$187,MATCH($A35,Base_OAPDI!$U$5:$U$187,0)),"") | H35: =IFERROR(INDEX(Base_OAPDI!$N$5:$N$187,MATCH($A35,Base_OAPDI!$U$5:$U$187,0)),"") | I35: =IFERROR(INDEX(Base_OAPDI!$P$5:$P$187,MATCH($A35,Base_OAPDI!$U$5:$U$187,0)),"") | J35: =IFERROR(INDEX(Base_OAPDI!$S$5:$S$187,MATCH($A35,Base_OAPDI!$U$5:$U$187,0)),"") | K35: =IFERROR(INDEX(Base_OAPDI!$T$5:$T$187,MATCH($A35,Base_OAPDI!$U$5:$U$187,0)),"") | L35: =IFERROR(INDEX(Base_OAPDI!$Q$5:$Q$187,MATCH($A35,Base_OAPDI!$U$5:$U$187,0)),"")
A36: 29 | B36: =IFERROR(INDEX(Base_OAPDI!$A$5:$A$187,MATCH($A36,Base_OAPDI!$U$5:$U$187,0)),"") | C36: =IFERROR(INDEX(Base_OAPDI!$C$5:$C$187,MATCH($A36,Base_OAPDI!$U$5:$U$187,0)),"") | D36: =IFERROR(INDEX(Base_OAPDI!$B$5:$B$187,MATCH($A36,Base_OAPDI!$U$5:$U$187,0)),"") | E36: =IFERROR(INDEX(Base_OAPDI!$E$5:$E$187,MATCH($A36,Base_OAPDI!$U$5:$U$187,0)),"") | F36: =IFERROR(INDEX(Base_OAPDI!$H$5:$H$187,MATCH($A36,Base_OAPDI!$U$5:$U$187,0)),"") | G36: =IFERROR(INDEX(Base_OAPDI!$R$5:$R$187,MATCH($A36,Base_OAPDI!$U$5:$U$187,0)),"") | H36: =IFERROR(INDEX(Base_OAPDI!$N$5:$N$187,MATCH($A36,Base_OAPDI!$U$5:$U$187,0)),"") | I36: =IFERROR(INDEX(Base_OAPDI!$P$5:$P$187,MATCH($A36,Base_OAPDI!$U$5:$U$187,0)),"") | J36: =IFERROR(INDEX(Base_OAPDI!$S$5:$S$187,MATCH($A36,Base_OAPDI!$U$5:$U$187,0)),"") | K36: =IFERROR(INDEX(Base_OAPDI!$T$5:$T$187,MATCH($A36,Base_OAPDI!$U$5:$U$187,0)),"") | L36: =IFERROR(INDEX(Base_OAPDI!$Q$5:$Q$187,MATCH($A36,Base_OAPDI!$U$5:$U$187,0)),"")
A37: 30 | B37: =IFERROR(INDEX(Base_OAPDI!$A$5:$A$187,MATCH($A37,Base_OAPDI!$U$5:$U$187,0)),"") | C37: =IFERROR(INDEX(Base_OAPDI!$C$5:$C$187,MATCH($A37,Base_OAPDI!$U$5:$U$187,0)),"") | D37: =IFERROR(INDEX(Base_OAPDI!$B$5:$B$187,MATCH($A37,Base_OAPDI!$U$5:$U$187,0)),"") | E37: =IFERROR(INDEX(Base_OAPDI!$E$5:$E$187,MATCH($A37,Base_OAPDI!$U$5:$U$187,0)),"") | F37: =IFERROR(INDEX(Base_OAPDI!$H$5:$H$187,MATCH($A37,Base_OAPDI!$U$5:$U$187,0)),"") | G37: =IFERROR(INDEX(Base_OAPDI!$R$5:$R$187,MATCH($A37,Base_OAPDI!$U$5:$U$187,0)),"") | H37: =IFERROR(INDEX(Base_OAPDI!$N$5:$N$187,MATCH($A37,Base_OAPDI!$U$5:$U$187,0)),"") | I37: =IFERROR(INDEX(Base_OAPDI!$P$5:$P$187,MATCH($A37,Base_OAPDI!$U$5:$U$187,0)),"") | J37: =IFERROR(INDEX(Base_OAPDI!$S$5:$S$187,MATCH($A37,Base_OAPDI!$U$5:$U$187,0)),"") | K37: =IFERROR(INDEX(Base_OAPDI!$T$5:$T$187,MATCH($A37,Base_OAPDI!$U$5:$U$187,0)),"") | L37: =IFERROR(INDEX(Base_OAPDI!$Q$5:$Q$187,MATCH($A37,Base_OAPDI!$U$5:$U$187,0)),"")
A38: 31 | B38: =IFERROR(INDEX(Base_OAPDI!$A$5:$A$187,MATCH($A38,Base_OAPDI!$U$5:$U$187,0)),"") | C38: =IFERROR(INDEX(Base_OAPDI!$C$5:$C$187,MATCH($A38,Base_OAPDI!$U$5:$U$187,0)),"") | D38: =IFERROR(INDEX(Base_OAPDI!$B$5:$B$187,MATCH($A38,Base_OAPDI!$U$5:$U$187,0)),"") | E38: =IFERROR(INDEX(Base_OAPDI!$E$5:$E$187,MATCH($A38,Base_OAPDI!$U$5:$U$187,0)),"") | F38: =IFERROR(INDEX(Base_OAPDI!$H$5:$H$187,MATCH($A38,Base_OAPDI!$U$5:$U$187,0)),"") | G38: =IFERROR(INDEX(Base_OAPDI!$R$5:$R$187,MATCH($A38,Base_OAPDI!$U$5:$U$187,0)),"") | H38: =IFERROR(INDEX(Base_OAPDI!$N$5:$N$187,MATCH($A38,Base_OAPDI!$U$5:$U$187,0)),"") | I38: =IFERROR(INDEX(Base_OAPDI!$P$5:$P$187,MATCH($A38,Base_OAPDI!$U$5:$U$187,0)),"") | J38: =IFERROR(INDEX(Base_OAPDI!$S$5:$S$187,MATCH($A38,Base_OAPDI!$U$5:$U$187,0)),"") | K38: =IFERROR(INDEX(Base_OAPDI!$T$5:$T$187,MATCH($A38,Base_OAPDI!$U$5:$U$187,0)),"") | L38: =IFERROR(INDEX(Base_OAPDI!$Q$5:$Q$187,MATCH($A38,Base_OAPDI!$U$5:$U$187,0)),"")
A39: 32 | B39: =IFERROR(INDEX(Base_OAPDI!$A$5:$A$187,MATCH($A39,Base_OAPDI!$U$5:$U$187,0)),"") | C39: =IFERROR(INDEX(Base_OAPDI!$C$5:$C$187,MATCH($A39,Base_OAPDI!$U$5:$U$187,0)),"") | D39: =IFERROR(INDEX(Base_OAPDI!$B$5:$B$187,MATCH($A39,Base_OAPDI!$U$5:$U$187,0)),"") | E39: =IFERROR(INDEX(Base_OAPDI!$E$5:$E$187,MATCH($A39,Base_OAPDI!$U$5:$U$187,0)),"") | F39: =IFERROR(INDEX(Base_OAPDI!$H$5:$H$187,MATCH($A39,Base_OAPDI!$U$5:$U$187,0)),"") | G39: =IFERROR(INDEX(Base_OAPDI!$R$5:$R$187,MATCH($A39,Base_OAPDI!$U$5:$U$187,0)),"") | H39: =IFERROR(INDEX(Base_OAPDI!$N$5:$N$187,MATCH($A39,Base_OAPDI!$U$5:$U$187,0)),"") | I39: =IFERROR(INDEX(Base_OAPDI!$P$5:$P$187,MATCH($A39,Base_OAPDI!$U$5:$U$187,0)),"") | J39: =IFERROR(INDEX(Base_OAPDI!$S$5:$S$187,MATCH($A39,Base_OAPDI!$U$5:$U$187,0)),"") | K39: =IFERROR(INDEX(Base_OAPDI!$T$5:$T$187,MATCH($A39,Base_OAPDI!$U$5:$U$187,0)),"") | L39: =IFERROR(INDEX(Base_OAPDI!$Q$5:$Q$187,MATCH($A39,Base_OAPDI!$U$5:$U$187,0)),"")
A40: 33 | B40: =IFERROR(INDEX(Base_OAPDI!$A$5:$A$187,MATCH($A40,Base_OAPDI!$U$5:$U$187,0)),"") | C40: =IFERROR(INDEX(Base_OAPDI!$C$5:$C$187,MATCH($A40,Base_OAPDI!$U$5:$U$187,0)),"") | D40: =IFERROR(INDEX(Base_OAPDI!$B$5:$B$187,MATCH($A40,Base_OAPDI!$U$5:$U$187,0)),"") | E40: =IFERROR(INDEX(Base_OAPDI!$E$5:$E$187,MATCH($A40,Base_OAPDI!$U$5:$U$187,0)),"") | F40: =IFERROR(INDEX(Base_OAPDI!$H$5:$H$187,MATCH($A40,Base_OAPDI!$U$5:$U$187,0)),"") | G40: =IFERROR(INDEX(Base_OAPDI!$R$5:$R$187,MATCH($A40,Base_OAPDI!$U$5:$U$187,0)),"") | H40: =IFERROR(INDEX(Base_OAPDI!$N$5:$N$187,MATCH($A40,Base_OAPDI!$U$5:$U$187,0)),"") | I40: =IFERROR(INDEX(Base_OAPDI!$P$5:$P$187,MATCH($A40,Base_OAPDI!$U$5:$U$187,0)),"") | J40: =IFERROR(INDEX(Base_OAPDI!$S$5:$S$187,MATCH($A40,Base_OAPDI!$U$5:$U$187,0)),"") | K40: =IFERROR(INDEX(Base_OAPDI!$T$5:$T$187,MATCH($A40,Base_OAPDI!$U$5:$U$187,0)),"") | L40: =IFERROR(INDEX(Base_OAPDI!$Q$5:$Q$187,MATCH($A40,Base_OAPDI!$U$5:$U$187,0)),"")
A41: 34 | B41: =IFERROR(INDEX(Base_OAPDI!$A$5:$A$187,MATCH($A41,Base_OAPDI!$U$5:$U$187,0)),"") | C41: =IFERROR(INDEX(Base_OAPDI!$C$5:$C$187,MATCH($A41,Base_OAPDI!$U$5:$U$187,0)),"") | D41: =IFERROR(INDEX(Base_OAPDI!$B$5:$B$187,MATCH($A41,Base_OAPDI!$U$5:$U$187,0)),"") | E41: =IFERROR(INDEX(Base_OAPDI!$E$5:$E$187,MATCH($A41,Base_OAPDI!$U$5:$U$187,0)),"") | F41: =IFERROR(INDEX(Base_OAPDI!$H$5:$H$187,MATCH($A41,Base_OAPDI!$U$5:$U$187,0)),"") | G41: =IFERROR(INDEX(Base_OAPDI!$R$5:$R$187,MATCH($A41,Base_OAPDI!$U$5:$U$187,0)),"") | H41: =IFERROR(INDEX(Base_OAPDI!$N$5:$N$187,MATCH($A41,Base_OAPDI!$U$5:$U$187,0)),"") | I41: =IFERROR(INDEX(Base_OAPDI!$P$5:$P$187,MATCH($A41,Base_OAPDI!$U$5:$U$187,0)),"") | J41: =IFERROR(INDEX(Base_OAPDI!$S$5:$S$187,MATCH($A41,Base_OAPDI!$U$5:$U$187,0)),"") | K41: =IFERROR(INDEX(Base_OAPDI!$T$5:$T$187,MATCH($A41,Base_OAPDI!$U$5:$U$187,0)),"") | L41: =IFERROR(INDEX(Base_OAPDI!$Q$5:$Q$187,MATCH($A41,Base_OAPDI!$U$5:$U$187,0)),"")
A42: 35 | B42: =IFERROR(INDEX(Base_OAPDI!$A$5:$A$187,MATCH($A42,Base_OAPDI!$U$5:$U$187,0)),"") | C42: =IFERROR(INDEX(Base_OAPDI!$C$5:$C$187,MATCH($A42,Base_OAPDI!$U$5:$U$187,0)),"") | D42: =IFERROR(INDEX(Base_OAPDI!$B$5:$B$187,MATCH($A42,Base_OAPDI!$U$5:$U$187,0)),"") | E42: =IFERROR(INDEX(Base_OAPDI!$E$5:$E$187,MATCH($A42,Base_OAPDI!$U$5:$U$187,0)),"") | F42: =IFERROR(INDEX(Base_OAPDI!$H$5:$H$187,MATCH($A42,Base_OAPDI!$U$5:$U$187,0)),"") | G42: =IFERROR(INDEX(Base_OAPDI!$R$5:$R$187,MATCH($A42,Base_OAPDI!$U$5:$U$187,0)),"") | H42: =IFERROR(INDEX(Base_OAPDI!$N$5:$N$187,MATCH($A42,Base_OAPDI!$U$5:$U$187,0)),"") | I42: =IFERROR(INDEX(Base_OAPDI!$P$5:$P$187,MATCH($A42,Base_OAPDI!$U$5:$U$187,0)),"") | J42: =IFERROR(INDEX(Base_OAPDI!$S$5:$S$187,MATCH($A42,Base_OAPDI!$U$5:$U$187,0)),"") | K42: =IFERROR(INDEX(Base_OAPDI!$T$5:$T$187,MATCH($A42,Base_OAPDI!$U$5:$U$187,0)),"") | L42: =IFERROR(INDEX(Base_OAPDI!$Q$5:$Q$187,MATCH($A42,Base_OAPDI!$U$5:$U$187,0)),"")
A43: 36 | B43: =IFERROR(INDEX(Base_OAPDI!$A$5:$A$187,MATCH($A43,Base_OAPDI!$U$5:$U$187,0)),"") | C43: =IFERROR(INDEX(Base_OAPDI!$C$5:$C$187,MATCH($A43,Base_OAPDI!$U$5:$U$187,0)),"") | D43: =IFERROR(INDEX(Base_OAPDI!$B$5:$B$187,MATCH($A43,Base_OAPDI!$U$5:$U$187,0)),"") | E43: =IFERROR(INDEX(Base_OAPDI!$E$5:$E$187,MATCH($A43,Base_OAPDI!$U$5:$U$187,0)),"") | F43: =IFERROR(INDEX(Base_OAPDI!$H$5:$H$187,MATCH($A43,Base_OAPDI!$U$5:$U$187,0)),"") | G43: =IFERROR(INDEX(Base_OAPDI!$R$5:$R$187,MATCH($A43,Base_OAPDI!$U$5:$U$187,0)),"") | H43: =IFERROR(INDEX(Base_OAPDI!$N$5:$N$187,MATCH($A43,Base_OAPDI!$U$5:$U$187,0)),"") | I43: =IFERROR(INDEX(Base_OAPDI!$P$5:$P$187,MATCH($A43,Base_OAPDI!$U$5:$U$187,0)),"") | J43: =IFERROR(INDEX(Base_OAPDI!$S$5:$S$187,MATCH($A43,Base_OAPDI!$U$5:$U$187,0)),"") | K43: =IFERROR(INDEX(Base_OAPDI!$T$5:$T$187,MATCH($A43,Base_OAPDI!$U$5:$U$187,0)),"") | L43: =IFERROR(INDEX(Base_OAPDI!$Q$5:$Q$187,MATCH($A43,Base_OAPDI!$U$5:$U$187,0)),"")
A44: 37 | B44: =IFERROR(INDEX(Base_OAPDI!$A$5:$A$187,MATCH($A44,Base_OAPDI!$U$5:$U$187,0)),"") | C44: =IFERROR(INDEX(Base_OAPDI!$C$5:$C$187,MATCH($A44,Base_OAPDI!$U$5:$U$187,0)),"") | D44: =IFERROR(INDEX(Base_OAPDI!$B$5:$B$187,MATCH($A44,Base_OAPDI!$U$5:$U$187,0)),"") | E44: =IFERROR(INDEX(Base_OAPDI!$E$5:$E$187,MATCH($A44,Base_OAPDI!$U$5:$U$187,0)),"") | F44: =IFERROR(INDEX(Base_OAPDI!$H$5:$H$187,MATCH($A44,Base_OAPDI!$U$5:$U$187,0)),"") | G44: =IFERROR(INDEX(Base_OAPDI!$R$5:$R$187,MATCH($A44,Base_OAPDI!$U$5:$U$187,0)),"") | H44: =IFERROR(INDEX(Base_OAPDI!$N$5:$N$187,MATCH($A44,Base_OAPDI!$U$5:$U$187,0)),"") | I44: =IFERROR(INDEX(Base_OAPDI!$P$5:$P$187,MATCH($A44,Base_OAPDI!$U$5:$U$187,0)),"") | J44: =IFERROR(INDEX(Base_OAPDI!$S$5:$S$187,MATCH($A44,Base_OAPDI!$U$5:$U$187,0)),"") | K44: =IFERROR(INDEX(Base_OAPDI!$T$5:$T$187,MATCH($A44,Base_OAPDI!$U$5:$U$187,0)),"") | L44: =IFERROR(INDEX(Base_OAPDI!$Q$5:$Q$187,MATCH($A44,Base_OAPDI!$U$5:$U$187,0)),"")
A45: 38 | B45: =IFERROR(INDEX(Base_OAPDI!$A$5:$A$187,MATCH($A45,Base_OAPDI!$U$5:$U$187,0)),"") | C45: =IFERROR(INDEX(Base_OAPDI!$C$5:$C$187,MATCH($A45,Base_OAPDI!$U$5:$U$187,0)),"") | D45: =IFERROR(INDEX(Base_OAPDI!$B$5:$B$187,MATCH($A45,Base_OAPDI!$U$5:$U$187,0)),"") | E45: =IFERROR(INDEX(Base_OAPDI!$E$5:$E$187,MATCH($A45,Base_OAPDI!$U$5:$U$187,0)),"") | F45: =IFERROR(INDEX(Base_OAPDI!$H$5:$H$187,MATCH($A45,Base_OAPDI!$U$5:$U$187,0)),"") | G45: =IFERROR(INDEX(Base_OAPDI!$R$5:$R$187,MATCH($A45,Base_OAPDI!$U$5:$U$187,0)),"") | H45: =IFERROR(INDEX(Base_OAPDI!$N$5:$N$187,MATCH($A45,Base_OAPDI!$U$5:$U$187,0)),"") | I45: =IFERROR(INDEX(Base_OAPDI!$P$5:$P$187,MATCH($A45,Base_OAPDI!$U$5:$U$187,0)),"") | J45: =IFERROR(INDEX(Base_OAPDI!$S$5:$S$187,MATCH($A45,Base_OAPDI!$U$5:$U$187,0)),"") | K45: =IFERROR(INDEX(Base_OAPDI!$T$5:$T$187,MATCH($A45,Base_OAPDI!$U$5:$U$187,0)),"") | L45: =IFERROR(INDEX(Base_OAPDI!$Q$5:$Q$187,MATCH($A45,Base_OAPDI!$U$5:$U$187,0)),"")
... A47: 40 | B47: =IFERROR(INDEX(Base_OAPDI!$A$5:$A$187,MATCH($A47,Base_OAPDI!$U$5:$U$187,0)),"") | C47: =IFERROR(INDEX(Base_OAPDI!$C$5:$C$187,MATCH($A47,Base_OAPDI!$U$5:$U$187,0)),"") | D47: =IFERROR(INDEX(Base_OAPDI!$B$5:$B$187,MATCH($A47,Base_OAPDI!$U$5:$U$187,0)),"") | E47: =IFERROR(INDEX(Base_OAPDI!$E$5:$E$187,MATCH($A47,Base_OAPDI!$U$5:$U$187,0)),"") | F47: =IFERROR(INDEX(Base_OAPDI!$H$5:$H$187,MATCH($A47,Base_OAPDI!$U$5:$U$187,0)),"") | G47: =IFERROR(INDEX(Base_OAPDI!$R$5:$R$187,MATCH($A47,Base_OAPDI!$U$5:$U$187,0)),"") | H47: =IFERROR(INDEX(Base_OAPDI!$N$5:$N$187,MATCH($A47,Base_OAPDI!$U$5:$U$187,0)),"") | I47: =IFERROR(INDEX(Base_OAPDI!$P$5:$P$187,MATCH($A47,Base_OAPDI!$U$5:$U$187,0)),"") | J47: =IFERROR(INDEX(Base_OAPDI!$S$5:$S$187,MATCH($A47,Base_OAPDI!$U$5:$U$187,0)),"") | K47: =IFERROR(INDEX(Base_OAPDI!$T$5:$T$187,MATCH($A47,Base_OAPDI!$U$5:$U$187,0)),"") | L47: =IFERROR(INDEX(Base_OAPDI!$Q$5:$Q$187,MATCH($A47,Base_OAPDI!$U$5:$U$187,0)),"")
A49: ACCIONES ADICIONALES DEL ÁREA (diligenciar)
A50: N.° | B50: Área funcional (lista) | C50: Código de meta PDI (lista) | D50: Eje | E50: Línea | F50: Meta estratégica (PDI) | G50: Origen de la acción | H50: Nombre de la acción | I50: Descripción de la acción | J50: Producto esperado | K50: Fecha de inicio (dd/mm/aaaa) | L50: Fecha de fin (dd/mm/aaaa) | M50: Responsable (correo institucional) | N50: Indicador de seguimiento | O50: Meta 2027 de la acción | P50: Unidad de medida | Q50: Dimensión de impacto | R50: Indicador de impacto (Guía Metodológica) | S50: Categoría de impacto (automática) | T50: ¿Retoma un compromiso pendiente 2026? | U50: Evidencia verificable | V50: Observaciones | W50: Alerta de consistencia
A51: 1 | D51: =IF(C51="","",INDEX(Catalogos!$C$5:$C$49,MATCH(LEFT(C51,7),Catalogos!$A$5:$A$49,0))) | E51: =IF(C51="","",INDEX(Catalogos!$D$5:$D$49,MATCH(LEFT(C51,7),Catalogos!$A$5:$A$49,0))&" "&INDEX(Catalogos!$E$5:$E$49,MATCH(LEFT(C51,7),Catalogos!$A$5:$A$49,0))) | F51: =IF(C51="","",INDEX(Catalogos!$F$5:$F$49,MATCH(LEFT(C51,7),Catalogos!$A$5:$A$49,0))) | S51: =IF(R51="","",INDEX(Catalogos!$Y$5:$Y$25,MATCH(R51,L_IMP,0))) | W51: =IF(H51="","Pendiente por formular",IF(OR(J51="",K51="",L51="",M51="",N51="",O51="",Q51="",R51="",B51="",C51="",G51=""),"Incompleta: faltan campos obligatorios",IF(OR(NOT(ISNUMBER(K51)),NOT(ISNUMBER(L51))),"Fecha inválida",IF(L51<K51,"La fecha de fin es anterior a la de inicio",IF(OR(YEAR(K51)<>2027,YEAR(L51)<>2027),"Fechas fuera de la vigencia 2027",IF(ISERROR(SEARCH("@itc.edu.co",M51)),"El responsable no tiene correo institucional",IF(ISERROR(SEARCH(Q51,INDEX(Catalogos!$Z$5:$Z$25,MATCH(R51,L_IMP,0)))),"La dimensión no corresponde al indicador de impacto","OK"))))))) -> Pendiente por formular
A52: 2 | D52: =IF(C52="","",INDEX(Catalogos!$C$5:$C$49,MATCH(LEFT(C52,7),Catalogos!$A$5:$A$49,0))) | E52: =IF(C52="","",INDEX(Catalogos!$D$5:$D$49,MATCH(LEFT(C52,7),Catalogos!$A$5:$A$49,0))&" "&INDEX(Catalogos!$E$5:$E$49,MATCH(LEFT(C52,7),Catalogos!$A$5:$A$49,0))) | F52: =IF(C52="","",INDEX(Catalogos!$F$5:$F$49,MATCH(LEFT(C52,7),Catalogos!$A$5:$A$49,0))) | S52: =IF(R52="","",INDEX(Catalogos!$Y$5:$Y$25,MATCH(R52,L_IMP,0))) | W52: =IF(H52="","Pendiente por formular",IF(OR(J52="",K52="",L52="",M52="",N52="",O52="",Q52="",R52="",B52="",C52="",G52=""),"Incompleta: faltan campos obligatorios",IF(OR(NOT(ISNUMBER(K52)),NOT(ISNUMBER(L52))),"Fecha inválida",IF(L52<K52,"La fecha de fin es anterior a la de inicio",IF(OR(YEAR(K52)<>2027,YEAR(L52)<>2027),"Fechas fuera de la vigencia 2027",IF(ISERROR(SEARCH("@itc.edu.co",M52)),"El responsable no tiene correo institucional",IF(ISERROR(SEARCH(Q52,INDEX(Catalogos!$Z$5:$Z$25,MATCH(R52,L_IMP,0)))),"La dimensión no corresponde al indicador de impacto","OK"))))))) -> Pendiente por formular
A53: 3 | D53: =IF(C53="","",INDEX(Catalogos!$C$5:$C$49,MATCH(LEFT(C53,7),Catalogos!$A$5:$A$49,0))) | E53: =IF(C53="","",INDEX(Catalogos!$D$5:$D$49,MATCH(LEFT(C53,7),Catalogos!$A$5:$A$49,0))&" "&INDEX(Catalogos!$E$5:$E$49,MATCH(LEFT(C53,7),Catalogos!$A$5:$A$49,0))) | F53: =IF(C53="","",INDEX(Catalogos!$F$5:$F$49,MATCH(LEFT(C53,7),Catalogos!$A$5:$A$49,0))) | S53: =IF(R53="","",INDEX(Catalogos!$Y$5:$Y$25,MATCH(R53,L_IMP,0))) | W53: =IF(H53="","Pendiente por formular",IF(OR(J53="",K53="",L53="",M53="",N53="",O53="",Q53="",R53="",B53="",C53="",G53=""),"Incompleta: faltan campos obligatorios",IF(OR(NOT(ISNUMBER(K53)),NOT(ISNUMBER(L53))),"Fecha inválida",IF(L53<K53,"La fecha de fin es anterior a la de inicio",IF(OR(YEAR(K53)<>2027,YEAR(L53)<>2027),"Fechas fuera de la vigencia 2027",IF(ISERROR(SEARCH("@itc.edu.co",M53)),"El responsable no tiene correo institucional",IF(ISERROR(SEARCH(Q53,INDEX(Catalogos!$Z$5:$Z$25,MATCH(R53,L_IMP,0)))),"La dimensión no corresponde al indicador de impacto","OK"))))))) -> Pendiente por formular
A54: 4 | D54: =IF(C54="","",INDEX(Catalogos!$C$5:$C$49,MATCH(LEFT(C54,7),Catalogos!$A$5:$A$49,0))) | E54: =IF(C54="","",INDEX(Catalogos!$D$5:$D$49,MATCH(LEFT(C54,7),Catalogos!$A$5:$A$49,0))&" "&INDEX(Catalogos!$E$5:$E$49,MATCH(LEFT(C54,7),Catalogos!$A$5:$A$49,0))) | F54: =IF(C54="","",INDEX(Catalogos!$F$5:$F$49,MATCH(LEFT(C54,7),Catalogos!$A$5:$A$49,0))) | S54: =IF(R54="","",INDEX(Catalogos!$Y$5:$Y$25,MATCH(R54,L_IMP,0))) | W54: =IF(H54="","Pendiente por formular",IF(OR(J54="",K54="",L54="",M54="",N54="",O54="",Q54="",R54="",B54="",C54="",G54=""),"Incompleta: faltan campos obligatorios",IF(OR(NOT(ISNUMBER(K54)),NOT(ISNUMBER(L54))),"Fecha inválida",IF(L54<K54,"La fecha de fin es anterior a la de inicio",IF(OR(YEAR(K54)<>2027,YEAR(L54)<>2027),"Fechas fuera de la vigencia 2027",IF(ISERROR(SEARCH("@itc.edu.co",M54)),"El responsable no tiene correo institucional",IF(ISERROR(SEARCH(Q54,INDEX(Catalogos!$Z$5:$Z$25,MATCH(R54,L_IMP,0)))),"La dimensión no corresponde al indicador de impacto","OK"))))))) -> Pendiente por formular
A55: 5 | D55: =IF(C55="","",INDEX(Catalogos!$C$5:$C$49,MATCH(LEFT(C55,7),Catalogos!$A$5:$A$49,0))) | E55: =IF(C55="","",INDEX(Catalogos!$D$5:$D$49,MATCH(LEFT(C55,7),Catalogos!$A$5:$A$49,0))&" "&INDEX(Catalogos!$E$5:$E$49,MATCH(LEFT(C55,7),Catalogos!$A$5:$A$49,0))) | F55: =IF(C55="","",INDEX(Catalogos!$F$5:$F$49,MATCH(LEFT(C55,7),Catalogos!$A$5:$A$49,0))) | S55: =IF(R55="","",INDEX(Catalogos!$Y$5:$Y$25,MATCH(R55,L_IMP,0))) | W55: =IF(H55="","Pendiente por formular",IF(OR(J55="",K55="",L55="",M55="",N55="",O55="",Q55="",R55="",B55="",C55="",G55=""),"Incompleta: faltan campos obligatorios",IF(OR(NOT(ISNUMBER(K55)),NOT(ISNUMBER(L55))),"Fecha inválida",IF(L55<K55,"La fecha de fin es anterior a la de inicio",IF(OR(YEAR(K55)<>2027,YEAR(L55)<>2027),"Fechas fuera de la vigencia 2027",IF(ISERROR(SEARCH("@itc.edu.co",M55)),"El responsable no tiene correo institucional",IF(ISERROR(SEARCH(Q55,INDEX(Catalogos!$Z$5:$Z$25,MATCH(R55,L_IMP,0)))),"La dimensión no corresponde al indicador de impacto","OK"))))))) -> Pendiente por formular
A56: 6 | D56: =IF(C56="","",INDEX(Catalogos!$C$5:$C$49,MATCH(LEFT(C56,7),Catalogos!$A$5:$A$49,0))) | E56: =IF(C56="","",INDEX(Catalogos!$D$5:$D$49,MATCH(LEFT(C56,7),Catalogos!$A$5:$A$49,0))&" "&INDEX(Catalogos!$E$5:$E$49,MATCH(LEFT(C56,7),Catalogos!$A$5:$A$49,0))) | F56: =IF(C56="","",INDEX(Catalogos!$F$5:$F$49,MATCH(LEFT(C56,7),Catalogos!$A$5:$A$49,0))) | S56: =IF(R56="","",INDEX(Catalogos!$Y$5:$Y$25,MATCH(R56,L_IMP,0))) | W56: =IF(H56="","Pendiente por formular",IF(OR(J56="",K56="",L56="",M56="",N56="",O56="",Q56="",R56="",B56="",C56="",G56=""),"Incompleta: faltan campos obligatorios",IF(OR(NOT(ISNUMBER(K56)),NOT(ISNUMBER(L56))),"Fecha inválida",IF(L56<K56,"La fecha de fin es anterior a la de inicio",IF(OR(YEAR(K56)<>2027,YEAR(L56)<>2027),"Fechas fuera de la vigencia 2027",IF(ISERROR(SEARCH("@itc.edu.co",M56)),"El responsable no tiene correo institucional",IF(ISERROR(SEARCH(Q56,INDEX(Catalogos!$Z$5:$Z$25,MATCH(R56,L_IMP,0)))),"La dimensión no corresponde al indicador de impacto","OK"))))))) -> Pendiente por formular
A57: 7 | D57: =IF(C57="","",INDEX(Catalogos!$C$5:$C$49,MATCH(LEFT(C57,7),Catalogos!$A$5:$A$49,0))) | E57: =IF(C57="","",INDEX(Catalogos!$D$5:$D$49,MATCH(LEFT(C57,7),Catalogos!$A$5:$A$49,0))&" "&INDEX(Catalogos!$E$5:$E$49,MATCH(LEFT(C57,7),Catalogos!$A$5:$A$49,0))) | F57: =IF(C57="","",INDEX(Catalogos!$F$5:$F$49,MATCH(LEFT(C57,7),Catalogos!$A$5:$A$49,0))) | S57: =IF(R57="","",INDEX(Catalogos!$Y$5:$Y$25,MATCH(R57,L_IMP,0))) | W57: =IF(H57="","Pendiente por formular",IF(OR(J57="",K57="",L57="",M57="",N57="",O57="",Q57="",R57="",B57="",C57="",G57=""),"Incompleta: faltan campos obligatorios",IF(OR(NOT(ISNUMBER(K57)),NOT(ISNUMBER(L57))),"Fecha inválida",IF(L57<K57,"La fecha de fin es anterior a la de inicio",IF(OR(YEAR(K57)<>2027,YEAR(L57)<>2027),"Fechas fuera de la vigencia 2027",IF(ISERROR(SEARCH("@itc.edu.co",M57)),"El responsable no tiene correo institucional",IF(ISERROR(SEARCH(Q57,INDEX(Catalogos!$Z$5:$Z$25,MATCH(R57,L_IMP,0)))),"La dimensión no corresponde al indicador de impacto","OK"))))))) -> Pendiente por formular
A58: 8 | D58: =IF(C58="","",INDEX(Catalogos!$C$5:$C$49,MATCH(LEFT(C58,7),Catalogos!$A$5:$A$49,0))) | E58: =IF(C58="","",INDEX(Catalogos!$D$5:$D$49,MATCH(LEFT(C58,7),Catalogos!$A$5:$A$49,0))&" "&INDEX(Catalogos!$E$5:$E$49,MATCH(LEFT(C58,7),Catalogos!$A$5:$A$49,0))) | F58: =IF(C58="","",INDEX(Catalogos!$F$5:$F$49,MATCH(LEFT(C58,7),Catalogos!$A$5:$A$49,0))) | S58: =IF(R58="","",INDEX(Catalogos!$Y$5:$Y$25,MATCH(R58,L_IMP,0))) | W58: =IF(H58="","Pendiente por formular",IF(OR(J58="",K58="",L58="",M58="",N58="",O58="",Q58="",R58="",B58="",C58="",G58=""),"Incompleta: faltan campos obligatorios",IF(OR(NOT(ISNUMBER(K58)),NOT(ISNUMBER(L58))),"Fecha inválida",IF(L58<K58,"La fecha de fin es anterior a la de inicio",IF(OR(YEAR(K58)<>2027,YEAR(L58)<>2027),"Fechas fuera de la vigencia 2027",IF(ISERROR(SEARCH("@itc.edu.co",M58)),"El responsable no tiene correo institucional",IF(ISERROR(SEARCH(Q58,INDEX(Catalogos!$Z$5:$Z$25,MATCH(R58,L_IMP,0)))),"La dimensión no corresponde al indicador de impacto","OK"))))))) -> Pendiente por formular
A59: 9 | D59: =IF(C59="","",INDEX(Catalogos!$C$5:$C$49,MATCH(LEFT(C59,7),Catalogos!$A$5:$A$49,0))) | E59: =IF(C59="","",INDEX(Catalogos!$D$5:$D$49,MATCH(LEFT(C59,7),Catalogos!$A$5:$A$49,0))&" "&INDEX(Catalogos!$E$5:$E$49,MATCH(LEFT(C59,7),Catalogos!$A$5:$A$49,0))) | F59: =IF(C59="","",INDEX(Catalogos!$F$5:$F$49,MATCH(LEFT(C59,7),Catalogos!$A$5:$A$49,0))) | S59: =IF(R59="","",INDEX(Catalogos!$Y$5:$Y$25,MATCH(R59,L_IMP,0))) | W59: =IF(H59="","Pendiente por formular",IF(OR(J59="",K59="",L59="",M59="",N59="",O59="",Q59="",R59="",B59="",C59="",G59=""),"Incompleta: faltan campos obligatorios",IF(OR(NOT(ISNUMBER(K59)),NOT(ISNUMBER(L59))),"Fecha inválida",IF(L59<K59,"La fecha de fin es anterior a la de inicio",IF(OR(YEAR(K59)<>2027,YEAR(L59)<>2027),"Fechas fuera de la vigencia 2027",IF(ISERROR(SEARCH("@itc.edu.co",M59)),"El responsable no tiene correo institucional",IF(ISERROR(SEARCH(Q59,INDEX(Catalogos!$Z$5:$Z$25,MATCH(R59,L_IMP,0)))),"La dimensión no corresponde al indicador de impacto","OK"))))))) -> Pendiente por formular
A60: 10 | D60: =IF(C60="","",INDEX(Catalogos!$C$5:$C$49,MATCH(LEFT(C60,7),Catalogos!$A$5:$A$49,0))) | E60: =IF(C60="","",INDEX(Catalogos!$D$5:$D$49,MATCH(LEFT(C60,7),Catalogos!$A$5:$A$49,0))&" "&INDEX(Catalogos!$E$5:$E$49,MATCH(LEFT(C60,7),Catalogos!$A$5:$A$49,0))) | F60: =IF(C60="","",INDEX(Catalogos!$F$5:$F$49,MATCH(LEFT(C60,7),Catalogos!$A$5:$A$49,0))) | S60: =IF(R60="","",INDEX(Catalogos!$Y$5:$Y$25,MATCH(R60,L_IMP,0))) | W60: =IF(H60="","Pendiente por formular",IF(OR(J60="",K60="",L60="",M60="",N60="",O60="",Q60="",R60="",B60="",C60="",G60=""),"Incompleta: faltan campos obligatorios",IF(OR(NOT(ISNUMBER(K60)),NOT(ISNUMBER(L60))),"Fecha inválida",IF(L60<K60,"La fecha de fin es anterior a la de inicio",IF(OR(YEAR(K60)<>2027,YEAR(L60)<>2027),"Fechas fuera de la vigencia 2027",IF(ISERROR(SEARCH("@itc.edu.co",M60)),"El responsable no tiene correo institucional",IF(ISERROR(SEARCH(Q60,INDEX(Catalogos!$Z$5:$Z$25,MATCH(R60,L_IMP,0)))),"La dimensión no corresponde al indicador de impacto","OK"))))))) -> Pendiente por formular
A61: 11 | D61: =IF(C61="","",INDEX(Catalogos!$C$5:$C$49,MATCH(LEFT(C61,7),Catalogos!$A$5:$A$49,0))) | E61: =IF(C61="","",INDEX(Catalogos!$D$5:$D$49,MATCH(LEFT(C61,7),Catalogos!$A$5:$A$49,0))&" "&INDEX(Catalogos!$E$5:$E$49,MATCH(LEFT(C61,7),Catalogos!$A$5:$A$49,0))) | F61: =IF(C61="","",INDEX(Catalogos!$F$5:$F$49,MATCH(LEFT(C61,7),Catalogos!$A$5:$A$49,0))) | S61: =IF(R61="","",INDEX(Catalogos!$Y$5:$Y$25,MATCH(R61,L_IMP,0))) | W61: =IF(H61="","Pendiente por formular",IF(OR(J61="",K61="",L61="",M61="",N61="",O61="",Q61="",R61="",B61="",C61="",G61=""),"Incompleta: faltan campos obligatorios",IF(OR(NOT(ISNUMBER(K61)),NOT(ISNUMBER(L61))),"Fecha inválida",IF(L61<K61,"La fecha de fin es anterior a la de inicio",IF(OR(YEAR(K61)<>2027,YEAR(L61)<>2027),"Fechas fuera de la vigencia 2027",IF(ISERROR(SEARCH("@itc.edu.co",M61)),"El responsable no tiene correo institucional",IF(ISERROR(SEARCH(Q61,INDEX(Catalogos!$Z$5:$Z$25,MATCH(R61,L_IMP,0)))),"La dimensión no corresponde al indicador de impacto","OK"))))))) -> Pendiente por formular
A62: 12 | D62: =IF(C62="","",INDEX(Catalogos!$C$5:$C$49,MATCH(LEFT(C62,7),Catalogos!$A$5:$A$49,0))) | E62: =IF(C62="","",INDEX(Catalogos!$D$5:$D$49,MATCH(LEFT(C62,7),Catalogos!$A$5:$A$49,0))&" "&INDEX(Catalogos!$E$5:$E$49,MATCH(LEFT(C62,7),Catalogos!$A$5:$A$49,0))) | F62: =IF(C62="","",INDEX(Catalogos!$F$5:$F$49,MATCH(LEFT(C62,7),Catalogos!$A$5:$A$49,0))) | S62: =IF(R62="","",INDEX(Catalogos!$Y$5:$Y$25,MATCH(R62,L_IMP,0))) | W62: =IF(H62="","Pendiente por formular",IF(OR(J62="",K62="",L62="",M62="",N62="",O62="",Q62="",R62="",B62="",C62="",G62=""),"Incompleta: faltan campos obligatorios",IF(OR(NOT(ISNUMBER(K62)),NOT(ISNUMBER(L62))),"Fecha inválida",IF(L62<K62,"La fecha de fin es anterior a la de inicio",IF(OR(YEAR(K62)<>2027,YEAR(L62)<>2027),"Fechas fuera de la vigencia 2027",IF(ISERROR(SEARCH("@itc.edu.co",M62)),"El responsable no tiene correo institucional",IF(ISERROR(SEARCH(Q62,INDEX(Catalogos!$Z$5:$Z$25,MATCH(R62,L_IMP,0)))),"La dimensión no corresponde al indicador de impacto","OK"))))))) -> Pendiente por formular
... A150: 100 | D150: =IF(C150="","",INDEX(Catalogos!$C$5:$C$49,MATCH(LEFT(C150,7),Catalogos!$A$5:$A$49,0))) | E150: =IF(C150="","",INDEX(Catalogos!$D$5:$D$49,MATCH(LEFT(C150,7),Catalogos!$A$5:$A$49,0))&" "&INDEX(Catalogos!$E$5:$E$49,MATCH(LEFT(C150,7),Catalogos!$A$5:$A$49,0))) | F150: =IF(C150="","",INDEX(Catalogos!$F$5:$F$49,MATCH(LEFT(C150,7),Catalogos!$A$5:$A$49,0))) | S150: =IF(R150="","",INDEX(Catalogos!$Y$5:$Y$25,MATCH(R150,L_IMP,0))) | W150: =IF(H150="","Pendiente por formular",IF(OR(J150="",K150="",L150="",M150="",N150="",O150="",Q150="",R150="",B150="",C150="",G150=""),"Incompleta: faltan campos obligatorios",IF(OR(NOT(ISNUMBER(K150)),NOT(ISNUMBER(L150))),"Fecha inválida",IF(L150<K150,"La fecha de fin es anterior a la de inicio",IF(OR(YEAR(K150)<>2027,YEAR(L150)<>2027),"Fechas fuera de la vigencia 2027",IF(ISERROR(SEARCH("@itc.edu.co",M150)),"El responsable no tiene correo institucional",IF(ISERROR(SEARCH(Q150,INDEX(Catalogos!$Z$5:$Z$25,MATCH(R150,L_IMP,0)))),"La dimensión no corresponde al indicador de impacto","OK"))))))) -> Pendiente por formular

Sheet Eje1_Formacion
A1: Eje estratégico 1. Formación y pedagogía de calidad — Formulación del Plan de Acción 2027
A2: Objetivo estratégico del eje: Consolidar a la ETITC como un referente educativo de excelencia, ampliando su oferta académica y garantizando la calidad en todos sus programas mediante una actualización continua y una estrecha vinculación con el entorno.
A3: Columnas grises: base definida por la OAPDI (no modificar). Columnas amarillas: las diligencia el área responsable, una acción por fila. Si necesita formular más acciones para una meta, use la hoja Buscador_Formulacion.
A5: BASE DEFINIDA POR LA OAPDI | Q5: FORMULACIÓN DEL ÁREA RESPONSABLE | AF5: CONTROL
A6: Id asignación | B6: Código meta | C6: Línea | D6: Meta estratégica (PDI) | E6: Indicador de la meta | F6: Meta 2032 | G6: Meta institucional 2027 | H6: Id área | I6: Dependencia | J6: Área funcional | K6: Proceso | L6: Productos 2026 (sábana vigente) | M6: Pendientes 2026 | N6: Compromisos de proyectos estructurantes | O6: Aporte esperado del área 2027 | P6: Indicadores de impacto sugeridos | Q6: Nombre de la acción | R6: Descripción de la acción | S6: Producto esperado | T6: Fecha de inicio (dd/mm/aaaa) | U6: Fecha de fin (dd/mm/aaaa) | V6: Responsable (correo institucional) | W6: Indicador de seguimiento | X6: Meta 2027 de la acción | Y6: Unidad de medida | Z6: Dimensión de impacto | AA6: Indicador de impacto (Guía Metodológica) | AB6: Categoría de impacto (automática) | AC6: ¿Retoma un compromiso pendiente 2026? | AD6: Evidencia verificable | AE6: Observaciones | AF6: Alerta de consistencia
A7: =Base_OAPDI!A5 -> E1-001 | B7: =Base_OAPDI!B5 -> 1.1.1.1 | C7: =Base_OAPDI!D5 -> 1.1 Ampliación de cobertura | D7: =Base_OAPDI!E5 -> Contar con 11.000 estudiantes vinculados a programas de educación superior al 2032. | E7: =Base_OAPDI!F5 -> N.° de estudiantes matriculados en programas de educación superior (SNIES) | F7: =Base_OAPDI!G5 -> 11.000 estudiantes | G7: =Base_OAPDI!H5 -> 5.400 estudiantes | H7: =Base_OAPDI!I5 -> A02 | I7: =Base_OAPDI!J5 -> 100 · Rectoría | J7: =Base_OAPDI!K5 -> Comunicaciones y Mercadeo | K7: =Base_OAPDI!L5 -> Gestión de Comunicaciones | L7: =Base_OAPDI!N5 -> 1 | M7: =Base_OAPDI!P5 -> 0 | N7: =Base_OAPDI!Q5 -> 0 | O7: =Base_OAPDI!R5 -> Formular al menos una acción que contribuya a la meta institucional 2027 de esta meta. | P7: =Base_OAPDI!S5 -> IMP-12; IMP-13 | AB7: =IF(AA7="","",INDEX(Catalogos!$Y$5:$Y$25,MATCH(AA7,L_IMP,0))) | AF7: =IF(Q7="","Pendiente por formular",IF(OR(S7="",T7="",U7="",V7="",W7="",X7="",Z7="",AA7=""),"Incompleta: faltan campos obligatorios",IF(OR(NOT(ISNUMBER(T7)),NOT(ISNUMBER(U7))),"Fecha inválida",IF(U7<T7,"La fecha de fin es anterior a la de inicio",IF(OR(YEAR(T7)<>2027,YEAR(U7)<>2027),"Fechas fuera de la vigencia 2027",IF(ISERROR(SEARCH("@itc.edu.co",V7)),"El responsable no tiene correo institucional",IF(ISERROR(SEARCH(Z7,INDEX(Catalogos!$Z$5:$Z$25,MATCH(AA7,L_IMP,0)))),"La dimensión no corresponde al indicador de impacto","OK"))))))) -> Pendiente por formular
A8: =Base_OAPDI!A6 -> E1-002 | B8: =Base_OAPDI!B6 -> 1.1.1.1 | C8: =Base_OAPDI!D6 -> 1.1 Ampliación de cobertura | D8: =Base_OAPDI!E6 -> Contar con 11.000 estudiantes vinculados a programas de educación superior al 2032. | E8: =Base_OAPDI!F6 -> N.° de estudiantes matriculados en programas de educación superior (SNIES) | F8: =Base_OAPDI!G6 -> 11.000 estudiantes | G8: =Base_OAPDI!H6 -> 5.400 estudiantes | H8: =Base_OAPDI!I6 -> A05 | I8: =Base_OAPDI!J6 -> 101 · Oficina Asesora de Planeación y Desarrollo Institucional | J8: =Base_OAPDI!K6 -> Planeación y Plan de Acción | K8: =Base_OAPDI!L6 -> Direccionamiento Institucional | L8: =Base_OAPDI!N6 -> 2 | M8: =Base_OAPDI!P6 -> 2 | N8: =Base_OAPDI!Q6 -> 2 | O8: =Base_OAPDI!R6 -> Acciones propuestas por la OAPDI (valídelas y formúlelas en esta fila o en Acciones adicionales): A27-001 Adoptar el crecimiento neto de primer curso como indicador de meta, junto con nuevos atendidos. Cerrar o reprogramar 2 producto(s) 2026 pendiente(s) de esta meta. Atender 2 compromiso(s) de proyectos estructurantes (hoja Compromisos_2026). | P8: =Base_OAPDI!S6 -> IMP-12; IMP-13 | AB8: =IF(AA8="","",INDEX(Catalogos!$Y$5:$Y$25,MATCH(AA8,L_IMP,0))) | AF8: =IF(Q8="","Pendiente por formular",IF(OR(S8="",T8="",U8="",V8="",W8="",X8="",Z8="",AA8=""),"Incompleta: faltan campos obligatorios",IF(OR(NOT(ISNUMBER(T8)),NOT(ISNUMBER(U8))),"Fecha inválida",IF(U8<T8,"La fecha de fin es anterior a la de inicio",IF(OR(YEAR(T8)<>2027,YEAR(U8)<>2027),"Fechas fuera de la vigencia 2027",IF(ISERROR(SEARCH("@itc.edu.co",V8)),"El responsable no tiene correo institucional",IF(ISERROR(SEARCH(Z8,INDEX(Catalogos!$Z$5:$Z$25,MATCH(AA8,L_IMP,0)))),"La dimensión no corresponde al indicador de impacto","OK"))))))) -> Pendiente por formular
A9: =Base_OAPDI!A7 -> E1-003 | B9: =Base_OAPDI!B7 -> 1.1.1.1 | C9: =Base_OAPDI!D7 -> 1.1 Ampliación de cobertura | D9: =Base_OAPDI!E7 -> Contar con 11.000 estudiantes vinculados a programas de educación superior al 2032. | E9: =Base_OAPDI!F7 -> N.° de estudiantes matriculados en programas de educación superior (SNIES) | F9: =Base_OAPDI!G7 -> 11.000 estudiantes | G9: =Base_OAPDI!H7 -> 5.400 estudiantes | H9: =Base_OAPDI!I7 -> A06 | I9: =Base_OAPDI!J7 -> 101 · Oficina Asesora de Planeación y Desarrollo Institucional | J9: =Base_OAPDI!K7 -> Gestión de Proyectos | K9: =Base_OAPDI!L7 -> Direccionamiento Institucional | L9: =Base_OAPDI!N7 -> 1 | M9: =Base_OAPDI!P7 -> 1 | N9: =Base_OAPDI!Q7 -> 0 | O9: =Base_OAPDI!R7 -> Cerrar o reprogramar 1 producto(s) 2026 pendiente(s) de esta meta. | P9: =Base_OAPDI!S7 -> IMP-12; IMP-13 | AB9: =IF(AA9="","",INDEX(Catalogos!$Y$5:$Y$25,MATCH(AA9,L_IMP,0))) | AF9: =IF(Q9="","Pendiente por formular",IF(OR(S9="",T9="",U9="",V9="",W9="",X9="",Z9="",AA9=""),"Incompleta: faltan campos obligatorios",IF(OR(NOT(ISNUMBER(T9)),NOT(ISNUMBER(U9))),"Fecha inválida",IF(U9<T9,"La fecha de fin es anterior a la de inicio",IF(OR(YEAR(T9)<>2027,YEAR(U9)<>2027),"Fechas fuera de la vigencia 2027",IF(ISERROR(SEARCH("@itc.edu.co",V9)),"El responsable no tiene correo institucional",IF(ISERROR(SEARCH(Z9,INDEX(Catalogos!$Z$5:$Z$25,MATCH(AA9,L_IMP,0)))),"La dimensión no corresponde al indicador de impacto","OK"))))))) -> Pendiente por formular
A10: =Base_OAPDI!A8 -> E1-004 | B10: =Base_OAPDI!B8 -> 1.1.1.1 | C10: =Base_OAPDI!D8 -> 1.1 Ampliación de cobertura | D10: =Base_OAPDI!E8 -> Contar con 11.000 estudiantes vinculados a programas de educación superior al 2032. | E10: =Base_OAPDI!F8 -> N.° de estudiantes matriculados en programas de educación superior (SNIES) | F10: =Base_OAPDI!G8 -> 11.000 estudiantes | G10: =Base_OAPDI!H8 -> 5.400 estudiantes | H10: =Base_OAPDI!I8 -> A07 | I10: =Base_OAPDI!J8 -> 101 · Oficina Asesora de Planeación y Desarrollo Institucional | J10: =Base_OAPDI!K8 -> Autoevaluación y Acreditación | K10: =Base_OAPDI!L8 -> Gestión del Sistema Integrado de Aseguramiento | L10: =Base_OAPDI!N8 -> 0 | M10: =Base_OAPDI!P8 -> 0 | N10: =Base_OAPDI!Q8 -> 0 | O10: =Base_OAPDI!R8 -> Formular al menos una acción que contribuya a la meta institucional 2027 de esta meta. | P10: =Base_OAPDI!S8 -> IMP-12; IMP-13 | AB10: =IF(AA10="","",INDEX(Catalogos!$Y$5:$Y$25,MATCH(AA10,L_IMP,0))) | AF10: =IF(Q10="","Pendiente por formular",IF(OR(S10="",T10="",U10="",V10="",W10="",X10="",Z10="",AA10=""),"Incompleta: faltan campos obligatorios",IF(OR(NOT(ISNUMBER(T10)),NOT(ISNUMBER(U10))),"Fecha inválida",IF(U10<T10,"La fecha de fin es anterior a la de inicio",IF(OR(YEAR(T10)<>2027,YEAR(U10)<>2027),"Fechas fuera de la vigencia 2027",IF(ISERROR(SEARCH("@itc.edu.co",V10)),"El responsable no tiene correo institucional",IF(ISERROR(SEARCH(Z10,INDEX(Catalogos!$Z$5:$Z$25,MATCH(AA10,L_IMP,0)))),"La dimensión no corresponde al indicador de impacto","OK"))))))) -> Pendiente por formular
A11: =Base_OAPDI!A9 -> E1-005 | B11: =Base_OAPDI!B9 -> 1.1.1.1 | C11: =Base_OAPDI!D9 -> 1.1 Ampliación de cobertura | D11: =Base_OAPDI!E9 -> Contar con 11.000 estudiantes vinculados a programas de educación superior al 2032. | E11: =Base_OAPDI!F9 -> N.° de estudiantes matriculados en programas de educación superior (SNIES) | F11: =Base_OAPDI!G9 -> 11.000 estudiantes | G11: =Base_OAPDI!H9 -> 5.400 estudiantes | H11: =Base_OAPDI!I9 -> A14 | I11: =Base_OAPDI!J9 -> 130 · Vicerrectoría Administrativa y Financiera | J11: =Base_OAPDI!K9 -> Contratación y Adquisiciones | K11: =Base_OAPDI!L9 -> Gestión de Adquisiciones | L11: =Base_OAPDI!N9 -> 1 | M11: =Base_OAPDI!P9 -> 1 | N11: =Base_OAPDI!Q9 -> 0 | O11: =Base_OAPDI!R9 -> Cerrar o reprogramar 1 producto(s) 2026 pendiente(s) de esta meta. | P11: =Base_OAPDI!S9 -> IMP-12; IMP-13 | AB11: =IF(AA11="","",INDEX(Catalogos!$Y$5:$Y$25,MATCH(AA11,L_IMP,0))) | AF11: =IF(Q11="","Pendiente por formular",IF(OR(S11="",T11="",U11="",V11="",W11="",X11="",Z11="",AA11=""),"Incompleta: faltan campos obligatorios",IF(OR(NOT(ISNUMBER(T11)),NOT(ISNUMBER(U11))),"Fecha inválida",IF(U11<T11,"La fecha de fin es anterior a la de inicio",IF(OR(YEAR(T11)<>2027,YEAR(U11)<>2027),"Fechas fuera de la vigencia 2027",IF(ISERROR(SEARCH("@itc.edu.co",V11)),"El responsable no tiene correo institucional",IF(ISERROR(SEARCH(Z11,INDEX(Catalogos!$Z$5:$Z$25,MATCH(AA11,L_IMP,0)))),"La dimensión no corresponde al indicador de impacto","OK"))))))) -> Pendiente por formular
A12: =Base_OAPDI!A10 -> E1-006 | B12: =Base_OAPDI!B10 -> 1.1.1.1 | C12: =Base_OAPDI!D10 -> 1.1 Ampliación de cobertura | D12: =Base_OAPDI!E10 -> Contar con 11.000 estudiantes vinculados a programas de educación superior al 2032. | E12: =Base_OAPDI!F10 -> N.° de estudiantes matriculados en programas de educación superior (SNIES) | F12: =Base_OAPDI!G10 -> 11.000 estudiantes | G12: =Base_OAPDI!H10 -> 5.400 estudiantes | H12: =Base_OAPDI!I10 -> A15 | I12: =Base_OAPDI!J10 -> 120 · Vicerrectoría Académica | J12: =Base_OAPDI!K10 -> Despacho de la Vicerrectoría Académica | K12: =Base_OAPDI!L10 -> Docencia PES | L12: =Base_OAPDI!N10 -> 5 | M12: =Base_OAPDI!P10 -> 5 | N12: =Base_OAPDI!Q10 -> 4 | O12: =Base_OAPDI!R10 -> Acciones propuestas por la OAPDI (valídelas y formúlelas en esta fila o en Acciones adicionales): A27-003 Concentrar cupos en programas con demanda creciente y revisar la oferta de programas en descenso; A27-004 Ejecutar la cohorte 2027-1 en La Primavera (Vichada) con 80 cupos adicionales. Cerrar o reprogramar 5 producto(s) 2026 pendiente(s) de esta meta. Atender 4 compromiso(s) de proyectos estructurantes (hoja Compromisos_2026). | P12: =Base_OAPDI!S10 -> IMP-12; IMP-13 | AB12: =IF(AA12="","",INDEX(Catalogos!$Y$5:$Y$25,MATCH(AA12,L_IMP,0))) | AF12: =IF(Q12="","Pendiente por formular",IF(OR(S12="",T12="",U12="",V12="",W12="",X12="",Z12="",AA12=""),"Incompleta: faltan campos obligatorios",IF(OR(NOT(ISNUMBER(T12)),NOT(ISNUMBER(U12))),"Fecha inválida",IF(U12<T12,"La fecha de fin es anterior a la de inicio",IF(OR(YEAR(T12)<>2027,YEAR(U12)<>2027),"Fechas fuera de la vigencia 2027",IF(ISERROR(SEARCH("@itc.edu.co",V12)),"El responsable no tiene correo institucional",IF(ISERROR(SEARCH(Z12,INDEX(Catalogos!$Z$5:$Z$25,MATCH(AA12,L_IMP,0)))),"La dimensión no corresponde al indicador de impacto","OK"))))))) -> Pendiente por formular
A13: =Base_OAPDI!A11 -> E1-007 | B13: =Base_OAPDI!B11 -> 1.1.1.1 | C13: =Base_OAPDI!D11 -> 1.1 Ampliación de cobertura | D13: =Base_OAPDI!E11 -> Contar con 11.000 estudiantes vinculados a programas de educación superior al 2032. | E13: =Base_OAPDI!F11 -> N.° de estudiantes matriculados en programas de educación superior (SNIES) | F13: =Base_OAPDI!G11 -> 11.000 estudiantes | G13: =Base_OAPDI!H11 -> 5.400 estudiantes | H13: =Base_OAPDI!I11 -> A23 | I13: =Base_OAPDI!J11 -> 123 · Facultades | J13: =Base_OAPDI!K11 -> Facultad de Mecánica | K13: =Base_OAPDI!L11 -> Docencia PES | L13: =Base_OAPDI!N11 -> 0 | M13: =Base_OAPDI!P11 -> 0 | N13: =Base_OAPDI!Q11 -> 0 | O13: =Base_OAPDI!R11 -> Formular al menos una acción que contribuya a la meta institucional 2027 de esta meta. | P13: =Base_OAPDI!S11 -> IMP-12; IMP-13 | AB13: =IF(AA13="","",INDEX(Catalogos!$Y$5:$Y$25,MATCH(AA13,L_IMP,0))) | AF13: =IF(Q13="","Pendiente por formular",IF(OR(S13="",T13="",U13="",V13="",W13="",X13="",Z13="",AA13=""),"Incompleta: faltan campos obligatorios",IF(OR(NOT(ISNUMBER(T13)),NOT(ISNUMBER(U13))),"Fecha inválida",IF(U13<T13,"La fecha de fin es anterior a la de inicio",IF(OR(YEAR(T13)<>2027,YEAR(U13)<>2027),"Fechas fuera de la vigencia 2027",IF(ISERROR(SEARCH("@itc.edu.co",V13)),"El responsable no tiene correo institucional",IF(ISERROR(SEARCH(Z13,INDEX(Catalogos!$Z$5:$Z$25,MATCH(AA13,L_IMP,0)))),"La dimensión no corresponde al indicador de impacto","OK"))))))) -> Pendiente por formular
A14: =Base_OAPDI!A12 -> E1-008 | B14: =Base_OAPDI!B12 -> 1.1.1.1 | C14: =Base_OAPDI!D12 -> 1.1 Ampliación de cobertura | D14: =Base_OAPDI!E12 -> Contar con 11.000 estudiantes vinculados a programas de educación superior al 2032. | E14: =Base_OAPDI!F12 -> N.° de estudiantes matriculados en programas de educación superior (SNIES) | F14: =Base_OAPDI!G12 -> 11.000 estudiantes | G14: =Base_OAPDI!H12 -> 5.400 estudiantes | H14: =Base_OAPDI!I12 -> A30 | I14: =Base_OAPDI!J12 -> 130 · Vicerrectoría Administrativa y Financiera | J14: =Base_OAPDI!K12 -> Despacho de la Vicerrectoría Administrativa y Financiera | K14: =Base_OAPDI!L12 -> Gestión Financiera | L14: =Base_OAPDI!N12 -> 0 | M14: =Base_OAPDI!P12 -> 0 | N14: =Base_OAPDI!Q12 -> 0 | O14: =Base_OAPDI!R12 -> Formular al menos una acción que contribuya a la meta institucional 2027 de esta meta. | P14: =Base_OAPDI!S12 -> IMP-12; IMP-13 | AB14: =IF(AA14="","",INDEX(Catalogos!$Y$5:$Y$25,MATCH(AA14,L_IMP,0))) | AF14: =IF(Q14="","Pendiente por formular",IF(OR(S14="",T14="",U14="",V14="",W14="",X14="",Z14="",AA14=""),"Incompleta: faltan campos obligatorios",IF(OR(NOT(ISNUMBER(T14)),NOT(ISNUMBER(U14))),"Fecha inválida",IF(U14<T14,"La fecha de fin es anterior a la de inicio",IF(OR(YEAR(T14)<>2027,YEAR(U14)<>2027),"Fechas fuera de la vigencia 2027",IF(ISERROR(SEARCH("@itc.edu.co",V14)),"El responsable no tiene correo institucional",IF(ISERROR(SEARCH(Z14,INDEX(Catalogos!$Z$5:$Z$25,MATCH(AA14,L_IMP,0)))),"La dimensión no corresponde al indicador de impacto","OK"))))))) -> Pendiente por formular
A15: =Base_OAPDI!A13 -> E1-009 | B15: =Base_OAPDI!B13 -> 1.1.1.1 | C15: =Base_OAPDI!D13 -> 1.1 Ampliación de cobertura | D15: =Base_OAPDI!E13 -> Contar con 11.000 estudiantes vinculados a programas de educación superior al 2032. | E15: =Base_OAPDI!F13 -> N.° de estudiantes matriculados en programas de educación superior (SNIES) | F15: =Base_OAPDI!G13 -> 11.000 estudiantes | G15: =Base_OAPDI!H13 -> 5.400 estudiantes | H15: =Base_OAPDI!I13 -> A29 | I15: =Base_OAPDI!J13 -> 126 · GIT Registro y Control | J15: =Base_OAPDI!K13 -> GIT Registro, Control y Admisiones | K15: =Base_OAPDI!L13 -> Docencia PES | L15: =Base_OAPDI!N13 -> 0 | M15: =Base_OAPDI!P13 -> 0 | N15: =Base_OAPDI!Q13 -> 3 | O15: =Base_OAPDI!R13 -> Acciones propuestas por la OAPDI (valídelas y formúlelas en esta fila o en Acciones adicionales): A27-002 Armonizar el calendario de admisiones con la asignación de recursos del MEN. Atender 3 compromiso(s) de proyectos estructurantes (hoja Compromisos_2026). | P15: =Base_OAPDI!S13 -> IMP-12; IMP-13 | AB15: =IF(AA15="","",INDEX(Catalogos!$Y$5:$Y$25,MATCH(AA15,L_IMP,0))) | AF15: =IF(Q15="","Pendiente por formular",IF(OR(S15="",T15="",U15="",V15="",W15="",X15="",Z15="",AA15=""),"Incompleta: faltan campos obligatorios",IF(OR(NOT(ISNUMBER(T15)),NOT(ISNUMBER(U15))),"Fecha inválida",IF(U15<T15,"La fecha de fin es anterior a la de inicio",IF(OR(YEAR(T15)<>2027,YEAR(U15)<>2027),"Fechas fuera de la vigencia 2027",IF(ISERROR(SEARCH("@itc.edu.co",V15)),"El responsable no tiene correo institucional",IF(ISERROR(SEARCH(Z15,INDEX(Catalogos!$Z$5:$Z$25,MATCH(AA15,L_IMP,0)))),"La dimensión no corresponde al indicador de impacto","OK"))))))) -> Pendiente por formular
A16: =Base_OAPDI!A14 -> E1-010 | B16: =Base_OAPDI!B14 -> 1.1.1.1 | C16: =Base_OAPDI!D14 -> 1.1 Ampliación de cobertura | D16: =Base_OAPDI!E14 -> Contar con 11.000 estudiantes vinculados a programas de educación superior al 2032. | E16: =Base_OAPDI!F14 -> N.° de estudiantes matriculados en programas de educación superior (SNIES) | F16: =Base_OAPDI!G14 -> 11.000 estudiantes | G16: =Base_OAPDI!H14 -> 5.400 estudiantes | H16: =Base_OAPDI!I14 -> A47 | I16: =Base_OAPDI!J14 -> 130 · Vicerrectoría Administrativa y Financiera | J16: =Base_OAPDI!K14 -> Gestión Financiera (Presupuesto, Contabilidad, Tesorería) | K16: =Base_OAPDI!L14 -> Gestión Financiera | L16: =Base_OAPDI!N14 -> 0 | M16: =Base_OAPDI!P14 -> 0 | N16: =Base_OAPDI!Q14 -> 1 | O16: =Base_OAPDI!R14 -> Atender 1 compromiso(s) de proyectos estructurantes (hoja Compromisos_2026). | P16: =Base_OAPDI!S14 -> IMP-12; IMP-13 | AB16: =IF(AA16="","",INDEX(Catalogos!$Y$5:$Y$25,MATCH(AA16,L_IMP,0))) | AF16: =IF(Q16="","Pendiente por formular",IF(OR(S16="",T16="",U16="",V16="",W16="",X16="",Z16="",AA16=""),"Incompleta: faltan campos obligatorios",IF(OR(NOT(ISNUMBER(T16)),NOT(ISNUMBER(U16))),"Fecha inválida",IF(U16<T16,"La fecha de fin es anterior a la de inicio",IF(OR(YEAR(T16)<>2027,YEAR(U16)<>2027),"Fechas fuera de la vigencia 2027",IF(ISERROR(SEARCH("@itc.edu.co",V16)),"El responsable no tiene correo institucional",IF(ISERROR(SEARCH(Z16,INDEX(Catalogos!$Z$5:$Z$25,MATCH(AA16,L_IMP,0)))),"La dimensión no corresponde al indicador de impacto","OK"))))))) -> Pendiente por formular
A17: =Base_OAPDI!A15 -> E1-011 | B17: =Base_OAPDI!B15 -> 1.1.1.1 | C17: =Base_OAPDI!D15 -> 1.1 Ampliación de cobertura | D17: =Base_OAPDI!E15 -> Contar con 11.000 estudiantes vinculados a programas de educación superior al 2032. | E17: =Base_OAPDI!F15 -> N.° de estudiantes matriculados en programas de educación superior (SNIES) | F17: =Base_OAPDI!G15 -> 11.000 estudiantes | G17: =Base_OAPDI!H15 -> 5.400 estudiantes | H17: =Base_OAPDI!I15 -> A43 | I17: =Base_OAPDI!J15 -> 141 · GIT Extensión y Proyección Social | J17: =Base_OAPDI!K15 -> Egresados y Bolsa de Empleo | K17: =Base_OAPDI!L15 -> Egresados | L17: =Base_OAPDI!N15 -> 0 | M17: =Base_OAPDI!P15 -> 0 | N17: =Base_OAPDI!Q15 -> 1 | O17: =Base_OAPDI!R15 -> Acciones propuestas por la OAPDI (valídelas y formúlelas en esta fila o en Acciones adicionales): A27-006 Iniciar el estudio de impacto de Egresados. Atender 1 compromiso(s) de proyectos estructurantes (hoja Compromisos_2026). | P17: =Base_OAPDI!S15 -> IMP-12; IMP-13 | AB17: =IF(AA17="","",INDEX(Catalogos!$Y$5:$Y$25,MATCH(AA17,L_IMP,0))) | AF17: =IF(Q17="","Pendiente por formular",IF(OR(S17="",T17="",U17="",V17="",W17="",X17="",Z17="",AA17=""),"Incompleta: faltan campos obligatorios",IF(OR(NOT(ISNUMBER(T17)),NOT(ISNUMBER(U17))),"Fecha inválida",IF(U17<T17,"La fecha de fin es anterior a la de inicio",IF(OR(YEAR(T17)<>2027,YEAR(U17)<>2027),"Fechas fuera de la vigencia 2027",IF(ISERROR(SEARCH("@itc.edu.co",V17)),"El responsable no tiene correo institucional",IF(ISERROR(SEARCH(Z17,INDEX(Catalogos!$Z$5:$Z$25,MATCH(AA17,L_IMP,0)))),"La dimensión no corresponde al indicador de impacto","OK"))))))) -> Pendiente por formular
A18: =Base_OAPDI!A16 -> E1-012 | B18: =Base_OAPDI!B16 -> 1.1.1.1 | C18: =Base_OAPDI!D16 -> 1.1 Ampliación de cobertura | D18: =Base_OAPDI!E16 -> Contar con 11.000 estudiantes vinculados a programas de educación superior al 2032. | E18: =Base_OAPDI!F16 -> N.° de estudiantes matriculados en programas de educación superior (SNIES) | F18: =Base_OAPDI!G16 -> 11.000 estudiantes | G18: =Base_OAPDI!H16 -> 5.400 estudiantes | H18: =Base_OAPDI!I16 -> A45 | I18: =Base_OAPDI!J16 -> 120 · Vicerrectoría Académica | J18: =Base_OAPDI!K16 -> Sedes Tintal / Soacha-UPK / Viotá | K18: =Base_OAPDI!L16 -> Docencia PES | L18: =Base_OAPDI!N16 -> 0 | M18: =Base_OAPDI!P16 -> 0 | N18: =Base_OAPDI!Q16 -> 0 | O18: =Base_OAPDI!R16 -> Acciones propuestas por la OAPDI (valídelas y formúlelas en esta fila o en Acciones adicionales): A27-005 Ofertar y matricular en Zipaquirá bajo lugares de desarrollo transitorios. | P18: =Base_OAPDI!S16 -> IMP-12; IMP-13 | AB18: =IF(AA18="","",INDEX(Catalogos!$Y$5:$Y$25,MATCH(AA18,L_IMP,0))) | AF18: =IF(Q18="","Pendiente por formular",IF(OR(S18="",T18="",U18="",V18="",W18="",X18="",Z18="",AA18=""),"Incompleta: faltan campos obligatorios",IF(OR(NOT(ISNUMBER(T18)),NOT(ISNUMBER(U18))),"Fecha inválida",IF(U18<T18,"La fecha de fin es anterior a la de inicio",IF(OR(YEAR(T18)<>2027,YEAR(U18)<>2027),"Fechas fuera de la vigencia 2027",IF(ISERROR(SEARCH("@itc.edu.co",V18)),"El responsable no tiene correo institucional",IF(ISERROR(SEARCH(Z18,INDEX(Catalogos!$Z$5:$Z$25,MATCH(AA18,L_IMP,0)))),"La dimensión no corresponde al indicador de impacto","OK"))))))) -> Pendiente por formular
... A66: =Base_OAPDI!A64 -> E1-060 | B66: =Base_OAPDI!B64 -> 1.5.1.2 | C66: =Base_OAPDI!D64 -> 1.5 Fortalecimiento del cuerpo docente | D66: =Base_OAPDI!E64 -> 80% en formación docentes de planta. | E66: =Base_OAPDI!F64 -> % de docentes de planta en formación avanzada o continuada | F66: =Base_OAPDI!G64 -> 80% | G66: =Base_OAPDI!H64 -> 6 docentes de planta en maestría y 40 docentes en formación continuada | H66: =Base_OAPDI!I64 -> A35 | I66: =Base_OAPDI!J64 -> 133 · GIT Gestión de Talento Humano | J66: =Base_OAPDI!K64 -> GIT Talento Humano | K66: =Base_OAPDI!L64 -> Gestión de Talento Humano | L66: =Base_OAPDI!N64 -> 0 | M66: =Base_OAPDI!P64 -> 0 | N66: =Base_OAPDI!Q64 -> 0 | O66: =Base_OAPDI!R64 -> Acciones propuestas por la OAPDI (valídelas y formúlelas en esta fila o en Acciones adicionales): A27-032 Ofrecer cursos de formación continuada a docentes. | P66: =Base_OAPDI!S64 -> IMP-08; IMP-19 | AB66: =IF(AA66="","",INDEX(Catalogos!$Y$5:$Y$25,MATCH(AA66,L_IMP,0))) | AF66: =IF(Q66="","Pendiente por formular",IF(OR(S66="",T66="",U66="",V66="",W66="",X66="",Z66="",AA66=""),"Incompleta: faltan campos obligatorios",IF(OR(NOT(ISNUMBER(T66)),NOT(ISNUMBER(U66))),"Fecha inválida",IF(U66<T66,"La fecha de fin es anterior a la de inicio",IF(OR(YEAR(T66)<>2027,YEAR(U66)<>2027),"Fechas fuera de la vigencia 2027",IF(ISERROR(SEARCH("@itc.edu.co",V66)),"El responsable no tiene correo institucional",IF(ISERROR(SEARCH(Z66,INDEX(Catalogos!$Z$5:$Z$25,MATCH(AA66,L_IMP,0)))),"La dimensión no corresponde al indicador de impacto","OK"))))))) -> Pendiente por formular

Sheet Eje2_Investigacion
A1: Eje estratégico 2. Investigación y producción técnico-científica — Formulación del Plan de Acción 2027
A2: Objetivo estratégico del eje: Generar y fortalecer las capacidades técnico científica y de innovación de la ETITC mediante la consolidación de la investigación aplicada, la generación de alianzas estratégicas y la integración de la innovación con la formación académica.
A3: Columnas grises: base definida por la OAPDI (no modificar). Columnas amarillas: las diligencia el área responsable, una acción por fila. Si necesita formular más acciones para una meta, use la hoja Buscador_Formulacion.
A5: BASE DEFINIDA POR LA OAPDI | Q5: FORMULACIÓN DEL ÁREA RESPONSABLE | AF5: CONTROL
A6: Id asignación | B6: Código meta | C6: Línea | D6: Meta estratégica (PDI) | E6: Indicador de la meta | F6: Meta 2032 | G6: Meta institucional 2027 | H6: Id área | I6: Dependencia | J6: Área funcional | K6: Proceso | L6: Productos 2026 (sábana vigente) | M6: Pendientes 2026 | N6: Compromisos de proyectos estructurantes | O6: Aporte esperado del área 2027 | P6: Indicadores de impacto sugeridos | Q6: Nombre de la acción | R6: Descripción de la acción | S6: Producto esperado | T6: Fecha de inicio (dd/mm/aaaa) | U6: Fecha de fin (dd/mm/aaaa) | V6: Responsable (correo institucional) | W6: Indicador de seguimiento | X6: Meta 2027 de la acción | Y6: Unidad de medida | Z6: Dimensión de impacto | AA6: Indicador de impacto (Guía Metodológica) | AB6: Categoría de impacto (automática) | AC6: ¿Retoma un compromiso pendiente 2026? | AD6: Evidencia verificable | AE6: Observaciones | AF6: Alerta de consistencia
A7: =Base_OAPDI!A65 -> E2-001 | B7: =Base_OAPDI!B65 -> 2.1.1.1 | C7: =Base_OAPDI!D65 -> 2.1 Capacidades de investigación e innovación | D7: =Base_OAPDI!E65 -> Contar como mínimo por vigencia con un (1) grupo de investigación en clasificación A (en MinCiencias). | E7: =Base_OAPDI!F65 -> N.° de grupos categoría A/A1 en MinCiencias | F7: =Base_OAPDI!G65 -> 1 grupo A (MPI: 8 grupos A) | G7: =Base_OAPDI!H65 -> Sugerido: (1 grupo con ruta de ascenso a categoría A aprobada y con la producción de nuevo conocimiento requerida para la siguiente medición) | H7: =Base_OAPDI!I65 -> A06 | I7: =Base_OAPDI!J65 -> 101 · Oficina Asesora de Planeación y Desarrollo Institucional | J7: =Base_OAPDI!K65 -> Gestión de Proyectos | K7: =Base_OAPDI!L65 -> Direccionamiento Institucional | L7: =Base_OAPDI!N65 -> 1 | M7: =Base_OAPDI!P65 -> 1 | N7: =Base_OAPDI!Q65 -> 0 | O7: =Base_OAPDI!R65 -> Cerrar o reprogramar 1 producto(s) 2026 pendiente(s) de esta meta. | P7: =Base_OAPDI!S65 -> IMP-20; IMP-21 | AB7: =IF(AA7="","",INDEX(Catalogos!$Y$5:$Y$25,MATCH(AA7,L_IMP,0))) | AF7: =IF(Q7="","Pendiente por formular",IF(OR(S7="",T7="",U7="",V7="",W7="",X7="",Z7="",AA7=""),"Incompleta: faltan campos obligatorios",IF(OR(NOT(ISNUMBER(T7)),NOT(ISNUMBER(U7))),"Fecha inválida",IF(U7<T7,"La fecha de fin es anterior a la de inicio",IF(OR(YEAR(T7)<>2027,YEAR(U7)<>2027),"Fechas fuera de la vigencia 2027",IF(ISERROR(SEARCH("@itc.edu.co",V7)),"El responsable no tiene correo institucional",IF(ISERROR(SEARCH(Z7,INDEX(Catalogos!$Z$5:$Z$25,MATCH(AA7,L_IMP,0)))),"La dimensión no corresponde al indicador de impacto","OK"))))))) -> Pendiente por formular
A8: =Base_OAPDI!A66 -> E2-002 | B8: =Base_OAPDI!B66 -> 2.1.1.1 | C8: =Base_OAPDI!D66 -> 2.1 Capacidades de investigación e innovación | D8: =Base_OAPDI!E66 -> Contar como mínimo por vigencia con un (1) grupo de investigación en clasificación A (en MinCiencias). | E8: =Base_OAPDI!F66 -> N.° de grupos categoría A/A1 en MinCiencias | F8: =Base_OAPDI!G66 -> 1 grupo A (MPI: 8 grupos A) | G8: =Base_OAPDI!H66 -> Sugerido: (1 grupo con ruta de ascenso a categoría A aprobada y con la producción de nuevo conocimiento requerida para la siguiente medición) | H8: =Base_OAPDI!I66 -> A39 | I8: =Base_OAPDI!J66 -> 140 · Vicerrectoría de Investigación, Extensión y Transferencia | J8: =Base_OAPDI!K66 -> Investigación (grupos, semilleros, revista, centro de pensamiento) | K8: =Base_OAPDI!L66 -> Investigación | L8: =Base_OAPDI!N66 -> 17 | M8: =Base_OAPDI!P66 -> 3 | N8: =Base_OAPDI!Q66 -> 1 | O8: =Base_OAPDI!R66 -> Acciones propuestas por la OAPDI (valídelas y formúlelas en esta fila o en Acciones adicionales): A27-033 Diagnosticar la producción de cada grupo frente al modelo de medición de MinCiencias; A27-035 Iniciar el estudio de impacto de Investigación. Cerrar o reprogramar 3 producto(s) 2026 pendiente(s) de esta meta. Atender 1 compromiso(s) de proyectos estructurantes (hoja Compromisos_2026). | P8: =Base_OAPDI!S66 -> IMP-20; IMP-21 | AB8: =IF(AA8="","",INDEX(Catalogos!$Y$5:$Y$25,MATCH(AA8,L_IMP,0))) | AF8: =IF(Q8="","Pendiente por formular",IF(OR(S8="",T8="",U8="",V8="",W8="",X8="",Z8="",AA8=""),"Incompleta: faltan campos obligatorios",IF(OR(NOT(ISNUMBER(T8)),NOT(ISNUMBER(U8))),"Fecha inválida",IF(U8<T8,"La fecha de fin es anterior a la de inicio",IF(OR(YEAR(T8)<>2027,YEAR(U8)<>2027),"Fechas fuera de la vigencia 2027",IF(ISERROR(SEARCH("@itc.edu.co",V8)),"El responsable no tiene correo institucional",IF(ISERROR(SEARCH(Z8,INDEX(Catalogos!$Z$5:$Z$25,MATCH(AA8,L_IMP,0)))),"La dimensión no corresponde al indicador de impacto","OK"))))))) -> Pendiente por formular
A9: =Base_OAPDI!A67 -> E2-003 | B9: =Base_OAPDI!B67 -> 2.1.1.1 | C9: =Base_OAPDI!D67 -> 2.1 Capacidades de investigación e innovación | D9: =Base_OAPDI!E67 -> Contar como mínimo por vigencia con un (1) grupo de investigación en clasificación A (en MinCiencias). | E9: =Base_OAPDI!F67 -> N.° de grupos categoría A/A1 en MinCiencias | F9: =Base_OAPDI!G67 -> 1 grupo A (MPI: 8 grupos A) | G9: =Base_OAPDI!H67 -> Sugerido: (1 grupo con ruta de ascenso a categoría A aprobada y con la producción de nuevo conocimiento requerida para la siguiente medición) | H9: =Base_OAPDI!I67 -> A38 | I9: =Base_OAPDI!J67 -> 140 · Vicerrectoría de Investigación, Extensión y Transferencia | J9: =Base_OAPDI!K67 -> Despacho de la VIET | K9: =Base_OAPDI!L67 -> Investigación | L9: =Base_OAPDI!N67 -> 0 | M9: =Base_OAPDI!P67 -> 0 | N9: =Base_OAPDI!Q67 -> 0 | O9: =Base_OAPDI!R67 -> Acciones propuestas por la OAPDI (valídelas y formúlelas en esta fila o en Acciones adicionales): A27-034 Definir la ruta de ascenso del grupo con mayor producción (metas de nuevo conocimiento y formación). | P9: =Base_OAPDI!S67 -> IMP-20; IMP-21 | AB9: =IF(AA9="","",INDEX(Catalogos!$Y$5:$Y$25,MATCH(AA9,L_IMP,0))) | AF9: =IF(Q9="","Pendiente por formular",IF(OR(S9="",T9="",U9="",V9="",W9="",X9="",Z9="",AA9=""),"Incompleta: faltan campos obligatorios",IF(OR(NOT(ISNUMBER(T9)),NOT(ISNUMBER(U9))),"Fecha inválida",IF(U9<T9,"La fecha de fin es anterior a la de inicio",IF(OR(YEAR(T9)<>2027,YEAR(U9)<>2027),"Fechas fuera de la vigencia 2027",IF(ISERROR(SEARCH("@itc.edu.co",V9)),"El responsable no tiene correo institucional",IF(ISERROR(SEARCH(Z9,INDEX(Catalogos!$Z$5:$Z$25,MATCH(AA9,L_IMP,0)))),"La dimensión no corresponde al indicador de impacto","OK"))))))) -> Pendiente por formular
A10: =Base_OAPDI!A68 -> E2-004 | B10: =Base_OAPDI!B68 -> 2.1.1.2 | C10: =Base_OAPDI!D68 -> 2.1 Capacidades de investigación e innovación | D10: =Base_OAPDI!E68 -> Tres (3) grupos en B. | E10: =Base_OAPDI!F68 -> N.° de grupos categoría B en MinCiencias | F10: =Base_OAPDI!G68 -> 3 grupos B (MPI: 16) | G10: =Base_OAPDI!H68 -> Sugerido: (1 grupo clasificado en B —ascenso de uno de los 2 grupos en C—) | H10: =Base_OAPDI!I68 -> A38 | I10: =Base_OAPDI!J68 -> 140 · Vicerrectoría de Investigación, Extensión y Transferencia | J10: =Base_OAPDI!K68 -> Despacho de la VIET | K10: =Base_OAPDI!L68 -> Investigación | L10: =Base_OAPDI!N68 -> 4 | M10: =Base_OAPDI!P68 -> 2 | N10: =Base_OAPDI!Q68 -> 0 | O10: =Base_OAPDI!R68 -> Cerrar o reprogramar 2 producto(s) 2026 pendiente(s) de esta meta. | P10: =Base_OAPDI!S68 -> IMP-20; IMP-21 | AB10: =IF(AA10="","",INDEX(Catalogos!$Y$5:$Y$25,MATCH(AA10,L_IMP,0))) | AF10: =IF(Q10="","Pendiente por formular",IF(OR(S10="",T10="",U10="",V10="",W10="",X10="",Z10="",AA10=""),"Incompleta: faltan campos obligatorios",IF(OR(NOT(ISNUMBER(T10)),NOT(ISNUMBER(U10))),"Fecha inválida",IF(U10<T10,"La fecha de fin es anterior a la de inicio",IF(OR(YEAR(T10)<>2027,YEAR(U10)<>2027),"Fechas fuera de la vigencia 2027",IF(ISERROR(SEARCH("@itc.edu.co",V10)),"El responsable no tiene correo institucional",IF(ISERROR(SEARCH(Z10,INDEX(Catalogos!$Z$5:$Z$25,MATCH(AA10,L_IMP,0)))),"La dimensión no corresponde al indicador de impacto","OK"))))))) -> Pendiente por formular
A11: =Base_OAPDI!A69 -> E2-005 | B11: =Base_OAPDI!B69 -> 2.1.1.2 | C11: =Base_OAPDI!D69 -> 2.1 Capacidades de investigación e innovación | D11: =Base_OAPDI!E69 -> Tres (3) grupos en B. | E11: =Base_OAPDI!F69 -> N.° de grupos categoría B en MinCiencias | F11: =Base_OAPDI!G69 -> 3 grupos B (MPI: 16) | G11: =Base_OAPDI!H69 -> Sugerido: (1 grupo clasificado en B —ascenso de uno de los 2 grupos en C—) | H11: =Base_OAPDI!I69 -> A39 | I11: =Base_OAPDI!J69 -> 140 · Vicerrectoría de Investigación, Extensión y Transferencia | J11: =Base_OAPDI!K69 -> Investigación (grupos, semilleros, revista, centro de pensamiento) | K11: =Base_OAPDI!L69 -> Investigación | L11: =Base_OAPDI!N69 -> 36 | M11: =Base_OAPDI!P69 -> 16 | N11: =Base_OAPDI!Q69 -> 0 | O11: =Base_OAPDI!R69 -> Acciones propuestas por la OAPDI (valídelas y formúlelas en esta fila o en Acciones adicionales): A27-036 Asesorar a los grupos en C (Virtus y GEA) en productos de nuevo conocimiento y apropiación; A27-037 Postular los grupos en la convocatoria de medición vigente. Cerrar o reprogramar 16 producto(s) 2026 pendiente(s) de esta meta. | P11: =Base_OAPDI!S69 -> IMP-20; IMP-21 | AB11: =IF(AA11="","",INDEX(Catalogos!$Y$5:$Y$25,MATCH(AA11,L_IMP,0))) | AF11: =IF(Q11="","Pendiente por formular",IF(OR(S11="",T11="",U11="",V11="",W11="",X11="",Z11="",AA11=""),"Incompleta: faltan campos obligatorios",IF(OR(NOT(ISNUMBER(T11)),NOT(ISNUMBER(U11))),"Fecha inválida",IF(U11<T11,"La fecha de fin es anterior a la de inicio",IF(OR(YEAR(T11)<>2027,YEAR(U11)<>2027),"Fechas fuera de la vigencia 2027",IF(ISERROR(SEARCH("@itc.edu.co",V11)),"El responsable no tiene correo institucional",IF(ISERROR(SEARCH(Z11,INDEX(Catalogos!$Z$5:$Z$25,MATCH(AA11,L_IMP,0)))),"La dimensión no corresponde al indicador de impacto","OK"))))))) -> Pendiente por formular
A12: =Base_OAPDI!A70 -> E2-006 | B12: =Base_OAPDI!B70 -> 2.1.1.2 | C12: =Base_OAPDI!D70 -> 2.1 Capacidades de investigación e innovación | D12: =Base_OAPDI!E70 -> Tres (3) grupos en B. | E12: =Base_OAPDI!F70 -> N.° de grupos categoría B en MinCiencias | F12: =Base_OAPDI!G70 -> 3 grupos B (MPI: 16) | G12: =Base_OAPDI!H70 -> Sugerido: (1 grupo clasificado en B —ascenso de uno de los 2 grupos en C—) | H12: =Base_OAPDI!I70 -> A40 | I12: =Base_OAPDI!J70 -> 140 · Vicerrectoría de Investigación, Extensión y Transferencia | J12: =Base_OAPDI!K70 -> Innovación y Laboratorio Inteligente | K12: =Base_OAPDI!L70 -> Investigación | L12: =Base_OAPDI!N70 -> 11 | M12: =Base_OAPDI!P70 -> 7 | N12: =Base_OAPDI!Q70 -> 0 | O12: =Base_OAPDI!R70 -> Cerrar o reprogramar 7 producto(s) 2026 pendiente(s) de esta meta. | P12: =Base_OAPDI!S70 -> IMP-20; IMP-21 | AB12: =IF(AA12="","",INDEX(Catalogos!$Y$5:$Y$25,MATCH(AA12,L_IMP,0))) | AF12: =IF(Q12="","Pendiente por formular",IF(OR(S12="",T12="",U12="",V12="",W12="",X12="",Z12="",AA12=""),"Incompleta: faltan campos obligatorios",IF(OR(NOT(ISNUMBER(T12)),NOT(ISNUMBER(U12))),"Fecha inválida",IF(U12<T12,"La fecha de fin es anterior a la de inicio",IF(OR(YEAR(T12)<>2027,YEAR(U12)<>2027),"Fechas fuera de la vigencia 2027",IF(ISERROR(SEARCH("@itc.edu.co",V12)),"El responsable no tiene correo institucional",IF(ISERROR(SEARCH(Z12,INDEX(Catalogos!$Z$5:$Z$25,MATCH(AA12,L_IMP,0)))),"La dimensión no corresponde al indicador de impacto","OK"))))))) -> Pendiente por formular
A13: =Base_OAPDI!A71 -> E2-007 | B13: =Base_OAPDI!B71 -> 2.1.1.3 | C13: =Base_OAPDI!D71 -> 2.1 Capacidades de investigación e innovación | D13: =Base_OAPDI!E71 -> Cuatro (4) grupos en C. | E13: =Base_OAPDI!F71 -> N.° de grupos categoría C en MinCiencias | F13: =Base_OAPDI!G71 -> 4 grupos C (MPI: 14) | G13: =Base_OAPDI!H71 -> Sugerido: (4 grupos en C: mantener Virtus y GEA y clasificar 2 de los 7 grupos registrados sin categoría) | H13: =Base_OAPDI!I71 -> A39 | I13: =Base_OAPDI!J71 -> 140 · Vicerrectoría de Investigación, Extensión y Transferencia | J13: =Base_OAPDI!K71 -> Investigación (grupos, semilleros, revista, centro de pensamiento) | K13: =Base_OAPDI!L71 -> Investigación | L13: =Base_OAPDI!N71 -> 22 | M13: =Base_OAPDI!P71 -> 6 | N13: =Base_OAPDI!Q71 -> 0 | O13: =Base_OAPDI!R71 -> Acciones propuestas por la OAPDI (valídelas y formúlelas en esta fila o en Acciones adicionales): A27-038 Actualizar GrupLAC y CvLAC de los 7 grupos sin categoría; A27-039 Acompañar a los 2 grupos con más producción para su clasificación en C. Cerrar o reprogramar 6 producto(s) 2026 pendiente(s) de esta meta. | P13: =Base_OAPDI!S71 -> IMP-20; IMP-21 | AB13: =IF(AA13="","",INDEX(Catalogos!$Y$5:$Y$25,MATCH(AA13,L_IMP,0))) | AF13: =IF(Q13="","Pendiente por formular",IF(OR(S13="",T13="",U13="",V13="",W13="",X13="",Z13="",AA13=""),"Incompleta: faltan campos obligatorios",IF(OR(NOT(ISNUMBER(T13)),NOT(ISNUMBER(U13))),"Fecha inválida",IF(U13<T13,"La fecha de fin es anterior a la de inicio",IF(OR(YEAR(T13)<>2027,YEAR(U13)<>2027),"Fechas fuera de la vigencia 2027",IF(ISERROR(SEARCH("@itc.edu.co",V13)),"El responsable no tiene correo institucional",IF(ISERROR(SEARCH(Z13,INDEX(Catalogos!$Z$5:$Z$25,MATCH(AA13,L_IMP,0)))),"La dimensión no corresponde al indicador de impacto","OK"))))))) -> Pendiente por formular
A14: =Base_OAPDI!A72 -> E2-008 | B14: =Base_OAPDI!B72 -> 2.1.1.3 | C14: =Base_OAPDI!D72 -> 2.1 Capacidades de investigación e innovación | D14: =Base_OAPDI!E72 -> Cuatro (4) grupos en C. | E14: =Base_OAPDI!F72 -> N.° de grupos categoría C en MinCiencias | F14: =Base_OAPDI!G72 -> 4 grupos C (MPI: 14) | G14: =Base_OAPDI!H72 -> Sugerido: (4 grupos en C: mantener Virtus y GEA y clasificar 2 de los 7 grupos registrados sin categoría) | H14: =Base_OAPDI!I72 -> A40 | I14: =Base_OAPDI!J72 -> 140 · Vicerrectoría de Investigación, Extensión y Transferencia | J14: =Base_OAPDI!K72 -> Innovación y Laboratorio Inteligente | K14: =Base_OAPDI!L72 -> Investigación | L14: =Base_OAPDI!N72 -> 3 | M14: =Base_OAPDI!P72 -> 3 | N14: =Base_OAPDI!Q72 -> 0 | O14: =Base_OAPDI!R72 -> Cerrar o reprogramar 3 producto(s) 2026 pendiente(s) de esta meta. | P14: =Base_OAPDI!S72 -> IMP-20; IMP-21 | AB14: =IF(AA14="","",INDEX(Catalogos!$Y$5:$Y$25,MATCH(AA14,L_IMP,0))) | AF14: =IF(Q14="","Pendiente por formular",IF(OR(S14="",T14="",U14="",V14="",W14="",X14="",Z14="",AA14=""),"Incompleta: faltan campos obligatorios",IF(OR(NOT(ISNUMBER(T14)),NOT(ISNUMBER(U14))),"Fecha inválida",IF(U14<T14,"La fecha de fin es anterior a la de inicio",IF(OR(YEAR(T14)<>2027,YEAR(U14)<>2027),"Fechas fuera de la vigencia 2027",IF(ISERROR(SEARCH("@itc.edu.co",V14)),"El responsable no tiene correo institucional",IF(ISERROR(SEARCH(Z14,INDEX(Catalogos!$Z$5:$Z$25,MATCH(AA14,L_IMP,0)))),"La dimensión no corresponde al indicador de impacto","OK"))))))) -> Pendiente por formular
A15: =Base_OAPDI!A73 -> E2-009 | B15: =Base_OAPDI!B73 -> 2.2.1.1 | C15: =Base_OAPDI!D73 -> 2.2 Producción técnico-científica | D15: =Base_OAPDI!E73 -> Lograr como mínimo por vigencia la publicación de dos (2) artículos en revistas internacionales indexadas. | E15: =Base_OAPDI!F73 -> N.° de artículos publicados en revistas internacionales indexadas | F15: =Base_OAPDI!G73 -> 2 por vigencia (16 en el periodo, según MPI) | G15: =Base_OAPDI!H73 -> 2 artículos | H15: =Base_OAPDI!I73 -> A39 | I15: =Base_OAPDI!J73 -> 140 · Vicerrectoría de Investigación, Extensión y Transferencia | J15: =Base_OAPDI!K73 -> Investigación (grupos, semilleros, revista, centro de pensamiento) | K15: =Base_OAPDI!L73 -> Investigación | L15: =Base_OAPDI!N73 -> 1 | M15: =Base_OAPDI!P73 -> 1 | N15: =Base_OAPDI!Q73 -> 0 | O15: =Base_OAPDI!R73 -> Acciones propuestas por la OAPDI (valídelas y formúlelas en esta fila o en Acciones adicionales): A27-040 Abrir la convocatoria de estímulos a la publicación 2027; A27-041 Acompañar la traducción y el sometimiento a revistas internacionales indexadas. Cerrar o reprogramar 1 producto(s) 2026 pendiente(s) de esta meta. | P15: =Base_OAPDI!S73 -> IMP-21; IMP-20 | AB15: =IF(AA15="","",INDEX(Catalogos!$Y$5:$Y$25,MATCH(AA15,L_IMP,0))) | AF15: =IF(Q15="","Pendiente por formular",IF(OR(S15="",T15="",U15="",V15="",W15="",X15="",Z15="",AA15=""),"Incompleta: faltan campos obligatorios",IF(OR(NOT(ISNUMBER(T15)),NOT(ISNUMBER(U15))),"Fecha inválida",IF(U15<T15,"La fecha de fin es anterior a la de inicio",IF(OR(YEAR(T15)<>2027,YEAR(U15)<>2027),"Fechas fuera de la vigencia 2027",IF(ISERROR(SEARCH("@itc.edu.co",V15)),"El responsable no tiene correo institucional",IF(ISERROR(SEARCH(Z15,INDEX(Catalogos!$Z$5:$Z$25,MATCH(AA15,L_IMP,0)))),"La dimensión no corresponde al indicador de impacto","OK"))))))) -> Pendiente por formular
A16: =Base_OAPDI!A74 -> E2-010 | B16: =Base_OAPDI!B74 -> 2.2.1.2 | C16: =Base_OAPDI!D74 -> 2.2 Producción técnico-científica | D16: =Base_OAPDI!E74 -> Lograr la publicación de ocho (8) artículos en revistas nacionales indexadas. | E16: =Base_OAPDI!F74 -> N.° de artículos publicados en revistas nacionales indexadas | F16: =Base_OAPDI!G74 -> 8 (MPI: 8 por año, 48 en total) | G16: =Base_OAPDI!H74 -> 8 artículos [validar si es anual] | H16: =Base_OAPDI!I74 -> A39 | I16: =Base_OAPDI!J74 -> 140 · Vicerrectoría de Investigación, Extensión y Transferencia | J16: =Base_OAPDI!K74 -> Investigación (grupos, semilleros, revista, centro de pensamiento) | K16: =Base_OAPDI!L74 -> Investigación | L16: =Base_OAPDI!N74 -> 5 | M16: =Base_OAPDI!P74 -> 3 | N16: =Base_OAPDI!Q74 -> 0 | O16: =Base_OAPDI!R74 -> Acciones propuestas por la OAPDI (valídelas y formúlelas en esta fila o en Acciones adicionales): A27-042 Fortalecer la Revista Letras ETITC y Cuadernos ETITC (pares, convocatorias); A27-043 Vincular trabajos de grado y semilleros a artículos con docentes. Cerrar o reprogramar 3 producto(s) 2026 pendiente(s) de esta meta. | P16: =Base_OAPDI!S74 -> IMP-21; IMP-20 | AB16: =IF(AA16="","",INDEX(Catalogos!$Y$5:$Y$25,MATCH(AA16,L_IMP,0))) | AF16: =IF(Q16="","Pendiente por formular",IF(OR(S16="",T16="",U16="",V16="",W16="",X16="",Z16="",AA16=""),"Incompleta: faltan campos obligatorios",IF(OR(NOT(ISNUMBER(T16)),NOT(ISNUMBER(U16))),"Fecha inválida",IF(U16<T16,"La fecha de fin es anterior a la de inicio",IF(OR(YEAR(T16)<>2027,YEAR(U16)<>2027),"Fechas fuera de la vigencia 2027",IF(ISERROR(SEARCH("@itc.edu.co",V16)),"El responsable no tiene correo institucional",IF(ISERROR(SEARCH(Z16,INDEX(Catalogos!$Z$5:$Z$25,MATCH(AA16,L_IMP,0)))),"La dimensión no corresponde al indicador de impacto","OK"))))))) -> Pendiente por formular
A17: =Base_OAPDI!A75 -> E2-011 | B17: =Base_OAPDI!B75 -> 2.3.1.1 | C17: =Base_OAPDI!D75 -> 2.3 Alianzas estratégicas para la investigación | D17: =Base_OAPDI!E75 -> Contar con cuatro (4) patentes registradas sobre la base de los desarrollos logrados con las alianzas con el sector productivo o institucional. | E17: =Base_OAPDI!F75 -> N.° de solicitudes y de patentes registradas | F17: =Base_OAPDI!G75 -> 4 patentes | G17: =Base_OAPDI!H75 -> Sugerido: (2 solicitudes de patente o modelo de utilidad radicadas ante la SIC —avance hacia 4 en 2032— y mantenimiento de la patente vigente) | H17: =Base_OAPDI!I75 -> A06 | I17: =Base_OAPDI!J75 -> 101 · Oficina Asesora de Planeación y Desarrollo Institucional | J17: =Base_OAPDI!K75 -> Gestión de Proyectos | K17: =Base_OAPDI!L75 -> Direccionamiento Institucional | L17: =Base_OAPDI!N75 -> 1 | M17: =Base_OAPDI!P75 -> 0 | N17: =Base_OAPDI!Q75 -> 0 | O17: =Base_OAPDI!R75 -> Formular al menos una acción que contribuya a la meta institucional 2027 de esta meta. | P17: =Base_OAPDI!S75 -> IMP-17; IMP-20 | AB17: =IF(AA17="","",INDEX(Catalogos!$Y$5:$Y$25,MATCH(AA17,L_IMP,0))) | AF17: =IF(Q17="","Pendiente por formular",IF(OR(S17="",T17="",U17="",V17="",W17="",X17="",Z17="",AA17=""),"Incompleta: faltan campos obligatorios",IF(OR(NOT(ISNUMBER(T17)),NOT(ISNUMBER(U17))),"Fecha inválida",IF(U17<T17,"La fecha de fin es anterior a la de inicio",IF(OR(YEAR(T17)<>2027,YEAR(U17)<>2027),"Fechas fuera de la vigencia 2027",IF(ISERROR(SEARCH("@itc.edu.co",V17)),"El responsable no tiene correo institucional",IF(ISERROR(SEARCH(Z17,INDEX(Catalogos!$Z$5:$Z$25,MATCH(AA17,L_IMP,0)))),"La dimensión no corresponde al indicador de impacto","OK"))))))) -> Pendiente por formular
A18: =Base_OAPDI!A76 -> E2-012 | B18: =Base_OAPDI!B76 -> 2.3.1.1 | C18: =Base_OAPDI!D76 -> 2.3 Alianzas estratégicas para la investigación | D18: =Base_OAPDI!E76 -> Contar con cuatro (4) patentes registradas sobre la base de los desarrollos logrados con las alianzas con el sector productivo o institucional. | E18: =Base_OAPDI!F76 -> N.° de solicitudes y de patentes registradas | F18: =Base_OAPDI!G76 -> 4 patentes | G18: =Base_OAPDI!H76 -> Sugerido: (2 solicitudes de patente o modelo de utilidad radicadas ante la SIC —avance hacia 4 en 2032— y mantenimiento de la patente vigente) | H18: =Base_OAPDI!I76 -> A38 | I18: =Base_OAPDI!J76 -> 140 · Vicerrectoría de Investigación, Extensión y Transferencia | J18: =Base_OAPDI!K76 -> Despacho de la VIET | K18: =Base_OAPDI!L76 -> Investigación | L18: =Base_OAPDI!N76 -> 2 | M18: =Base_OAPDI!P76 -> 1 | N18: =Base_OAPDI!Q76 -> 0 | O18: =Base_OAPDI!R76 -> Acciones propuestas por la OAPDI (valídelas y formúlelas en esta fila o en Acciones adicionales): A27-045 Formalizar alianzas de codesarrollo con IES, empresas, centros y entidades públicas. Cerrar o reprogramar 1 producto(s) 2026 pendiente(s) de esta meta. | P18: =Base_OAPDI!S76 -> IMP-17; IMP-20 | AB18: =IF(AA18="","",INDEX(Catalogos!$Y$5:$Y$25,MATCH(AA18,L_IMP,0))) | AF18: =IF(Q18="","Pendiente por formular",IF(OR(S18="",T18="",U18="",V18="",W18="",X18="",Z18="",AA18=""),"Incompleta: faltan campos obligatorios",IF(OR(NOT(ISNUMBER(T18)),NOT(ISNUMBER(U18))),"Fecha inválida",IF(U18<T18,"La fecha de fin es anterior a la de inicio",IF(OR(YEAR(T18)<>2027,YEAR(U18)<>2027),"Fechas fuera de la vigencia 2027",IF(ISERROR(SEARCH("@itc.edu.co",V18)),"El responsable no tiene correo institucional",IF(ISERROR(SEARCH(Z18,INDEX(Catalogos!$Z$5:$Z$25,MATCH(AA18,L_IMP,0)))),"La dimensión no corresponde al indicador de impacto","OK"))))))) -> Pendiente por formular
... A22: =Base_OAPDI!A80 -> E2-016 | B22: =Base_OAPDI!B80 -> 2.4.1.1 | C22: =Base_OAPDI!D80 -> 2.4 Vinculación de lo investigativo con lo académico | D22: =Base_OAPDI!E80 -> Contar con un (1) centro de pensamiento y desarrollo tecnológico registrado en Colciencias (MinCiencias) y articulado con el Parque Tecnológico de Funza. | E22: =Base_OAPDI!F80 -> Centro de pensamiento reconocido por MinCiencias (fase de avance) | F22: =Base_OAPDI!G80 -> 1 centro reconocido | G22: =Base_OAPDI!H80 -> Puesta en marcha del Centro de Pensamiento | H22: =Base_OAPDI!I80 -> A40 | I22: =Base_OAPDI!J80 -> 140 · Vicerrectoría de Investigación, Extensión y Transferencia | J22: =Base_OAPDI!K80 -> Innovación y Laboratorio Inteligente | K22: =Base_OAPDI!L80 -> Investigación | L22: =Base_OAPDI!N80 -> 7 | M22: =Base_OAPDI!P80 -> 2 | N22: =Base_OAPDI!Q80 -> 0 | O22: =Base_OAPDI!R80 -> Cerrar o reprogramar 2 producto(s) 2026 pendiente(s) de esta meta. | P22: =Base_OAPDI!S80 -> IMP-20; IMP-03 | AB22: =IF(AA22="","",INDEX(Catalogos!$Y$5:$Y$25,MATCH(AA22,L_IMP,0))) | AF22: =IF(Q22="","Pendiente por formular",IF(OR(S22="",T22="",U22="",V22="",W22="",X22="",Z22="",AA22=""),"Incompleta: faltan campos obligatorios",IF(OR(NOT(ISNUMBER(T22)),NOT(ISNUMBER(U22))),"Fecha inválida",IF(U22<T22,"La fecha de fin es anterior a la de inicio",IF(OR(YEAR(T22)<>2027,YEAR(U22)<>2027),"Fechas fuera de la vigencia 2027",IF(ISERROR(SEARCH("@itc.edu.co",V22)),"El responsable no tiene correo institucional",IF(ISERROR(SEARCH(Z22,INDEX(Catalogos!$Z$5:$Z$25,MATCH(AA22,L_IMP,0)))),"La dimensión no corresponde al indicador de impacto","OK"))))))) -> Pendiente por formular

Sheet Eje3_Extension
A1: Eje estratégico 3. Extensión y proyección institucional — Formulación del Plan de Acción 2027
A2: Objetivo estratégico del eje: Ofrecer programas y servicios innovadores y de alta calidad que respondan eficazmente a las necesidades del sector productivo y social, promoviendo su bienestar y su desarrollo sostenible.
A3: Columnas grises: base definida por la OAPDI (no modificar). Columnas amarillas: las diligencia el área responsable, una acción por fila. Si necesita formular más acciones para una meta, use la hoja Buscador_Formulacion.
A5: BASE DEFINIDA POR LA OAPDI | Q5: FORMULACIÓN DEL ÁREA RESPONSABLE | AF5: CONTROL
A6: Id asignación | B6: Código meta | C6: Línea | D6: Meta estratégica (PDI) | E6: Indicador de la meta | F6: Meta 2032 | G6: Meta institucional 2027 | H6: Id área | I6: Dependencia | J6: Área funcional | K6: Proceso | L6: Productos 2026 (sábana vigente) | M6: Pendientes 2026 | N6: Compromisos de proyectos estructurantes | O6: Aporte esperado del área 2027 | P6: Indicadores de impacto sugeridos | Q6: Nombre de la acción | R6: Descripción de la acción | S6: Producto esperado | T6: Fecha de inicio (dd/mm/aaaa) | U6: Fecha de fin (dd/mm/aaaa) | V6: Responsable (correo institucional) | W6: Indicador de seguimiento | X6: Meta 2027 de la acción | Y6: Unidad de medida | Z6: Dimensión de impacto | AA6: Indicador de impacto (Guía Metodológica) | AB6: Categoría de impacto (automática) | AC6: ¿Retoma un compromiso pendiente 2026? | AD6: Evidencia verificable | AE6: Observaciones | AF6: Alerta de consistencia
A7: =Base_OAPDI!A81 -> E3-001 | B7: =Base_OAPDI!B81 -> 3.1.1.1 | C7: =Base_OAPDI!D81 -> 3.1 Autonomía y posicionamiento de la Extensión y Proyección Institucional | D7: =Base_OAPDI!E81 -> Disponer a mediano plazo de una vicerrectoría de extensión y proyección social. | E7: =Base_OAPDI!F81 -> Modelo de gestión autónoma de la extensión adoptado y operando (fase) | F7: =Base_OAPDI!G81 -> Sugerido: (extensión con autonomía administrativa y financiera operando desde el GIT de Extensión y Proyección Social, sin crear una nueva vicerrectoría) | G7: =Base_OAPDI!H81 -> Sugerido: (modelo de gestión autónoma de la extensión adoptado por acto administrativo: estatuto de extensión actualizado, centro de costos propio del GIT y procedimientos de la extensión en el SGC) | H7: =Base_OAPDI!I81 -> A38 | I7: =Base_OAPDI!J81 -> 140 · Vicerrectoría de Investigación, Extensión y Transferencia | J7: =Base_OAPDI!K81 -> Despacho de la VIET | K7: =Base_OAPDI!L81 -> Investigación | L7: =Base_OAPDI!N81 -> 0 | M7: =Base_OAPDI!P81 -> 0 | N7: =Base_OAPDI!Q81 -> 0 | O7: =Base_OAPDI!R81 -> Formular al menos una acción que contribuya a la meta institucional 2027 de esta meta. | P7: =Base_OAPDI!S81 -> IMP-18; IMP-17 | AB7: =IF(AA7="","",INDEX(Catalogos!$Y$5:$Y$25,MATCH(AA7,L_IMP,0))) | AF7: =IF(Q7="","Pendiente por formular",IF(OR(S7="",T7="",U7="",V7="",W7="",X7="",Z7="",AA7=""),"Incompleta: faltan campos obligatorios",IF(OR(NOT(ISNUMBER(T7)),NOT(ISNUMBER(U7))),"Fecha inválida",IF(U7<T7,"La fecha de fin es anterior a la de inicio",IF(OR(YEAR(T7)<>2027,YEAR(U7)<>2027),"Fechas fuera de la vigencia 2027",IF(ISERROR(SEARCH("@itc.edu.co",V7)),"El responsable no tiene correo institucional",IF(ISERROR(SEARCH(Z7,INDEX(Catalogos!$Z$5:$Z$25,MATCH(AA7,L_IMP,0)))),"La dimensión no corresponde al indicador de impacto","OK"))))))) -> Pendiente por formular
A8: =Base_OAPDI!A82 -> E3-002 | B8: =Base_OAPDI!B82 -> 3.1.1.1 | C8: =Base_OAPDI!D82 -> 3.1 Autonomía y posicionamiento de la Extensión y Proyección Institucional | D8: =Base_OAPDI!E82 -> Disponer a mediano plazo de una vicerrectoría de extensión y proyección social. | E8: =Base_OAPDI!F82 -> Modelo de gestión autónoma de la extensión adoptado y operando (fase) | F8: =Base_OAPDI!G82 -> Sugerido: (extensión con autonomía administrativa y financiera operando desde el GIT de Extensión y Proyección Social, sin crear una nueva vicerrectoría) | G8: =Base_OAPDI!H82 -> Sugerido: (modelo de gestión autónoma de la extensión adoptado por acto administrativo: estatuto de extensión actualizado, centro de costos propio del GIT y procedimientos de la extensión en el SGC) | H8: =Base_OAPDI!I82 -> A41 | I8: =Base_OAPDI!J82 -> 141 · GIT Extensión y Proyección Social | J8: =Base_OAPDI!K82 -> GIT Extensión y Proyección Social (incluye ETDH) | K8: =Base_OAPDI!L82 -> Extensión y Proyección Social | L8: =Base_OAPDI!N82 -> 0 | M8: =Base_OAPDI!P82 -> 0 | N8: =Base_OAPDI!Q82 -> 0 | O8: =Base_OAPDI!R82 -> Acciones propuestas por la OAPDI (valídelas y formúlelas en esta fila o en Acciones adicionales): A27-051 Actualizar el estatuto o reglamento de extensión con las reglas de autonomía del GIT (contratación de servicios, precios, excedentes); A27-053 Documentar y codificar en el SGC los procedimientos de la extensión. | P8: =Base_OAPDI!S82 -> IMP-18; IMP-17 | AB8: =IF(AA8="","",INDEX(Catalogos!$Y$5:$Y$25,MATCH(AA8,L_IMP,0))) | AF8: =IF(Q8="","Pendiente por formular",IF(OR(S8="",T8="",U8="",V8="",W8="",X8="",Z8="",AA8=""),"Incompleta: faltan campos obligatorios",IF(OR(NOT(ISNUMBER(T8)),NOT(ISNUMBER(U8))),"Fecha inválida",IF(U8<T8,"La fecha de fin es anterior a la de inicio",IF(OR(YEAR(T8)<>2027,YEAR(U8)<>2027),"Fechas fuera de la vigencia 2027",IF(ISERROR(SEARCH("@itc.edu.co",V8)),"El responsable no tiene correo institucional",IF(ISERROR(SEARCH(Z8,INDEX(Catalogos!$Z$5:$Z$25,MATCH(AA8,L_IMP,0)))),"La dimensión no corresponde al indicador de impacto","OK"))))))) -> Pendiente por formular
A9: =Base_OAPDI!A83 -> E3-003 | B9: =Base_OAPDI!B83 -> 3.1.1.1 | C9: =Base_OAPDI!D83 -> 3.1 Autonomía y posicionamiento de la Extensión y Proyección Institucional | D9: =Base_OAPDI!E83 -> Disponer a mediano plazo de una vicerrectoría de extensión y proyección social. | E9: =Base_OAPDI!F83 -> Modelo de gestión autónoma de la extensión adoptado y operando (fase) | F9: =Base_OAPDI!G83 -> Sugerido: (extensión con autonomía administrativa y financiera operando desde el GIT de Extensión y Proyección Social, sin crear una nueva vicerrectoría) | G9: =Base_OAPDI!H83 -> Sugerido: (modelo de gestión autónoma de la extensión adoptado por acto administrativo: estatuto de extensión actualizado, centro de costos propio del GIT y procedimientos de la extensión en el SGC) | H9: =Base_OAPDI!I83 -> A47 | I9: =Base_OAPDI!J83 -> 130 · Vicerrectoría Administrativa y Financiera | J9: =Base_OAPDI!K83 -> Gestión Financiera (Presupuesto, Contabilidad, Tesorería) | K9: =Base_OAPDI!L83 -> Gestión Financiera | L9: =Base_OAPDI!N83 -> 0 | M9: =Base_OAPDI!P83 -> 0 | N9: =Base_OAPDI!Q83 -> 0 | O9: =Base_OAPDI!R83 -> Acciones propuestas por la OAPDI (valídelas y formúlelas en esta fila o en Acciones adicionales): A27-052 Crear el centro de costos propio de la extensión con Gestión Financiera. | P9: =Base_OAPDI!S83 -> IMP-18; IMP-17 | AB9: =IF(AA9="","",INDEX(Catalogos!$Y$5:$Y$25,MATCH(AA9,L_IMP,0))) | AF9: =IF(Q9="","Pendiente por formular",IF(OR(S9="",T9="",U9="",V9="",W9="",X9="",Z9="",AA9=""),"Incompleta: faltan campos obligatorios",IF(OR(NOT(ISNUMBER(T9)),NOT(ISNUMBER(U9))),"Fecha inválida",IF(U9<T9,"La fecha de fin es anterior a la de inicio",IF(OR(YEAR(T9)<>2027,YEAR(U9)<>2027),"Fechas fuera de la vigencia 2027",IF(ISERROR(SEARCH("@itc.edu.co",V9)),"El responsable no tiene correo institucional",IF(ISERROR(SEARCH(Z9,INDEX(Catalogos!$Z$5:$Z$25,MATCH(AA9,L_IMP,0)))),"La dimensión no corresponde al indicador de impacto","OK"))))))) -> Pendiente por formular
A10: =Base_OAPDI!A84 -> E3-004 | B10: =Base_OAPDI!B84 -> 3.1.1.1 | C10: =Base_OAPDI!D84 -> 3.1 Autonomía y posicionamiento de la Extensión y Proyección Institucional | D10: =Base_OAPDI!E84 -> Disponer a mediano plazo de una vicerrectoría de extensión y proyección social. | E10: =Base_OAPDI!F84 -> Modelo de gestión autónoma de la extensión adoptado y operando (fase) | F10: =Base_OAPDI!G84 -> Sugerido: (extensión con autonomía administrativa y financiera operando desde el GIT de Extensión y Proyección Social, sin crear una nueva vicerrectoría) | G10: =Base_OAPDI!H84 -> Sugerido: (modelo de gestión autónoma de la extensión adoptado por acto administrativo: estatuto de extensión actualizado, centro de costos propio del GIT y procedimientos de la extensión en el SGC) | H10: =Base_OAPDI!I84 -> A05 | I10: =Base_OAPDI!J84 -> 101 · Oficina Asesora de Planeación y Desarrollo Institucional | J10: =Base_OAPDI!K84 -> Planeación y Plan de Acción | K10: =Base_OAPDI!L84 -> Direccionamiento Institucional | L10: =Base_OAPDI!N84 -> 0 | M10: =Base_OAPDI!P84 -> 0 | N10: =Base_OAPDI!Q84 -> 0 | O10: =Base_OAPDI!R84 -> Acciones propuestas por la OAPDI (valídelas y formúlelas en esta fila o en Acciones adicionales): A27-054 Presentar al Consejo Directivo la propuesta de ajuste del enunciado de la meta 3.1.1.1 en la revisión del PDI. | P10: =Base_OAPDI!S84 -> IMP-18; IMP-17 | AB10: =IF(AA10="","",INDEX(Catalogos!$Y$5:$Y$25,MATCH(AA10,L_IMP,0))) | AF10: =IF(Q10="","Pendiente por formular",IF(OR(S10="",T10="",U10="",V10="",W10="",X10="",Z10="",AA10=""),"Incompleta: faltan campos obligatorios",IF(OR(NOT(ISNUMBER(T10)),NOT(ISNUMBER(U10))),"Fecha inválida",IF(U10<T10,"La fecha de fin es anterior a la de inicio",IF(OR(YEAR(T10)<>2027,YEAR(U10)<>2027),"Fechas fuera de la vigencia 2027",IF(ISERROR(SEARCH("@itc.edu.co",V10)),"El responsable no tiene correo institucional",IF(ISERROR(SEARCH(Z10,INDEX(Catalogos!$Z$5:$Z$25,MATCH(AA10,L_IMP,0)))),"La dimensión no corresponde al indicador de impacto","OK"))))))) -> Pendiente por formular
A11: =Base_OAPDI!A85 -> E3-005 | B11: =Base_OAPDI!B85 -> 3.2.1.1 | C11: =Base_OAPDI!D85 -> 3.2 Fortalecimiento de la innovación para la Proyección Institucional | D11: =Base_OAPDI!E85 -> Diseñar y diversificar la oferta de programas de educación continuada y Educación para el Trabajo y el Desarrollo Humano. | E11: =Base_OAPDI!F85 -> N.° de ofertas de educación continuada y ETDH, participantes y % en modalidad virtual | F11: =Base_OAPDI!G85 -> Sugerido: (60 ofertas anuales, 30% en modalidad virtual o b-learning) | G11: =Base_OAPDI!H85 -> Sugerido: (34 ofertas —+20% sobre 2025—, de las cuales al menos 8 en modalidad virtual o b-learning, y 2 programas ETDH reactivados) | H11: =Base_OAPDI!I85 -> A07 | I11: =Base_OAPDI!J85 -> 101 · Oficina Asesora de Planeación y Desarrollo Institucional | J11: =Base_OAPDI!K85 -> Autoevaluación y Acreditación | K11: =Base_OAPDI!L85 -> Gestión del Sistema Integrado de Aseguramiento | L11: =Base_OAPDI!N85 -> 3 | M11: =Base_OAPDI!P85 -> 0 | N11: =Base_OAPDI!Q85 -> 0 | O11: =Base_OAPDI!R85 -> Formular al menos una acción que contribuya a la meta institucional 2027 de esta meta. | P11: =Base_OAPDI!S85 -> IMP-10; IMP-11 | AB11: =IF(AA11="","",INDEX(Catalogos!$Y$5:$Y$25,MATCH(AA11,L_IMP,0))) | AF11: =IF(Q11="","Pendiente por formular",IF(OR(S11="",T11="",U11="",V11="",W11="",X11="",Z11="",AA11=""),"Incompleta: faltan campos obligatorios",IF(OR(NOT(ISNUMBER(T11)),NOT(ISNUMBER(U11))),"Fecha inválida",IF(U11<T11,"La fecha de fin es anterior a la de inicio",IF(OR(YEAR(T11)<>2027,YEAR(U11)<>2027),"Fechas fuera de la vigencia 2027",IF(ISERROR(SEARCH("@itc.edu.co",V11)),"El responsable no tiene correo institucional",IF(ISERROR(SEARCH(Z11,INDEX(Catalogos!$Z$5:$Z$25,MATCH(AA11,L_IMP,0)))),"La dimensión no corresponde al indicador de impacto","OK"))))))) -> Pendiente por formular
A12: =Base_OAPDI!A86 -> E3-006 | B12: =Base_OAPDI!B86 -> 3.2.1.1 | C12: =Base_OAPDI!D86 -> 3.2 Fortalecimiento de la innovación para la Proyección Institucional | D12: =Base_OAPDI!E86 -> Diseñar y diversificar la oferta de programas de educación continuada y Educación para el Trabajo y el Desarrollo Humano. | E12: =Base_OAPDI!F86 -> N.° de ofertas de educación continuada y ETDH, participantes y % en modalidad virtual | F12: =Base_OAPDI!G86 -> Sugerido: (60 ofertas anuales, 30% en modalidad virtual o b-learning) | G12: =Base_OAPDI!H86 -> Sugerido: (34 ofertas —+20% sobre 2025—, de las cuales al menos 8 en modalidad virtual o b-learning, y 2 programas ETDH reactivados) | H12: =Base_OAPDI!I86 -> A41 | I12: =Base_OAPDI!J86 -> 141 · GIT Extensión y Proyección Social | J12: =Base_OAPDI!K86 -> GIT Extensión y Proyección Social (incluye ETDH) | K12: =Base_OAPDI!L86 -> Extensión y Proyección Social | L12: =Base_OAPDI!N86 -> 8 | M12: =Base_OAPDI!P86 -> 4 | N12: =Base_OAPDI!Q86 -> 0 | O12: =Base_OAPDI!R86 -> Acciones propuestas por la OAPDI (valídelas y formúlelas en esta fila o en Acciones adicionales): A27-055 Analizar necesidades y mercado (egresados, empresas, regiones) y actualizar el portafolio; A27-057 Reactivar 2 programas ETDH con reglamento de formadores; A27-058 Ejecutar y evaluar la oferta 2027. Cerrar o reprogramar 4 producto(s) 2026 pendiente(s) de esta meta. | P12: =Base_OAPDI!S86 -> IMP-10; IMP-11 | AB12: =IF(AA12="","",INDEX(Catalogos!$Y$5:$Y$25,MATCH(AA12,L_IMP,0))) | AF12: =IF(Q12="","Pendiente por formular",IF(OR(S12="",T12="",U12="",V12="",W12="",X12="",Z12="",AA12=""),"Incompleta: faltan campos obligatorios",IF(OR(NOT(ISNUMBER(T12)),NOT(ISNUMBER(U12))),"Fecha inválida",IF(U12<T12,"La fecha de fin es anterior a la de inicio",IF(OR(YEAR(T12)<>2027,YEAR(U12)<>2027),"Fechas fuera de la vigencia 2027",IF(ISERROR(SEARCH("@itc.edu.co",V12)),"El responsable no tiene correo institucional",IF(ISERROR(SEARCH(Z12,INDEX(Catalogos!$Z$5:$Z$25,MATCH(AA12,L_IMP,0)))),"La dimensión no corresponde al indicador de impacto","OK"))))))) -> Pendiente por formular
A13: =Base_OAPDI!A87 -> E3-007 | B13: =Base_OAPDI!B87 -> 3.2.1.1 | C13: =Base_OAPDI!D87 -> 3.2 Fortalecimiento de la innovación para la Proyección Institucional | D13: =Base_OAPDI!E87 -> Diseñar y diversificar la oferta de programas de educación continuada y Educación para el Trabajo y el Desarrollo Humano. | E13: =Base_OAPDI!F87 -> N.° de ofertas de educación continuada y ETDH, participantes y % en modalidad virtual | F13: =Base_OAPDI!G87 -> Sugerido: (60 ofertas anuales, 30% en modalidad virtual o b-learning) | G13: =Base_OAPDI!H87 -> Sugerido: (34 ofertas —+20% sobre 2025—, de las cuales al menos 8 en modalidad virtual o b-learning, y 2 programas ETDH reactivados) | H13: =Base_OAPDI!I87 -> A17 | I13: =Base_OAPDI!J87 -> 120 · Vicerrectoría Académica | J13: =Base_OAPDI!K87 -> Unidad B-Learning | K13: =Base_OAPDI!L87 -> Docencia PES | L13: =Base_OAPDI!N87 -> 0 | M13: =Base_OAPDI!P87 -> 0 | N13: =Base_OAPDI!Q87 -> 0 | O13: =Base_OAPDI!R87 -> Acciones propuestas por la OAPDI (valídelas y formúlelas en esta fila o en Acciones adicionales): A27-056 Virtualizar 8 ofertas con la Unidad B-Learning (certificaciones, diplomados, cursos de lenguas). | P13: =Base_OAPDI!S87 -> IMP-10; IMP-11 | AB13: =IF(AA13="","",INDEX(Catalogos!$Y$5:$Y$25,MATCH(AA13,L_IMP,0))) | AF13: =IF(Q13="","Pendiente por formular",IF(OR(S13="",T13="",U13="",V13="",W13="",X13="",Z13="",AA13=""),"Incompleta: faltan campos obligatorios",IF(OR(NOT(ISNUMBER(T13)),NOT(ISNUMBER(U13))),"Fecha inválida",IF(U13<T13,"La fecha de fin es anterior a la de inicio",IF(OR(YEAR(T13)<>2027,YEAR(U13)<>2027),"Fechas fuera de la vigencia 2027",IF(ISERROR(SEARCH("@itc.edu.co",V13)),"El responsable no tiene correo institucional",IF(ISERROR(SEARCH(Z13,INDEX(Catalogos!$Z$5:$Z$25,MATCH(AA13,L_IMP,0)))),"La dimensión no corresponde al indicador de impacto","OK"))))))) -> Pendiente por formular
A14: =Base_OAPDI!A88 -> E3-008 | B14: =Base_OAPDI!B88 -> 3.2.1.2 | C14: =Base_OAPDI!D88 -> 3.2 Fortalecimiento de la innovación para la Proyección Institucional | D14: =Base_OAPDI!E88 -> Generar ingresos para la ETITC mediante la comercialización de su portafolio de servicios, fortaleciendo su sostenibilidad financiera por vigencia. | E14: =Base_OAPDI!F88 -> Ingresos por venta de servicios de extensión (millones $) | F14: =Base_OAPDI!G88 -> Sugerido: (crecimiento sostenido del 7% anual) | G14: =Base_OAPDI!H88 -> Sugerido: ($590 millones —7% anual sobre el recaudo 2025—) | H14: =Base_OAPDI!I88 -> A41 | I14: =Base_OAPDI!J88 -> 141 · GIT Extensión y Proyección Social | J14: =Base_OAPDI!K88 -> GIT Extensión y Proyección Social (incluye ETDH) | K14: =Base_OAPDI!L88 -> Extensión y Proyección Social | L14: =Base_OAPDI!N88 -> 15 | M14: =Base_OAPDI!P88 -> 8 | N14: =Base_OAPDI!Q88 -> 0 | O14: =Base_OAPDI!R88 -> Acciones propuestas por la OAPDI (valídelas y formúlelas en esta fila o en Acciones adicionales): A27-059 Definir precios y metas de venta por servicio; A27-060 Ofertar certificaciones, diplomados, consultorías y cursos a la medida para empresas. Cerrar o reprogramar 8 producto(s) 2026 pendiente(s) de esta meta. | P14: =Base_OAPDI!S88 -> IMP-17 | AB14: =IF(AA14="","",INDEX(Catalogos!$Y$5:$Y$25,MATCH(AA14,L_IMP,0))) | AF14: =IF(Q14="","Pendiente por formular",IF(OR(S14="",T14="",U14="",V14="",W14="",X14="",Z14="",AA14=""),"Incompleta: faltan campos obligatorios",IF(OR(NOT(ISNUMBER(T14)),NOT(ISNUMBER(U14))),"Fecha inválida",IF(U14<T14,"La fecha de fin es anterior a la de inicio",IF(OR(YEAR(T14)<>2027,YEAR(U14)<>2027),"Fechas fuera de la vigencia 2027",IF(ISERROR(SEARCH("@itc.edu.co",V14)),"El responsable no tiene correo institucional",IF(ISERROR(SEARCH(Z14,INDEX(Catalogos!$Z$5:$Z$25,MATCH(AA14,L_IMP,0)))),"La dimensión no corresponde al indicador de impacto","OK"))))))) -> Pendiente por formular
A15: =Base_OAPDI!A89 -> E3-009 | B15: =Base_OAPDI!B89 -> 3.2.1.2 | C15: =Base_OAPDI!D89 -> 3.2 Fortalecimiento de la innovación para la Proyección Institucional | D15: =Base_OAPDI!E89 -> Generar ingresos para la ETITC mediante la comercialización de su portafolio de servicios, fortaleciendo su sostenibilidad financiera por vigencia. | E15: =Base_OAPDI!F89 -> Ingresos por venta de servicios de extensión (millones $) | F15: =Base_OAPDI!G89 -> Sugerido: (crecimiento sostenido del 7% anual) | G15: =Base_OAPDI!H89 -> Sugerido: ($590 millones —7% anual sobre el recaudo 2025—) | H15: =Base_OAPDI!I89 -> A47 | I15: =Base_OAPDI!J89 -> 130 · Vicerrectoría Administrativa y Financiera | J15: =Base_OAPDI!K89 -> Gestión Financiera (Presupuesto, Contabilidad, Tesorería) | K15: =Base_OAPDI!L89 -> Gestión Financiera | L15: =Base_OAPDI!N89 -> 0 | M15: =Base_OAPDI!P89 -> 0 | N15: =Base_OAPDI!Q89 -> 0 | O15: =Base_OAPDI!R89 -> Acciones propuestas por la OAPDI (valídelas y formúlelas en esta fila o en Acciones adicionales): A27-061 Hacer seguimiento trimestral al recaudo con Gestión Financiera. | P15: =Base_OAPDI!S89 -> IMP-17 | AB15: =IF(AA15="","",INDEX(Catalogos!$Y$5:$Y$25,MATCH(AA15,L_IMP,0))) | AF15: =IF(Q15="","Pendiente por formular",IF(OR(S15="",T15="",U15="",V15="",W15="",X15="",Z15="",AA15=""),"Incompleta: faltan campos obligatorios",IF(OR(NOT(ISNUMBER(T15)),NOT(ISNUMBER(U15))),"Fecha inválida",IF(U15<T15,"La fecha de fin es anterior a la de inicio",IF(OR(YEAR(T15)<>2027,YEAR(U15)<>2027),"Fechas fuera de la vigencia 2027",IF(ISERROR(SEARCH("@itc.edu.co",V15)),"El responsable no tiene correo institucional",IF(ISERROR(SEARCH(Z15,INDEX(Catalogos!$Z$5:$Z$25,MATCH(AA15,L_IMP,0)))),"La dimensión no corresponde al indicador de impacto","OK"))))))) -> Pendiente por formular
A16: =Base_OAPDI!A90 -> E3-010 | B16: =Base_OAPDI!B90 -> 3.2.1.3 | C16: =Base_OAPDI!D90 -> 3.2 Fortalecimiento de la innovación para la Proyección Institucional | D16: =Base_OAPDI!E90 -> Implementar mecanismos de retroalimentación continua de la oferta de programas de extensión y proyección social. | E16: =Base_OAPDI!F90 -> N.° de mecanismos aplicados y % de ofertas evaluadas | F16: =Base_OAPDI!G90 -> Sugerido: (100% de las ofertas evaluadas cada periodo) | G16: =Base_OAPDI!H90 -> Sugerido: (1 mecanismo institucional de retroalimentación aplicado al 100% de las ofertas de extensión 2027, con informe semestral) | H16: =Base_OAPDI!I90 -> A41 | I16: =Base_OAPDI!J90 -> 141 · GIT Extensión y Proyección Social | J16: =Base_OAPDI!K90 -> GIT Extensión y Proyección Social (incluye ETDH) | K16: =Base_OAPDI!L90 -> Extensión y Proyección Social | L16: =Base_OAPDI!N90 -> 7 | M16: =Base_OAPDI!P90 -> 3 | N16: =Base_OAPDI!Q90 -> 0 | O16: =Base_OAPDI!R90 -> Acciones propuestas por la OAPDI (valídelas y formúlelas en esta fila o en Acciones adicionales): A27-062 Diseñar el instrumento único de retroalimentación (satisfacción, pertinencia, aplicación en el trabajo); A27-063 Aplicarlo al cierre de cada oferta y consolidar resultados; A27-064 Ajustar el portafolio con base en los resultados. Cerrar o reprogramar 3 producto(s) 2026 pendiente(s) de esta meta. | P16: =Base_OAPDI!S90 -> IMP-18 | AB16: =IF(AA16="","",INDEX(Catalogos!$Y$5:$Y$25,MATCH(AA16,L_IMP,0))) | AF16: =IF(Q16="","Pendiente por formular",IF(OR(S16="",T16="",U16="",V16="",W16="",X16="",Z16="",AA16=""),"Incompleta: faltan campos obligatorios",IF(OR(NOT(ISNUMBER(T16)),NOT(ISNUMBER(U16))),"Fecha inválida",IF(U16<T16,"La fecha de fin es anterior a la de inicio",IF(OR(YEAR(T16)<>2027,YEAR(U16)<>2027),"Fechas fuera de la vigencia 2027",IF(ISERROR(SEARCH("@itc.edu.co",V16)),"El responsable no tiene correo institucional",IF(ISERROR(SEARCH(Z16,INDEX(Catalogos!$Z$5:$Z$25,MATCH(AA16,L_IMP,0)))),"La dimensión no corresponde al indicador de impacto","OK"))))))) -> Pendiente por formular
A17: =Base_OAPDI!A91 -> E3-011 | B17: =Base_OAPDI!B91 -> 3.2.1.3 | C17: =Base_OAPDI!D91 -> 3.2 Fortalecimiento de la innovación para la Proyección Institucional | D17: =Base_OAPDI!E91 -> Implementar mecanismos de retroalimentación continua de la oferta de programas de extensión y proyección social. | E17: =Base_OAPDI!F91 -> N.° de mecanismos aplicados y % de ofertas evaluadas | F17: =Base_OAPDI!G91 -> Sugerido: (100% de las ofertas evaluadas cada periodo) | G17: =Base_OAPDI!H91 -> Sugerido: (1 mecanismo institucional de retroalimentación aplicado al 100% de las ofertas de extensión 2027, con informe semestral) | H17: =Base_OAPDI!I91 -> A42 | I17: =Base_OAPDI!J91 -> 141 · GIT Extensión y Proyección Social | J17: =Base_OAPDI!K91 -> Centro de Lenguas (CEL) | K17: =Base_OAPDI!L91 -> Extensión y Proyección Social | L17: =Base_OAPDI!N91 -> 2 | M17: =Base_OAPDI!P91 -> 1 | N17: =Base_OAPDI!Q91 -> 0 | O17: =Base_OAPDI!R91 -> Cerrar o reprogramar 1 producto(s) 2026 pendiente(s) de esta meta. | P17: =Base_OAPDI!S91 -> IMP-18 | AB17: =IF(AA17="","",INDEX(Catalogos!$Y$5:$Y$25,MATCH(AA17,L_IMP,0))) | AF17: =IF(Q17="","Pendiente por formular",IF(OR(S17="",T17="",U17="",V17="",W17="",X17="",Z17="",AA17=""),"Incompleta: faltan campos obligatorios",IF(OR(NOT(ISNUMBER(T17)),NOT(ISNUMBER(U17))),"Fecha inválida",IF(U17<T17,"La fecha de fin es anterior a la de inicio",IF(OR(YEAR(T17)<>2027,YEAR(U17)<>2027),"Fechas fuera de la vigencia 2027",IF(ISERROR(SEARCH("@itc.edu.co",V17)),"El responsable no tiene correo institucional",IF(ISERROR(SEARCH(Z17,INDEX(Catalogos!$Z$5:$Z$25,MATCH(AA17,L_IMP,0)))),"La dimensión no corresponde al indicador de impacto","OK"))))))) -> Pendiente por formular
A18: =Base_OAPDI!A92 -> E3-012 | B18: =Base_OAPDI!B92 -> 3.2.1.4 | C18: =Base_OAPDI!D92 -> 3.2 Fortalecimiento de la innovación para la Proyección Institucional | D18: =Base_OAPDI!E92 -> Alinear la formación en una segunda lengua en la ETITC con los estándares del Marco Común Europeo de Referencia para las Lenguas. | E18: =Base_OAPDI!F92 -> % de cursos de segunda lengua alineados al MCER | F18: =Base_OAPDI!G92 -> Sugerido: (100% de los cursos alineados y certificados por nivel MCER) | G18: =Base_OAPDI!H92 -> Sugerido: (100% de los cursos con syllabus y evaluación alineados a niveles MCER A1-B2, prueba de clasificación institucional y 2 cursos virtuales) | H18: =Base_OAPDI!I92 -> A42 | I18: =Base_OAPDI!J92 -> 141 · GIT Extensión y Proyección Social | J18: =Base_OAPDI!K92 -> Centro de Lenguas (CEL) | K18: =Base_OAPDI!L92 -> Extensión y Proyección Social | L18: =Base_OAPDI!N92 -> 4 | M18: =Base_OAPDI!P92 -> 1 | N18: =Base_OAPDI!Q92 -> 0 | O18: =Base_OAPDI!R92 -> Acciones propuestas por la OAPDI (valídelas y formúlelas en esta fila o en Acciones adicionales): A27-065 Diagnosticar los cursos frente a los descriptores del MCER; A27-066 Ajustar syllabus, evaluación y prueba de clasificación; A27-067 Ofrecer 2 cursos virtuales de segunda lengua. Cerrar o reprogramar 1 producto(s) 2026 pendiente(s) de esta meta. | P18: =Base_OAPDI!S92 -> IMP-11; IMP-07 | AB18: =IF(AA18="","",INDEX(Catalogos!$Y$5:$Y$25,MATCH(AA18,L_IMP,0))) | AF18: =IF(Q18="","Pendiente por formular",IF(OR(S18="",T18="",U18="",V18="",W18="",X18="",Z18="",AA18=""),"Incompleta: faltan campos obligatorios",IF(OR(NOT(ISNUMBER(T18)),NOT(ISNUMBER(U18))),"Fecha inválida",IF(U18<T18,"La fecha de fin es anterior a la de inicio",IF(OR(YEAR(T18)<>2027,YEAR(U18)<>2027),"Fechas fuera de la vigencia 2027",IF(ISERROR(SEARCH("@itc.edu.co",V18)),"El responsable no tiene correo institucional",IF(ISERROR(SEARCH(Z18,INDEX(Catalogos!$Z$5:$Z$25,MATCH(AA18,L_IMP,0)))),"La dimensión no corresponde al indicador de impacto","OK"))))))) -> Pendiente por formular
... A23: =Base_OAPDI!A97 -> E3-017 | B23: =Base_OAPDI!B97 -> 3.3.1.3 | C23: =Base_OAPDI!D97 -> 3.3 Interacción con el sector productivo y social | D23: =Base_OAPDI!E97 -> Establecer convenios y fortalecer redes de colaboración con sectores productivos, sociales y educativos, tanto públicos como privados. | E23: =Base_OAPDI!F97 -> N.° de convenios y redes activos | F23: =Base_OAPDI!G97 -> Sugerido: (90 convenios activos) | G23: =Base_OAPDI!H97 -> Sugerido: (75 convenios activos —renovación de los que vencen y 4 nuevos— y 2 redes nuevas) | H23: =Base_OAPDI!I97 -> A03 | I23: =Base_OAPDI!J97 -> 100 · Rectoría | J23: =Base_OAPDI!K97 -> Internacionalización (ORII) | K23: =Base_OAPDI!L97 -> Gestión de Internacionalización | L23: =Base_OAPDI!N97 -> 0 | M23: =Base_OAPDI!P97 -> 0 | N23: =Base_OAPDI!Q97 -> 0 | O23: =Base_OAPDI!R97 -> Acciones propuestas por la OAPDI (valídelas y formúlelas en esta fila o en Acciones adicionales): A27-075 Afiliarse a 2 redes nuevas (por ejemplo, RIUC y renovación RCI ASCUN). | P23: =Base_OAPDI!S97 -> IMP-03; IMP-04 | AB23: =IF(AA23="","",INDEX(Catalogos!$Y$5:$Y$25,MATCH(AA23,L_IMP,0))) | AF23: =IF(Q23="","Pendiente por formular",IF(OR(S23="",T23="",U23="",V23="",W23="",X23="",Z23="",AA23=""),"Incompleta: faltan campos obligatorios",IF(OR(NOT(ISNUMBER(T23)),NOT(ISNUMBER(U23))),"Fecha inválida",IF(U23<T23,"La fecha de fin es anterior a la de inicio",IF(OR(YEAR(T23)<>2027,YEAR(U23)<>2027),"Fechas fuera de la vigencia 2027",IF(ISERROR(SEARCH("@itc.edu.co",V23)),"El responsable no tiene correo institucional",IF(ISERROR(SEARCH(Z23,INDEX(Catalogos!$Z$5:$Z$25,MATCH(AA23,L_IMP,0)))),"La dimensión no corresponde al indicador de impacto","OK"))))))) -> Pendiente por formular

Sheet Eje4_Transformacion
A1: Eje estratégico 4. Transformación institucional — Formulación del Plan de Acción 2027
A2: Objetivo estratégico del eje: Pensar la ETITC mediante el desarrollo de sus horizontes de sentido, para que la comunidad contribuya en la transformación de vida de los integrantes de la institución, la sociedad y el planeta.
A3: Columnas grises: base definida por la OAPDI (no modificar). Columnas amarillas: las diligencia el área responsable, una acción por fila. Si necesita formular más acciones para una meta, use la hoja Buscador_Formulacion.
A5: BASE DEFINIDA POR LA OAPDI | Q5: FORMULACIÓN DEL ÁREA RESPONSABLE | AF5: CONTROL
A6: Id asignación | B6: Código meta | C6: Línea | D6: Meta estratégica (PDI) | E6: Indicador de la meta | F6: Meta 2032 | G6: Meta institucional 2027 | H6: Id área | I6: Dependencia | J6: Área funcional | K6: Proceso | L6: Productos 2026 (sábana vigente) | M6: Pendientes 2026 | N6: Compromisos de proyectos estructurantes | O6: Aporte esperado del área 2027 | P6: Indicadores de impacto sugeridos | Q6: Nombre de la acción | R6: Descripción de la acción | S6: Producto esperado | T6: Fecha de inicio (dd/mm/aaaa) | U6: Fecha de fin (dd/mm/aaaa) | V6: Responsable (correo institucional) | W6: Indicador de seguimiento | X6: Meta 2027 de la acción | Y6: Unidad de medida | Z6: Dimensión de impacto | AA6: Indicador de impacto (Guía Metodológica) | AB6: Categoría de impacto (automática) | AC6: ¿Retoma un compromiso pendiente 2026? | AD6: Evidencia verificable | AE6: Observaciones | AF6: Alerta de consistencia
A7: =Base_OAPDI!A98 -> E4-001 | B7: =Base_OAPDI!B98 -> 4.1.1.1 | C7: =Base_OAPDI!D98 -> 4.1 Dimensión estratégica | D7: =Base_OAPDI!E98 -> Cumplir al 2032 con el 90% en el Plan de Desarrollo Institucional 2025-2032 de la ETITC. | E7: =Base_OAPDI!F98 -> % de avance acumulado del PDI | F7: =Base_OAPDI!G98 -> 90% | G7: =Base_OAPDI!H98 -> 33% de avance acumulado del PDI | H7: =Base_OAPDI!I98 -> A05 | I7: =Base_OAPDI!J98 -> 101 · Oficina Asesora de Planeación y Desarrollo Institucional | J7: =Base_OAPDI!K98 -> Planeación y Plan de Acción | K7: =Base_OAPDI!L98 -> Direccionamiento Institucional | L7: =Base_OAPDI!N98 -> 4 | M7: =Base_OAPDI!P98 -> 4 | N7: =Base_OAPDI!Q98 -> 2 | O7: =Base_OAPDI!R98 -> Acciones propuestas por la OAPDI (valídelas y formúlelas en esta fila o en Acciones adicionales): A27-076 Adoptar el protocolo de mesas de trabajo en el SGC; A27-077 Extender la revisión de pertinencia a todos los productos ejecutados; A27-078 Hacer seguimiento trimestral del PAA 2027 en el Navegador Estratégico. Cerrar o reprogramar 4 producto(s) 2026 pendiente(s) de esta meta. Atender 2 compromiso(s) de proyectos estructurantes (hoja Compromisos_2026). | P7: =Base_OAPDI!S98 -> IMP-14; IMP-18 | AB7: =IF(AA7="","",INDEX(Catalogos!$Y$5:$Y$25,MATCH(AA7,L_IMP,0))) | AF7: =IF(Q7="","Pendiente por formular",IF(OR(S7="",T7="",U7="",V7="",W7="",X7="",Z7="",AA7=""),"Incompleta: faltan campos obligatorios",IF(OR(NOT(ISNUMBER(T7)),NOT(ISNUMBER(U7))),"Fecha inválida",IF(U7<T7,"La fecha de fin es anterior a la de inicio",IF(OR(YEAR(T7)<>2027,YEAR(U7)<>2027),"Fechas fuera de la vigencia 2027",IF(ISERROR(SEARCH("@itc.edu.co",V7)),"El responsable no tiene correo institucional",IF(ISERROR(SEARCH(Z7,INDEX(Catalogos!$Z$5:$Z$25,MATCH(AA7,L_IMP,0)))),"La dimensión no corresponde al indicador de impacto","OK"))))))) -> Pendiente por formular
A8: =Base_OAPDI!A99 -> E4-002 | B8: =Base_OAPDI!B99 -> 4.1.1.1 | C8: =Base_OAPDI!D99 -> 4.1 Dimensión estratégica | D8: =Base_OAPDI!E99 -> Cumplir al 2032 con el 90% en el Plan de Desarrollo Institucional 2025-2032 de la ETITC. | E8: =Base_OAPDI!F99 -> % de avance acumulado del PDI | F8: =Base_OAPDI!G99 -> 90% | G8: =Base_OAPDI!H99 -> 33% de avance acumulado del PDI | H8: =Base_OAPDI!I99 -> A01 | I8: =Base_OAPDI!J99 -> 100 · Rectoría | J8: =Base_OAPDI!K99 -> Despacho de Rectoría | K8: =Base_OAPDI!L99 -> Direccionamiento Institucional | L8: =Base_OAPDI!N99 -> 0 | M8: =Base_OAPDI!P99 -> 0 | N8: =Base_OAPDI!Q99 -> 0 | O8: =Base_OAPDI!R99 -> Acciones propuestas por la OAPDI (valídelas y formúlelas en esta fila o en Acciones adicionales): A27-079 Adelantar los trámites de transformación a universidad (Ley 30 de 1992, Ley 749 de 2002). | P8: =Base_OAPDI!S99 -> IMP-14; IMP-18 | AB8: =IF(AA8="","",INDEX(Catalogos!$Y$5:$Y$25,MATCH(AA8,L_IMP,0))) | AF8: =IF(Q8="","Pendiente por formular",IF(OR(S8="",T8="",U8="",V8="",W8="",X8="",Z8="",AA8=""),"Incompleta: faltan campos obligatorios",IF(OR(NOT(ISNUMBER(T8)),NOT(ISNUMBER(U8))),"Fecha inválida",IF(U8<T8,"La fecha de fin es anterior a la de inicio",IF(OR(YEAR(T8)<>2027,YEAR(U8)<>2027),"Fechas fuera de la vigencia 2027",IF(ISERROR(SEARCH("@itc.edu.co",V8)),"El responsable no tiene correo institucional",IF(ISERROR(SEARCH(Z8,INDEX(Catalogos!$Z$5:$Z$25,MATCH(AA8,L_IMP,0)))),"La dimensión no corresponde al indicador de impacto","OK"))))))) -> Pendiente por formular
A9: =Base_OAPDI!A100 -> E4-003 | B9: =Base_OAPDI!B100 -> 4.1.1.2 | C9: =Base_OAPDI!D100 -> 4.1 Dimensión estratégica | D9: =Base_OAPDI!E100 -> Alcanzar el 92% en el Índice de Desempeño Institucional del FURAG. | E9: =Base_OAPDI!F100 -> Índice de Desempeño Institucional (FURAG) | F9: =Base_OAPDI!G100 -> 92% | G9: =Base_OAPDI!H100 -> Sugerido: (90% —la trayectoria lineal de 87,7% en 2024 a 92% en 2032 da 89,3% en 2027—) | H9: =Base_OAPDI!I100 -> A08 | I9: =Base_OAPDI!J100 -> 101 · Oficina Asesora de Planeación y Desarrollo Institucional | J9: =Base_OAPDI!K100 -> Aseguramiento de la Calidad, MIPG y Registros Calificados | K9: =Base_OAPDI!L100 -> Gestión del Sistema Integrado de Aseguramiento | L9: =Base_OAPDI!N100 -> 2 | M9: =Base_OAPDI!P100 -> 2 | N9: =Base_OAPDI!Q100 -> 0 | O9: =Base_OAPDI!R100 -> Acciones propuestas por la OAPDI (valídelas y formúlelas en esta fila o en Acciones adicionales): A27-080 Formular el plan de mejora por política MIPG con base en el último FURAG. Cerrar o reprogramar 2 producto(s) 2026 pendiente(s) de esta meta. | P9: =Base_OAPDI!S100 -> IMP-14; IMP-15 | AB9: =IF(AA9="","",INDEX(Catalogos!$Y$5:$Y$25,MATCH(AA9,L_IMP,0))) | AF9: =IF(Q9="","Pendiente por formular",IF(OR(S9="",T9="",U9="",V9="",W9="",X9="",Z9="",AA9=""),"Incompleta: faltan campos obligatorios",IF(OR(NOT(ISNUMBER(T9)),NOT(ISNUMBER(U9))),"Fecha inválida",IF(U9<T9,"La fecha de fin es anterior a la de inicio",IF(OR(YEAR(T9)<>2027,YEAR(U9)<>2027),"Fechas fuera de la vigencia 2027",IF(ISERROR(SEARCH("@itc.edu.co",V9)),"El responsable no tiene correo institucional",IF(ISERROR(SEARCH(Z9,INDEX(Catalogos!$Z$5:$Z$25,MATCH(AA9,L_IMP,0)))),"La dimensión no corresponde al indicador de impacto","OK"))))))) -> Pendiente por formular
A10: =Base_OAPDI!A101 -> E4-004 | B10: =Base_OAPDI!B101 -> 4.1.1.2 | C10: =Base_OAPDI!D101 -> 4.1 Dimensión estratégica | D10: =Base_OAPDI!E101 -> Alcanzar el 92% en el Índice de Desempeño Institucional del FURAG. | E10: =Base_OAPDI!F101 -> Índice de Desempeño Institucional (FURAG) | F10: =Base_OAPDI!G101 -> 92% | G10: =Base_OAPDI!H101 -> Sugerido: (90% —la trayectoria lineal de 87,7% en 2024 a 92% en 2032 da 89,3% en 2027—) | H10: =Base_OAPDI!I101 -> A09 | I10: =Base_OAPDI!J101 -> 132 · GIT Gestión de Informática y Telecomunicaciones | J10: =Base_OAPDI!K101 -> Seguridad Digital y Continuidad | K10: =Base_OAPDI!L101 -> Gestión de Informática y Telecomunicaciones | L10: =Base_OAPDI!N101 -> 30 | M10: =Base_OAPDI!P101 -> 17 | N10: =Base_OAPDI!Q101 -> 0 | O10: =Base_OAPDI!R101 -> Cerrar o reprogramar 17 producto(s) 2026 pendiente(s) de esta meta. | P10: =Base_OAPDI!S101 -> IMP-14; IMP-15 | AB10: =IF(AA10="","",INDEX(Catalogos!$Y$5:$Y$25,MATCH(AA10,L_IMP,0))) | AF10: =IF(Q10="","Pendiente por formular",IF(OR(S10="",T10="",U10="",V10="",W10="",X10="",Z10="",AA10=""),"Incompleta: faltan campos obligatorios",IF(OR(NOT(ISNUMBER(T10)),NOT(ISNUMBER(U10))),"Fecha inválida",IF(U10<T10,"La fecha de fin es anterior a la de inicio",IF(OR(YEAR(T10)<>2027,YEAR(U10)<>2027),"Fechas fuera de la vigencia 2027",IF(ISERROR(SEARCH("@itc.edu.co",V10)),"El responsable no tiene correo institucional",IF(ISERROR(SEARCH(Z10,INDEX(Catalogos!$Z$5:$Z$25,MATCH(AA10,L_IMP,0)))),"La dimensión no corresponde al indicador de impacto","OK"))))))) -> Pendiente por formular
A11: =Base_OAPDI!A102 -> E4-005 | B11: =Base_OAPDI!B102 -> 4.1.1.2 | C11: =Base_OAPDI!D102 -> 4.1 Dimensión estratégica | D11: =Base_OAPDI!E102 -> Alcanzar el 92% en el Índice de Desempeño Institucional del FURAG. | E11: =Base_OAPDI!F102 -> Índice de Desempeño Institucional (FURAG) | F11: =Base_OAPDI!G102 -> 92% | G11: =Base_OAPDI!H102 -> Sugerido: (90% —la trayectoria lineal de 87,7% en 2024 a 92% en 2032 da 89,3% en 2027—) | H11: =Base_OAPDI!I102 -> A29 | I11: =Base_OAPDI!J102 -> 126 · GIT Registro y Control | J11: =Base_OAPDI!K102 -> GIT Registro, Control y Admisiones | K11: =Base_OAPDI!L102 -> Docencia PES | L11: =Base_OAPDI!N102 -> 0 | M11: =Base_OAPDI!P102 -> 0 | N11: =Base_OAPDI!Q102 -> 0 | O11: =Base_OAPDI!R102 -> Formular al menos una acción que contribuya a la meta institucional 2027 de esta meta. | P11: =Base_OAPDI!S102 -> IMP-14; IMP-15 | AB11: =IF(AA11="","",INDEX(Catalogos!$Y$5:$Y$25,MATCH(AA11,L_IMP,0))) | AF11: =IF(Q11="","Pendiente por formular",IF(OR(S11="",T11="",U11="",V11="",W11="",X11="",Z11="",AA11=""),"Incompleta: faltan campos obligatorios",IF(OR(NOT(ISNUMBER(T11)),NOT(ISNUMBER(U11))),"Fecha inválida",IF(U11<T11,"La fecha de fin es anterior a la de inicio",IF(OR(YEAR(T11)<>2027,YEAR(U11)<>2027),"Fechas fuera de la vigencia 2027",IF(ISERROR(SEARCH("@itc.edu.co",V11)),"El responsable no tiene correo institucional",IF(ISERROR(SEARCH(Z11,INDEX(Catalogos!$Z$5:$Z$25,MATCH(AA11,L_IMP,0)))),"La dimensión no corresponde al indicador de impacto","OK"))))))) -> Pendiente por formular
A12: =Base_OAPDI!A103 -> E4-006 | B12: =Base_OAPDI!B103 -> 4.1.1.2 | C12: =Base_OAPDI!D103 -> 4.1 Dimensión estratégica | D12: =Base_OAPDI!E103 -> Alcanzar el 92% en el Índice de Desempeño Institucional del FURAG. | E12: =Base_OAPDI!F103 -> Índice de Desempeño Institucional (FURAG) | F12: =Base_OAPDI!G103 -> 92% | G12: =Base_OAPDI!H103 -> Sugerido: (90% —la trayectoria lineal de 87,7% en 2024 a 92% en 2032 da 89,3% en 2027—) | H12: =Base_OAPDI!I103 -> A34 | I12: =Base_OAPDI!J103 -> 132 · GIT Gestión de Informática y Telecomunicaciones | J12: =Base_OAPDI!K103 -> GIT Informática y Telecomunicaciones | K12: =Base_OAPDI!L103 -> Gestión de Informática y Telecomunicaciones | L12: =Base_OAPDI!N103 -> 0 | M12: =Base_OAPDI!P103 -> 0 | N12: =Base_OAPDI!Q103 -> 0 | O12: =Base_OAPDI!R103 -> Formular al menos una acción que contribuya a la meta institucional 2027 de esta meta. | P12: =Base_OAPDI!S103 -> IMP-14; IMP-15 | AB12: =IF(AA12="","",INDEX(Catalogos!$Y$5:$Y$25,MATCH(AA12,L_IMP,0))) | AF12: =IF(Q12="","Pendiente por formular",IF(OR(S12="",T12="",U12="",V12="",W12="",X12="",Z12="",AA12=""),"Incompleta: faltan campos obligatorios",IF(OR(NOT(ISNUMBER(T12)),NOT(ISNUMBER(U12))),"Fecha inválida",IF(U12<T12,"La fecha de fin es anterior a la de inicio",IF(OR(YEAR(T12)<>2027,YEAR(U12)<>2027),"Fechas fuera de la vigencia 2027",IF(ISERROR(SEARCH("@itc.edu.co",V12)),"El responsable no tiene correo institucional",IF(ISERROR(SEARCH(Z12,INDEX(Catalogos!$Z$5:$Z$25,MATCH(AA12,L_IMP,0)))),"La dimensión no corresponde al indicador de impacto","OK"))))))) -> Pendiente por formular
A13: =Base_OAPDI!A104 -> E4-007 | B13: =Base_OAPDI!B104 -> 4.1.1.2 | C13: =Base_OAPDI!D104 -> 4.1 Dimensión estratégica | D13: =Base_OAPDI!E104 -> Alcanzar el 92% en el Índice de Desempeño Institucional del FURAG. | E13: =Base_OAPDI!F104 -> Índice de Desempeño Institucional (FURAG) | F13: =Base_OAPDI!G104 -> 92% | G13: =Base_OAPDI!H104 -> Sugerido: (90% —la trayectoria lineal de 87,7% en 2024 a 92% en 2032 da 89,3% en 2027—) | H13: =Base_OAPDI!I104 -> A47 | I13: =Base_OAPDI!J104 -> 130 · Vicerrectoría Administrativa y Financiera | J13: =Base_OAPDI!K104 -> Gestión Financiera (Presupuesto, Contabilidad, Tesorería) | K13: =Base_OAPDI!L104 -> Gestión Financiera | L13: =Base_OAPDI!N104 -> 0 | M13: =Base_OAPDI!P104 -> 0 | N13: =Base_OAPDI!Q104 -> 8 | O13: =Base_OAPDI!R104 -> Acciones propuestas por la OAPDI (valídelas y formúlelas en esta fila o en Acciones adicionales): A27-081 Fijar calendario de cierre con corte único y constituir el rezago a tiempo; A27-082 Ejecutar el Plan de Mejoramiento con la CGR (7 hallazgos, 24 metas); A27-083 Formular indicadores financieros y contables (razón corriente, margen, rotación de cartera). Atender 8 compromiso(s) de proyectos estructurantes (hoja Compromisos_2026). | P13: =Base_OAPDI!S104 -> IMP-14; IMP-15 | AB13: =IF(AA13="","",INDEX(Catalogos!$Y$5:$Y$25,MATCH(AA13,L_IMP,0))) | AF13: =IF(Q13="","Pendiente por formular",IF(OR(S13="",T13="",U13="",V13="",W13="",X13="",Z13="",AA13=""),"Incompleta: faltan campos obligatorios",IF(OR(NOT(ISNUMBER(T13)),NOT(ISNUMBER(U13))),"Fecha inválida",IF(U13<T13,"La fecha de fin es anterior a la de inicio",IF(OR(YEAR(T13)<>2027,YEAR(U13)<>2027),"Fechas fuera de la vigencia 2027",IF(ISERROR(SEARCH("@itc.edu.co",V13)),"El responsable no tiene correo institucional",IF(ISERROR(SEARCH(Z13,INDEX(Catalogos!$Z$5:$Z$25,MATCH(AA13,L_IMP,0)))),"La dimensión no corresponde al indicador de impacto","OK"))))))) -> Pendiente por formular
A14: =Base_OAPDI!A105 -> E4-008 | B14: =Base_OAPDI!B105 -> 4.1.1.2 | C14: =Base_OAPDI!D105 -> 4.1 Dimensión estratégica | D14: =Base_OAPDI!E105 -> Alcanzar el 92% en el Índice de Desempeño Institucional del FURAG. | E14: =Base_OAPDI!F105 -> Índice de Desempeño Institucional (FURAG) | F14: =Base_OAPDI!G105 -> 92% | G14: =Base_OAPDI!H105 -> Sugerido: (90% —la trayectoria lineal de 87,7% en 2024 a 92% en 2032 da 89,3% en 2027—) | H14: =Base_OAPDI!I105 -> A05 | I14: =Base_OAPDI!J105 -> 101 · Oficina Asesora de Planeación y Desarrollo Institucional | J14: =Base_OAPDI!K105 -> Planeación y Plan de Acción | K14: =Base_OAPDI!L105 -> Direccionamiento Institucional | L14: =Base_OAPDI!N105 -> 0 | M14: =Base_OAPDI!P105 -> 0 | N14: =Base_OAPDI!Q105 -> 1 | O14: =Base_OAPDI!R105 -> Atender 1 compromiso(s) de proyectos estructurantes (hoja Compromisos_2026). | P14: =Base_OAPDI!S105 -> IMP-14; IMP-15 | AB14: =IF(AA14="","",INDEX(Catalogos!$Y$5:$Y$25,MATCH(AA14,L_IMP,0))) | AF14: =IF(Q14="","Pendiente por formular",IF(OR(S14="",T14="",U14="",V14="",W14="",X14="",Z14="",AA14=""),"Incompleta: faltan campos obligatorios",IF(OR(NOT(ISNUMBER(T14)),NOT(ISNUMBER(U14))),"Fecha inválida",IF(U14<T14,"La fecha de fin es anterior a la de inicio",IF(OR(YEAR(T14)<>2027,YEAR(U14)<>2027),"Fechas fuera de la vigencia 2027",IF(ISERROR(SEARCH("@itc.edu.co",V14)),"El responsable no tiene correo institucional",IF(ISERROR(SEARCH(Z14,INDEX(Catalogos!$Z$5:$Z$25,MATCH(AA14,L_IMP,0)))),"La dimensión no corresponde al indicador de impacto","OK"))))))) -> Pendiente por formular
A15: =Base_OAPDI!A106 -> E4-009 | B15: =Base_OAPDI!B106 -> 4.1.1.2 | C15: =Base_OAPDI!D106 -> 4.1 Dimensión estratégica | D15: =Base_OAPDI!E106 -> Alcanzar el 92% en el Índice de Desempeño Institucional del FURAG. | E15: =Base_OAPDI!F106 -> Índice de Desempeño Institucional (FURAG) | F15: =Base_OAPDI!G106 -> 92% | G15: =Base_OAPDI!H106 -> Sugerido: (90% —la trayectoria lineal de 87,7% en 2024 a 92% en 2032 da 89,3% en 2027—) | H15: =Base_OAPDI!I106 -> A30 | I15: =Base_OAPDI!J106 -> 130 · Vicerrectoría Administrativa y Financiera | J15: =Base_OAPDI!K106 -> Despacho de la Vicerrectoría Administrativa y Financiera | K15: =Base_OAPDI!L106 -> Gestión Financiera | L15: =Base_OAPDI!N106 -> 0 | M15: =Base_OAPDI!P106 -> 0 | N15: =Base_OAPDI!Q106 -> 2 | O15: =Base_OAPDI!R106 -> Acciones propuestas por la OAPDI (valídelas y formúlelas en esta fila o en Acciones adicionales): A27-084 Documentar y codificar los procedimientos de gratuidad. Atender 2 compromiso(s) de proyectos estructurantes (hoja Compromisos_2026). | P15: =Base_OAPDI!S106 -> IMP-14; IMP-15 | AB15: =IF(AA15="","",INDEX(Catalogos!$Y$5:$Y$25,MATCH(AA15,L_IMP,0))) | AF15: =IF(Q15="","Pendiente por formular",IF(OR(S15="",T15="",U15="",V15="",W15="",X15="",Z15="",AA15=""),"Incompleta: faltan campos obligatorios",IF(OR(NOT(ISNUMBER(T15)),NOT(ISNUMBER(U15))),"Fecha inválida",IF(U15<T15,"La fecha de fin es anterior a la de inicio",IF(OR(YEAR(T15)<>2027,YEAR(U15)<>2027),"Fechas fuera de la vigencia 2027",IF(ISERROR(SEARCH("@itc.edu.co",V15)),"El responsable no tiene correo institucional",IF(ISERROR(SEARCH(Z15,INDEX(Catalogos!$Z$5:$Z$25,MATCH(AA15,L_IMP,0)))),"La dimensión no corresponde al indicador de impacto","OK"))))))) -> Pendiente por formular
A16: =Base_OAPDI!A107 -> E4-010 | B16: =Base_OAPDI!B107 -> 4.1.1.2 | C16: =Base_OAPDI!D107 -> 4.1 Dimensión estratégica | D16: =Base_OAPDI!E107 -> Alcanzar el 92% en el Índice de Desempeño Institucional del FURAG. | E16: =Base_OAPDI!F107 -> Índice de Desempeño Institucional (FURAG) | F16: =Base_OAPDI!G107 -> 92% | G16: =Base_OAPDI!H107 -> Sugerido: (90% —la trayectoria lineal de 87,7% en 2024 a 92% en 2032 da 89,3% en 2027—) | H16: =Base_OAPDI!I107 -> A11 | I16: =Base_OAPDI!J107 -> 110 · Secretaría General | J16: =Base_OAPDI!K107 -> Despacho de Secretaría General | K16: =Base_OAPDI!L107 -> Direccionamiento Institucional | L16: =Base_OAPDI!N107 -> 0 | M16: =Base_OAPDI!P107 -> 0 | N16: =Base_OAPDI!Q107 -> 2 | O16: =Base_OAPDI!R107 -> Atender 2 compromiso(s) de proyectos estructurantes (hoja Compromisos_2026). | P16: =Base_OAPDI!S107 -> IMP-14; IMP-15 | AB16: =IF(AA16="","",INDEX(Catalogos!$Y$5:$Y$25,MATCH(AA16,L_IMP,0))) | AF16: =IF(Q16="","Pendiente por formular",IF(OR(S16="",T16="",U16="",V16="",W16="",X16="",Z16="",AA16=""),"Incompleta: faltan campos obligatorios",IF(OR(NOT(ISNUMBER(T16)),NOT(ISNUMBER(U16))),"Fecha inválida",IF(U16<T16,"La fecha de fin es anterior a la de inicio",IF(OR(YEAR(T16)<>2027,YEAR(U16)<>2027),"Fechas fuera de la vigencia 2027",IF(ISERROR(SEARCH("@itc.edu.co",V16)),"El responsable no tiene correo institucional",IF(ISERROR(SEARCH(Z16,INDEX(Catalogos!$Z$5:$Z$25,MATCH(AA16,L_IMP,0)))),"La dimensión no corresponde al indicador de impacto","OK"))))))) -> Pendiente por formular
A17: =Base_OAPDI!A108 -> E4-011 | B17: =Base_OAPDI!B108 -> 4.1.1.2 | C17: =Base_OAPDI!D108 -> 4.1 Dimensión estratégica | D17: =Base_OAPDI!E108 -> Alcanzar el 92% en el Índice de Desempeño Institucional del FURAG. | E17: =Base_OAPDI!F108 -> Índice de Desempeño Institucional (FURAG) | F17: =Base_OAPDI!G108 -> 92% | G17: =Base_OAPDI!H108 -> Sugerido: (90% —la trayectoria lineal de 87,7% en 2024 a 92% en 2032 da 89,3% en 2027—) | H17: =Base_OAPDI!I108 -> A35 | I17: =Base_OAPDI!J108 -> 133 · GIT Gestión de Talento Humano | J17: =Base_OAPDI!K108 -> GIT Talento Humano | K17: =Base_OAPDI!L108 -> Gestión de Talento Humano | L17: =Base_OAPDI!N108 -> 0 | M17: =Base_OAPDI!P108 -> 0 | N17: =Base_OAPDI!Q108 -> 2 | O17: =Base_OAPDI!R108 -> Acciones propuestas por la OAPDI (valídelas y formúlelas en esta fila o en Acciones adicionales): A27-085 Incluir capacitación contable en el Plan Institucional de Capacitación. Atender 2 compromiso(s) de proyectos estructurantes (hoja Compromisos_2026). | P17: =Base_OAPDI!S108 -> IMP-14; IMP-15 | AB17: =IF(AA17="","",INDEX(Catalogos!$Y$5:$Y$25,MATCH(AA17,L_IMP,0))) | AF17: =IF(Q17="","Pendiente por formular",IF(OR(S17="",T17="",U17="",V17="",W17="",X17="",Z17="",AA17=""),"Incompleta: faltan campos obligatorios",IF(OR(NOT(ISNUMBER(T17)),NOT(ISNUMBER(U17))),"Fecha inválida",IF(U17<T17,"La fecha de fin es anterior a la de inicio",IF(OR(YEAR(T17)<>2027,YEAR(U17)<>2027),"Fechas fuera de la vigencia 2027",IF(ISERROR(SEARCH("@itc.edu.co",V17)),"El responsable no tiene correo institucional",IF(ISERROR(SEARCH(Z17,INDEX(Catalogos!$Z$5:$Z$25,MATCH(AA17,L_IMP,0)))),"La dimensión no corresponde al indicador de impacto","OK"))))))) -> Pendiente por formular
A18: =Base_OAPDI!A109 -> E4-012 | B18: =Base_OAPDI!B109 -> 4.1.1.2 | C18: =Base_OAPDI!D109 -> 4.1 Dimensión estratégica | D18: =Base_OAPDI!E109 -> Alcanzar el 92% en el Índice de Desempeño Institucional del FURAG. | E18: =Base_OAPDI!F109 -> Índice de Desempeño Institucional (FURAG) | F18: =Base_OAPDI!G109 -> 92% | G18: =Base_OAPDI!H109 -> Sugerido: (90% —la trayectoria lineal de 87,7% en 2024 a 92% en 2032 da 89,3% en 2027—) | H18: =Base_OAPDI!I109 -> A14 | I18: =Base_OAPDI!J109 -> 130 · Vicerrectoría Administrativa y Financiera | J18: =Base_OAPDI!K109 -> Contratación y Adquisiciones | K18: =Base_OAPDI!L109 -> Gestión de Adquisiciones | L18: =Base_OAPDI!N109 -> 0 | M18: =Base_OAPDI!P109 -> 0 | N18: =Base_OAPDI!Q109 -> 1 | O18: =Base_OAPDI!R109 -> Atender 1 compromiso(s) de proyectos estructurantes (hoja Compromisos_2026). | P18: =Base_OAPDI!S109 -> IMP-14; IMP-15 | AB18: =IF(AA18="","",INDEX(Catalogos!$Y$5:$Y$25,MATCH(AA18,L_IMP,0))) | AF18: =IF(Q18="","Pendiente por formular",IF(OR(S18="",T18="",U18="",V18="",W18="",X18="",Z18="",AA18=""),"Incompleta: faltan campos obligatorios",IF(OR(NOT(ISNUMBER(T18)),NOT(ISNUMBER(U18))),"Fecha inválida",IF(U18<T18,"La fecha de fin es anterior a la de inicio",IF(OR(YEAR(T18)<>2027,YEAR(U18)<>2027),"Fechas fuera de la vigencia 2027",IF(ISERROR(SEARCH("@itc.edu.co",V18)),"El responsable no tiene correo institucional",IF(ISERROR(SEARCH(Z18,INDEX(Catalogos!$Z$5:$Z$25,MATCH(AA18,L_IMP,0)))),"La dimensión no corresponde al indicador de impacto","OK"))))))) -> Pendiente por formular
... A59: =Base_OAPDI!A150 -> E4-053 | B59: =Base_OAPDI!B150 -> 4.5.1.2 | C59: =Base_OAPDI!D150 -> 4.5 Cultura organizacional | D59: =Base_OAPDI!E150 -> Consolidar un (1) modelo de gestión de la cultura que contemple un (1) instrumento de evaluación permanente. | E59: =Base_OAPDI!F150 -> Modelo de gestión de la cultura con instrumento de evaluación (fase) | F59: =Base_OAPDI!G150 -> 1 modelo + 1 instrumento | G59: =Base_OAPDI!H150 -> Instrumento de evaluación diseñado y aplicado | H59: =Base_OAPDI!I150 -> A37 | I59: =Base_OAPDI!J150 -> 133 · GIT Gestión de Talento Humano | J59: =Base_OAPDI!K150 -> Bienestar Laboral | K59: =Base_OAPDI!L150 -> Gestión de Talento Humano | L59: =Base_OAPDI!N150 -> 12 | M59: =Base_OAPDI!P150 -> 6 | N59: =Base_OAPDI!Q150 -> 0 | O59: =Base_OAPDI!R150 -> Cerrar o reprogramar 6 producto(s) 2026 pendiente(s) de esta meta. | P59: =Base_OAPDI!S150 -> IMP-15; IMP-14 | AB59: =IF(AA59="","",INDEX(Catalogos!$Y$5:$Y$25,MATCH(AA59,L_IMP,0))) | AF59: =IF(Q59="","Pendiente por formular",IF(OR(S59="",T59="",U59="",V59="",W59="",X59="",Z59="",AA59=""),"Incompleta: faltan campos obligatorios",IF(OR(NOT(ISNUMBER(T59)),NOT(ISNUMBER(U59))),"Fecha inválida",IF(U59<T59,"La fecha de fin es anterior a la de inicio",IF(OR(YEAR(T59)<>2027,YEAR(U59)<>2027),"Fechas fuera de la vigencia 2027",IF(ISERROR(SEARCH("@itc.edu.co",V59)),"El responsable no tiene correo institucional",IF(ISERROR(SEARCH(Z59,INDEX(Catalogos!$Z$5:$Z$25,MATCH(AA59,L_IMP,0)))),"La dimensión no corresponde al indicador de impacto","OK"))))))) -> Pendiente por formular

Sheet Eje5_Infraestructura
A1: Eje estratégico 5. Ampliación y modernización de la infraestructura — Formulación del Plan de Acción 2027
A2: Objetivo estratégico del eje: Proveer la infraestructura física y tecnológica necesaria para la calidad en la oferta educativa.
A3: Columnas grises: base definida por la OAPDI (no modificar). Columnas amarillas: las diligencia el área responsable, una acción por fila. Si necesita formular más acciones para una meta, use la hoja Buscador_Formulacion.
A5: BASE DEFINIDA POR LA OAPDI | Q5: FORMULACIÓN DEL ÁREA RESPONSABLE | AF5: CONTROL
A6: Id asignación | B6: Código meta | C6: Línea | D6: Meta estratégica (PDI) | E6: Indicador de la meta | F6: Meta 2032 | G6: Meta institucional 2027 | H6: Id área | I6: Dependencia | J6: Área funcional | K6: Proceso | L6: Productos 2026 (sábana vigente) | M6: Pendientes 2026 | N6: Compromisos de proyectos estructurantes | O6: Aporte esperado del área 2027 | P6: Indicadores de impacto sugeridos | Q6: Nombre de la acción | R6: Descripción de la acción | S6: Producto esperado | T6: Fecha de inicio (dd/mm/aaaa) | U6: Fecha de fin (dd/mm/aaaa) | V6: Responsable (correo institucional) | W6: Indicador de seguimiento | X6: Meta 2027 de la acción | Y6: Unidad de medida | Z6: Dimensión de impacto | AA6: Indicador de impacto (Guía Metodológica) | AB6: Categoría de impacto (automática) | AC6: ¿Retoma un compromiso pendiente 2026? | AD6: Evidencia verificable | AE6: Observaciones | AF6: Alerta de consistencia
A7: =Base_OAPDI!A151 -> E5-001 | B7: =Base_OAPDI!B151 -> 5.1.1.1 | C7: =Base_OAPDI!D151 -> 5.1 Sedes propias | D7: =Base_OAPDI!E151 -> Contar con 4 sedes: 1. Calle 18, 2. Funza, 3. Guaymaral, 4. Central, con infraestructura y dotación para la prestación de servicios educativos. | E7: =Base_OAPDI!F151 -> N.° de sedes propias habilitadas y operando | F7: =Base_OAPDI!G151 -> 4 sedes | G7: =Base_OAPDI!H151 -> Calle 18: fase III (licencias, estudios y diseños, vigencias futuras MEN). Funza: puesta en marcha fase I. Guaymaral: puesta en marcha de la sede de Bienestar. | H7: =Base_OAPDI!I151 -> A05 | I7: =Base_OAPDI!J151 -> 101 · Oficina Asesora de Planeación y Desarrollo Institucional | J7: =Base_OAPDI!K151 -> Planeación y Plan de Acción | K7: =Base_OAPDI!L151 -> Direccionamiento Institucional | L7: =Base_OAPDI!N151 -> 9 | M7: =Base_OAPDI!P151 -> 9 | N7: =Base_OAPDI!Q151 -> 0 | O7: =Base_OAPDI!R151 -> Cerrar o reprogramar 9 producto(s) 2026 pendiente(s) de esta meta. | P7: =Base_OAPDI!S151 -> IMP-12; IMP-13 | AB7: =IF(AA7="","",INDEX(Catalogos!$Y$5:$Y$25,MATCH(AA7,L_IMP,0))) | AF7: =IF(Q7="","Pendiente por formular",IF(OR(S7="",T7="",U7="",V7="",W7="",X7="",Z7="",AA7=""),"Incompleta: faltan campos obligatorios",IF(OR(NOT(ISNUMBER(T7)),NOT(ISNUMBER(U7))),"Fecha inválida",IF(U7<T7,"La fecha de fin es anterior a la de inicio",IF(OR(YEAR(T7)<>2027,YEAR(U7)<>2027),"Fechas fuera de la vigencia 2027",IF(ISERROR(SEARCH("@itc.edu.co",V7)),"El responsable no tiene correo institucional",IF(ISERROR(SEARCH(Z7,INDEX(Catalogos!$Z$5:$Z$25,MATCH(AA7,L_IMP,0)))),"La dimensión no corresponde al indicador de impacto","OK"))))))) -> Pendiente por formular
A8: =Base_OAPDI!A152 -> E5-002 | B8: =Base_OAPDI!B152 -> 5.1.1.1 | C8: =Base_OAPDI!D152 -> 5.1 Sedes propias | D8: =Base_OAPDI!E152 -> Contar con 4 sedes: 1. Calle 18, 2. Funza, 3. Guaymaral, 4. Central, con infraestructura y dotación para la prestación de servicios educativos. | E8: =Base_OAPDI!F152 -> N.° de sedes propias habilitadas y operando | F8: =Base_OAPDI!G152 -> 4 sedes | G8: =Base_OAPDI!H152 -> Calle 18: fase III (licencias, estudios y diseños, vigencias futuras MEN). Funza: puesta en marcha fase I. Guaymaral: puesta en marcha de la sede de Bienestar. | H8: =Base_OAPDI!I152 -> A31 | I8: =Base_OAPDI!J152 -> 130 · Vicerrectoría Administrativa y Financiera | J8: =Base_OAPDI!K152 -> Recursos Físicos e Infraestructura | K8: =Base_OAPDI!L152 -> Gestión de Recursos Físicos | L8: =Base_OAPDI!N152 -> 3 | M8: =Base_OAPDI!P152 -> 3 | N8: =Base_OAPDI!Q152 -> 2 | O8: =Base_OAPDI!R152 -> Acciones propuestas por la OAPDI (valídelas y formúlelas en esta fila o en Acciones adicionales): A27-114 Calle 18: gestionar licencias de construcción y demolición, estudios y diseños y vigencias futuras; A27-116 Funza (Ecoparque): contratar estudios y diseños, licencias e infraestructura modular; A27-117 Guaymaral: poner en marcha la sede de Bienestar (espacios deportivos); A27-118 Adecuar los nuevos inmuebles adquiridos (estudios y diseños); A27-119 Incluir criterios de eficiencia energética y construcción sostenible en los estudios y diseños de las nuevas sedes (incluida Fusagasugá), para no generar sobrecostos futuros. Cerrar o reprogramar 3 producto(s) 2026 pendiente(s) de esta meta. Atender 2 compromiso(s) de proyectos estructurantes (hoja Compromisos_2026). | P8: =Base_OAPDI!S152 -> IMP-12; IMP-13 | AB8: =IF(AA8="","",INDEX(Catalogos!$Y$5:$Y$25,MATCH(AA8,L_IMP,0))) | AF8: =IF(Q8="","Pendiente por formular",IF(OR(S8="",T8="",U8="",V8="",W8="",X8="",Z8="",AA8=""),"Incompleta: faltan campos obligatorios",IF(OR(NOT(ISNUMBER(T8)),NOT(ISNUMBER(U8))),"Fecha inválida",IF(U8<T8,"La fecha de fin es anterior a la de inicio",IF(OR(YEAR(T8)<>2027,YEAR(U8)<>2027),"Fechas fuera de la vigencia 2027",IF(ISERROR(SEARCH("@itc.edu.co",V8)),"El responsable no tiene correo institucional",IF(ISERROR(SEARCH(Z8,INDEX(Catalogos!$Z$5:$Z$25,MATCH(AA8,L_IMP,0)))),"La dimensión no corresponde al indicador de impacto","OK"))))))) -> Pendiente por formular
A9: =Base_OAPDI!A153 -> E5-003 | B9: =Base_OAPDI!B153 -> 5.1.1.1 | C9: =Base_OAPDI!D153 -> 5.1 Sedes propias | D9: =Base_OAPDI!E153 -> Contar con 4 sedes: 1. Calle 18, 2. Funza, 3. Guaymaral, 4. Central, con infraestructura y dotación para la prestación de servicios educativos. | E9: =Base_OAPDI!F153 -> N.° de sedes propias habilitadas y operando | F9: =Base_OAPDI!G153 -> 4 sedes | G9: =Base_OAPDI!H153 -> Calle 18: fase III (licencias, estudios y diseños, vigencias futuras MEN). Funza: puesta en marcha fase I. Guaymaral: puesta en marcha de la sede de Bienestar. | H9: =Base_OAPDI!I153 -> A30 | I9: =Base_OAPDI!J153 -> 130 · Vicerrectoría Administrativa y Financiera | J9: =Base_OAPDI!K153 -> Despacho de la Vicerrectoría Administrativa y Financiera | K9: =Base_OAPDI!L153 -> Gestión Financiera | L9: =Base_OAPDI!N153 -> 0 | M9: =Base_OAPDI!P153 -> 0 | N9: =Base_OAPDI!Q153 -> 0 | O9: =Base_OAPDI!R153 -> Formular al menos una acción que contribuya a la meta institucional 2027 de esta meta. | P9: =Base_OAPDI!S153 -> IMP-12; IMP-13 | AB9: =IF(AA9="","",INDEX(Catalogos!$Y$5:$Y$25,MATCH(AA9,L_IMP,0))) | AF9: =IF(Q9="","Pendiente por formular",IF(OR(S9="",T9="",U9="",V9="",W9="",X9="",Z9="",AA9=""),"Incompleta: faltan campos obligatorios",IF(OR(NOT(ISNUMBER(T9)),NOT(ISNUMBER(U9))),"Fecha inválida",IF(U9<T9,"La fecha de fin es anterior a la de inicio",IF(OR(YEAR(T9)<>2027,YEAR(U9)<>2027),"Fechas fuera de la vigencia 2027",IF(ISERROR(SEARCH("@itc.edu.co",V9)),"El responsable no tiene correo institucional",IF(ISERROR(SEARCH(Z9,INDEX(Catalogos!$Z$5:$Z$25,MATCH(AA9,L_IMP,0)))),"La dimensión no corresponde al indicador de impacto","OK"))))))) -> Pendiente por formular
A10: =Base_OAPDI!A154 -> E5-004 | B10: =Base_OAPDI!B154 -> 5.1.1.1 | C10: =Base_OAPDI!D154 -> 5.1 Sedes propias | D10: =Base_OAPDI!E154 -> Contar con 4 sedes: 1. Calle 18, 2. Funza, 3. Guaymaral, 4. Central, con infraestructura y dotación para la prestación de servicios educativos. | E10: =Base_OAPDI!F154 -> N.° de sedes propias habilitadas y operando | F10: =Base_OAPDI!G154 -> 4 sedes | G10: =Base_OAPDI!H154 -> Calle 18: fase III (licencias, estudios y diseños, vigencias futuras MEN). Funza: puesta en marcha fase I. Guaymaral: puesta en marcha de la sede de Bienestar. | H10: =Base_OAPDI!I154 -> A12 | I10: =Base_OAPDI!J154 -> 110 · Secretaría General | J10: =Base_OAPDI!K154 -> Gestión Jurídica | K10: =Base_OAPDI!L154 -> Gestión Jurídica | L10: =Base_OAPDI!N154 -> 0 | M10: =Base_OAPDI!P154 -> 0 | N10: =Base_OAPDI!Q154 -> 0 | O10: =Base_OAPDI!R154 -> Acciones propuestas por la OAPDI (valídelas y formúlelas en esta fila o en Acciones adicionales): A27-115 Funza: adelantar trámites de notariado, registro e impuestos de los predios. | P10: =Base_OAPDI!S154 -> IMP-12; IMP-13 | AB10: =IF(AA10="","",INDEX(Catalogos!$Y$5:$Y$25,MATCH(AA10,L_IMP,0))) | AF10: =IF(Q10="","Pendiente por formular",IF(OR(S10="",T10="",U10="",V10="",W10="",X10="",Z10="",AA10=""),"Incompleta: faltan campos obligatorios",IF(OR(NOT(ISNUMBER(T10)),NOT(ISNUMBER(U10))),"Fecha inválida",IF(U10<T10,"La fecha de fin es anterior a la de inicio",IF(OR(YEAR(T10)<>2027,YEAR(U10)<>2027),"Fechas fuera de la vigencia 2027",IF(ISERROR(SEARCH("@itc.edu.co",V10)),"El responsable no tiene correo institucional",IF(ISERROR(SEARCH(Z10,INDEX(Catalogos!$Z$5:$Z$25,MATCH(AA10,L_IMP,0)))),"La dimensión no corresponde al indicador de impacto","OK"))))))) -> Pendiente por formular
A11: =Base_OAPDI!A155 -> E5-005 | B11: =Base_OAPDI!B155 -> 5.2.1.1 | C11: =Base_OAPDI!D155 -> 5.2 Modernización de la infraestructura | D11: =Base_OAPDI!E155 -> 3 bloques reforzados estructuralmente en la sede centro. | E11: =Base_OAPDI!F155 -> N.° de bloques con reforzamiento estructural terminado | F11: =Base_OAPDI!G155 -> 3 bloques | G11: =Base_OAPDI!H155 -> Viabilidad presupuestal y permisos para los bloques pendientes | H11: =Base_OAPDI!I155 -> A31 | I11: =Base_OAPDI!J155 -> 130 · Vicerrectoría Administrativa y Financiera | J11: =Base_OAPDI!K155 -> Recursos Físicos e Infraestructura | K11: =Base_OAPDI!L155 -> Gestión de Recursos Físicos | L11: =Base_OAPDI!N155 -> 26 | M11: =Base_OAPDI!P155 -> 19 | N11: =Base_OAPDI!Q155 -> 0 | O11: =Base_OAPDI!R155 -> Acciones propuestas por la OAPDI (valídelas y formúlelas en esta fila o en Acciones adicionales): A27-120 Gestionar permisos y licencias ante el Ministerio de Cultura y la curaduría; A27-122 Integrar al reforzamiento de los bloques F, G y H las medidas de la matriz de oportunidades de eficiencia energética (avance parcial PGEE 2026). Cerrar o reprogramar 19 producto(s) 2026 pendiente(s) de esta meta. | P11: =Base_OAPDI!S155 -> IMP-18 | AB11: =IF(AA11="","",INDEX(Catalogos!$Y$5:$Y$25,MATCH(AA11,L_IMP,0))) | AF11: =IF(Q11="","Pendiente por formular",IF(OR(S11="",T11="",U11="",V11="",W11="",X11="",Z11="",AA11=""),"Incompleta: faltan campos obligatorios",IF(OR(NOT(ISNUMBER(T11)),NOT(ISNUMBER(U11))),"Fecha inválida",IF(U11<T11,"La fecha de fin es anterior a la de inicio",IF(OR(YEAR(T11)<>2027,YEAR(U11)<>2027),"Fechas fuera de la vigencia 2027",IF(ISERROR(SEARCH("@itc.edu.co",V11)),"El responsable no tiene correo institucional",IF(ISERROR(SEARCH(Z11,INDEX(Catalogos!$Z$5:$Z$25,MATCH(AA11,L_IMP,0)))),"La dimensión no corresponde al indicador de impacto","OK"))))))) -> Pendiente por formular
A12: =Base_OAPDI!A156 -> E5-006 | B12: =Base_OAPDI!B156 -> 5.2.1.1 | C12: =Base_OAPDI!D156 -> 5.2 Modernización de la infraestructura | D12: =Base_OAPDI!E156 -> 3 bloques reforzados estructuralmente en la sede centro. | E12: =Base_OAPDI!F156 -> N.° de bloques con reforzamiento estructural terminado | F12: =Base_OAPDI!G156 -> 3 bloques | G12: =Base_OAPDI!H156 -> Viabilidad presupuestal y permisos para los bloques pendientes | H12: =Base_OAPDI!I156 -> A30 | I12: =Base_OAPDI!J156 -> 130 · Vicerrectoría Administrativa y Financiera | J12: =Base_OAPDI!K156 -> Despacho de la Vicerrectoría Administrativa y Financiera | K12: =Base_OAPDI!L156 -> Gestión Financiera | L12: =Base_OAPDI!N156 -> 0 | M12: =Base_OAPDI!P156 -> 0 | N12: =Base_OAPDI!Q156 -> 0 | O12: =Base_OAPDI!R156 -> Acciones propuestas por la OAPDI (valídelas y formúlelas en esta fila o en Acciones adicionales): A27-121 Obtener la viabilidad presupuestal del reforzamiento estructural. | P12: =Base_OAPDI!S156 -> IMP-18 | AB12: =IF(AA12="","",INDEX(Catalogos!$Y$5:$Y$25,MATCH(AA12,L_IMP,0))) | AF12: =IF(Q12="","Pendiente por formular",IF(OR(S12="",T12="",U12="",V12="",W12="",X12="",Z12="",AA12=""),"Incompleta: faltan campos obligatorios",IF(OR(NOT(ISNUMBER(T12)),NOT(ISNUMBER(U12))),"Fecha inválida",IF(U12<T12,"La fecha de fin es anterior a la de inicio",IF(OR(YEAR(T12)<>2027,YEAR(U12)<>2027),"Fechas fuera de la vigencia 2027",IF(ISERROR(SEARCH("@itc.edu.co",V12)),"El responsable no tiene correo institucional",IF(ISERROR(SEARCH(Z12,INDEX(Catalogos!$Z$5:$Z$25,MATCH(AA12,L_IMP,0)))),"La dimensión no corresponde al indicador de impacto","OK"))))))) -> Pendiente por formular
A13: =Base_OAPDI!A157 -> E5-007 | B13: =Base_OAPDI!B157 -> 5.2.1.2 | C13: =Base_OAPDI!D157 -> 5.2 Modernización de la infraestructura | D13: =Base_OAPDI!E157 -> 100% de los talleres y laboratorios actualizados de acuerdo con el plan maestro, modernizados y viabilizados con buenas prácticas ambientales. | E13: =Base_OAPDI!F157 -> % de talleres y laboratorios modernizados | F13: =Base_OAPDI!G157 -> 100% | G13: =Base_OAPDI!H157 -> Plan Maestro Institucional (PMI) formulado y en marcha | H13: =Base_OAPDI!I157 -> A15 | I13: =Base_OAPDI!J157 -> 120 · Vicerrectoría Académica | J13: =Base_OAPDI!K157 -> Despacho de la Vicerrectoría Académica | K13: =Base_OAPDI!L157 -> Docencia PES | L13: =Base_OAPDI!N157 -> 10 | M13: =Base_OAPDI!P157 -> 8 | N13: =Base_OAPDI!Q157 -> 0 | O13: =Base_OAPDI!R157 -> Cerrar o reprogramar 8 producto(s) 2026 pendiente(s) de esta meta. | P13: =Base_OAPDI!S157 -> IMP-07; IMP-01 | AB13: =IF(AA13="","",INDEX(Catalogos!$Y$5:$Y$25,MATCH(AA13,L_IMP,0))) | AF13: =IF(Q13="","Pendiente por formular",IF(OR(S13="",T13="",U13="",V13="",W13="",X13="",Z13="",AA13=""),"Incompleta: faltan campos obligatorios",IF(OR(NOT(ISNUMBER(T13)),NOT(ISNUMBER(U13))),"Fecha inválida",IF(U13<T13,"La fecha de fin es anterior a la de inicio",IF(OR(YEAR(T13)<>2027,YEAR(U13)<>2027),"Fechas fuera de la vigencia 2027",IF(ISERROR(SEARCH("@itc.edu.co",V13)),"El responsable no tiene correo institucional",IF(ISERROR(SEARCH(Z13,INDEX(Catalogos!$Z$5:$Z$25,MATCH(AA13,L_IMP,0)))),"La dimensión no corresponde al indicador de impacto","OK"))))))) -> Pendiente por formular
A14: =Base_OAPDI!A158 -> E5-008 | B14: =Base_OAPDI!B158 -> 5.2.1.2 | C14: =Base_OAPDI!D158 -> 5.2 Modernización de la infraestructura | D14: =Base_OAPDI!E158 -> 100% de los talleres y laboratorios actualizados de acuerdo con el plan maestro, modernizados y viabilizados con buenas prácticas ambientales. | E14: =Base_OAPDI!F158 -> % de talleres y laboratorios modernizados | F14: =Base_OAPDI!G158 -> 100% | G14: =Base_OAPDI!H158 -> Plan Maestro Institucional (PMI) formulado y en marcha | H14: =Base_OAPDI!I158 -> A28 | I14: =Base_OAPDI!J158 -> 125 · GIT Talleres y Laboratorios | J14: =Base_OAPDI!K158 -> GIT Talleres y Laboratorios | K14: =Base_OAPDI!L158 -> Gestión de Recursos Físicos | L14: =Base_OAPDI!N158 -> 6 | M14: =Base_OAPDI!P158 -> 6 | N14: =Base_OAPDI!Q158 -> 0 | O14: =Base_OAPDI!R158 -> Acciones propuestas por la OAPDI (valídelas y formúlelas en esta fila o en Acciones adicionales): A27-124 Priorizar talleres y laboratorios según el PMI y la nueva oferta; A27-125 Modernizar talleres y laboratorios según el plan de inversiones. Cerrar o reprogramar 6 producto(s) 2026 pendiente(s) de esta meta. | P14: =Base_OAPDI!S158 -> IMP-07; IMP-01 | AB14: =IF(AA14="","",INDEX(Catalogos!$Y$5:$Y$25,MATCH(AA14,L_IMP,0))) | AF14: =IF(Q14="","Pendiente por formular",IF(OR(S14="",T14="",U14="",V14="",W14="",X14="",Z14="",AA14=""),"Incompleta: faltan campos obligatorios",IF(OR(NOT(ISNUMBER(T14)),NOT(ISNUMBER(U14))),"Fecha inválida",IF(U14<T14,"La fecha de fin es anterior a la de inicio",IF(OR(YEAR(T14)<>2027,YEAR(U14)<>2027),"Fechas fuera de la vigencia 2027",IF(ISERROR(SEARCH("@itc.edu.co",V14)),"El responsable no tiene correo institucional",IF(ISERROR(SEARCH(Z14,INDEX(Catalogos!$Z$5:$Z$25,MATCH(AA14,L_IMP,0)))),"La dimensión no corresponde al indicador de impacto","OK"))))))) -> Pendiente por formular
A15: =Base_OAPDI!A159 -> E5-009 | B15: =Base_OAPDI!B159 -> 5.2.1.2 | C15: =Base_OAPDI!D159 -> 5.2 Modernización de la infraestructura | D15: =Base_OAPDI!E159 -> 100% de los talleres y laboratorios actualizados de acuerdo con el plan maestro, modernizados y viabilizados con buenas prácticas ambientales. | E15: =Base_OAPDI!F159 -> % de talleres y laboratorios modernizados | F15: =Base_OAPDI!G159 -> 100% | G15: =Base_OAPDI!H159 -> Plan Maestro Institucional (PMI) formulado y en marcha | H15: =Base_OAPDI!I159 -> A38 | I15: =Base_OAPDI!J159 -> 140 · Vicerrectoría de Investigación, Extensión y Transferencia | J15: =Base_OAPDI!K159 -> Despacho de la VIET | K15: =Base_OAPDI!L159 -> Investigación | L15: =Base_OAPDI!N159 -> 3 | M15: =Base_OAPDI!P159 -> 2 | N15: =Base_OAPDI!Q159 -> 0 | O15: =Base_OAPDI!R159 -> Cerrar o reprogramar 2 producto(s) 2026 pendiente(s) de esta meta. | P15: =Base_OAPDI!S159 -> IMP-07; IMP-01 | AB15: =IF(AA15="","",INDEX(Catalogos!$Y$5:$Y$25,MATCH(AA15,L_IMP,0))) | AF15: =IF(Q15="","Pendiente por formular",IF(OR(S15="",T15="",U15="",V15="",W15="",X15="",Z15="",AA15=""),"Incompleta: faltan campos obligatorios",IF(OR(NOT(ISNUMBER(T15)),NOT(ISNUMBER(U15))),"Fecha inválida",IF(U15<T15,"La fecha de fin es anterior a la de inicio",IF(OR(YEAR(T15)<>2027,YEAR(U15)<>2027),"Fechas fuera de la vigencia 2027",IF(ISERROR(SEARCH("@itc.edu.co",V15)),"El responsable no tiene correo institucional",IF(ISERROR(SEARCH(Z15,INDEX(Catalogos!$Z$5:$Z$25,MATCH(AA15,L_IMP,0)))),"La dimensión no corresponde al indicador de impacto","OK"))))))) -> Pendiente por formular
A16: =Base_OAPDI!A160 -> E5-010 | B16: =Base_OAPDI!B160 -> 5.2.1.2 | C16: =Base_OAPDI!D160 -> 5.2 Modernización de la infraestructura | D16: =Base_OAPDI!E160 -> 100% de los talleres y laboratorios actualizados de acuerdo con el plan maestro, modernizados y viabilizados con buenas prácticas ambientales. | E16: =Base_OAPDI!F160 -> % de talleres y laboratorios modernizados | F16: =Base_OAPDI!G160 -> 100% | G16: =Base_OAPDI!H160 -> Plan Maestro Institucional (PMI) formulado y en marcha | H16: =Base_OAPDI!I160 -> A31 | I16: =Base_OAPDI!J160 -> 130 · Vicerrectoría Administrativa y Financiera | J16: =Base_OAPDI!K160 -> Recursos Físicos e Infraestructura | K16: =Base_OAPDI!L160 -> Gestión de Recursos Físicos | L16: =Base_OAPDI!N160 -> 0 | M16: =Base_OAPDI!P160 -> 0 | N16: =Base_OAPDI!Q160 -> 1 | O16: =Base_OAPDI!R160 -> Acciones propuestas por la OAPDI (valídelas y formúlelas en esta fila o en Acciones adicionales): A27-123 Contratar la consultoría del Plan Maestro Institucional. Atender 1 compromiso(s) de proyectos estructurantes (hoja Compromisos_2026). | P16: =Base_OAPDI!S160 -> IMP-07; IMP-01 | AB16: =IF(AA16="","",INDEX(Catalogos!$Y$5:$Y$25,MATCH(AA16,L_IMP,0))) | AF16: =IF(Q16="","Pendiente por formular",IF(OR(S16="",T16="",U16="",V16="",W16="",X16="",Z16="",AA16=""),"Incompleta: faltan campos obligatorios",IF(OR(NOT(ISNUMBER(T16)),NOT(ISNUMBER(U16))),"Fecha inválida",IF(U16<T16,"La fecha de fin es anterior a la de inicio",IF(OR(YEAR(T16)<>2027,YEAR(U16)<>2027),"Fechas fuera de la vigencia 2027",IF(ISERROR(SEARCH("@itc.edu.co",V16)),"El responsable no tiene correo institucional",IF(ISERROR(SEARCH(Z16,INDEX(Catalogos!$Z$5:$Z$25,MATCH(AA16,L_IMP,0)))),"La dimensión no corresponde al indicador de impacto","OK"))))))) -> Pendiente por formular
A17: =Base_OAPDI!A161 -> E5-011 | B17: =Base_OAPDI!B161 -> 5.2.1.3 | C17: =Base_OAPDI!D161 -> 5.2 Modernización de la infraestructura | D17: =Base_OAPDI!E161 -> Reposición del 100% de computadores de apoyo a la academia con antigüedad mayor a 3 años. | E17: =Base_OAPDI!F161 -> % de computadores de apoyo académico con antigüedad ≤ 3 años | F17: =Base_OAPDI!G161 -> 100% | G17: =Base_OAPDI!H161 -> Sugerido: (240 computadores de salas de sistemas repuestos —100% de las salas priorizadas— e inventario de antigüedad del parque tecnológico) | H17: =Base_OAPDI!I161 -> A34 | I17: =Base_OAPDI!J161 -> 132 · GIT Gestión de Informática y Telecomunicaciones | J17: =Base_OAPDI!K161 -> GIT Informática y Telecomunicaciones | K17: =Base_OAPDI!L161 -> Gestión de Informática y Telecomunicaciones | L17: =Base_OAPDI!N161 -> 3 | M17: =Base_OAPDI!P161 -> 3 | N17: =Base_OAPDI!Q161 -> 0 | O17: =Base_OAPDI!R161 -> Acciones propuestas por la OAPDI (valídelas y formúlelas en esta fila o en Acciones adicionales): A27-126 Levantar el inventario de antigüedad de los equipos académicos; A27-127 Reponer los equipos de cómputo de salas de sistemas. Cerrar o reprogramar 3 producto(s) 2026 pendiente(s) de esta meta. | P17: =Base_OAPDI!S161 -> IMP-07 | AB17: =IF(AA17="","",INDEX(Catalogos!$Y$5:$Y$25,MATCH(AA17,L_IMP,0))) | AF17: =IF(Q17="","Pendiente por formular",IF(OR(S17="",T17="",U17="",V17="",W17="",X17="",Z17="",AA17=""),"Incompleta: faltan campos obligatorios",IF(OR(NOT(ISNUMBER(T17)),NOT(ISNUMBER(U17))),"Fecha inválida",IF(U17<T17,"La fecha de fin es anterior a la de inicio",IF(OR(YEAR(T17)<>2027,YEAR(U17)<>2027),"Fechas fuera de la vigencia 2027",IF(ISERROR(SEARCH("@itc.edu.co",V17)),"El responsable no tiene correo institucional",IF(ISERROR(SEARCH(Z17,INDEX(Catalogos!$Z$5:$Z$25,MATCH(AA17,L_IMP,0)))),"La dimensión no corresponde al indicador de impacto","OK"))))))) -> Pendiente por formular
A18: =Base_OAPDI!A162 -> E5-012 | B18: =Base_OAPDI!B162 -> 5.3.1.1 | C18: =Base_OAPDI!D162 -> 5.3 Infraestructura de terceros | D18: =Base_OAPDI!E162 -> Hacer presencia con oferta académica en 4 sedes de terceros y multicampus: 1. Zipaquirá, 2. Multicampus de Suba, 3. Soacha, 4. Multicampus Tintal. | E18: =Base_OAPDI!F162 -> N.° de sedes de terceros con oferta activa | F18: =Base_OAPDI!G162 -> 4 sedes de terceros | G18: =Base_OAPDI!H162 -> Convenio ETITC-MinTIC suscrito; oferta en Zipaquirá; oferta 2027-1 en La Primavera, Villeta y 3 municipios de Casanare | H18: =Base_OAPDI!I162 -> A30 | I18: =Base_OAPDI!J162 -> 130 · Vicerrectoría Administrativa y Financiera | J18: =Base_OAPDI!K162 -> Despacho de la Vicerrectoría Administrativa y Financiera | K18: =Base_OAPDI!L162 -> Gestión Financiera | L18: =Base_OAPDI!N162 -> 0 | M18: =Base_OAPDI!P162 -> 0 | N18: =Base_OAPDI!Q162 -> 1 | O18: =Base_OAPDI!R162 -> Atender 1 compromiso(s) de proyectos estructurantes (hoja Compromisos_2026). | P18: =Base_OAPDI!S162 -> IMP-12; IMP-13 | AB18: =IF(AA18="","",INDEX(Catalogos!$Y$5:$Y$25,MATCH(AA18,L_IMP,0))) | AF18: =IF(Q18="","Pendiente por formular",IF(OR(S18="",T18="",U18="",V18="",W18="",X18="",Z18="",AA18=""),"Incompleta: faltan campos obligatorios",IF(OR(NOT(ISNUMBER(T18)),NOT(ISNUMBER(U18))),"Fecha inválida",IF(U18<T18,"La fecha de fin es anterior a la de inicio",IF(OR(YEAR(T18)<>2027,YEAR(U18)<>2027),"Fechas fuera de la vigencia 2027",IF(ISERROR(SEARCH("@itc.edu.co",V18)),"El responsable no tiene correo institucional",IF(ISERROR(SEARCH(Z18,INDEX(Catalogos!$Z$5:$Z$25,MATCH(AA18,L_IMP,0)))),"La dimensión no corresponde al indicador de impacto","OK"))))))) -> Pendiente por formular
... A27: =Base_OAPDI!A171 -> E5-021 | B27: =Base_OAPDI!B171 -> 5.4.1.1 | C27: =Base_OAPDI!D171 -> 5.4 Infraestructura para programas presenciales y semipresenciales | D27: =Base_OAPDI!E171 -> Contar con el 100% de la infraestructura de talleres y laboratorios a través de convenios con instituciones y sector productivo (programas no presenciales). | E27: =Base_OAPDI!F171 -> % de la infraestructura requerida cubierta por convenios | F27: =Base_OAPDI!G171 -> 100% | G27: =Base_OAPDI!H171 -> Sugerido: (100% de los programas a distancia o híbridos ofertados en 2027 con convenio de uso de talleres y laboratorios —mínimo 3 convenios—) | H27: =Base_OAPDI!I171 -> A15 | I27: =Base_OAPDI!J171 -> 120 · Vicerrectoría Académica | J27: =Base_OAPDI!K171 -> Despacho de la Vicerrectoría Académica | K27: =Base_OAPDI!L171 -> Docencia PES | L27: =Base_OAPDI!N171 -> 0 | M27: =Base_OAPDI!P171 -> 0 | N27: =Base_OAPDI!Q171 -> 0 | O27: =Base_OAPDI!R171 -> Acciones propuestas por la OAPDI (valídelas y formúlelas en esta fila o en Acciones adicionales): A27-133 Identificar la infraestructura práctica que requieren los programas no presenciales. | P27: =Base_OAPDI!S171 -> IMP-13; IMP-07 | AB27: =IF(AA27="","",INDEX(Catalogos!$Y$5:$Y$25,MATCH(AA27,L_IMP,0))) | AF27: =IF(Q27="","Pendiente por formular",IF(OR(S27="",T27="",U27="",V27="",W27="",X27="",Z27="",AA27=""),"Incompleta: faltan campos obligatorios",IF(OR(NOT(ISNUMBER(T27)),NOT(ISNUMBER(U27))),"Fecha inválida",IF(U27<T27,"La fecha de fin es anterior a la de inicio",IF(OR(YEAR(T27)<>2027,YEAR(U27)<>2027),"Fechas fuera de la vigencia 2027",IF(ISERROR(SEARCH("@itc.edu.co",V27)),"El responsable no tiene correo institucional",IF(ISERROR(SEARCH(Z27,INDEX(Catalogos!$Z$5:$Z$25,MATCH(AA27,L_IMP,0)))),"La dimensión no corresponde al indicador de impacto","OK"))))))) -> Pendiente por formular

Sheet Eje6_Bienestar
A1: Eje estratégico 6. Cuidado por el bienestar y la vida — Formulación del Plan de Acción 2027
A2: Objetivo estratégico del eje: Consolidar una cultura institucional de autocuidado, cuidado del otro, cuidado del ambiente, garantizando espacios seguros, inclusivos y sostenibles para la construcción de un bienestar integral, personal y colectivo.
A3: Columnas grises: base definida por la OAPDI (no modificar). Columnas amarillas: las diligencia el área responsable, una acción por fila. Si necesita formular más acciones para una meta, use la hoja Buscador_Formulacion.
A5: BASE DEFINIDA POR LA OAPDI | Q5: FORMULACIÓN DEL ÁREA RESPONSABLE | AF5: CONTROL
A6: Id asignación | B6: Código meta | C6: Línea | D6: Meta estratégica (PDI) | E6: Indicador de la meta | F6: Meta 2032 | G6: Meta institucional 2027 | H6: Id área | I6: Dependencia | J6: Área funcional | K6: Proceso | L6: Productos 2026 (sábana vigente) | M6: Pendientes 2026 | N6: Compromisos de proyectos estructurantes | O6: Aporte esperado del área 2027 | P6: Indicadores de impacto sugeridos | Q6: Nombre de la acción | R6: Descripción de la acción | S6: Producto esperado | T6: Fecha de inicio (dd/mm/aaaa) | U6: Fecha de fin (dd/mm/aaaa) | V6: Responsable (correo institucional) | W6: Indicador de seguimiento | X6: Meta 2027 de la acción | Y6: Unidad de medida | Z6: Dimensión de impacto | AA6: Indicador de impacto (Guía Metodológica) | AB6: Categoría de impacto (automática) | AC6: ¿Retoma un compromiso pendiente 2026? | AD6: Evidencia verificable | AE6: Observaciones | AF6: Alerta de consistencia
A7: =Base_OAPDI!A172 -> E6-001 | B7: =Base_OAPDI!B172 -> 6.1.1.1 | C7: =Base_OAPDI!D172 -> 6.1 Condiciones para el Bienestar | D7: =Base_OAPDI!E172 -> El 100% de las áreas de la Institución comprometidas con el Bienestar Universitario integral. | E7: =Base_OAPDI!F172 -> % de áreas con condiciones de bienestar consolidadas · % de áreas con enlace ambiental y campaña de uso racional de energía y agua aplicada | F7: =Base_OAPDI!G172 -> 100% | G7: =Base_OAPDI!H172 -> Sugerido: (85% de las áreas con condiciones de bienestar consolidadas y 100% de las áreas con enlace ambiental designado y campaña de uso racional de energía y agua aplicada) | H7: =Base_OAPDI!I172 -> A21 | I7: =Base_OAPDI!J172 -> 122 · GIT Bienestar Universitario | J7: =Base_OAPDI!K172 -> GIT Bienestar Universitario | K7: =Base_OAPDI!L172 -> Gestión de Bienestar Universitario | L7: =Base_OAPDI!N172 -> 0 | M7: =Base_OAPDI!P172 -> 0 | N7: =Base_OAPDI!Q172 -> 2 | O7: =Base_OAPDI!R172 -> Acciones propuestas por la OAPDI (valídelas y formúlelas en esta fila o en Acciones adicionales): A27-135 Cerrar el ciclo PFB 2025 (pruebas psicológicas, transporte, soportes); A27-136 Implementar las condiciones clave para el bienestar integral (política, programas, cobertura, evaluación); A27-137 Operar el tablero mensual de seguimiento del PFB. Atender 2 compromiso(s) de proyectos estructurantes (hoja Compromisos_2026). | P7: =Base_OAPDI!S172 -> IMP-16; IMP-15; IMP-01 | AB7: =IF(AA7="","",INDEX(Catalogos!$Y$5:$Y$25,MATCH(AA7,L_IMP,0))) | AF7: =IF(Q7="","Pendiente por formular",IF(OR(S7="",T7="",U7="",V7="",W7="",X7="",Z7="",AA7=""),"Incompleta: faltan campos obligatorios",IF(OR(NOT(ISNUMBER(T7)),NOT(ISNUMBER(U7))),"Fecha inválida",IF(U7<T7,"La fecha de fin es anterior a la de inicio",IF(OR(YEAR(T7)<>2027,YEAR(U7)<>2027),"Fechas fuera de la vigencia 2027",IF(ISERROR(SEARCH("@itc.edu.co",V7)),"El responsable no tiene correo institucional",IF(ISERROR(SEARCH(Z7,INDEX(Catalogos!$Z$5:$Z$25,MATCH(AA7,L_IMP,0)))),"La dimensión no corresponde al indicador de impacto","OK"))))))) -> Pendiente por formular
A8: =Base_OAPDI!A173 -> E6-002 | B8: =Base_OAPDI!B173 -> 6.1.1.1 | C8: =Base_OAPDI!D173 -> 6.1 Condiciones para el Bienestar | D8: =Base_OAPDI!E173 -> El 100% de las áreas de la Institución comprometidas con el Bienestar Universitario integral. | E8: =Base_OAPDI!F173 -> % de áreas con condiciones de bienestar consolidadas · % de áreas con enlace ambiental y campaña de uso racional de energía y agua aplicada | F8: =Base_OAPDI!G173 -> 100% | G8: =Base_OAPDI!H173 -> Sugerido: (85% de las áreas con condiciones de bienestar consolidadas y 100% de las áreas con enlace ambiental designado y campaña de uso racional de energía y agua aplicada) | H8: =Base_OAPDI!I173 -> A36 | I8: =Base_OAPDI!J173 -> 133 · GIT Gestión de Talento Humano | J8: =Base_OAPDI!K173 -> Seguridad y Salud en el Trabajo | K8: =Base_OAPDI!L173 -> Gestión de Talento Humano | L8: =Base_OAPDI!N173 -> 0 | M8: =Base_OAPDI!P173 -> 0 | N8: =Base_OAPDI!Q173 -> 0 | O8: =Base_OAPDI!R173 -> Formular al menos una acción que contribuya a la meta institucional 2027 de esta meta. | P8: =Base_OAPDI!S173 -> IMP-16; IMP-15; IMP-01 | AB8: =IF(AA8="","",INDEX(Catalogos!$Y$5:$Y$25,MATCH(AA8,L_IMP,0))) | AF8: =IF(Q8="","Pendiente por formular",IF(OR(S8="",T8="",U8="",V8="",W8="",X8="",Z8="",AA8=""),"Incompleta: faltan campos obligatorios",IF(OR(NOT(ISNUMBER(T8)),NOT(ISNUMBER(U8))),"Fecha inválida",IF(U8<T8,"La fecha de fin es anterior a la de inicio",IF(OR(YEAR(T8)<>2027,YEAR(U8)<>2027),"Fechas fuera de la vigencia 2027",IF(ISERROR(SEARCH("@itc.edu.co",V8)),"El responsable no tiene correo institucional",IF(ISERROR(SEARCH(Z8,INDEX(Catalogos!$Z$5:$Z$25,MATCH(AA8,L_IMP,0)))),"La dimensión no corresponde al indicador de impacto","OK"))))))) -> Pendiente por formular
A9: =Base_OAPDI!A174 -> E6-003 | B9: =Base_OAPDI!B174 -> 6.1.1.1 | C9: =Base_OAPDI!D174 -> 6.1 Condiciones para el Bienestar | D9: =Base_OAPDI!E174 -> El 100% de las áreas de la Institución comprometidas con el Bienestar Universitario integral. | E9: =Base_OAPDI!F174 -> % de áreas con condiciones de bienestar consolidadas · % de áreas con enlace ambiental y campaña de uso racional de energía y agua aplicada | F9: =Base_OAPDI!G174 -> 100% | G9: =Base_OAPDI!H174 -> Sugerido: (85% de las áreas con condiciones de bienestar consolidadas y 100% de las áreas con enlace ambiental designado y campaña de uso racional de energía y agua aplicada) | H9: =Base_OAPDI!I174 -> A37 | I9: =Base_OAPDI!J174 -> 133 · GIT Gestión de Talento Humano | J9: =Base_OAPDI!K174 -> Bienestar Laboral | K9: =Base_OAPDI!L174 -> Gestión de Talento Humano | L9: =Base_OAPDI!N174 -> 0 | M9: =Base_OAPDI!P174 -> 0 | N9: =Base_OAPDI!Q174 -> 0 | O9: =Base_OAPDI!R174 -> Formular al menos una acción que contribuya a la meta institucional 2027 de esta meta. | P9: =Base_OAPDI!S174 -> IMP-16; IMP-15; IMP-01 | AB9: =IF(AA9="","",INDEX(Catalogos!$Y$5:$Y$25,MATCH(AA9,L_IMP,0))) | AF9: =IF(Q9="","Pendiente por formular",IF(OR(S9="",T9="",U9="",V9="",W9="",X9="",Z9="",AA9=""),"Incompleta: faltan campos obligatorios",IF(OR(NOT(ISNUMBER(T9)),NOT(ISNUMBER(U9))),"Fecha inválida",IF(U9<T9,"La fecha de fin es anterior a la de inicio",IF(OR(YEAR(T9)<>2027,YEAR(U9)<>2027),"Fechas fuera de la vigencia 2027",IF(ISERROR(SEARCH("@itc.edu.co",V9)),"El responsable no tiene correo institucional",IF(ISERROR(SEARCH(Z9,INDEX(Catalogos!$Z$5:$Z$25,MATCH(AA9,L_IMP,0)))),"La dimensión no corresponde al indicador de impacto","OK"))))))) -> Pendiente por formular
